Workbook

Sheet Coffres
A1: ID coffre | B1: Nom | C1: Position | D1: Description
A2: e90f29b9-f199-4889-ae16-c647b42a0b4a | B2: Coffre de l'Armurerie | C2: Salle des cartes, sous la table des cartes. | D2: Armes, Bouclier, Armures de Blancherive
A3: 52d52cb8-fa70-4f9e-8f25-d1e7aed1b342 | B3: Coffre des soldes | C3: Geoles | D3: Septimes, armes gardes spécial

Sheet Inventaire
A1: ID coffre | B1: ID objet | C1: Nom | D1: Quantité
A2: e90f29b9-f199-4889-ae16-c647b42a0b4a | B2: sentinel - city guards.esp|000806 | C2: Whiterun Guard's Helmet | D2: 5
A3: e90f29b9-f199-4889-ae16-c647b42a0b4a | B3: sentinel - city guards.esp|000800 | C3: Whiterun Guard's Armor | D3: 19
A4: e90f29b9-f199-4889-ae16-c647b42a0b4a | B4: sentinel - city guards.esp|000805 | C4: Whiterun Guard's Heavy Gauntlets | D4: 1
A5: e90f29b9-f199-4889-ae16-c647b42a0b4a | B5: sentinel - city guards.esp|000801 | C5: Whiterun Guard's Heavy Armor | D5: 19
A6: e90f29b9-f199-4889-ae16-c647b42a0b4a | B6: sentinel - city guards.esp|000808 | C6: Whiterun Guard's Heavy Helmet | D6: 29
A7: e90f29b9-f199-4889-ae16-c647b42a0b4a | B7: sentinel - city guards.esp|000809 | C7: Whiterun Light Shield | D7: 5
A8: e90f29b9-f199-4889-ae16-c647b42a0b4a | B8: sentinel - city guards.esp|00080A | C8: Whiterun Shield | D8: 1
A9: e90f29b9-f199-4889-ae16-c647b42a0b4a | B9: sentinel.esp|000906 | C9: Common Gambeson | D9: 2
A10: e90f29b9-f199-4889-ae16-c647b42a0b4a | B10: kzlhorses.esp|01024E | C10: Prisoner's Cuffs | D10: 23
A11: e90f29b9-f199-4889-ae16-c647b42a0b4a | B11: evgnnsmpaccessories.esp|00082D | C11: Quilted Mantle | D11: 2
A12: e90f29b9-f199-4889-ae16-c647b42a0b4a | B12: evgnnsmpaccessories.esp|000834 | C12: Reinforced Mantle | D12: 3
A13: e90f29b9-f199-4889-ae16-c647b42a0b4a | B13: sentinel - city guards.esp|000804 | C13: Whiterun Ceremonial Cloak | D13: 6
... A24: e90f29b9-f199-4889-ae16-c647b42a0b4a | B24: sentinel - city guards.esp|0008E0 | C24: Whiterun Sword | D24: 8
A25: 52d52cb8-fa70-4f9e-8f25-d1e7aed1b342 | C25: Epée d'argent | D25: 1

Sheet Objets
A1: ID objet | B1: Nom | C1: Type
A2: dragonborn.esm|01BFEF | B2: Zahkrii Do Dovahkiin | C2: Arme
A3: windhelmsse.esp|1252B7 | B3: Akaviri Snakesword | C3: Arme
A4: aaagranitehill.esp|3BC29A | B4: Amon's Cheese Steel Dagger | C4: Arme
A5: skyrim.esm|106252 | B5: Ancien espadon nordique ardent affûté | C5: Arme
A6: dragonborn.esm|036689 | B6: Animortis | C6: Arme
A7: skyrim.esm|06EA8B | B7: Aquilon | C7: Arme
A8: dawnguard.esm|000801 | B8: Arbalète | C8: Arme
A9: dawnguard.esm|00F19E | B9: Arbalète améliorée | C9: Arme
A10: dawnguard.esm|00D0BE | B10: Arbalète bénie | C10: Arme
A11: dawnguard.esm|00D0C7 | B11: Arbalète d'amenuisement | C11: Arme
A12: dawnguard.esm|00D0C5 | B12: Arbalète d'éclairs | C12: Arme
... A10132: skyrim.esm|03133C | B10132: Wine | C10132: Potion / nourriture

Sheet SoldesGrades
A1: Grade | B1: Solde journalière (septims)
A2: Par défaut | B2: 50
A3: Maréchal | B3: 100
A4: Commander | B4: 100
A5: Major | B5: 75
A6: Capitaine | B6: 50
A7: Lieutenant-Chef | B7: 50
A8: Lieutenant | B8: 50
A9: Sergent-Chef | B9: 50
A10: Sergent | B10: 50
A11: Caporal-Chef | B11: 50
A12: Caporal | B12: 50
A13: Garde | B13: 50
... A15: Recrue | B15: 0

Sheet HistoriqueEffectifs
A1: ID événement | B1: Date ISO | C1: ID membre | D1: Type | E1: Nom | F1: Changements JSON | G1: État JSON | H1: Source
A2: 19bb8717-fc55-43e7-aea0-a062215c33f0 | B2: 2026-09-06T11:12:57.322Z | D2: initialisation | F2: [] | G2: {} | H2: Détection
A3: aa2df3fa-8c22-4d03-9be7-b080f99c5e08 | B3: 2026-09-06T11:12:57.322Z | C3: d46f0957-73ed-4c3c-9135-84cc8f768643 | D3: reference | E3: Lazabard Jemelred | F3: [] | G3: {"prenom":"Lazabard","nom":"Jemelred","grade":"Maréchal","corps":"Etat-Major","status":"En service actif"} | H3: Détection
A4: 2ed5527f-c150-41d4-8f5c-9c03d1a2dd5f | B4: 2026-09-06T11:12:57.322Z | C4: 99c04539-4625-4073-b805-d47570970809 | D4: reference | E4: Filoki | F4: [] | G4: {"prenom":"Filoki","nom":"","grade":"Commander","corps":"Etat-Major","status":"En service actif"} | H4: Détection
A5: 19e80916-a210-4e2e-ab97-8cf999287642 | B5: 2026-09-06T11:12:57.322Z | C5: ae3bc537-6b70-4a20-bc22-394ed7a3ebed | D5: reference | E5: Dagbara Gronez | F5: [] | G5: {"prenom":"Dagbara","nom":"Gronez","grade":"Major","corps":"Etat-Major","status":"Mis en réserve"} | H5: Détection
A6: 4143667e-dc10-4a67-a015-b16afd8734e6 | B6: 2026-09-06T11:12:57.322Z | C6: 066ffa57-32e1-4df1-b986-fecbc974f94f | D6: reference | E6: Astrid Lame-Fine | F6: [] | G6: {"prenom":"Astrid","nom":"Lame-Fine","grade":"Capitaine","corps":"Cité de Blancherive","status":"En service actif"} | H6: Détection
A7: 565fada4-80a6-4ad3-bd38-94e070a1e597 | B7: 2026-09-06T11:12:57.322Z | C7: be4acc2e-1d02-4737-864e-ac54f1ff672a | D7: reference | E7: Glaemorandir Oeil-Perçant | F7: [] | G7: {"prenom":"Glaemorandir","nom":"Oeil-Perçant","grade":"Capitaine","corps":"Eclaireur","status":"En service actif"} | H7: Détection
A8: bb66b8c2-baa8-4d51-b2e6-52e00440a67b | B8: 2026-09-06T11:12:57.322Z | C8: d063b504-c415-4cfd-a859-953178822915 | D8: reference | E8: Edward Winters | F8: [] | G8: {"prenom":"Edward","nom":"Winters","grade":"Capitaine","corps":"Cité de Blancherive","status":"Mis en réserve"} | H8: Détection
A9: 905ad0a4-0911-410d-93be-6ec287e4c167 | B9: 2026-09-06T11:12:57.322Z | C9: b2cf2258-4446-43c9-b850-e157c81f93fc | D9: reference | E9: Kah-Shir Sombre Griffe | F9: [] | G9: {"prenom":"Kah-Shir","nom":"Sombre Griffe","grade":"Capitaine","corps":"Faubourgs de Blancherive","status":"En service actif"} | H9: Détection
A10: 95f772ea-a38a-4e0a-88de-8d0c4dc93b7c | B10: 2026-09-06T11:12:57.322Z | C10: f89b63e9-4f33-4f63-9666-0289c90a22e1 | D10: reference | E10: Clemnir Arc-Vif | F10: [] | G10: {"prenom":"Clemnir","nom":"Arc-Vif","grade":"Capitaine","corps":"Eclaireur","status":"Mort en service actif"} | H10: Détection
A11: a104fd1d-7aed-44c6-87d8-5bf6ba4ad457 | B11: 2026-09-06T11:12:57.322Z | C11: 3f7cf32c-5eda-447f-b5e1-9bd0d6fb6940 | D11: reference | E11: Sigurd Grisetoison | F11: [] | G11: {"prenom":"Sigurd","nom":"Grisetoison","grade":"Capitaine","corps":"Rivebois","status":"Déserteur"} | H11: Détection
A12: 6f840cc7-dbf1-47f6-9352-577524625103 | B12: 2026-09-06T11:12:57.322Z | C12: 9bd100c0-2019-43c5-807d-bcc8a177174d | D12: reference | E12: Hastelvin | F12: [] | G12: {"prenom":"Hastelvin","nom":"","grade":"Capitaine","corps":"Cap Granite","status":"En service actif"} | H12: Détection
A13: a9c65bcf-cd83-4972-9944-3a547412c790 | B13: 2026-09-06T11:12:57.322Z | C13: e194b9d1-cea0-4e22-b10f-e7dee3aec987 | D13: reference | E13: Ulfar | F13: [] | G13: {"prenom":"Ulfar","nom":"","grade":"Major","corps":"Etat-Major","status":"En service actif"} | H13: Détection
A14: b40e1512-e0d1-4e1f-9cc2-efe4087cfc7f | B14: 2026-09-06T11:12:57.322Z | C14: 3ff8c6c7-e0ec-44d3-9d43-062229456eeb | D14: reference | E14: Ronin | F14: [] | G14: {"prenom":"Ronin","nom":"","grade":"Lieutenant","corps":"Cité de Blancherive","status":"En service actif"} | H14: Détection
... A213: d7da8d20-6bc5-4ec1-8ca0-2dda7a20f5dc | B213: 2026-09-26T23:20:28.600Z | C213: 0005762a-098e-4ce4-93bc-10132427bf0f | D213: changement | E213: Crocozaure | F213: [{"type":"corps","avant":"Cité de Blancherive","apres":"Eclaireur"}] | G213: {"prenom":"Crocozaure","nom":"","grade":"Cadet","corps":"Eclaireur","status":"En service actif"} | H213: Application

Sheet Effectifs
A1: Assermenté | B1: Grade | C1: Prénom | D1: Nom | E1: Corps | F1: Spécialité | G1: Status | H1: Métier | AA1: ID membre
A2: TRUE | B2: Maréchal | C2: Lazabard | D2: Jemelred | E2: Etat-Major | F2: Garde, Collecteur de la garde | G2: En service actif | AA2: d46f0957-73ed-4c3c-9135-84cc8f768643
A3: TRUE | B3: Commander | C3: Filoki | E3: Etat-Major | F3: Garde, Collecteur de la garde | G3: En service actif | AA3: 99c04539-4625-4073-b805-d47570970809
A4: TRUE | B4: Major | C4: Dagbara | D4: Gronez | E4: Etat-Major | F4: Garde | G4: Mis en réserve | AA4: ae3bc537-6b70-4a20-bc22-394ed7a3ebed
A5: TRUE | B5: Capitaine | C5: Astrid | D5: Lame-Fine | E5: Cité de Blancherive | F5: Garde, Collecteur de la garde | G5: En service actif | H5: Chasseur | AA5: 066ffa57-32e1-4df1-b986-fecbc974f94f
A6: TRUE | B6: Capitaine | C6: Glaemorandir | D6: Oeil-Perçant | E6: Eclaireur | F6: Eclaireur, Garde, Collecteur de la garde | G6: En service actif | H6: Chasseur | AA6: be4acc2e-1d02-4737-864e-ac54f1ff672a
A7: TRUE | B7: Capitaine | C7: Edward | D7: Winters | E7: Cité de Blancherive | F7: Hird | G7: Mis en réserve | AA7: d063b504-c415-4cfd-a859-953178822915
A8: TRUE | B8: Capitaine | C8: Kah-Shir | D8: Sombre Griffe | E8: Faubourgs de Blancherive | G8: Radié du service actif | AA8: b2cf2258-4446-43c9-b850-e157c81f93fc
A9: TRUE | B9: Capitaine | C9: Clemnir | D9: Arc-Vif | E9: Eclaireur | F9: Eclaireur | G9: Mort en service actif | H9: Chasseur | AA9: f89b63e9-4f33-4f63-9666-0289c90a22e1
A10: FALSE | B10: Capitaine | C10: Sigurd | D10: Grisetoison | E10: Rivebois | F10: Garde, Collecteur de la garde | G10: Déserteur | AA10: 3f7cf32c-5eda-447f-b5e1-9bd0d6fb6940
A11: FALSE | B11: Capitaine | C11: Hastelvin | E11: Cap Granite | F11: Garde, Collecteur de la garde | G11: Démissionnaire | AA11: 9bd100c0-2019-43c5-807d-bcc8a177174d
A12: TRUE | B12: Major | C12: Ulfar | E12: Etat-Major | F12: Garde, Collecteur de la garde | G12: En service actif | AA12: e194b9d1-cea0-4e22-b10f-e7dee3aec987
A13: TRUE | B13: Lieutenant-Chef | C13: Ronin | E13: Cité de Blancherive | F13: Garde, Collecteur de la garde | G13: En service actif | H13: Guerrier | AA13: 3ff8c6c7-e0ec-44d3-9d43-062229456eeb
A14: TRUE | B14: Lieutenant | C14: Thorin | D14: Rivegel | E14: Cité de Blancherive | F14: Garde | G14: Déserteur | H14: Guerrier | AA14: bd991a26-51dd-4828-934e-6491f8612420
A15: TRUE | B15: Lieutenant-Chef | C15: Gisbern | D15: Isenbjorn | E15: Cité de Blancherive | F15: Garde | G15: Déserteur | AA15: 3337fcb2-cdd2-425e-9899-3efe84a5bf31
A16: TRUE | B16: Lieutenant | C16: Rorik | D16: Marche-Hiver | E16: Cité de Blancherive | F16: Garde, Intendant de la garde | G16: En service actif | AA16: 7f06b07a-819f-460f-b37b-0874f474bd94
A17: TRUE | B17: Sergent-Chef | C17: Erwan | E17: Cité de Blancherive | F17: Garde | G17: En service actif | AA17: 387160c7-839d-4249-b44d-61ae80f8aad4
A18: TRUE | B18: Lieutenant | C18: Daric | E18: Rivebois | F18: Garde | G18: En service actif | AA18: 90d91845-36aa-44bd-ab58-cfc0dba6f40a
A19: TRUE | B19: Caporal-Chef | C19: Ilflynn | E19: Cité de Blancherive | F19: Garde | G19: En service actif | AA19: 44162c0c-aec1-4836-bcd0-538e837f915b
A20: TRUE | B20: Sergent-Chef | C20: Magnar | D20: Traquebrume | E20: Eclaireur | F20: Eclaireur, Garde | G20: En service actif | H20: Chasseur | AA20: 8a386dc7-8b4c-4075-add4-d6bdb563f82c
A21: TRUE | B21: Lieutenant-Chef | C21: Pethiceor | D21: Le Borgne | E21: Eclaireur | F21: Eclaireur, Garde | G21: En service actif | H21: Chasseur | AA21: 089e2535-16b8-4f30-b745-f4e8247bb3dc
A22: TRUE | B22: Garde | C22: Laureen | D22: Toison-de-Sang | E22: Cité de Blancherive | F22: Eclaireur, Garde | G22: En service actif | H22: Chasseur | AA22: b4583989-fdc0-4056-a9c3-05a4acb3c5dd
A23: TRUE | B23: Garde | C23: Ma'arl | E23: Eclaireur | F23: Eclaireur, Garde | G23: En service actif | H23: Mineur | AA23: c03971ee-4407-406e-adb5-e6060c104fda
A24: TRUE | B24: Garde | C24: Andor | D24: Viraes | E24: Cité de Blancherive | F24: Garde | G24: Mis en réserve | AA24: 0edc5da4-f3d8-466c-9551-4a086cf04e6a
A25: FALSE | B25: Sergent-Chef | C25: Astrild | E25: Cité de Blancherive | F25: Garde | G25: En service actif | AA25: e46cd881-a491-4ea4-9a64-da434a735c58
A26: TRUE | B26: Caporal | C26: Athlan | E26: Rivebois | F26: Garde | G26: En service actif | AA26: b7594f74-7299-4d5c-a0df-29b71c5c2ae0
A27: FALSE | B27: Lieutenant | C27: Encore-Un-Espoir | E27: Cité de Blancherive | F27: Garde, Tortionnaire, Instructeur | G27: Démissionnaire | AA27: d7cf260e-6fc9-4f55-b7a0-872095e1d48a
A28: TRUE | B28: Garde | C28: Al'Dran | E28: Cité de Blancherive | F28: Garde | G28: Démissionnaire | AA28: b1fdb1fa-73a3-4be9-8167-fe80c5c9e26a
A29: TRUE | B29: Caporal | C29: Kendall | D29: Delamare | E29: Cité de Blancherive | F29: Garde | G29: En service actif | AA29: 2792c1dd-ac31-415d-b9fc-17fbd08549ee
A30: FALSE | B30: Garde | C30: Léonce | D30: Réve-épine | E30: Faubourgs de Blancherive | G30: Radié du service actif | AA30: f62f8cc2-8070-4dc2-8416-6edea1971841
A31: FALSE | B31: Garde | C31: Kronk | D31: Grognon | E31: Hird du Jarl | F31: Hird | G31: En service actif | AA31: 91e4da48-8791-43fe-8ff4-5b0ffe3453b4
A32: FALSE | B32: Garde | C32: Gronk | D32: Grognon | E32: Hird du Jarl | F32: Hird | G32: En service actif | AA32: 16f4937d-03da-4800-b9f3-dfec048f76f5
A33: FALSE | B33: Garde | C33: S'Khar | E33: Hird du Jarl | F33: Hird | G33: En service actif | AA33: 4cd4fcb0-0b5f-4cf0-8d04-5d7df12211f3
A34: TRUE | B34: Garde | C34: Do'Rhazir | E34: Eclaireur | F34: Eclaireur, Garde | G34: En service actif | H34: Menuisier-Charbonnier | AA34: 423e12c6-ff0e-4b0c-aa09-b1edab69bb1d
A35: FALSE | B35: Cadet | C35: Eldrim | D35: Hache-Grise | E35: Cité de Blancherive | F35: Garde | G35: Déserteur | AA35: 871d3680-6678-4e2f-b020-f57f61b8f3fa
A36: FALSE | B36: Recrue | C36: Ro'minet | E36: Cité de Blancherive | F36: Garde | G36: Radié du service actif | AA36: d2280313-4392-40e5-9b5b-0fbe1cc78ee8
A37: TRUE | B37: Garde | C37: Bjorn | D37: Kornseen | E37: Cité de Blancherive | F37: Garde | G37: En service actif | AA37: 33cfe266-c918-4bde-b0d1-d4b850aa6e55
A38: TRUE | B38: Garde | C38: Wulfgar | D38: Durrock | E38: Cité de Blancherive | F38: Garde | G38: En service actif | AA38: 762a804c-ab03-4d62-8faf-f0c4431f891a
A39: FALSE | B39: Garde | C39: Lyosha | D39: Sullapierre | E39: Cité de Blancherive | F39: Garde | G39: Mis en réserve | AA39: 3c461949-7a70-483a-a9b4-47977284876c
A40: FALSE | B40: Garde | C40: Brandon | D40: Alprazz | E40: Cité de Blancherive | F40: Garde | G40: Mis en réserve | AA40: c4151012-867f-4255-9483-8157805efc88
A41: TRUE | B41: Garde | C41: Aldric | D41: Cendre-coeur | E41: Cité de Blancherive | F41: Garde | G41: En service actif | AA41: b3abe128-af40-4a15-9a7c-8cdcc8994d2b
A42: FALSE | B42: Lieutenant-Chef | C42: Il-draz | D42: De Chasse-au-bois | E42: Faubourgs de Blancherive | G42: Radié du service actif | AA42: 2452efb3-8cb1-4a39-ad9e-073d0e29b787
A43: FALSE | B43: Lieutenant | C43: Gorvin | D43: Le-Moite | E43: Faubourgs de Blancherive | G43: Radié du service actif | AA43: 0badcd94-1448-431c-b18e-9dcb012cc107
A44: FALSE | B44: Garde | C44: Smaug | E44: Faubourgs de Blancherive | G44: Radié du service actif | AA44: 10f63f95-8b1b-4def-bf62-63350d615c0a
A45: FALSE | B45: Garde | C45: Njalda | E45: Faubourgs de Blancherive | G45: Radié du service actif | AA45: c3f9c322-f7c3-428b-a5fd-fe458e11f2ee
A46: FALSE | B46: Garde | C46: Darina | E46: Faubourgs de Blancherive | G46: Radié du service actif | AA46: 81c0e6b0-622b-46a0-aa0c-4a5b5402c3c9
A47: FALSE | B47: Sergent | C47: Jeebam-dee | E47: Faubourgs de Blancherive | G47: Radié du service actif | AA47: 08bf8ece-aaf0-4c1e-9752-c9727c1f725f
A48: FALSE | B48: Garde | C48: Torald | D48: Brise-Roche | E48: Faubourgs de Blancherive | G48: Radié du service actif | AA48: 26457a4b-f3b0-4f08-b497-6b55323ec993
A49: FALSE | B49: Garde | C49: Bernis | E49: Faubourgs de Blancherive | F49: Garde | G49: Radié du service actif | AA49: ba48e38b-db25-47be-ab51-69ea09f7d610
A50: FALSE | B50: Cadet | C50: Ina'ra | E50: Faubourgs de Blancherive | G50: Radié du service actif | AA50: 8f420ced-2d88-4d69-9266-ecde48c0bc1d
A51: FALSE | B51: Sergent | C51: Ja'Shanir | E51: Faubourgs de Blancherive | F51: Garde | G51: Démissionnaire | AA51: 29a146ce-c373-436c-9adf-bbdbb0e96213
A52: FALSE | B52: Garde | C52: Malivor | D52: Xernes | E52: Cap Granite | F52: Garde | G52: Démissionnaire | AA52: 32f691bf-33e6-469c-841b-1ac47e3abcba
A53: TRUE | B53: Garde | C53: Bakhir | E53: Cap Granite | F53: Garde | G53: En service actif | AA53: 1f0c5315-ddbe-4ad1-8f29-da513ad2a68f
A54: TRUE | B54: Lieutenant-Chef | C54: Starkos | D54: Coeurebene | E54: Cap Granite | F54: Garde | G54: En service actif | AA54: 29103983-2f74-4c62-a5a3-efdfd3e28c7b
A55: FALSE | B55: Garde | C55: Drakgor | D55: gro-Drakar | E55: Cap Granite | F55: Garde | G55: Démissionnaire | AA55: 9ae91e95-f358-46de-ba13-1b63f5645817
A56: FALSE | B56: Lieutenant | C56: Barnabas | D56: Tharmr | E56: Cap Granite | F56: Garde | G56: En service actif | AA56: 25b0ea59-7eaa-4cc8-ac58-a1e48d5e2c07
A57: FALSE | B57: Capitaine | C57: Pavis | D57: Gurdalval | E57: Cap Granite | F57: Garde | G57: En service actif | AA57: ea784d3f-800a-4fad-8a20-a81de3897f62
A58: FALSE | B58: Garde | C58: Gorbash | D58: Tête-de-Pierre | E58: Hird du Jarl | F58: Hird | G58: En service actif | AA58: e1253a4b-1f53-4627-8f73-fe96ee9d81aa
A59: FALSE | B59: Garde | C59: Armand | D59: De Valclair | E59: Hird du Jarl | F59: Hird | G59: Démissionnaire | AA59: a29e27a5-463b-4e75-894f-cc4afb7dbad7
A60: FALSE | B60: Garde | C60: Si'Yara | D60: dite Fou | E60: Hird du Jarl | F60: Hird | G60: En service actif | AA60: 30bd0047-1d64-4563-8234-65116be04943
A61: FALSE | B61: Garde | C61: Lokh | D61: Tar | E61: Hird du Jarl | F61: Hird | G61: En service actif | AA61: 5582c923-001b-4a38-b703-3cfec7ef331e
A62: FALSE | B62: Capitaine | C62: Theodrek | D62: Heid | E62: Hird du Jarl | F62: Hird | G62: En service actif | AA62: 2ca5598a-8d00-426f-be65-297d498a2758
A63: FALSE | B63: Garde | C63: Selene | E63: Hird du Jarl | F63: Hird | G63: En service actif | AA63: 19286ce6-b924-4665-8d2d-ffcdced15bc6
A64: FALSE | B64: Garde | C64: Lucius | D64: Ravenshield | E64: Hird du Jarl | F64: Hird | G64: En service actif | AA64: f5887192-48eb-402b-a4ef-aee281289118
A65: FALSE | B65: Major | C65: Krakan | D65: Valyn | E65: Rivebois | F65: Garde | G65: En service actif | AA65: e93bd27c-bbf4-43fa-838a-03a31a2d133d
A66: TRUE | B66: Major | C66: Rusco | E66: Bois-de-Chêne | F66: Garde | G66: En service actif | AA66: 9a276680-eab1-4ad0-afe2-9e0ec0f949ba
A67: FALSE | B67: Garde | C67: Faynir | E67: Hird du Jarl | F67: Hird | G67: En service actif | AA67: b9a9c9a2-ed09-4feb-859a-86e26b14b335
A68: FALSE | B68: Garde | C68: Varaa | D68: Uzgar | E68: Hird du Jarl | F68: Hird | G68: En service actif | AA68: 6918ece7-b7ec-4afb-b10d-b1df2d7c074e
A69: FALSE | B69: Recrue | C69: Aldrok | E69: Cité de Blancherive | F69: Garde | G69: Radié du service actif | AA69: e2924263-8d6a-4881-ae81-e58e0faf58ef
A70: TRUE | B70: Garde | C70: Ri'Jhan | D70: MoonShadow | E70: Eclaireur | F70: Garde, Eclaireur | G70: En service actif | AA70: 709bdae5-6486-472b-ba26-5ea2c772de07
A71: TRUE | B71: Garde | C71: Zeid | D71: Le Brise-Lames | E71: Cité de Blancherive | F71: Garde | G71: En service actif | AA71: 04b0b645-ffb7-4ddf-b96d-39f9ccca30e0
A72: FALSE | B72: Recrue | C72: Gruseldorf | D72: E. Jackeet | E72: Cité de Blancherive | F72: Garde | G72: Radié du service actif | AA72: 9af789dd-bbde-4d78-9481-fb4509ef7676
A73: FALSE | B73: Recrue | C73: Mordecai | D73: E. Jackeet | E73: Cité de Blancherive | F73: Garde | G73: Radié du service actif | AA73: b1752186-394b-4a2d-b039-df9acfb90ea1
A74: FALSE | B74: Capitaine | C74: Hakon | D74: Grisetoison | E74: Rivebois | F74: Garde, Collecteur de la garde | G74: Mort en service actif | AA74: 49f87d58-8963-4006-8f10-294c8bd138f1
A75: FALSE | B75: Caporal-Chef | C75: Lous | D75: Bois | E75: Rivebois | F75: Garde | G75: En service actif | AA75: 1c97bbd8-d5df-4652-8393-72894785d6de
A76: FALSE | B76: Capitaine | C76: Brand | D76: Grisetoison | E76: Rivebois | F76: Garde, Collecteur de la garde | G76: Mort en service actif | AA76: 7cb90c75-65ca-46e6-add2-a5c77060a767
A77: FALSE | B77: Recrue | C77: Darius | D77: Blacktorn | E77: Bois-de-Chêne | F77: Garde, Collecteur de la garde | G77: Radié du service actif | AA77: face1afb-cd8a-4038-b9aa-70462d72da8b
A78: FALSE | B78: Sergent-Chef | C78: Vranx | D78: Thorgar | E78: Cap Granite | F78: Garde | G78: En service actif | AA78: d70149ff-2988-430e-83dd-f348ee6f8e2a
A79: FALSE | B79: Garde | C79: Silvius | D79: Varro | E79: Rivebois | F79: Garde | G79: En service actif | AA79: 46012936-87b9-48f5-99b8-d8bde9f4c43f
A80: TRUE | B80: Garde | C80: Jo'Vakhet | E80: Eclaireur | F80: Eclaireur, Garde | G80: En service actif | AA80: eee6681e-896a-4ac9-a320-448ae32e4dfe
A81: TRUE | B81: Capitaine | C81: Ra'zir | D81: Poing-de-fer | E81: Bois-de-Chêne | F81: Garde, Collecteur de la garde | G81: En service actif | AA81: 57f010a2-a8cd-4d97-90e1-8028f4dad1cb
A82: TRUE | B82: Sergent-Chef | C82: Björn | D82: Horudin | E82: Bois-de-Chêne | F82: Garde | G82: En service actif | AA82: cd84082b-c1f6-4132-abe1-70618fb5a084
A83: TRUE | B83: Garde | C83: Simon | D83: Démont | E83: Bois-de-Chêne | F83: Garde | G83: Déserteur | AA83: 6aaeb6d4-847e-472a-8696-a2ef25ba098d
A84: FALSE | B84: Sergent-Chef | C84: Thorulf | E84: Bois-de-Chêne | F84: Garde | G84: En service actif | AA84: afb4ffb6-1d2d-4622-b35f-d6e6c936a3ee
A85: FALSE | B85: Garde | C85: Aranthir | E85: Bois-de-Chêne | F85: Garde, Eclaireur | G85: Démissionnaire | AA85: ac782c10-e4f7-40fa-aaef-180ce5911145
A86: FALSE | B86: Garde | C86: Hemar | D86: War-seer | E86: Bois-de-Chêne | F86: Garde | G86: Déserteur | AA86: 6ee6abdd-b60c-411b-a58b-a87806f0fc08
A87: TRUE | B87: Garde | C87: Azan | D87: Korf | E87: Bois-de-Chêne | F87: Garde | G87: Démissionnaire | AA87: cb28b12c-9bf1-4d10-b0e3-9cc66b718297
A88: FALSE | B88: Garde | C88: Balmyra | E88: Bois-de-Chêne | F88: Garde | G88: En service actif | AA88: 301c60b3-011f-4563-90d9-1c464fa4bdad
A89: FALSE | B89: Garde | C89: Sigvard | D89: Coeurebene | E89: Cap Granite | F89: Garde | G89: En service actif | AA89: b1c24e40-9761-4a8f-bd58-d4aa4dde3b7e
A90: FALSE | B90: Garde | C90: Chasse-poulet | E90: Rivebois | F90: Garde | G90: En service actif | AA90: 5bc6c710-3aa1-4543-ad0e-cdce61d17e5c
A91: FALSE | B91: Garde | C91: Meta Peau de Braise | E91: Faubourgs de Blancherive | G91: Radié du service actif | AA91: ab16ca18-b3d6-4ade-aabb-f220936bdb8b
A92: FALSE | B92: Garde | C92: Hrolf | D92: Fine-Lame | E92: Rivebois | F92: Garde | G92: En service actif | AA92: ccf33449-f0ce-420a-9825-1498b7035493
A93: FALSE | B93: Caporal | C93: Laguerta | D93: Fende-Sillon | E93: Rivebois | F93: Garde | G93: En service actif | AA93: 0404ac94-b63b-44e7-9763-06ab70f5b162
A94: FALSE | B94: Garde | C94: Naevor | D94: Feuille-Sombre | E94: Rivebois | F94: Garde | G94: En service actif | AA94: e1c7c522-0129-44c2-b785-7299c79ae3b3
A95: FALSE | B95: Recrue | C95: Razim | D95: Al-Rihad | E95: Cité de Blancherive | F95: Garde | G95: Radié du service actif | AA95: 09a58636-901b-4784-9000-10451a1ec2e9
A96: FALSE | B96: Lieutenant-Chef | C96: Ulfgar | D96: L'oiseau de nuit | E96: Rivebois | F96: Garde | G96: En service actif | AA96: f5bd71db-1e6f-4fd2-ad14-83cd302789c8
A97: TRUE | B97: Lieutenant-Chef | C97: Thov | D97: Lémartes | E97: Faubourgs de Blancherive | F97: Garde | G97: En service actif | AA97: f0cb3e9c-7ad3-4470-913f-de86110c910f
A98: FALSE | B98: Garde | C98: Asvald'ur | E98: Faubourgs de Blancherive | G98: Démissionnaire | AA98: 920ff286-90b4-4601-b045-f42717fd37fd
A99: FALSE | B99: Recrue | C99: Alza'gar | E99: Cité de Blancherive | F99: Garde | G99: Démissionnaire | AA99: 83d0f55b-2452-4ecd-9bd8-704603fd6925
A100: TRUE | B100: Lieutenant | C100: Claudus | E100: Faubourgs de Blancherive | F100: Garde | G100: En service actif | AA100: 680988bb-a857-4edc-be2e-f27afbbaff2c
...

Sheet Présences
A1: Semaine | B1: Corps de garde | C1: Grade | D1: Prénom | E1: Nom | F1: Lun | G1: Mar | H1: Mer | I1: Jeu | J1: Ven | K1: Sam | L1: Dim | M1: Jours présents | N1: Solde | O1: Payé
A2: 35 | B2: Cap Granite | C2: Garde | D2: Bakhir | F2: FALSE | G2: FALSE | H2: FALSE | I2: FALSE | J2: FALSE | K2: FALSE | L2: FALSE | M2: =COUNTIF(F2:L2,TRUE) -> 0 | N2: =IF(OR(B2="Hird du Jarl",C2="Recrue"),0,IF(C2="Aspirant-Garde",M2*50/2,M2*50)) -> 0 | O2: FALSE
A3: 35 | B3: Cap Granite | C3: Garde | D3: Barnabas | E3: Tharmr | F3: FALSE | G3: FALSE | H3: FALSE | I3: FALSE | J3: FALSE | K3: FALSE | L3: FALSE | M3: =COUNTIF(F3:L3,TRUE) -> 0 | N3: =IF(OR(B3="Hird du Jarl",C3="Recrue"),0,IF(C3="Aspirant-Garde",M3*50/2,M3*50)) -> 0 | O3: FALSE | Q3: N'ajoutez jamais de ligne sur cette feuille. Si l'effectif a été modifié dans la page Effectifs, lancez le script "regenererSemaineCourante" pour ajouter les entrées manquantes ou changés tout en conservant les données précédentes.
A4: 35 | B4: Cap Granite | C4: Garde | D4: Drakgor | E4: gro-Drakar | F4: FALSE | G4: FALSE | H4: FALSE | I4: FALSE | J4: FALSE | K4: FALSE | L4: FALSE | M4: =COUNTIF(F4:L4,TRUE) -> 0 | N4: =IF(OR(B4="Hird du Jarl",C4="Recrue"),0,IF(C4="Aspirant-Garde",M4*50/2,M4*50)) -> 0 | O4: FALSE
A5: 35 | B5: Cap Granite | C5: Capitaine | D5: Hastelvin | F5: FALSE | G5: FALSE | H5: FALSE | I5: FALSE | J5: FALSE | K5: FALSE | L5: FALSE | M5: =COUNTIF(F5:L5,TRUE) -> 0 | N5: =IF(OR(B5="Hird du Jarl",C5="Recrue"),0,IF(C5="Aspirant-Garde",M5*50/2,M5*50)) -> 0 | O5: FALSE
A6: 35 | B6: Cap Granite | C6: Garde | D6: Malivor | E6: Xernes | F6: FALSE | G6: FALSE | H6: FALSE | I6: FALSE | J6: FALSE | K6: FALSE | L6: FALSE | M6: =COUNTIF(F6:L6,TRUE) -> 0 | N6: =IF(OR(B6="Hird du Jarl",C6="Recrue"),0,IF(C6="Aspirant-Garde",M6*50/2,M6*50)) -> 0 | O6: FALSE
A7: 35 | B7: Cap Granite | C7: Lieutenant-Chef | D7: Pavis | E7: Gurdalval | F7: FALSE | G7: FALSE | H7: FALSE | I7: FALSE | J7: FALSE | K7: FALSE | L7: FALSE | M7: =COUNTIF(F7:L7,TRUE) -> 0 | N7: =IF(OR(B7="Hird du Jarl",C7="Recrue"),0,IF(C7="Aspirant-Garde",M7*50/2,M7*50)) -> 0 | O7: FALSE
A8: 35 | B8: Cap Granite | C8: Garde | D8: Ragniir | E8: Coeurebene | F8: FALSE | G8: FALSE | H8: FALSE | I8: FALSE | J8: FALSE | K8: FALSE | L8: FALSE | M8: =COUNTIF(F8:L8,TRUE) -> 0 | N8: =IF(OR(B8="Hird du Jarl",C8="Recrue"),0,IF(C8="Aspirant-Garde",M8*50/2,M8*50)) -> 0 | O8: FALSE
A9: 35 | B9: Cap Granite | C9: Garde | D9: Starkos | E9: Coeurebene | F9: FALSE | G9: FALSE | H9: FALSE | I9: FALSE | J9: FALSE | K9: FALSE | L9: FALSE | M9: =COUNTIF(F9:L9,TRUE) -> 0 | N9: =IF(OR(B9="Hird du Jarl",C9="Recrue"),0,IF(C9="Aspirant-Garde",M9*50/2,M9*50)) -> 0 | O9: FALSE
A10: 35 | B10: Cité de Blancherive | C10: Garde | D10: Al'Dran | F10: TRUE | G10: TRUE | H10: TRUE | I10: TRUE | J10: TRUE | K10: TRUE | L10: TRUE | M10: =COUNTIF(F10:L10,TRUE) -> 7 | N10: =IF(OR(B10="Hird du Jarl",C10="Recrue"),0,IF(C10="Aspirant-Garde",M10*50/2,M10*50)) -> 350 | O10: TRUE
A11: 35 | B11: Cité de Blancherive | C11: Recrue | D11: Aldric | E11: Cendre-coeur | F11: FALSE | G11: FALSE | H11: FALSE | I11: FALSE | J11: FALSE | K11: TRUE | L11: FALSE | M11: =COUNTIF(F11:L11,TRUE) -> 1 | N11: =IF(OR(B11="Hird du Jarl",C11="Recrue"),0,IF(C11="Aspirant-Garde",M11*50/2,M11*50)) -> 0 | O11: FALSE
A12: 35 | B12: Cité de Blancherive | C12: Garde | D12: Andor | E12: Viraes | F12: FALSE | G12: FALSE | H12: FALSE | I12: FALSE | J12: FALSE | K12: FALSE | L12: FALSE | M12: =COUNTIF(F12:L12,TRUE) -> 0 | N12: =IF(OR(B12="Hird du Jarl",C12="Recrue"),0,IF(C12="Aspirant-Garde",M12*50/2,M12*50)) -> 0 | O12: TRUE
A13: 35 | B13: Cité de Blancherive | C13: Capitaine | D13: Astrid | E13: Lame-Fine | F13: TRUE | G13: TRUE | H13: TRUE | I13: FALSE | J13: TRUE | K13: TRUE | L13: TRUE | M13: =COUNTIF(F13:L13,TRUE) -> 6 | N13: =IF(OR(B13="Hird du Jarl",C13="Recrue"),0,IF(C13="Aspirant-Garde",M13*50/2,M13*50)) -> 300 | O13: TRUE
A14: 35 | B14: Cité de Blancherive | C14: Garde | D14: Athlan | F14: FALSE | G14: TRUE | H14: TRUE | I14: FALSE | J14: FALSE | K14: FALSE | L14: FALSE | M14: =COUNTIF(F14:L14,TRUE) -> 2 | N14: =IF(OR(B14="Hird du Jarl",C14="Recrue"),0,IF(C14="Aspirant-Garde",M14*50/2,M14*50)) -> 100 | O14: TRUE
A15: 35 | B15: Cité de Blancherive | C15: Garde | D15: Bjorn | E15: Kornseen | F15: TRUE | G15: TRUE | H15: FALSE | I15: TRUE | J15: FALSE | K15: TRUE | L15: TRUE | M15: =COUNTIF(F15:L15,TRUE) -> 5 | N15: =IF(OR(B15="Hird du Jarl",C15="Recrue"),0,IF(C15="Aspirant-Garde",M15*50/2,M15*50)) -> 250 | O15: TRUE
A16: 35 | B16: Cité de Blancherive | C16: Sergent | D16: Daric | F16: FALSE | G16: FALSE | H16: FALSE | I16: FALSE | J16: FALSE | K16: FALSE | L16: FALSE | M16: =COUNTIF(F16:L16,TRUE) -> 0 | N16: =IF(OR(B16="Hird du Jarl",C16="Recrue"),0,IF(C16="Aspirant-Garde",M16*50/2,M16*50)) -> 0 | O16: FALSE
A17: 35 | B17: Cité de Blancherive | C17: Aspirant-Garde | D17: Eldrim | E17: Hache-Grise | F17: FALSE | G17: FALSE | H17: FALSE | I17: FALSE | J17: FALSE | K17: FALSE | L17: FALSE | M17: =COUNTIF(F17:L17,TRUE) -> 0 | N17: =IF(OR(B17="Hird du Jarl",C17="Recrue"),0,IF(C17="Aspirant-Garde",M17*50/2,M17*50)) -> 0 | O17: FALSE
A18: 35 | B18: Cité de Blancherive | C18: Garde | D18: Encore-Un-Espoir | F18: FALSE | G18: FALSE | H18: FALSE | I18: FALSE | J18: FALSE | K18: FALSE | L18: FALSE | M18: =COUNTIF(F18:L18,TRUE) -> 0 | N18: =IF(OR(B18="Hird du Jarl",C18="Recrue"),0,IF(C18="Aspirant-Garde",M18*50/2,M18*50)) -> 0 | O18: FALSE
A19: 35 | B19: Cité de Blancherive | C19: Sergent | D19: Erwan | F19: TRUE | G19: TRUE | H19: FALSE | I19: TRUE | J19: FALSE | K19: TRUE | L19: TRUE | M19: =COUNTIF(F19:L19,TRUE) -> 5 | N19: =IF(OR(B19="Hird du Jarl",C19="Recrue"),0,IF(C19="Aspirant-Garde",M19*50/2,M19*50)) -> 250 | O19: TRUE
A20: 35 | B20: Cité de Blancherive | C20: Lieutenant | D20: Gisbern | E20: Isenbjorn | F20: TRUE | G20: TRUE | H20: FALSE | I20: FALSE | J20: TRUE | K20: FALSE | L20: FALSE | M20: =COUNTIF(F20:L20,TRUE) -> 3 | N20: =IF(OR(B20="Hird du Jarl",C20="Recrue"),0,IF(C20="Aspirant-Garde",M20*50/2,M20*50)) -> 150 | O20: TRUE | Q20: Solde anticipée totale de la semaine courante | R20: =SUMIF('Présences'!A2:A619,ISOWEEKNUM(TODAY()),'Présences'!N2:N619) -> 0
A21: 35 | B21: Cité de Blancherive | C21: Recrue | D21: Grub | F21: TRUE | G21: TRUE | H21: TRUE | I21: FALSE | J21: FALSE | K21: FALSE | L21: FALSE | M21: =COUNTIF(F21:L21,TRUE) -> 3 | N21: =IF(OR(B21="Hird du Jarl",C21="Recrue"),0,IF(C21="Aspirant-Garde",M21*50/2,M21*50)) -> 0 | O21: FALSE | Q21: Solde totale à payer des semaines passés | R21: =SUMIFS( 'Présences'!N2:N619, 'Présences'!N2:N619,">0", 'Présences'!O2:O619,FALSE ) -> 8500
A22: 35 | B22: Cité de Blancherive | C22: Caporal-Chef | D22: Ilflynn | F22: TRUE | G22: TRUE | H22: TRUE | I22: TRUE | J22: TRUE | K22: TRUE | L22: TRUE | M22: =COUNTIF(F22:L22,TRUE) -> 7 | N22: =IF(OR(B22="Hird du Jarl",C22="Recrue"),0,IF(C22="Aspirant-Garde",M22*50/2,M22*50)) -> 350 | O22: TRUE | Q22: Soldes impayés des semaines passés | R22: =COUNTIFS( 'Présences'!N2:N619,">0", 'Présences'!O2:O619,FALSE ) -> 47
A23: 35 | B23: Cité de Blancherive | C23: Garde | D23: Kendall | E23: Delamare | F23: TRUE | G23: TRUE | H23: FALSE | I23: TRUE | J23: FALSE | K23: TRUE | L23: TRUE | M23: =COUNTIF(F23:L23,TRUE) -> 5 | N23: =IF(OR(B23="Hird du Jarl",C23="Recrue"),0,IF(C23="Aspirant-Garde",M23*50/2,M23*50)) -> 250 | O23: TRUE
A24: 35 | B24: Cité de Blancherive | C24: Recrue | D24: Léonce | E24: Réve-épine | F24: FALSE | G24: FALSE | H24: FALSE | I24: FALSE | J24: FALSE | K24: FALSE | L24: FALSE | M24: =COUNTIF(F24:L24,TRUE) -> 0 | N24: =IF(OR(B24="Hird du Jarl",C24="Recrue"),0,IF(C24="Aspirant-Garde",M24*50/2,M24*50)) -> 0 | O24: FALSE
A25: 35 | B25: Cité de Blancherive | C25: Recrue | D25: Ro'minet | F25: TRUE | G25: FALSE | H25: FALSE | I25: FALSE | J25: FALSE | K25: FALSE | L25: FALSE | M25: =COUNTIF(F25:L25,TRUE) -> 1 | N25: =IF(OR(B25="Hird du Jarl",C25="Recrue"),0,IF(C25="Aspirant-Garde",M25*50/2,M25*50)) -> 0 | O25: FALSE
A26: 35 | B26: Cité de Blancherive | C26: Lieutenant | D26: Ronin | F26: TRUE | G26: TRUE | H26: TRUE | I26: TRUE | J26: TRUE | K26: TRUE | L26: TRUE | M26: =COUNTIF(F26:L26,TRUE) -> 7 | N26: =IF(OR(B26="Hird du Jarl",C26="Recrue"),0,IF(C26="Aspirant-Garde",M26*50/2,M26*50)) -> 350 | O26: TRUE
A27: 35 | B27: Cité de Blancherive | C27: Sergent-Chef | D27: Rorik | E27: Marche-Hiver | F27: TRUE | G27: TRUE | H27: TRUE | I27: TRUE | J27: TRUE | K27: TRUE | L27: TRUE | M27: =COUNTIF(F27:L27,TRUE) -> 7 | N27: =IF(OR(B27="Hird du Jarl",C27="Recrue"),0,IF(C27="Aspirant-Garde",M27*50/2,M27*50)) -> 350 | O27: TRUE
A28: 35 | B28: Cité de Blancherive | C28: Lieutenant-Chef | D28: Ulfar | F28: TRUE | G28: FALSE | H28: TRUE | I28: FALSE | J28: TRUE | K28: FALSE | L28: TRUE | M28: =COUNTIF(F28:L28,TRUE) -> 4 | N28: =IF(OR(B28="Hird du Jarl",C28="Recrue"),0,IF(C28="Aspirant-Garde",M28*50/2,M28*50)) -> 200 | O28: TRUE
A29: 35 | B29: Cité de Blancherive | C29: Garde | D29: Wulfgar | E29: Durrock | F29: FALSE | G29: FALSE | H29: FALSE | I29: FALSE | J29: FALSE | K29: FALSE | L29: TRUE | M29: =COUNTIF(F29:L29,TRUE) -> 1 | N29: =IF(OR(B29="Hird du Jarl",C29="Recrue"),0,IF(C29="Aspirant-Garde",M29*50/2,M29*50)) -> 50 | O29: TRUE
A30: 35 | B30: Eclaireur | C30: Recrue | D30: Do'Rhazir | F30: FALSE | G30: FALSE | H30: FALSE | I30: FALSE | J30: TRUE | K30: TRUE | L30: TRUE | M30: =COUNTIF(F30:L30,TRUE) -> 3 | N30: =IF(OR(B30="Hird du Jarl",C30="Recrue"),0,IF(C30="Aspirant-Garde",M30*50/2,M30*50)) -> 0 | O30: TRUE
A31: 35 | B31: Eclaireur | C31: Capitaine | D31: Glaemorandir | E31: Oeil-Perçant | F31: TRUE | G31: TRUE | H31: TRUE | I31: TRUE | J31: TRUE | K31: TRUE | L31: TRUE | M31: =COUNTIF(F31:L31,TRUE) -> 7 | N31: =IF(OR(B31="Hird du Jarl",C31="Recrue"),0,IF(C31="Aspirant-Garde",M31*50/2,M31*50)) -> 350 | O31: TRUE
A32: 35 | B32: Eclaireur | C32: Garde | D32: Laureen | E32: Toison-de-Sang | F32: TRUE | G32: TRUE | H32: TRUE | I32: TRUE | J32: TRUE | K32: TRUE | L32: TRUE | M32: =COUNTIF(F32:L32,TRUE) -> 7 | N32: =IF(OR(B32="Hird du Jarl",C32="Recrue"),0,IF(C32="Aspirant-Garde",M32*50/2,M32*50)) -> 350 | O32: TRUE
A33: 35 | B33: Eclaireur | C33: Recrue | D33: Ma'arl | F33: FALSE | G33: TRUE | H33: TRUE | I33: FALSE | J33: TRUE | K33: TRUE | L33: TRUE | M33: =COUNTIF(F33:L33,TRUE) -> 5 | N33: =IF(OR(B33="Hird du Jarl",C33="Recrue"),0,IF(C33="Aspirant-Garde",M33*50/2,M33*50)) -> 0 | O33: TRUE
A34: 35 | B34: Eclaireur | C34: Garde | D34: Magnar | E34: Traquebrume | F34: TRUE | G34: TRUE | H34: TRUE | I34: TRUE | J34: TRUE | K34: FALSE | L34: TRUE | M34: =COUNTIF(F34:L34,TRUE) -> 6 | N34: =IF(OR(B34="Hird du Jarl",C34="Recrue"),0,IF(C34="Aspirant-Garde",M34*50/2,M34*50)) -> 300 | O34: TRUE
A35: 35 | B35: Eclaireur | C35: Lieutenant | D35: Thorin | E35: Rivegel | F35: FALSE | G35: FALSE | H35: FALSE | I35: FALSE | J35: FALSE | K35: FALSE | L35: FALSE | M35: =COUNTIF(F35:L35,TRUE) -> 0 | N35: =IF(OR(B35="Hird du Jarl",C35="Recrue"),0,IF(C35="Aspirant-Garde",M35*50/2,M35*50)) -> 0 | O35: FALSE
A36: 35 | B36: Etat-Major | C36: Commandant | D36: Filoki | F36: TRUE | G36: TRUE | H36: TRUE | I36: TRUE | J36: TRUE | K36: TRUE | L36: TRUE | M36: =COUNTIF(F36:L36,TRUE) -> 7 | N36: =IF(OR(B36="Hird du Jarl",C36="Recrue"),0,IF(C36="Aspirant-Garde",M36*50/2,M36*50)) -> 350 | O36: TRUE
A37: 35 | B37: Etat-Major | C37: Maréchal | D37: Lazabard | E37: Jemelred | F37: FALSE | G37: TRUE | H37: FALSE | I37: FALSE | J37: TRUE | K37: FALSE | L37: FALSE | M37: =COUNTIF(F37:L37,TRUE) -> 2 | N37: =IF(OR(B37="Hird du Jarl",C37="Recrue"),0,IF(C37="Aspirant-Garde",M37*50/2,M37*50)) -> 100 | O37: TRUE
A38: 35 | B38: Faubourgs de Blancherive | C38: Sergent-Chef | D38: Astrild | F38: FALSE | G38: FALSE | H38: FALSE | I38: FALSE | J38: FALSE | K38: FALSE | L38: FALSE | M38: =COUNTIF(F38:L38,TRUE) -> 0 | N38: =IF(OR(B38="Hird du Jarl",C38="Recrue"),0,IF(C38="Aspirant-Garde",M38*50/2,M38*50)) -> 0 | O38: FALSE
A39: 35 | B39: Faubourgs de Blancherive | C39: Garde | D39: Bernis | F39: FALSE | G39: FALSE | H39: FALSE | I39: FALSE | J39: FALSE | K39: FALSE | L39: FALSE | M39: =COUNTIF(F39:L39,TRUE) -> 0 | N39: =IF(OR(B39="Hird du Jarl",C39="Recrue"),0,IF(C39="Aspirant-Garde",M39*50/2,M39*50)) -> 0 | O39: FALSE
A40: 35 | B40: Faubourgs de Blancherive | C40: Garde | D40: Darina | F40: FALSE | G40: FALSE | H40: FALSE | I40: FALSE | J40: FALSE | K40: FALSE | L40: FALSE | M40: =COUNTIF(F40:L40,TRUE) -> 0 | N40: =IF(OR(B40="Hird du Jarl",C40="Recrue"),0,IF(C40="Aspirant-Garde",M40*50/2,M40*50)) -> 0 | O40: FALSE
A41: 35 | B41: Faubourgs de Blancherive | C41: Lieutenant | D41: Gorvin | E41: Le-Moite | F41: FALSE | G41: FALSE | H41: FALSE | I41: FALSE | J41: FALSE | K41: FALSE | L41: FALSE | M41: =COUNTIF(F41:L41,TRUE) -> 0 | N41: =IF(OR(B41="Hird du Jarl",C41="Recrue"),0,IF(C41="Aspirant-Garde",M41*50/2,M41*50)) -> 0 | O41: FALSE
A42: 35 | B42: Faubourgs de Blancherive | C42: Lieutenant-Chef | D42: Il-draz | E42: De Chasse-au-bois | F42: FALSE | G42: FALSE | H42: FALSE | I42: FALSE | J42: FALSE | K42: FALSE | L42: FALSE | M42: =COUNTIF(F42:L42,TRUE) -> 0 | N42: =IF(OR(B42="Hird du Jarl",C42="Recrue"),0,IF(C42="Aspirant-Garde",M42*50/2,M42*50)) -> 0 | O42: FALSE
A43: 35 | B43: Faubourgs de Blancherive | C43: Recrue | D43: Ina'ra | F43: FALSE | G43: FALSE | H43: FALSE | I43: FALSE | J43: FALSE | K43: FALSE | L43: FALSE | M43: =COUNTIF(F43:L43,TRUE) -> 0 | N43: =IF(OR(B43="Hird du Jarl",C43="Recrue"),0,IF(C43="Aspirant-Garde",M43*50/2,M43*50)) -> 0 | O43: FALSE
A44: 35 | B44: Faubourgs de Blancherive | C44: Sergent | D44: Ja'Shanir | F44: FALSE | G44: FALSE | H44: FALSE | I44: FALSE | J44: FALSE | K44: FALSE | L44: FALSE | M44: =COUNTIF(F44:L44,TRUE) -> 0 | N44: =IF(OR(B44="Hird du Jarl",C44="Recrue"),0,IF(C44="Aspirant-Garde",M44*50/2,M44*50)) -> 0 | O44: FALSE
A45: 35 | B45: Faubourgs de Blancherive | C45: Sergent | D45: Jeebam-dee | F45: FALSE | G45: FALSE | H45: FALSE | I45: FALSE | J45: FALSE | K45: FALSE | L45: FALSE | M45: =COUNTIF(F45:L45,TRUE) -> 0 | N45: =IF(OR(B45="Hird du Jarl",C45="Recrue"),0,IF(C45="Aspirant-Garde",M45*50/2,M45*50)) -> 0 | O45: FALSE
A46: 35 | B46: Faubourgs de Blancherive | C46: Capitaine | D46: Kah-Shir | E46: Sombre Griffe | F46: FALSE | G46: FALSE | H46: FALSE | I46: FALSE | J46: FALSE | K46: FALSE | L46: FALSE | M46: =COUNTIF(F46:L46,TRUE) -> 0 | N46: =IF(OR(B46="Hird du Jarl",C46="Recrue"),0,IF(C46="Aspirant-Garde",M46*50/2,M46*50)) -> 0 | O46: FALSE
A47: 35 | B47: Faubourgs de Blancherive | C47: Garde | D47: Léonce | F47: FALSE | G47: FALSE | H47: FALSE | I47: FALSE | J47: FALSE | K47: FALSE | L47: FALSE | M47: =COUNTIF(F47:L47,TRUE) -> 0 | N47: =IF(OR(B47="Hird du Jarl",C47="Recrue"),0,IF(C47="Aspirant-Garde",M47*50/2,M47*50)) -> 0 | O47: FALSE
A48: 35 | B48: Faubourgs de Blancherive | C48: Garde | D48: Njalda | F48: FALSE | G48: FALSE | H48: FALSE | I48: FALSE | J48: FALSE | K48: FALSE | L48: FALSE | M48: =COUNTIF(F48:L48,TRUE) -> 0 | N48: =IF(OR(B48="Hird du Jarl",C48="Recrue"),0,IF(C48="Aspirant-Garde",M48*50/2,M48*50)) -> 0 | O48: FALSE
A49: 35 | B49: Faubourgs de Blancherive | C49: Garde | D49: Smaug | F49: FALSE | G49: FALSE | H49: FALSE | I49: FALSE | J49: FALSE | K49: FALSE | L49: FALSE | M49: =COUNTIF(F49:L49,TRUE) -> 0 | N49: =IF(OR(B49="Hird du Jarl",C49="Recrue"),0,IF(C49="Aspirant-Garde",M49*50/2,M49*50)) -> 0 | O49: FALSE
A50: 35 | B50: Faubourgs de Blancherive | C50: Garde | D50: Torald | F50: FALSE | G50: FALSE | H50: FALSE | I50: FALSE | J50: FALSE | K50: FALSE | L50: FALSE | M50: =COUNTIF(F50:L50,TRUE) -> 0 | N50: =IF(OR(B50="Hird du Jarl",C50="Recrue"),0,IF(C50="Aspirant-Garde",M50*50/2,M50*50)) -> 0 | O50: FALSE
A51: 35 | B51: Hird du Jarl | C51: Garde | D51: Gronk | E51: Grognon | F51: FALSE | G51: FALSE | H51: FALSE | I51: FALSE | J51: FALSE | K51: FALSE | L51: FALSE | M51: =COUNTIF(F51:L51,TRUE) -> 0 | N51: =IF(OR(B51="Hird du Jarl",C51="Recrue"),0,IF(C51="Aspirant-Garde",M51*50/2,M51*50)) -> 0 | O51: FALSE
A52: 35 | B52: Hird du Jarl | C52: Garde | D52: Kronk | E52: Grognon | F52: FALSE | G52: FALSE | H52: FALSE | I52: FALSE | J52: FALSE | K52: FALSE | L52: FALSE | M52: =COUNTIF(F52:L52,TRUE) -> 0 | N52: =IF(OR(B52="Hird du Jarl",C52="Recrue"),0,IF(C52="Aspirant-Garde",M52*50/2,M52*50)) -> 0 | O52: FALSE
A53: 35 | B53: Hird du Jarl | C53: Garde | D53: S'Khar | F53: FALSE | G53: FALSE | H53: FALSE | I53: FALSE | J53: FALSE | K53: FALSE | L53: FALSE | M53: =COUNTIF(F53:L53,TRUE) -> 0 | N53: =IF(OR(B53="Hird du Jarl",C53="Recrue"),0,IF(C53="Aspirant-Garde",M53*50/2,M53*50)) -> 0 | O53: FALSE
A54: 35 | B54: Rivebois | C54: Capitaine | D54: Sigurd | E54: Grise-Toison | F54: FALSE | G54: FALSE | H54: FALSE | I54: FALSE | J54: FALSE | K54: FALSE | L54: FALSE | M54: =COUNTIF(F54:L54,TRUE) -> 0 | N54: =IF(OR(B54="Hird du Jarl",C54="Recrue"),0,IF(C54="Aspirant-Garde",M54*50/2,M54*50)) -> 0 | O54: FALSE
A55: 36 | B55: Bois-de-Chêne | C55: Garde | D55: Aranthir | F55: FALSE | G55: FALSE | H55: FALSE | I55: FALSE | J55: FALSE | K55: FALSE | L55: FALSE | M55: =COUNTIF(F55:L55,TRUE) -> 0 | N55: =M55*50 -> 0 | O55: FALSE
A56: 36 | B56: Bois-de-Chêne | C56: Garde | D56: Azan | E56: Korf | F56: FALSE | G56: FALSE | H56: FALSE | I56: FALSE | J56: FALSE | K56: FALSE | L56: FALSE | M56: =COUNTIF(F56:L56,TRUE) -> 0 | N56: =M56*50 -> 0 | O56: FALSE
A57: 36 | B57: Bois-de-Chêne | C57: Recrue | D57: Balmyra | F57: FALSE | G57: FALSE | H57: FALSE | I57: FALSE | J57: FALSE | K57: FALSE | L57: FALSE | M57: =COUNTIF(F57:L57,TRUE) -> 0 | N57: =M57*0 -> 0 | O57: FALSE
A58: 36 | B58: Bois-de-Chêne | C58: Garde | D58: Björn | E58: Horudin | F58: FALSE | G58: FALSE | H58: FALSE | I58: FALSE | J58: FALSE | K58: FALSE | L58: FALSE | M58: =COUNTIF(F58:L58,TRUE) -> 0 | N58: =M58*50 -> 0 | O58: FALSE
A59: 36 | B59: Bois-de-Chêne | C59: Garde | D59: Hemar | E59: War-seer | F59: FALSE | G59: FALSE | H59: FALSE | I59: FALSE | J59: FALSE | K59: FALSE | L59: FALSE | M59: =COUNTIF(F59:L59,TRUE) -> 0 | N59: =M59*50 -> 0 | O59: FALSE
A60: 36 | B60: Bois-de-Chêne | C60: Capitaine | D60: Ra'zir | E60: Poing-de-fer | F60: FALSE | G60: FALSE | H60: FALSE | I60: FALSE | J60: FALSE | K60: FALSE | L60: FALSE | M60: =COUNTIF(F60:L60,TRUE) -> 0 | N60: =M60*50 -> 0 | O60: FALSE
A61: 36 | B61: Bois-de-Chêne | C61: Major | D61: Rusco | F61: FALSE | G61: FALSE | H61: FALSE | I61: FALSE | J61: FALSE | K61: FALSE | L61: FALSE | M61: =COUNTIF(F61:L61,TRUE) -> 0 | N61: =M61*50 -> 0 | O61: FALSE
A62: 36 | B62: Bois-de-Chêne | C62: Garde | D62: Simon | E62: Démont | F62: FALSE | G62: FALSE | H62: FALSE | I62: FALSE | J62: FALSE | K62: FALSE | L62: FALSE | M62: =COUNTIF(F62:L62,TRUE) -> 0 | N62: =M62*50 -> 0 | O62: FALSE
A63: 36 | B63: Bois-de-Chêne | C63: Garde | D63: Thorulf | F63: FALSE | G63: FALSE | H63: FALSE | I63: FALSE | J63: FALSE | K63: FALSE | L63: FALSE | M63: =COUNTIF(F63:L63,TRUE) -> 0 | N63: =M63*50 -> 0 | O63: FALSE
A64: 36 | B64: Cap Granite | C64: Garde | D64: Bakhir | F64: TRUE | G64: TRUE | H64: TRUE | I64: FALSE | J64: TRUE | K64: TRUE | L64: FALSE | M64: =COUNTIF(F64:L64,TRUE) -> 5 | N64: =M64*50 -> 250 | O64: TRUE
A65: 36 | B65: Cap Granite | C65: Sergent-Chef | D65: Barnabas | E65: Tharmr | F65: TRUE | G65: TRUE | H65: FALSE | I65: TRUE | J65: TRUE | K65: TRUE | L65: FALSE | M65: =COUNTIF(F65:L65,TRUE) -> 5 | N65: =M65*50 -> 250 | O65: TRUE
A66: 36 | B66: Cap Granite | C66: Capitaine | D66: Hastelvin | F66: FALSE | G66: FALSE | H66: FALSE | I66: FALSE | J66: FALSE | K66: FALSE | L66: FALSE | M66: =COUNTIF(F66:L66,TRUE) -> 0 | N66: =M66*50 -> 0 | O66: TRUE
A67: 36 | B67: Cap Granite | C67: Garde | D67: Malivor | E67: Xernes | F67: TRUE | G67: TRUE | H67: TRUE | I67: TRUE | J67: TRUE | K67: FALSE | L67: FALSE | M67: =COUNTIF(F67:L67,TRUE) -> 5 | N67: =M67*50 -> 250 | O67: TRUE
A68: 36 | B68: Cap Granite | C68: Lieutenant-Chef | D68: Pavis | E68: Gurdalval | F68: FALSE | G68: FALSE | H68: FALSE | I68: TRUE | J68: FALSE | K68: FALSE | L68: FALSE | M68: =COUNTIF(F68:L68,TRUE) -> 1 | N68: =M68*50 -> 50 | O68: TRUE
A69: 36 | B69: Cap Granite | C69: Garde | D69: Sigvard | E69: Coeurebene | F69: FALSE | G69: FALSE | H69: FALSE | I69: FALSE | J69: FALSE | K69: FALSE | L69: TRUE | M69: =COUNTIF(F69:L69,TRUE) -> 1 | N69: =M69*50 -> 50 | O69: TRUE
A70: 36 | B70: Cap Granite | C70: Sergent-Chef | D70: Starkos | E70: Coeurebene | F70: TRUE | G70: TRUE | H70: TRUE | I70: TRUE | J70: TRUE | K70: TRUE | L70: TRUE | M70: =COUNTIF(F70:L70,TRUE) -> 7 | N70: =M70*50 -> 350 | O70: TRUE
A71: 36 | B71: Cap Granite | C71: Recrue | D71: Vranx | E71: Thorgar | F71: FALSE | G71: FALSE | H71: FALSE | I71: TRUE | J71: TRUE | K71: FALSE | L71: FALSE | M71: =COUNTIF(F71:L71,TRUE) -> 2 | N71: =M71*0 -> 0 | O71: TRUE
A72: 36 | B72: Cité de Blancherive | C72: Garde | D72: Al'Dran | F72: FALSE | G72: FALSE | H72: FALSE | I72: FALSE | J72: FALSE | K72: FALSE | L72: FALSE | M72: =COUNTIF(F72:L72,TRUE) -> 0 | N72: =M72*50 -> 0 | O72: FALSE
A73: 36 | B73: Cité de Blancherive | C73: Recrue | D73: Aldric | E73: Cendre-coeur | F73: FALSE | G73: TRUE | H73: FALSE | I73: FALSE | J73: FALSE | K73: FALSE | L73: FALSE | M73: =COUNTIF(F73:L73,TRUE) -> 1 | N73: =M73*0 -> 0 | O73: FALSE
A74: 36 | B74: Cité de Blancherive | C74: Capitaine | D74: Astrid | E74: Lame-Fine | F74: TRUE | G74: TRUE | H74: TRUE | I74: TRUE | J74: TRUE | K74: TRUE | L74: TRUE | M74: =COUNTIF(F74:L74,TRUE) -> 7 | N74: =M74*50 -> 350 | O74: TRUE
A75: 36 | B75: Cité de Blancherive | C75: Garde | D75: Bjorn | E75: Kornseen | F75: TRUE | G75: TRUE | H75: TRUE | I75: TRUE | J75: TRUE | K75: TRUE | L75: FALSE | M75: =COUNTIF(F75:L75,TRUE) -> 6 | N75: =M75*50 -> 300 | O75: TRUE
A76: 36 | B76: Cité de Blancherive | C76: Lieutenant | D76: Encore-Un-Espoir | F76: TRUE | G76: TRUE | H76: TRUE | I76: FALSE | J76: FALSE | K76: TRUE | L76: TRUE | M76: =COUNTIF(F76:L76,TRUE) -> 5 | N76: =M76*50 -> 250 | O76: TRUE
A77: 36 | B77: Cité de Blancherive | C77: Sergent-Chef | D77: Erwan | F77: TRUE | G77: FALSE | H77: TRUE | I77: TRUE | J77: FALSE | K77: TRUE | L77: FALSE | M77: =COUNTIF(F77:L77,TRUE) -> 4 | N77: =M77*50 -> 200 | O77: TRUE
A78: 36 | B78: Cité de Blancherive | C78: Lieutenant-Chef | D78: Gisbern | E78: Isenbjorn | F78: FALSE | G78: TRUE | H78: FALSE | I78: TRUE | J78: TRUE | K78: FALSE | L78: TRUE | M78: =COUNTIF(F78:L78,TRUE) -> 4 | N78: =M78*50 -> 200 | O78: TRUE
A79: 36 | B79: Cité de Blancherive | C79: Caporal-Chef | D79: Ilflynn | F79: TRUE | G79: TRUE | H79: TRUE | I79: TRUE | J79: FALSE | K79: TRUE | L79: TRUE | M79: =COUNTIF(F79:L79,TRUE) -> 6 | N79: =M79*50 -> 300 | O79: TRUE
A80: 36 | B80: Cité de Blancherive | C80: Garde | D80: Kendall | E80: Delamare | F80: FALSE | G80: TRUE | H80: TRUE | I80: TRUE | J80: TRUE | K80: TRUE | L80: TRUE | M80: =COUNTIF(F80:L80,TRUE) -> 6 | N80: =M80*50 -> 300 | O80: TRUE
A81: 36 | B81: Cité de Blancherive | C81: Lieutenant-Chef | D81: Ronin | F81: TRUE | G81: TRUE | H81: TRUE | I81: TRUE | J81: TRUE | K81: TRUE | L81: TRUE | M81: =COUNTIF(F81:L81,TRUE) -> 7 | N81: =M81*50 -> 350 | O81: TRUE
A82: 36 | B82: Cité de Blancherive | C82: Lieutenant | D82: Rorik | E82: Marche-Hiver | F82: TRUE | G82: TRUE | H82: TRUE | I82: TRUE | J82: TRUE | K82: TRUE | L82: TRUE | M82: =COUNTIF(F82:L82,TRUE) -> 7 | N82: =M82*50 -> 350 | O82: TRUE
A83: 36 | B83: Cité de Blancherive | C83: Lieutenant | D83: Thorin | E83: Rivegel | F83: FALSE | G83: FALSE | H83: FALSE | I83: FALSE | J83: FALSE | K83: FALSE | L83: FALSE | M83: =COUNTIF(F83:L83,TRUE) -> 0 | N83: =M83*50 -> 0 | O83: FALSE
A84: 36 | B84: Cité de Blancherive | C84: Garde | D84: Wulfgar | E84: Durrock | F84: TRUE | G84: TRUE | H84: TRUE | I84: TRUE | J84: TRUE | K84: TRUE | L84: TRUE | M84: =COUNTIF(F84:L84,TRUE) -> 7 | N84: =M84*50 -> 350 | O84: TRUE
A85: 36 | B85: Cité de Blancherive | C85: Cadet | D85: Zeid | E85: Le Brise-Lames | F85: FALSE | G85: TRUE | H85: TRUE | I85: TRUE | J85: TRUE | K85: TRUE | L85: TRUE | M85: =COUNTIF(F85:L85,TRUE) -> 6 | N85: =M85*50 -> 300 | O85: TRUE
A86: 36 | B86: Eclaireur | C86: Cadet | D86: Do'Rhazir | F86: TRUE | G86: TRUE | H86: TRUE | I86: TRUE | J86: TRUE | K86: TRUE | L86: TRUE | M86: =COUNTIF(F86:L86,TRUE) -> 7 | N86: =M86*50 -> 350 | O86: TRUE
A87: 36 | B87: Eclaireur | C87: Capitaine | D87: Glaemorandir | E87: Oeil-Perçant | F87: TRUE | G87: TRUE | H87: TRUE | I87: TRUE | J87: TRUE | K87: TRUE | L87: TRUE | M87: =COUNTIF(F87:L87,TRUE) -> 7 | N87: =M87*50 -> 350 | O87: TRUE
A88: 36 | B88: Eclaireur | C88: Recrue | D88: Jo'Vakhet | F88: FALSE | G88: FALSE | H88: FALSE | I88: FALSE | J88: FALSE | K88: TRUE | L88: TRUE | M88: =COUNTIF(F88:L88,TRUE) -> 2 | N88: =M88*0 -> 0 | O88: FALSE
A89: 36 | B89: Eclaireur | C89: Garde | D89: Laureen | E89: Toison-de-Sang | F89: TRUE | G89: TRUE | H89: TRUE | I89: TRUE | J89: FALSE | K89: TRUE | L89: TRUE | M89: =COUNTIF(F89:L89,TRUE) -> 6 | N89: =M89*50 -> 300 | O89: TRUE
A90: 36 | B90: Eclaireur | C90: Cadet | D90: Ma'arl | F90: TRUE | G90: TRUE | H90: TRUE | I90: TRUE | J90: TRUE | K90: TRUE | L90: TRUE | M90: =COUNTIF(F90:L90,TRUE) -> 7 | N90: =M90*50 -> 350 | O90: TRUE
A91: 36 | B91: Eclaireur | C91: Sergent-Chef | D91: Magnar | E91: Traquebrume | F91: TRUE | G91: TRUE | H91: TRUE | I91: TRUE | J91: TRUE | K91: TRUE | L91: TRUE | M91: =COUNTIF(F91:L91,TRUE) -> 7 | N91: =M91*50 -> 350 | O91: TRUE
A92: 36 | B92: Eclaireur | C92: Lieutenant-Chef | D92: Pethiceor | E92: Le Borgne | F92: FALSE | G92: FALSE | H92: FALSE | I92: FALSE | J92: FALSE | K92: FALSE | L92: TRUE | M92: =COUNTIF(F92:L92,TRUE) -> 1 | N92: =M92*50 -> 50 | O92: TRUE
A93: 36 | B93: Eclaireur | C93: Recrue | D93: Ri'Jhan | E93: MoonShadow | F93: FALSE | G93: TRUE | H93: TRUE | I93: TRUE | J93: TRUE | K93: TRUE | L93: FALSE | M93: =COUNTIF(F93:L93,TRUE) -> 5 | N93: =M93*0 -> 0 | O93: FALSE
A94: 36 | B94: Etat-Major | C94: Commander | D94: Filoki | F94: TRUE | G94: TRUE | H94: TRUE | I94: TRUE | J94: TRUE | K94: TRUE | L94: TRUE | M94: =COUNTIF(F94:L94,TRUE) -> 7 | N94: =M94*100 -> 700 | O94: TRUE
A95: 36 | B95: Etat-Major | C95: Maréchal | D95: Lazabard | E95: Jemelred | F95: TRUE | G95: FALSE | H95: TRUE | I95: FALSE | J95: FALSE | K95: FALSE | L95: FALSE | M95: =COUNTIF(F95:L95,TRUE) -> 2 | N95: =M95*50 -> 100 | O95: TRUE
A96: 36 | B96: Etat-Major | C96: Major | D96: Ulfar | F96: FALSE | G96: FALSE | H96: FALSE | I96: TRUE | J96: TRUE | K96: TRUE | L96: TRUE | M96: =COUNTIF(F96:L96,TRUE) -> 4 | N96: =M96*50 -> 200 | O96: TRUE
A97: 36 | B97: Faubourgs de Blancherive | C97: Sergent-Chef | D97: Astrild | F97: TRUE | G97: TRUE | H97: TRUE | I97: FALSE | J97: TRUE | K97: TRUE | L97: FALSE | M97: =COUNTIF(F97:L97,TRUE) -> 5 | N97: =M97*50 -> 250 | O97: TRUE
A98: 36 | B98: Faubourgs de Blancherive | C98: Garde | D98: Bernis | F98: FALSE | G98: FALSE | H98: FALSE | I98: FALSE | J98: FALSE | K98: FALSE | L98: FALSE | M98: =COUNTIF(F98:L98,TRUE) -> 0 | N98: =M98*50 -> 0 | O98: FALSE
A99: 36 | B99: Faubourgs de Blancherive | C99: Garde | D99: Darina | F99: FALSE | G99: FALSE | H99: FALSE | I99: FALSE | J99: FALSE | K99: FALSE | L99: TRUE | M99: =COUNTIF(F99:L99,TRUE) -> 1 | N99: =M99*50 -> 50 | O99: TRUE
A100: 36 | B100: Faubourgs de Blancherive | C100: Lieutenant | D100: Gorvin | E100: Le-Moite | F100: TRUE | G100: TRUE | H100: TRUE | I100: FALSE | J100: FALSE | K100: TRUE | L100: TRUE | M100: =COUNTIF(F100:L100,TRUE) -> 5 | N100: =M100*50 -> 250 | O100: TRUE
...

Sheet Ravitaillement
A1: Element | B1: Quantité
A2: Vegetal Soup | B2: 161
A3: Beef Stew | B3: 81
A4: Venison Stew | B4: 137

Sheet Amendes
A1: Date | B1: Garde | C1: Contrevenant | D1: Infraction | E1: Montant | F1: Payé | G1: Reversé
A2: 46267.5 | B2: Sigurd Grisetoison | C2: Jean Eude | D2: Art. 117 — Du vol dans les fermes | E2: 40 | F2: TRUE | G2: TRUE
A3: 46267.5 | B3: Erwan | C3: 'Lechatblanc'' | D3: Art. 114 — De la marche obligatoire | E3: 15 | F3: TRUE | G3: TRUE
A4: 46268.5 | B4: Wulfgar Durrock | C4: Daran la collectionneur | D4: Art. 114 — De la marche obligatoire | E4: 15 | F4: TRUE | G4: TRUE
A5: 46268.5 | B5: Ulfar | C5: Emric de la tour | D5: Art. 115 — Du visage découvert | E5: 15 | F5: TRUE | G5: TRUE
A6: 46268.5 | B6: Ulfar | C6: Moren Mont Sombre | D6: Art. 115 — Du visage découvert | E6: 15 | F6: TRUE | G6: TRUE
A7: 46269.5 | B7: Glaemorandir Oeil-Perçant | C7: Lucor | D7: Art. 115 — Du visage découvert | E7: 15 | F7: TRUE | G7: TRUE
A8: 46269.5 | B8: Glaemorandir Oeil-Perçant | C8: Georgeon Tranchon | D8: Art. 115 — Du visage découvert | E8: 15 | F8: TRUE | G8: TRUE
A9: 46269.5 | B9: Wulfgar Durrock | C9: mizma | D9: Art. 116 — Du saut des murailles | E9: 55 | F9: TRUE | G9: FALSE
A10: 46269.5 | B10: Wulfgar Durrock | C10: O reil | D10: Art. 114 — De la marche obligatoire | E10: 15 | F10: TRUE | G10: TRUE
A11: 46269.5 | B11: Wulfgar Durrock | C11: Bjorn | D11: Art. 115 — Du visage découvert | E11: 15 | F11: TRUE | G11: TRUE
A12: 46269.5 | B12: Wulfgar Durrock | C12: Bjorn | D12: Art. 115 — Du visage découvert | E12: 15 | F12: TRUE | G12: TRUE
A13: 46269.5 | B13: Wulfgar Durrock | C13: coupe les crocs | D13: Art. 114 — De la marche obligatoire | E13: 15 | F13: TRUE | G13: TRUE
... A41: 46273.5 | B41: Ilflynn | C41: Dornir rochever | D41: Art. 116 — Du saut des murailles | E41: 55 | F41: TRUE | G41: TRUE
A43: 46273.5 | B43: Erwan | C43: 'Vignar Corn'' | D43: Art. 6 — Des sanctions | F43: TRUE | G43: FALSE
A44: 46275.5 | B44: Wulfgar Durrock | C44: strenn pleure-vouivre | D44: Art. 115 — Du visage découvert | E44: 15 | F44: TRUE | G44: TRUE
A45: 46275.5 | B45: Wulfgar Durrock | C45: lucia | D45: Art. 115 — Du visage découvert | E45: 15 | F45: TRUE | G45: TRUE
A46: 46275.5 | B46: Wulfgar Durrock | C46: mizma | D46: Art. 114 — De la marche obligatoire | E46: 15 | F46: TRUE | G46: TRUE
A47: 46275.5 | B47: Erwan | C47: 'Amantus'' | D47: Art. 114 — De la marche obligatoire | E47: 15 | F47: TRUE | G47: TRUE
A48: 46276.5 | B48: Ma'arl | C48: ?? | D48: Art. 34 — De l’intrusion en propriété privée extérieure | E48: 50 | F48: TRUE | G48: TRUE
A49: 46278.5 | B49: Glaemorandir Oeil-Perçant | C49: Khajiit portant une couronne. Il prétend venir de Fortdhiver et a donné un faux nom. | D49: Motif personnalisé — Article 114 - De la marche obligatoire + 5 septimes car manque de respect et donne un faux nom | E49: 20 | F49: TRUE | G49: TRUE
A50: 46278.5 | B50: Ma'arl | C50: ?? | D50: Art. 116 — Du saut des murailles | E50: 55 | F50: TRUE | G50: TRUE
A51: 46278.5 | B51: Malivor Xernes | C51: ?? | D51: Motif personnalisé — Outrage à la garde + cours à Cap Granite | E51: 115 | F51: TRUE | G51: FALSE
A52: 46278.5 | B52: Malivor Xernes | C52: ?? | D52: Art. 114 — De la marche obligatoire | E52: 15 | F52: TRUE | G52: FALSE
A53: 46280.5 | B53: Wulfgar Durrock | C53: Sillas | D53: Art. 115 — Du visage découvert | E53: 15 | F53: TRUE | G53: FALSE
A54: 46280.5 | B54: Do'Rhazir | C54: Aranor | D54: Motif personnalisé — Art 116 : Saut de muraille La personne a été obéissante et gentil donc je lui ai seulement fait faire le blé pour payer ses crimes. Il m'a aussi donné une torche. | E54: 40 | F54: TRUE | G54: TRUE
A55: 46280.5 | B55: Do'Rhazir | C55: Astaera Griffacier | D55: Motif personnalisé — Art 116 : Saut de Muraille La personne a été compréhensive et gentil, et elle n'avait apparemment pas assez sur elle pour payer, elle m'a transmis la totalité de sa bourse. | E55: 50 | F55: TRUE | G55: TRUE
... A101: 46290.5 | B101: Filoki | C101: Kaelren veyr | D101: Motif personnalisé — Article 51 - Usurpation de fonction. L'individu s'est rendu de lui même. Il semblait vouloir dissiper le mal entendu. Peine commuée en travaux forcés. Remarque de suivit post libération: L'individu semble s'être présenter comme garde de Blancherive par le passé à plusieurs reprises, et huscarl du Thane de Cap Granite. Celui-ci semble mentir allègrement et aurait abuser de notre clémence. En cas de récidive. Un procès devant le jarl sera requis. | E101: 1 | F101: TRUE | G101: TRUE
E102: {=IF(D102="","",IFERROR(_xlfn.XLOOKUP(D102,SyncCodex!L:L,SyncCodex!M:M),""))} | F102: FALSE | G102: FALSE
E103: {=IF(D103="","",IFERROR(_xlfn.XLOOKUP(D103,SyncCodex!L:L,SyncCodex!M:M),""))} | F103: FALSE | G103: FALSE
E104: {=IF(D104="","",IFERROR(_xlfn.XLOOKUP(D104,SyncCodex!L:L,SyncCodex!M:M),""))} | F104: FALSE | G104: FALSE
E105: {=IF(D105="","",IFERROR(_xlfn.XLOOKUP(D105,SyncCodex!L:L,SyncCodex!M:M),""))} | F105: FALSE | G105: FALSE
E106: {=IF(D106="","",IFERROR(_xlfn.XLOOKUP(D106,SyncCodex!L:L,SyncCodex!M:M),""))} | F106: FALSE | G106: FALSE
E107: {=IF(D107="","",IFERROR(_xlfn.XLOOKUP(D107,SyncCodex!L:L,SyncCodex!M:M),""))} | F107: FALSE | G107: FALSE
E108: {=IF(D108="","",IFERROR(_xlfn.XLOOKUP(D108,SyncCodex!L:L,SyncCodex!M:M),""))} | F108: FALSE | G108: FALSE
E109: {=IF(D109="","",IFERROR(_xlfn.XLOOKUP(D109,SyncCodex!L:L,SyncCodex!M:M),""))} | F109: FALSE | G109: FALSE
E110: {=IF(D110="","",IFERROR(_xlfn.XLOOKUP(D110,SyncCodex!L:L,SyncCodex!M:M),""))} | F110: FALSE | G110: FALSE
E111: {=IF(D111="","",IFERROR(_xlfn.XLOOKUP(D111,SyncCodex!L:L,SyncCodex!M:M),""))} | F111: FALSE | G111: FALSE
E112: {=IF(D112="","",IFERROR(_xlfn.XLOOKUP(D112,SyncCodex!L:L,SyncCodex!M:M),""))} | F112: FALSE | G112: FALSE
E113: {=IF(D113="","",IFERROR(_xlfn.XLOOKUP(D113,SyncCodex!L:L,SyncCodex!M:M),""))} | F113: FALSE | G113: FALSE
... E993: {=IF(D993="","",IFERROR(_xlfn.XLOOKUP(D993,SyncCodex!L:L,SyncCodex!M:M),""))} | F993: FALSE | G993: FALSE

Sheet Prison
A1: Date | B1: Garde | C1: Détenu | D1: Cellule | E1: Infraction | F1: Durée prévue | G1: Heure d'entrée | H1: Heure de sortie prévue | I1: Libéré | J1: Saisies sur la personne | K1: Motif / Notes
A2: 46271.5 | B2: Filoki | C2: Lokir Bjornson | D2: 2 | E2: Art. 71 — De la désertion | G2: 46271.893 | I2: TRUE | J2: Ancient Nord Sword Bouclier 'acier Casque d'acier à cornes Nord Hero Sword Northern Steel Armor Steel Cuffed Boots Steel Nordic Gauntlets Bourse de 5460 septimes | K2: La bourse serai celle de la compagnie de l'écaille Rapport réalisé en présence de Kedall Delamre et Wulfgar Durrock.
A3: 46273.5 | B3: Ilflynn | C3: Alicia | D3: 1 | E3: Art. 79 — De l’usage de faux | F3: 2 | G3: 46273.624 | H3: 46273.707 | I3: TRUE | J3: [{"id":"skyrim.esm|07A91A","nom":"Cimeterre","quantite":1},{"id":"skyrim.esm|0D8E3F","nom":"Sucrelune","quantite":7}] | K3: Pour contrebande + usage de faux (se faire passer pour une personne en mission par le penitus) 350 septims. La Cimeterre est dans le tonneau des réquisitions prisonniers, et sera rendue seulement si la personne ramène les 350 septims.
A4: 46274.5 | B4: Astrid Lame-Fine | C4: Le petit con [ 2D19B ] | D4: 1 | E4: Art. 6 — Des sanctions | G4: 46274.051 | I4: TRUE | J4: [] | K4: La saisie a été effectuer par Illflynn voir avec lui. Prie Talos. Tentative de fuite a plusieurs reprises contre des gardes armés avec les armes en mains. Refus de donner l'intégralité de ses biens. Donne des coups de poings. Non respect des tortures.
A5: 46277.5 | B5: Ilflynn | C5: Gael Loïc | E5: Motif personnalisé — Il a couru vers le trône du Jarl malgré les sommations de s’arrêter. Nouvel arrivant en Bordeciel. | F5: 1 | G5: 46277.743 | H5: 46277.785 | I5: TRUE | J5: [{"id":"skyrim.esm|02F2F4","nom":"Hache de bûcheron","quantite":1},{"id":"skyrim.esm|0E3C16","nom":"Pioche","quantite":1}] | K5: Il passera le balais dans les geôles une heure
A6: 46278.5 | B6: Ilflynn | C6: Lokir | D6: 3 | E6: Motif personnalisé — Mis aux arrêts sur ordre du Jarl, pour avoir lancé un avis de recherche sur S’karr. Affaire gérée par la Hird et la cour, un procès serait prévu ce soir. Mis en cellule par Caelir Vaelion. | F6: 24 | G6: 46278.021 | H6: 46279.021 | I6: TRUE | J6: []
A7: 46281.5 | B7: Bjorn Kornseen | C7: Altor brise dent | D7: 1 | E7: Motif personnalisé — Altor Brise-Dent ne s’est présenté à aucun des deux jugements auxquels il avait pourtant préalablement confirmé sa présence.altor s'est rendu de son plein gré à la garde pour se justifier et a collaboré sans aucun problème, en attente de jugement | F7: 1 | G7: 46281.907 | H7: 46281.949 | I7: TRUE | J7: []
A8: 46282.5 | B8: Ilflynn | C8: Elerim | D8: 4 | E8: Motif personnalisé — Mis en geôles pour suspicion d’appartenir au culte de Vermina. Identifié par Astrid Lame-Fine. | F8: 2 | G8: 46281.979 | H8: 46282.062 | I8: TRUE | J8: [] | K8: Resté une heure en geôle le temps que les vigiles soient prévenus, puis un peu moins d’une heure pour l’interroger et délibérer. Après un interrogatoire Il a été jugé que les preuves n’étaient pas assez conséquentes pour le garder en geôles ou prouver qu’il soit lié de près ou de loin au culte. Néanmoins, les vigiles pensent tout comme moi qu’il est louche et qu’il faut le surveiller. Je pense aussi qu’il a menti.
A9: 46282.5 | B9: Filoki | C9: Craknar | D9: 1 | E9: Art. 35 — De l’intrusion en propriété privée intérieure | F9: 1 | G9: 46282.448 | H9: 46282.49 | I9: TRUE | J9: [{"id":"skyrim.esm|068C79","nom":"Nord Hero Battle Axe","quantite":1},{"id":"sentinel.esp|000849","nom":"Bosmer Mask","quantite":1}]
A10: 46282.5 | B10: Ilflynn | C10: Ra'zina | D10: 1 | E10: Motif personnalisé — Art. 35 — De l’intrusion en propriété privée intérieure Art. 17 - De la rébellion Art. 16 - Des menaces aggravées | F10: 24 | G10: 46282.958 | H10: 46283.958 | I10: TRUE | J10: [{"id":"","nom":"arbalette","quantite":1,"libre":true},{"id":"","nom":"Tenu khajiit","quantite":1,"libre":true},{"id":"","nom":"potion invibilité","quantite":1,"libre":true},{"id":"","nom":"potion de soin","quantite":1,"libre":true},{"id":"","nom":"lame bosmer","quantite":2,"libre":true}]
A11: 46282.5 | B11: Magnar Traquebrume | C11: Passereau (Dar'Jazir) | D11: 3 | E11: Motif personnalisé — Art. 35 — De l’intrusion en propriété privée intérieure Art. 17 - De la rébellion Art. 16 - Des menaces aggravées | F11: 24 | G11: 46282.958 | H11: 46283.958 | I11: TRUE | J11: [{"id":"","nom":"Crochet","quantite":95,"libre":true},{"id":"","nom":"Potion invisibilité prolongé","quantite":1,"libre":true},{"id":"","nom":"Tenue Khajiit","quantite":1,"libre":true}]
A12: 46283.5 | B12: Ronin | C12: Erik Marche-Brume | D12: 2 | E12: Motif personnalisé — Article 115 : Du port du masque Article 63 : Du refus d'obtempérer | F12: 1 | G12: 46283.719 | H12: 46283.76 | I12: TRUE | J12: []
A13: 46283.5 | B13: Ilflynn | C13: Grabouille | D13: 3 | E13: Art. 57 — Du trouble à l’ordre public | F13: 1 | G13: 46283.729 | H13: 46283.771 | I13: TRUE | J13: [] | K13: 45min de balais dans les geôles pour avoir embêté le Bazar, avoir posé des questions gênante à la marchande, grimpé aux poutre et ne voulait pas sortir.
A14: 46285.5 | B14: Selene | C14: Oswald Mandus | D14: 1 | E14: Motif personnalisé — *note supplémentaire ajouté* **suivant le Codex de Blancherive** Article 14 - De l'usurpation d'identité Article 15 - Des menaces Article 16 - Des menaces aggravées Article 22 - Des violences et agressions simples Article 23 - Des violences et agressions aggravées Article 29 - De la torture, de la mutilation et de la barbarie Article 51 - De l'usurpation de fonction Article 54 - De la dissimulation du visage Article 57 - Du trouble à l'ordre public Article 63 - Du refus d'obtempérer **Suivant le Decretum de Restitutione Bonorum Imperii** Article III De l'acquisition illégale, non respecté | F14: 24 | G14: 46285.167 | H14: 46286.167 | I14: TRUE | J14: [{"id":"skyrim.esm|01BE1B","nom":"Bottes","quantite":1},{"id":"sentinel.esp|000849","nom":"Bosmer Mask","quantite":1},{"id":"skyrim.esm|013999","nom":"Épée dwemer","quantite":1},{"id":"skyrim.esm|06F393","nom":"Armure de fourrure","quantite":1},{"id":"morecraftableequipment.esp|00083C","nom":"Grey Cowl","quantite":1},{"id":"skyrim.esm|06C1DA","nom":"Vêtements","quantite":1},{"id":"skyrim.esm|0877AB","nom":"Anneau d'argent et de grenat","quantite":2},{"id":"","nom":"Baton de Foi","quantite":1,"libre":true},{"id":"","nom":"Épée Falmer","quantite":1,"libre":true},{"id":"","nom":"capuche Rogueswood","quantite":1,"libre":true},{"id":"","nom":"Leather cape","quantite":1,"libre":true}] | K14: le bâton de magie de foi ; l’épée dwemer ; ainsi que l’équipement bosmer retrouvé en sa possession sans licence
A15: 46285.5 | B15: Ilflynn | C15: Talaka | D15: 4 | E15: Motif personnalisé — Article 74 | F15: 4 | G15: 46285.74 | H15: 46285.907 | I15: TRUE | J15: [] | K15: Article 74 outrage à la cour, la garde et la chatelerie.
A16: 46285.5 | B16: Theodrek Heid | C16: Runar Corbois | D16: 2eme a gauche en rentrant par salle du trône | E16: Motif personnalisé — Suspicion complicité de l'assassinat de Zandalar | F16: 6.000001 | G16: 46285.91 | H16: 46286.16 | I16: TRUE | J16: [{"id":"sentinel.esp|000912","nom":"Large Fur Collar","quantite":1},{"id":"skyrim.esm|086985","nom":"Casque d'officier des Sombrages","quantite":1},{"id":"skyrim.esm|03EB12","nom":"Breuvage de récupération","quantite":1},{"id":"skyrim.esm|03EB11","nom":"Potion de récupération","quantite":1},{"id":"skyrim.esm|03EB02","nom":"Potion de force","quantite":1},{"id":"sentinel.esp|0008B9","nom":"Stormcloak Heavy Lamellar Boots","quantite":1},{"id":"sentinel.esp|0008C4","nom":"Stormcloak Heavy Lamellar Gauntlets","quantite":1},{"id":"sentinel.esp|000B33","nom":"Bosmer Bow","quantite":1},{"id":"skyrim.esm|01397F","nom":"Flèche d'acier","quantite":219},{"id":"skyrim.esm|013984","nom":"Hache d'armes d'acier","quantite":1},{"id":"commonclothes.esp|001874","nom":"Leather Doublet","quantite":1}] | K16: En cellule jusqu'à son jugement.
A17: 46290.5 | B17: Laureen Toison-de-Sang | C17: Orel le dévastateur | D17: 1 | E17: Motif personnalisé — Soupçon d'être un vampire, porte du masque, racket. | F17: 24 | G17: 46290.773 | H17: 46291.773 | I17: TRUE | J17: [{"id":"","nom":"Arc orc, capuche noir","quantite":1,"libre":true}] | K17: Orsimer qui manipule la magie probablement Galgarot ou l'un de ces fils. ORDRE DE GHORBASH: ne pas rentrer dans la cellule sans la présence d'un vigile. ON ATTEND LES VIGILES
A18: 46290.5 | B18: Ronin | C18: Le dévastateur | D18: 1 | E18: Motif personnalisé — -Menaces aggravées -Suspicion vampirique -Rakhet | F18: 0.1 | G18: 46290.778 | H18: 46290.782 | I18: TRUE | J18: [{"id":"","nom":"Black Cowl","quantite":1,"libre":true},{"id":"","nom":"Arc orque","quantite":1,"libre":true}] | K18: En attente de la garde de l'aube
F19: {=IF(E19="","",IFERROR(_xlfn.XLOOKUP(E19,SyncCodex!N:N,SyncCodex!O:O),""))} | H19: =IF(OR(G19="",F19=""),"",G19+(F19/24)) | I19: FALSE
F20: {=IF(E20="","",IFERROR(_xlfn.XLOOKUP(E20,SyncCodex!N:N,SyncCodex!O:O),""))} | H20: =IF(OR(G20="",F20=""),"",G20+(F20/24)) | I20: FALSE
F21: {=IF(E21="","",IFERROR(_xlfn.XLOOKUP(E21,SyncCodex!N:N,SyncCodex!O:O),""))} | H21: =IF(OR(G21="",F21=""),"",G21+(F21/24)) | I21: FALSE
F22: {=IF(E22="","",IFERROR(_xlfn.XLOOKUP(E22,SyncCodex!N:N,SyncCodex!O:O),""))} | H22: =IF(OR(G22="",F22=""),"",G22+(F22/24)) | I22: FALSE
F23: {=IF(E23="","",IFERROR(_xlfn.XLOOKUP(E23,SyncCodex!N:N,SyncCodex!O:O),""))} | H23: =IF(OR(G23="",F23=""),"",G23+(F23/24)) | I23: FALSE
F24: {=IF(E24="","",IFERROR(_xlfn.XLOOKUP(E24,SyncCodex!N:N,SyncCodex!O:O),""))} | H24: =IF(OR(G24="",F24=""),"",G24+(F24/24)) | I24: FALSE
F25: {=IF(E25="","",IFERROR(_xlfn.XLOOKUP(E25,SyncCodex!N:N,SyncCodex!O:O),""))} | H25: =IF(OR(G25="",F25=""),"",G25+(F25/24)) | I25: FALSE
F26: {=IF(E26="","",IFERROR(_xlfn.XLOOKUP(E26,SyncCodex!N:N,SyncCodex!O:O),""))} | H26: =IF(OR(G26="",F26=""),"",G26+(F26/24)) | I26: FALSE
F27: {=IF(E27="","",IFERROR(_xlfn.XLOOKUP(E27,SyncCodex!N:N,SyncCodex!O:O),""))} | H27: =IF(OR(G27="",F27=""),"",G27+(F27/24)) | I27: FALSE
F28: {=IF(E28="","",IFERROR(_xlfn.XLOOKUP(E28,SyncCodex!N:N,SyncCodex!O:O),""))} | H28: =IF(OR(G28="",F28=""),"",G28+(F28/24)) | I28: FALSE
F29: {=IF(E29="","",IFERROR(_xlfn.XLOOKUP(E29,SyncCodex!N:N,SyncCodex!O:O),""))} | H29: =IF(OR(G29="",F29=""),"",G29+(F29/24)) | I29: FALSE
F30: {=IF(E30="","",IFERROR(_xlfn.XLOOKUP(E30,SyncCodex!N:N,SyncCodex!O:O),""))} | H30: =IF(OR(G30="",F30=""),"",G30+(F30/24)) | I30: FALSE
... F997: {=IF(E997="","",IFERROR(_xlfn.XLOOKUP(E997,SyncCodex!N:N,SyncCodex!O:O),""))} | H997: =IF(OR(G997="",F997=""),"",G997+(F997/24)) | I997: FALSE

Sheet Garde de Blancherive
A1: =IFERROR(__xludf.DUMMYFUNCTION("QUERY(Effectifs!A:Z, ""SELECT * WHERE E CONTAINS 'Cité' OR E CONTAINS 'Major' ORDER BY Z ASC"", 1)"),"Assermenté") -> Assermenté | B1: =IFERROR(__xludf.DUMMYFUNCTION("""COMPUTED_VALUE"""),"Grade") -> Grade | C1: =IFERROR(__xludf.DUMMYFUNCTION("""COMPUTED_VALUE"""),"Prénom") -> Prénom | D1: =IFERROR(__xludf.DUMMYFUNCTION("""COMPUTED_VALUE"""),"Nom") -> Nom | E1: =IFERROR(__xludf.DUMMYFUNCTION("""COMPUTED_VALUE"""),"Corps") -> Corps | F1: =IFERROR(__xludf.DUMMYFUNCTION("""COMPUTED_VALUE"""),"Spécialité") -> Spécialité | G1: =IFERROR(__xludf.DUMMYFUNCTION("""COMPUTED_VALUE"""),"Status") -> Status | H1: =IFERROR(__xludf.DUMMYFUNCTION("""COMPUTED_VALUE"""),"Métier") -> Métier | I1: =IFERROR(__xludf.DUMMYFUNCTION("""COMPUTED_VALUE"""),"") | J1: =IFERROR(__xludf.DUMMYFUNCTION("""COMPUTED_VALUE"""),"") | K1: =IFERROR(__xludf.DUMMYFUNCTION("""COMPUTED_VALUE"""),"") | L1: =IFERROR(__xludf.DUMMYFUNCTION("""COMPUTED_VALUE"""),"") | M1: =IFERROR(__xludf.DUMMYFUNCTION("""COMPUTED_VALUE"""),"") | N1: =IFERROR(__xludf.DUMMYFUNCTION("""COMPUTED_VALUE"""),"") | O1: =IFERROR(__xludf.DUMMYFUNCTION("""COMPUTED_VALUE"""),"") | P1: =IFERROR(__xludf.DUMMYFUNCTION("""COMPUTED_VALUE"""),"") | ... Z1: =IFERROR(__xludf.DUMMYFUNCTION("""COMPUTED_VALUE"""),"")
A2: =IFERROR(__xludf.DUMMYFUNCTION("""COMPUTED_VALUE"""),TRUE) -> TRUE | B2: =IFERROR(__xludf.DUMMYFUNCTION("""COMPUTED_VALUE"""),"Maréchal") -> Maréchal | C2: =IFERROR(__xludf.DUMMYFUNCTION("""COMPUTED_VALUE"""),"Lazabard") -> Lazabard | D2: =IFERROR(__xludf.DUMMYFUNCTION("""COMPUTED_VALUE"""),"Jemelred") -> Jemelred | E2: =IFERROR(__xludf.DUMMYFUNCTION("""COMPUTED_VALUE"""),"Etat-Major") -> Etat-Major | F2: =IFERROR(__xludf.DUMMYFUNCTION("""COMPUTED_VALUE"""),"Garde, Collecteur de la garde") -> Garde, Collecteur de la garde | G2: =IFERROR(__xludf.DUMMYFUNCTION("""COMPUTED_VALUE"""),"En service actif") -> En service actif
A3: =IFERROR(__xludf.DUMMYFUNCTION("""COMPUTED_VALUE"""),TRUE) -> TRUE | B3: =IFERROR(__xludf.DUMMYFUNCTION("""COMPUTED_VALUE"""),"Commander") -> Commander | C3: =IFERROR(__xludf.DUMMYFUNCTION("""COMPUTED_VALUE"""),"Filoki") -> Filoki | E3: =IFERROR(__xludf.DUMMYFUNCTION("""COMPUTED_VALUE"""),"Etat-Major") -> Etat-Major | F3: =IFERROR(__xludf.DUMMYFUNCTION("""COMPUTED_VALUE"""),"Garde, Collecteur de la garde") -> Garde, Collecteur de la garde | G3: =IFERROR(__xludf.DUMMYFUNCTION("""COMPUTED_VALUE"""),"En service actif") -> En service actif
A4: =IFERROR(__xludf.DUMMYFUNCTION("""COMPUTED_VALUE"""),TRUE) -> TRUE | B4: =IFERROR(__xludf.DUMMYFUNCTION("""COMPUTED_VALUE"""),"Major") -> Major | C4: =IFERROR(__xludf.DUMMYFUNCTION("""COMPUTED_VALUE"""),"Dagbara") -> Dagbara | D4: =IFERROR(__xludf.DUMMYFUNCTION("""COMPUTED_VALUE"""),"Gronez") -> Gronez | E4: =IFERROR(__xludf.DUMMYFUNCTION("""COMPUTED_VALUE"""),"Etat-Major") -> Etat-Major | F4: =IFERROR(__xludf.DUMMYFUNCTION("""COMPUTED_VALUE"""),"Garde") -> Garde | G4: =IFERROR(__xludf.DUMMYFUNCTION("""COMPUTED_VALUE"""),"Mis en réserve") -> Mis en réserve
A5: =IFERROR(__xludf.DUMMYFUNCTION("""COMPUTED_VALUE"""),TRUE) -> TRUE | B5: =IFERROR(__xludf.DUMMYFUNCTION("""COMPUTED_VALUE"""),"Capitaine") -> Capitaine | C5: =IFERROR(__xludf.DUMMYFUNCTION("""COMPUTED_VALUE"""),"Astrid") -> Astrid | D5: =IFERROR(__xludf.DUMMYFUNCTION("""COMPUTED_VALUE"""),"Lame-Fine") -> Lame-Fine | E5: =IFERROR(__xludf.DUMMYFUNCTION("""COMPUTED_VALUE"""),"Cité de Blancherive") -> Cité de Blancherive | F5: =IFERROR(__xludf.DUMMYFUNCTION("""COMPUTED_VALUE"""),"Garde, Collecteur de la garde") -> Garde, Collecteur de la garde | G5: =IFERROR(__xludf.DUMMYFUNCTION("""COMPUTED_VALUE"""),"En service actif") -> En service actif | H5: =IFERROR(__xludf.DUMMYFUNCTION("""COMPUTED_VALUE"""),"Chasseur") -> Chasseur
A6: =IFERROR(__xludf.DUMMYFUNCTION("""COMPUTED_VALUE"""),TRUE) -> TRUE | B6: =IFERROR(__xludf.DUMMYFUNCTION("""COMPUTED_VALUE"""),"Capitaine") -> Capitaine | C6: =IFERROR(__xludf.DUMMYFUNCTION("""COMPUTED_VALUE"""),"Edward") -> Edward | D6: =IFERROR(__xludf.DUMMYFUNCTION("""COMPUTED_VALUE"""),"Winters") -> Winters | E6: =IFERROR(__xludf.DUMMYFUNCTION("""COMPUTED_VALUE"""),"Cité de Blancherive") -> Cité de Blancherive | F6: =IFERROR(__xludf.DUMMYFUNCTION("""COMPUTED_VALUE"""),"Hird") -> Hird | G6: =IFERROR(__xludf.DUMMYFUNCTION("""COMPUTED_VALUE"""),"Mis en réserve") -> Mis en réserve
A7: =IFERROR(__xludf.DUMMYFUNCTION("""COMPUTED_VALUE"""),TRUE) -> TRUE | B7: =IFERROR(__xludf.DUMMYFUNCTION("""COMPUTED_VALUE"""),"Major") -> Major | C7: =IFERROR(__xludf.DUMMYFUNCTION("""COMPUTED_VALUE"""),"Ulfar") -> Ulfar | E7: =IFERROR(__xludf.DUMMYFUNCTION("""COMPUTED_VALUE"""),"Etat-Major") -> Etat-Major | F7: =IFERROR(__xludf.DUMMYFUNCTION("""COMPUTED_VALUE"""),"Garde, Collecteur de la garde") -> Garde, Collecteur de la garde | G7: =IFERROR(__xludf.DUMMYFUNCTION("""COMPUTED_VALUE"""),"En service actif") -> En service actif
A8: =IFERROR(__xludf.DUMMYFUNCTION("""COMPUTED_VALUE"""),TRUE) -> TRUE | B8: =IFERROR(__xludf.DUMMYFUNCTION("""COMPUTED_VALUE"""),"Lieutenant-Chef") -> Lieutenant-Chef | C8: =IFERROR(__xludf.DUMMYFUNCTION("""COMPUTED_VALUE"""),"Ronin") -> Ronin | E8: =IFERROR(__xludf.DUMMYFUNCTION("""COMPUTED_VALUE"""),"Cité de Blancherive") -> Cité de Blancherive | F8: =IFERROR(__xludf.DUMMYFUNCTION("""COMPUTED_VALUE"""),"Garde, Collecteur de la garde") -> Garde, Collecteur de la garde | G8: =IFERROR(__xludf.DUMMYFUNCTION("""COMPUTED_VALUE"""),"En service actif") -> En service actif | H8: =IFERROR(__xludf.DUMMYFUNCTION("""COMPUTED_VALUE"""),"Guerrier") -> Guerrier
A9: =IFERROR(__xludf.DUMMYFUNCTION("""COMPUTED_VALUE"""),TRUE) -> TRUE | B9: =IFERROR(__xludf.DUMMYFUNCTION("""COMPUTED_VALUE"""),"Lieutenant") -> Lieutenant | C9: =IFERROR(__xludf.DUMMYFUNCTION("""COMPUTED_VALUE"""),"Thorin") -> Thorin | D9: =IFERROR(__xludf.DUMMYFUNCTION("""COMPUTED_VALUE"""),"Rivegel") -> Rivegel | E9: =IFERROR(__xludf.DUMMYFUNCTION("""COMPUTED_VALUE"""),"Cité de Blancherive") -> Cité de Blancherive | F9: =IFERROR(__xludf.DUMMYFUNCTION("""COMPUTED_VALUE"""),"Garde") -> Garde | G9: =IFERROR(__xludf.DUMMYFUNCTION("""COMPUTED_VALUE"""),"Déserteur") -> Déserteur | H9: =IFERROR(__xludf.DUMMYFUNCTION("""COMPUTED_VALUE"""),"Guerrier") -> Guerrier
A10: =IFERROR(__xludf.DUMMYFUNCTION("""COMPUTED_VALUE"""),TRUE) -> TRUE | B10: =IFERROR(__xludf.DUMMYFUNCTION("""COMPUTED_VALUE"""),"Lieutenant-Chef") -> Lieutenant-Chef | C10: =IFERROR(__xludf.DUMMYFUNCTION("""COMPUTED_VALUE"""),"Gisbern") -> Gisbern | D10: =IFERROR(__xludf.DUMMYFUNCTION("""COMPUTED_VALUE"""),"Isenbjorn") -> Isenbjorn | E10: =IFERROR(__xludf.DUMMYFUNCTION("""COMPUTED_VALUE"""),"Cité de Blancherive") -> Cité de Blancherive | F10: =IFERROR(__xludf.DUMMYFUNCTION("""COMPUTED_VALUE"""),"Garde") -> Garde | G10: =IFERROR(__xludf.DUMMYFUNCTION("""COMPUTED_VALUE"""),"Déserteur") -> Déserteur
A11: =IFERROR(__xludf.DUMMYFUNCTION("""COMPUTED_VALUE"""),TRUE) -> TRUE | B11: =IFERROR(__xludf.DUMMYFUNCTION("""COMPUTED_VALUE"""),"Lieutenant") -> Lieutenant | C11: =IFERROR(__xludf.DUMMYFUNCTION("""COMPUTED_VALUE"""),"Rorik") -> Rorik | D11: =IFERROR(__xludf.DUMMYFUNCTION("""COMPUTED_VALUE"""),"Marche-Hiver") -> Marche-Hiver | E11: =IFERROR(__xludf.DUMMYFUNCTION("""COMPUTED_VALUE"""),"Cité de Blancherive") -> Cité de Blancherive | F11: =IFERROR(__xludf.DUMMYFUNCTION("""COMPUTED_VALUE"""),"Garde, Intendant de la garde") -> Garde, Intendant de la garde | G11: =IFERROR(__xludf.DUMMYFUNCTION("""COMPUTED_VALUE"""),"En service actif") -> En service actif
A12: =IFERROR(__xludf.DUMMYFUNCTION("""COMPUTED_VALUE"""),TRUE) -> TRUE | B12: =IFERROR(__xludf.DUMMYFUNCTION("""COMPUTED_VALUE"""),"Sergent-Chef") -> Sergent-Chef | C12: =IFERROR(__xludf.DUMMYFUNCTION("""COMPUTED_VALUE"""),"Erwan") -> Erwan | E12: =IFERROR(__xludf.DUMMYFUNCTION("""COMPUTED_VALUE"""),"Cité de Blancherive") -> Cité de Blancherive | F12: =IFERROR(__xludf.DUMMYFUNCTION("""COMPUTED_VALUE"""),"Garde") -> Garde | G12: =IFERROR(__xludf.DUMMYFUNCTION("""COMPUTED_VALUE"""),"En service actif") -> En service actif
A13: =IFERROR(__xludf.DUMMYFUNCTION("""COMPUTED_VALUE"""),TRUE) -> TRUE | B13: =IFERROR(__xludf.DUMMYFUNCTION("""COMPUTED_VALUE"""),"Caporal-Chef") -> Caporal-Chef | C13: =IFERROR(__xludf.DUMMYFUNCTION("""COMPUTED_VALUE"""),"Ilflynn") -> Ilflynn | E13: =IFERROR(__xludf.DUMMYFUNCTION("""COMPUTED_VALUE"""),"Cité de Blancherive") -> Cité de Blancherive | F13: =IFERROR(__xludf.DUMMYFUNCTION("""COMPUTED_VALUE"""),"Garde") -> Garde | G13: =IFERROR(__xludf.DUMMYFUNCTION("""COMPUTED_VALUE"""),"En service actif") -> En service actif
A14: =IFERROR(__xludf.DUMMYFUNCTION("""COMPUTED_VALUE"""),TRUE) -> TRUE | B14: =IFERROR(__xludf.DUMMYFUNCTION("""COMPUTED_VALUE"""),"Garde") -> Garde | C14: =IFERROR(__xludf.DUMMYFUNCTION("""COMPUTED_VALUE"""),"Laureen") -> Laureen | D14: =IFERROR(__xludf.DUMMYFUNCTION("""COMPUTED_VALUE"""),"Toison-de-Sang") -> Toison-de-Sang | E14: =IFERROR(__xludf.DUMMYFUNCTION("""COMPUTED_VALUE"""),"Cité de Blancherive") -> Cité de Blancherive | F14: =IFERROR(__xludf.DUMMYFUNCTION("""COMPUTED_VALUE"""),"Eclaireur, Garde") -> Eclaireur, Garde | G14: =IFERROR(__xludf.DUMMYFUNCTION("""COMPUTED_VALUE"""),"En service actif") -> En service actif | H14: =IFERROR(__xludf.DUMMYFUNCTION("""COMPUTED_VALUE"""),"Chasseur") -> Chasseur
A15: =IFERROR(__xludf.DUMMYFUNCTION("""COMPUTED_VALUE"""),TRUE) -> TRUE | B15: =IFERROR(__xludf.DUMMYFUNCTION("""COMPUTED_VALUE"""),"Garde") -> Garde | C15: =IFERROR(__xludf.DUMMYFUNCTION("""COMPUTED_VALUE"""),"Andor") -> Andor | D15: =IFERROR(__xludf.DUMMYFUNCTION("""COMPUTED_VALUE"""),"Viraes") -> Viraes | E15: =IFERROR(__xludf.DUMMYFUNCTION("""COMPUTED_VALUE"""),"Cité de Blancherive") -> Cité de Blancherive | F15: =IFERROR(__xludf.DUMMYFUNCTION("""COMPUTED_VALUE"""),"Garde") -> Garde | G15: =IFERROR(__xludf.DUMMYFUNCTION("""COMPUTED_VALUE"""),"Mis en réserve") -> Mis en réserve
A16: =IFERROR(__xludf.DUMMYFUNCTION("""COMPUTED_VALUE"""),FALSE) -> FALSE | B16: =IFERROR(__xludf.DUMMYFUNCTION("""COMPUTED_VALUE"""),"Sergent-Chef") -> Sergent-Chef | C16: =IFERROR(__xludf.DUMMYFUNCTION("""COMPUTED_VALUE"""),"Astrild") -> Astrild | E16: =IFERROR(__xludf.DUMMYFUNCTION("""COMPUTED_VALUE"""),"Cité de Blancherive") -> Cité de Blancherive | F16: =IFERROR(__xludf.DUMMYFUNCTION("""COMPUTED_VALUE"""),"Garde") -> Garde | G16: =IFERROR(__xludf.DUMMYFUNCTION("""COMPUTED_VALUE"""),"En service actif") -> En service actif
A17: =IFERROR(__xludf.DUMMYFUNCTION("""COMPUTED_VALUE"""),FALSE) -> FALSE | B17: =IFERROR(__xludf.DUMMYFUNCTION("""COMPUTED_VALUE"""),"Lieutenant") -> Lieutenant | C17: =IFERROR(__xludf.DUMMYFUNCTION("""COMPUTED_VALUE"""),"Encore-Un-Espoir") -> Encore-Un-Espoir | E17: =IFERROR(__xludf.DUMMYFUNCTION("""COMPUTED_VALUE"""),"Cité de Blancherive") -> Cité de Blancherive | F17: =IFERROR(__xludf.DUMMYFUNCTION("""COMPUTED_VALUE"""),"Garde, Tortionnaire, Instructeur") -> Garde, Tortionnaire, Instructeur | G17: =IFERROR(__xludf.DUMMYFUNCTION("""COMPUTED_VALUE"""),"Démissionnaire") -> Démissionnaire
A18: =IFERROR(__xludf.DUMMYFUNCTION("""COMPUTED_VALUE"""),TRUE) -> TRUE | B18: =IFERROR(__xludf.DUMMYFUNCTION("""COMPUTED_VALUE"""),"Garde") -> Garde | C18: =IFERROR(__xludf.DUMMYFUNCTION("""COMPUTED_VALUE"""),"Al'Dran") -> Al'Dran | E18: =IFERROR(__xludf.DUMMYFUNCTION("""COMPUTED_VALUE"""),"Cité de Blancherive") -> Cité de Blancherive | F18: =IFERROR(__xludf.DUMMYFUNCTION("""COMPUTED_VALUE"""),"Garde") -> Garde | G18: =IFERROR(__xludf.DUMMYFUNCTION("""COMPUTED_VALUE"""),"Démissionnaire") -> Démissionnaire
A19: =IFERROR(__xludf.DUMMYFUNCTION("""COMPUTED_VALUE"""),TRUE) -> TRUE | B19: =IFERROR(__xludf.DUMMYFUNCTION("""COMPUTED_VALUE"""),"Caporal") -> Caporal | C19: =IFERROR(__xludf.DUMMYFUNCTION("""COMPUTED_VALUE"""),"Kendall") -> Kendall | D19: =IFERROR(__xludf.DUMMYFUNCTION("""COMPUTED_VALUE"""),"Delamare") -> Delamare | E19: =IFERROR(__xludf.DUMMYFUNCTION("""COMPUTED_VALUE"""),"Cité de Blancherive") -> Cité de Blancherive | F19: =IFERROR(__xludf.DUMMYFUNCTION("""COMPUTED_VALUE"""),"Garde") -> Garde | G19: =IFERROR(__xludf.DUMMYFUNCTION("""COMPUTED_VALUE"""),"En service actif") -> En service actif
A20: =IFERROR(__xludf.DUMMYFUNCTION("""COMPUTED_VALUE"""),FALSE) -> FALSE | B20: =IFERROR(__xludf.DUMMYFUNCTION("""COMPUTED_VALUE"""),"Cadet") -> Cadet | C20: =IFERROR(__xludf.DUMMYFUNCTION("""COMPUTED_VALUE"""),"Eldrim") -> Eldrim | D20: =IFERROR(__xludf.DUMMYFUNCTION("""COMPUTED_VALUE"""),"Hache-Grise") -> Hache-Grise | E20: =IFERROR(__xludf.DUMMYFUNCTION("""COMPUTED_VALUE"""),"Cité de Blancherive") -> Cité de Blancherive | F20: =IFERROR(__xludf.DUMMYFUNCTION("""COMPUTED_VALUE"""),"Garde") -> Garde | G20: =IFERROR(__xludf.DUMMYFUNCTION("""COMPUTED_VALUE"""),"Déserteur") -> Déserteur
A21: =IFERROR(__xludf.DUMMYFUNCTION("""COMPUTED_VALUE"""),FALSE) -> FALSE | B21: =IFERROR(__xludf.DUMMYFUNCTION("""COMPUTED_VALUE"""),"Recrue") -> Recrue | C21: =IFERROR(__xludf.DUMMYFUNCTION("""COMPUTED_VALUE"""),"Ro'minet") -> Ro'minet | E21: =IFERROR(__xludf.DUMMYFUNCTION("""COMPUTED_VALUE"""),"Cité de Blancherive") -> Cité de Blancherive | F21: =IFERROR(__xludf.DUMMYFUNCTION("""COMPUTED_VALUE"""),"Garde") -> Garde | G21: =IFERROR(__xludf.DUMMYFUNCTION("""COMPUTED_VALUE"""),"Radié du service actif") -> Radié du service actif
A22: =IFERROR(__xludf.DUMMYFUNCTION("""COMPUTED_VALUE"""),TRUE) -> TRUE | B22: =IFERROR(__xludf.DUMMYFUNCTION("""COMPUTED_VALUE"""),"Garde") -> Garde | C22: =IFERROR(__xludf.DUMMYFUNCTION("""COMPUTED_VALUE"""),"Bjorn") -> Bjorn | D22: =IFERROR(__xludf.DUMMYFUNCTION("""COMPUTED_VALUE"""),"Kornseen") -> Kornseen | E22: =IFERROR(__xludf.DUMMYFUNCTION("""COMPUTED_VALUE"""),"Cité de Blancherive") -> Cité de Blancherive | F22: =IFERROR(__xludf.DUMMYFUNCTION("""COMPUTED_VALUE"""),"Garde") -> Garde | G22: =IFERROR(__xludf.DUMMYFUNCTION("""COMPUTED_VALUE"""),"En service actif") -> En service actif
A23: =IFERROR(__xludf.DUMMYFUNCTION("""COMPUTED_VALUE"""),TRUE) -> TRUE | B23: =IFERROR(__xludf.DUMMYFUNCTION("""COMPUTED_VALUE"""),"Garde") -> Garde | C23: =IFERROR(__xludf.DUMMYFUNCTION("""COMPUTED_VALUE"""),"Wulfgar") -> Wulfgar | D23: =IFERROR(__xludf.DUMMYFUNCTION("""COMPUTED_VALUE"""),"Durrock") -> Durrock | E23: =IFERROR(__xludf.DUMMYFUNCTION("""COMPUTED_VALUE"""),"Cité de Blancherive") -> Cité de Blancherive | F23: =IFERROR(__xludf.DUMMYFUNCTION("""COMPUTED_VALUE"""),"Garde") -> Garde | G23: =IFERROR(__xludf.DUMMYFUNCTION("""COMPUTED_VALUE"""),"En service actif") -> En service actif
A24: =IFERROR(__xludf.DUMMYFUNCTION("""COMPUTED_VALUE"""),FALSE) -> FALSE | B24: =IFERROR(__xludf.DUMMYFUNCTION("""COMPUTED_VALUE"""),"Garde") -> Garde | C24: =IFERROR(__xludf.DUMMYFUNCTION("""COMPUTED_VALUE"""),"Lyosha ") -> Lyosha | D24: =IFERROR(__xludf.DUMMYFUNCTION("""COMPUTED_VALUE"""),"Sullapierre") -> Sullapierre | E24: =IFERROR(__xludf.DUMMYFUNCTION("""COMPUTED_VALUE"""),"Cité de Blancherive") -> Cité de Blancherive | F24: =IFERROR(__xludf.DUMMYFUNCTION("""COMPUTED_VALUE"""),"Garde") -> Garde | G24: =IFERROR(__xludf.DUMMYFUNCTION("""COMPUTED_VALUE"""),"Mis en réserve") -> Mis en réserve
A25: =IFERROR(__xludf.DUMMYFUNCTION("""COMPUTED_VALUE"""),FALSE) -> FALSE | B25: =IFERROR(__xludf.DUMMYFUNCTION("""COMPUTED_VALUE"""),"Garde") -> Garde | C25: =IFERROR(__xludf.DUMMYFUNCTION("""COMPUTED_VALUE"""),"Brandon ") -> Brandon | D25: =IFERROR(__xludf.DUMMYFUNCTION("""COMPUTED_VALUE"""),"Alprazz") -> Alprazz | E25: =IFERROR(__xludf.DUMMYFUNCTION("""COMPUTED_VALUE"""),"Cité de Blancherive") -> Cité de Blancherive | F25: =IFERROR(__xludf.DUMMYFUNCTION("""COMPUTED_VALUE"""),"Garde") -> Garde | G25: =IFERROR(__xludf.DUMMYFUNCTION("""COMPUTED_VALUE"""),"Mis en réserve") -> Mis en réserve
A26: =IFERROR(__xludf.DUMMYFUNCTION("""COMPUTED_VALUE"""),TRUE) -> TRUE | B26: =IFERROR(__xludf.DUMMYFUNCTION("""COMPUTED_VALUE"""),"Garde") -> Garde | C26: =IFERROR(__xludf.DUMMYFUNCTION("""COMPUTED_VALUE"""),"Aldric") -> Aldric | D26: =IFERROR(__xludf.DUMMYFUNCTION("""COMPUTED_VALUE"""),"Cendre-coeur") -> Cendre-coeur | E26: =IFERROR(__xludf.DUMMYFUNCTION("""COMPUTED_VALUE"""),"Cité de Blancherive") -> Cité de Blancherive | F26: =IFERROR(__xludf.DUMMYFUNCTION("""COMPUTED_VALUE"""),"Garde") -> Garde | G26: =IFERROR(__xludf.DUMMYFUNCTION("""COMPUTED_VALUE"""),"En service actif") -> En service actif
A27: =IFERROR(__xludf.DUMMYFUNCTION("""COMPUTED_VALUE"""),FALSE) -> FALSE | B27: =IFERROR(__xludf.DUMMYFUNCTION("""COMPUTED_VALUE"""),"Recrue") -> Recrue | C27: =IFERROR(__xludf.DUMMYFUNCTION("""COMPUTED_VALUE"""),"Aldrok") -> Aldrok | E27: =IFERROR(__xludf.DUMMYFUNCTION("""COMPUTED_VALUE"""),"Cité de Blancherive") -> Cité de Blancherive | F27: =IFERROR(__xludf.DUMMYFUNCTION("""COMPUTED_VALUE"""),"Garde") -> Garde | G27: =IFERROR(__xludf.DUMMYFUNCTION("""COMPUTED_VALUE"""),"Radié du service actif") -> Radié du service actif
A28: =IFERROR(__xludf.DUMMYFUNCTION("""COMPUTED_VALUE"""),TRUE) -> TRUE | B28: =IFERROR(__xludf.DUMMYFUNCTION("""COMPUTED_VALUE"""),"Garde") -> Garde | C28: =IFERROR(__xludf.DUMMYFUNCTION("""COMPUTED_VALUE"""),"Zeid") -> Zeid | D28: =IFERROR(__xludf.DUMMYFUNCTION("""COMPUTED_VALUE"""),"Le Brise-Lames") -> Le Brise-Lames | E28: =IFERROR(__xludf.DUMMYFUNCTION("""COMPUTED_VALUE"""),"Cité de Blancherive") -> Cité de Blancherive | F28: =IFERROR(__xludf.DUMMYFUNCTION("""COMPUTED_VALUE"""),"Garde") -> Garde | G28: =IFERROR(__xludf.DUMMYFUNCTION("""COMPUTED_VALUE"""),"En service actif") -> En service actif
A29: =IFERROR(__xludf.DUMMYFUNCTION("""COMPUTED_VALUE"""),FALSE) -> FALSE | B29: =IFERROR(__xludf.DUMMYFUNCTION("""COMPUTED_VALUE"""),"Recrue") -> Recrue | C29: =IFERROR(__xludf.DUMMYFUNCTION("""COMPUTED_VALUE"""),"Gruseldorf") -> Gruseldorf | D29: =IFERROR(__xludf.DUMMYFUNCTION("""COMPUTED_VALUE"""),"E. Jackeet") -> E. Jackeet | E29: =IFERROR(__xludf.DUMMYFUNCTION("""COMPUTED_VALUE"""),"Cité de Blancherive") -> Cité de Blancherive | F29: =IFERROR(__xludf.DUMMYFUNCTION("""COMPUTED_VALUE"""),"Garde") -> Garde | G29: =IFERROR(__xludf.DUMMYFUNCTION("""COMPUTED_VALUE"""),"Radié du service actif") -> Radié du service actif
A30: =IFERROR(__xludf.DUMMYFUNCTION("""COMPUTED_VALUE"""),FALSE) -> FALSE | B30: =IFERROR(__xludf.DUMMYFUNCTION("""COMPUTED_VALUE"""),"Recrue") -> Recrue | C30: =IFERROR(__xludf.DUMMYFUNCTION("""COMPUTED_VALUE"""),"Mordecai") -> Mordecai | D30: =IFERROR(__xludf.DUMMYFUNCTION("""COMPUTED_VALUE"""),"E. Jackeet") -> E. Jackeet | E30: =IFERROR(__xludf.DUMMYFUNCTION("""COMPUTED_VALUE"""),"Cité de Blancherive") -> Cité de Blancherive | F30: =IFERROR(__xludf.DUMMYFUNCTION("""COMPUTED_VALUE"""),"Garde") -> Garde | G30: =IFERROR(__xludf.DUMMYFUNCTION("""COMPUTED_VALUE"""),"Radié du service actif") -> Radié du service actif
A31: =IFERROR(__xludf.DUMMYFUNCTION("""COMPUTED_VALUE"""),FALSE) -> FALSE | B31: =IFERROR(__xludf.DUMMYFUNCTION("""COMPUTED_VALUE"""),"Recrue") -> Recrue | C31: =IFERROR(__xludf.DUMMYFUNCTION("""COMPUTED_VALUE"""),"Razim") -> Razim | D31: =IFERROR(__xludf.DUMMYFUNCTION("""COMPUTED_VALUE"""),"Al-Rihad") -> Al-Rihad | E31: =IFERROR(__xludf.DUMMYFUNCTION("""COMPUTED_VALUE"""),"Cité de Blancherive") -> Cité de Blancherive | F31: =IFERROR(__xludf.DUMMYFUNCTION("""COMPUTED_VALUE"""),"Garde") -> Garde | G31: =IFERROR(__xludf.DUMMYFUNCTION("""COMPUTED_VALUE"""),"Radié du service actif") -> Radié du service actif
A32: =IFERROR(__xludf.DUMMYFUNCTION("""COMPUTED_VALUE"""),FALSE) -> FALSE | B32: =IFERROR(__xludf.DUMMYFUNCTION("""COMPUTED_VALUE"""),"Recrue") -> Recrue | C32: =IFERROR(__xludf.DUMMYFUNCTION("""COMPUTED_VALUE"""),"Alza'gar") -> Alza'gar | E32: =IFERROR(__xludf.DUMMYFUNCTION("""COMPUTED_VALUE"""),"Cité de Blancherive") -> Cité de Blancherive | F32: =IFERROR(__xludf.DUMMYFUNCTION("""COMPUTED_VALUE"""),"Garde") -> Garde | G32: =IFERROR(__xludf.DUMMYFUNCTION("""COMPUTED_VALUE"""),"Démissionnaire") -> Démissionnaire
A33: =IFERROR(__xludf.DUMMYFUNCTION("""COMPUTED_VALUE"""),FALSE) -> FALSE | B33: =IFERROR(__xludf.DUMMYFUNCTION("""COMPUTED_VALUE"""),"Recrue") -> Recrue | C33: =IFERROR(__xludf.DUMMYFUNCTION("""COMPUTED_VALUE"""),"Darius") -> Darius | D33: =IFERROR(__xludf.DUMMYFUNCTION("""COMPUTED_VALUE"""),"Valtor") -> Valtor | E33: =IFERROR(__xludf.DUMMYFUNCTION("""COMPUTED_VALUE"""),"Cité de Blancherive") -> Cité de Blancherive | F33: =IFERROR(__xludf.DUMMYFUNCTION("""COMPUTED_VALUE"""),"Garde") -> Garde | G33: =IFERROR(__xludf.DUMMYFUNCTION("""COMPUTED_VALUE"""),"En service actif") -> En service actif
A34: =IFERROR(__xludf.DUMMYFUNCTION("""COMPUTED_VALUE"""),FALSE) -> FALSE | B34: =IFERROR(__xludf.DUMMYFUNCTION("""COMPUTED_VALUE"""),"Recrue") -> Recrue | C34: =IFERROR(__xludf.DUMMYFUNCTION("""COMPUTED_VALUE"""),"Marius") -> Marius | D34: =IFERROR(__xludf.DUMMYFUNCTION("""COMPUTED_VALUE"""),"Renatus") -> Renatus | E34: =IFERROR(__xludf.DUMMYFUNCTION("""COMPUTED_VALUE"""),"Cité de Blancherive") -> Cité de Blancherive | F34: =IFERROR(__xludf.DUMMYFUNCTION("""COMPUTED_VALUE"""),"Garde") -> Garde | G34: =IFERROR(__xludf.DUMMYFUNCTION("""COMPUTED_VALUE"""),"En service actif") -> En service actif
A35: =IFERROR(__xludf.DUMMYFUNCTION("""COMPUTED_VALUE"""),FALSE) -> FALSE | B35: =IFERROR(__xludf.DUMMYFUNCTION("""COMPUTED_VALUE"""),"Recrue") -> Recrue | C35: =IFERROR(__xludf.DUMMYFUNCTION("""COMPUTED_VALUE"""),"Octan") -> Octan | D35: =IFERROR(__xludf.DUMMYFUNCTION("""COMPUTED_VALUE"""),"Renatus") -> Renatus | E35: =IFERROR(__xludf.DUMMYFUNCTION("""COMPUTED_VALUE"""),"Cité de Blancherive") -> Cité de Blancherive | F35: =IFERROR(__xludf.DUMMYFUNCTION("""COMPUTED_VALUE"""),"Garde") -> Garde | G35: =IFERROR(__xludf.DUMMYFUNCTION("""COMPUTED_VALUE"""),"Radié du service actif") -> Radié du service actif
A36: =IFERROR(__xludf.DUMMYFUNCTION("""COMPUTED_VALUE"""),FALSE) -> FALSE | B36: =IFERROR(__xludf.DUMMYFUNCTION("""COMPUTED_VALUE"""),"Recrue") -> Recrue | C36: =IFERROR(__xludf.DUMMYFUNCTION("""COMPUTED_VALUE"""),"Danse-parmis-les-fous") -> Danse-parmis-les-fous | E36: =IFERROR(__xludf.DUMMYFUNCTION("""COMPUTED_VALUE"""),"Cité de Blancherive") -> Cité de Blancherive | F36: =IFERROR(__xludf.DUMMYFUNCTION("""COMPUTED_VALUE"""),"Garde") -> Garde | G36: =IFERROR(__xludf.DUMMYFUNCTION("""COMPUTED_VALUE"""),"Démissionnaire") -> Démissionnaire
A37: =IFERROR(__xludf.DUMMYFUNCTION("""COMPUTED_VALUE"""),FALSE) -> FALSE | B37: =IFERROR(__xludf.DUMMYFUNCTION("""COMPUTED_VALUE"""),"Recrue") -> Recrue | C37: =IFERROR(__xludf.DUMMYFUNCTION("""COMPUTED_VALUE"""),"Gabbo") -> Gabbo | E37: =IFERROR(__xludf.DUMMYFUNCTION("""COMPUTED_VALUE"""),"Cité de Blancherive") -> Cité de Blancherive | G37: =IFERROR(__xludf.DUMMYFUNCTION("""COMPUTED_VALUE"""),"Démissionnaire") -> Démissionnaire
A38: =IFERROR(__xludf.DUMMYFUNCTION("""COMPUTED_VALUE"""),FALSE) -> FALSE | B38: =IFERROR(__xludf.DUMMYFUNCTION("""COMPUTED_VALUE"""),"Recrue") -> Recrue | C38: =IFERROR(__xludf.DUMMYFUNCTION("""COMPUTED_VALUE"""),"Drakane") -> Drakane | E38: =IFERROR(__xludf.DUMMYFUNCTION("""COMPUTED_VALUE"""),"Cité de Blancherive") -> Cité de Blancherive | F38: =IFERROR(__xludf.DUMMYFUNCTION("""COMPUTED_VALUE"""),"Garde") -> Garde | G38: =IFERROR(__xludf.DUMMYFUNCTION("""COMPUTED_VALUE"""),"En service actif") -> En service actif
A39: =IFERROR(__xludf.DUMMYFUNCTION("""COMPUTED_VALUE"""),FALSE) -> FALSE | B39: =IFERROR(__xludf.DUMMYFUNCTION("""COMPUTED_VALUE"""),"Recrue") -> Recrue | C39: =IFERROR(__xludf.DUMMYFUNCTION("""COMPUTED_VALUE"""),"Henry") -> Henry | D39: =IFERROR(__xludf.DUMMYFUNCTION("""COMPUTED_VALUE"""),"Bonacier") -> Bonacier | E39: =IFERROR(__xludf.DUMMYFUNCTION("""COMPUTED_VALUE"""),"Cité de Blancherive") -> Cité de Blancherive | F39: =IFERROR(__xludf.DUMMYFUNCTION("""COMPUTED_VALUE"""),"Garde") -> Garde | G39: =IFERROR(__xludf.DUMMYFUNCTION("""COMPUTED_VALUE"""),"En service actif") -> En service actif
A40: =IFERROR(__xludf.DUMMYFUNCTION("""COMPUTED_VALUE"""),FALSE) -> FALSE | B40: =IFERROR(__xludf.DUMMYFUNCTION("""COMPUTED_VALUE"""),"Recrue") -> Recrue | C40: =IFERROR(__xludf.DUMMYFUNCTION("""COMPUTED_VALUE"""),"Lyrielle") -> Lyrielle | D40: =IFERROR(__xludf.DUMMYFUNCTION("""COMPUTED_VALUE"""),"Audrin") -> Audrin | E40: =IFERROR(__xludf.DUMMYFUNCTION("""COMPUTED_VALUE"""),"Cité de Blancherive") -> Cité de Blancherive | F40: =IFERROR(__xludf.DUMMYFUNCTION("""COMPUTED_VALUE"""),"Garde") -> Garde | G40: =IFERROR(__xludf.DUMMYFUNCTION("""COMPUTED_VALUE"""),"En service actif") -> En service actif
A41: =IFERROR(__xludf.DUMMYFUNCTION("""COMPUTED_VALUE"""),FALSE) -> FALSE | B41: =IFERROR(__xludf.DUMMYFUNCTION("""COMPUTED_VALUE"""),"Recrue") -> Recrue | C41: =IFERROR(__xludf.DUMMYFUNCTION("""COMPUTED_VALUE"""),"Varkiath") -> Varkiath | E41: =IFERROR(__xludf.DUMMYFUNCTION("""COMPUTED_VALUE"""),"Cité de Blancherive") -> Cité de Blancherive | F41: =IFERROR(__xludf.DUMMYFUNCTION("""COMPUTED_VALUE"""),"Garde") -> Garde | G41: =IFERROR(__xludf.DUMMYFUNCTION("""COMPUTED_VALUE"""),"En service actif") -> En service actif
A42: =IFERROR(__xludf.DUMMYFUNCTION("""COMPUTED_VALUE"""),FALSE) -> FALSE | B42: =IFERROR(__xludf.DUMMYFUNCTION("""COMPUTED_VALUE"""),"Recrue") -> Recrue | C42: =IFERROR(__xludf.DUMMYFUNCTION("""COMPUTED_VALUE"""),"Amartas") -> Amartas | D42: =IFERROR(__xludf.DUMMYFUNCTION("""COMPUTED_VALUE"""),"Après-rouge") -> Après-rouge | E42: =IFERROR(__xludf.DUMMYFUNCTION("""COMPUTED_VALUE"""),"Cité de Blancherive") -> Cité de Blancherive | F42: =IFERROR(__xludf.DUMMYFUNCTION("""COMPUTED_VALUE"""),"Garde") -> Garde | G42: =IFERROR(__xludf.DUMMYFUNCTION("""COMPUTED_VALUE"""),"En service actif") -> En service actif
A43: =IFERROR(__xludf.DUMMYFUNCTION("""COMPUTED_VALUE"""),FALSE) -> FALSE | B43: =IFERROR(__xludf.DUMMYFUNCTION("""COMPUTED_VALUE"""),"Recrue") -> Recrue | C43: =IFERROR(__xludf.DUMMYFUNCTION("""COMPUTED_VALUE"""),"Ka") -> Ka | D43: =IFERROR(__xludf.DUMMYFUNCTION("""COMPUTED_VALUE"""),"Yak") -> Yak | E43: =IFERROR(__xludf.DUMMYFUNCTION("""COMPUTED_VALUE"""),"Cité de Blancherive") -> Cité de Blancherive | F43: =IFERROR(__xludf.DUMMYFUNCTION("""COMPUTED_VALUE"""),"Garde") -> Garde | G43: =IFERROR(__xludf.DUMMYFUNCTION("""COMPUTED_VALUE"""),"En service actif") -> En service actif
A44: =IFERROR(__xludf.DUMMYFUNCTION("""COMPUTED_VALUE"""),FALSE) -> FALSE | B44: =IFERROR(__xludf.DUMMYFUNCTION("""COMPUTED_VALUE"""),"Recrue") -> Recrue | C44: =IFERROR(__xludf.DUMMYFUNCTION("""COMPUTED_VALUE"""),"Maludrar") -> Maludrar | E44: =IFERROR(__xludf.DUMMYFUNCTION("""COMPUTED_VALUE"""),"Cité de Blancherive") -> Cité de Blancherive | F44: =IFERROR(__xludf.DUMMYFUNCTION("""COMPUTED_VALUE"""),"Garde") -> Garde | G44: =IFERROR(__xludf.DUMMYFUNCTION("""COMPUTED_VALUE"""),"En service actif") -> En service actif
A45: =IFERROR(__xludf.DUMMYFUNCTION("""COMPUTED_VALUE"""),FALSE) -> FALSE | B45: =IFERROR(__xludf.DUMMYFUNCTION("""COMPUTED_VALUE"""),"Recrue") -> Recrue | C45: =IFERROR(__xludf.DUMMYFUNCTION("""COMPUTED_VALUE"""),"Numerus") -> Numerus | D45: =IFERROR(__xludf.DUMMYFUNCTION("""COMPUTED_VALUE"""),"Clausus") -> Clausus | E45: =IFERROR(__xludf.DUMMYFUNCTION("""COMPUTED_VALUE"""),"Cité de Blancherive") -> Cité de Blancherive | F45: =IFERROR(__xludf.DUMMYFUNCTION("""COMPUTED_VALUE"""),"Garde") -> Garde | G45: =IFERROR(__xludf.DUMMYFUNCTION("""COMPUTED_VALUE"""),"En service actif") -> En service actif

Sheet Garde des Faubourgs
A1: =IFERROR(__xludf.DUMMYFUNCTION("QUERY(Effectifs!A:Z, ""SELECT * WHERE E CONTAINS 'Faubourgs' ORDER BY Z ASC"", 1)"),"Assermenté") -> Assermenté | B1: =IFERROR(__xludf.DUMMYFUNCTION("""COMPUTED_VALUE"""),"Grade") -> Grade | C1: =IFERROR(__xludf.DUMMYFUNCTION("""COMPUTED_VALUE"""),"Prénom") -> Prénom | D1: =IFERROR(__xludf.DUMMYFUNCTION("""COMPUTED_VALUE"""),"Nom") -> Nom | E1: =IFERROR(__xludf.DUMMYFUNCTION("""COMPUTED_VALUE"""),"Corps") -> Corps | F1: =IFERROR(__xludf.DUMMYFUNCTION("""COMPUTED_VALUE"""),"Spécialité") -> Spécialité | G1: =IFERROR(__xludf.DUMMYFUNCTION("""COMPUTED_VALUE"""),"Status") -> Status | H1: =IFERROR(__xludf.DUMMYFUNCTION("""COMPUTED_VALUE"""),"Métier") -> Métier | I1: =IFERROR(__xludf.DUMMYFUNCTION("""COMPUTED_VALUE"""),"") | J1: =IFERROR(__xludf.DUMMYFUNCTION("""COMPUTED_VALUE"""),"") | K1: =IFERROR(__xludf.DUMMYFUNCTION("""COMPUTED_VALUE"""),"") | L1: =IFERROR(__xludf.DUMMYFUNCTION("""COMPUTED_VALUE"""),"") | M1: =IFERROR(__xludf.DUMMYFUNCTION("""COMPUTED_VALUE"""),"") | N1: =IFERROR(__xludf.DUMMYFUNCTION("""COMPUTED_VALUE"""),"") | O1: =IFERROR(__xludf.DUMMYFUNCTION("""COMPUTED_VALUE"""),"") | P1: =IFERROR(__xludf.DUMMYFUNCTION("""COMPUTED_VALUE"""),"") | ... Z1: =IFERROR(__xludf.DUMMYFUNCTION("""COMPUTED_VALUE"""),"")
A2: =IFERROR(__xludf.DUMMYFUNCTION("""COMPUTED_VALUE"""),TRUE) -> TRUE | B2: =IFERROR(__xludf.DUMMYFUNCTION("""COMPUTED_VALUE"""),"Capitaine") -> Capitaine | C2: =IFERROR(__xludf.DUMMYFUNCTION("""COMPUTED_VALUE"""),"Kah-Shir") -> Kah-Shir | D2: =IFERROR(__xludf.DUMMYFUNCTION("""COMPUTED_VALUE"""),"Sombre Griffe") -> Sombre Griffe | E2: =IFERROR(__xludf.DUMMYFUNCTION("""COMPUTED_VALUE"""),"Faubourgs de Blancherive") -> Faubourgs de Blancherive | G2: =IFERROR(__xludf.DUMMYFUNCTION("""COMPUTED_VALUE"""),"Radié du service actif") -> Radié du service actif
A3: =IFERROR(__xludf.DUMMYFUNCTION("""COMPUTED_VALUE"""),FALSE) -> FALSE | B3: =IFERROR(__xludf.DUMMYFUNCTION("""COMPUTED_VALUE"""),"Garde") -> Garde | C3: =IFERROR(__xludf.DUMMYFUNCTION("""COMPUTED_VALUE"""),"Léonce") -> Léonce | D3: =IFERROR(__xludf.DUMMYFUNCTION("""COMPUTED_VALUE"""),"Réve-épine") -> Réve-épine | E3: =IFERROR(__xludf.DUMMYFUNCTION("""COMPUTED_VALUE"""),"Faubourgs de Blancherive") -> Faubourgs de Blancherive | G3: =IFERROR(__xludf.DUMMYFUNCTION("""COMPUTED_VALUE"""),"Radié du service actif") -> Radié du service actif
A4: =IFERROR(__xludf.DUMMYFUNCTION("""COMPUTED_VALUE"""),FALSE) -> FALSE | B4: =IFERROR(__xludf.DUMMYFUNCTION("""COMPUTED_VALUE"""),"Lieutenant-Chef") -> Lieutenant-Chef | C4: =IFERROR(__xludf.DUMMYFUNCTION("""COMPUTED_VALUE"""),"Il-draz ") -> Il-draz | D4: =IFERROR(__xludf.DUMMYFUNCTION("""COMPUTED_VALUE"""),"De Chasse-au-bois") -> De Chasse-au-bois | E4: =IFERROR(__xludf.DUMMYFUNCTION("""COMPUTED_VALUE"""),"Faubourgs de Blancherive") -> Faubourgs de Blancherive | G4: =IFERROR(__xludf.DUMMYFUNCTION("""COMPUTED_VALUE"""),"Radié du service actif") -> Radié du service actif
A5: =IFERROR(__xludf.DUMMYFUNCTION("""COMPUTED_VALUE"""),FALSE) -> FALSE | B5: =IFERROR(__xludf.DUMMYFUNCTION("""COMPUTED_VALUE"""),"Lieutenant") -> Lieutenant | C5: =IFERROR(__xludf.DUMMYFUNCTION("""COMPUTED_VALUE"""),"Gorvin") -> Gorvin | D5: =IFERROR(__xludf.DUMMYFUNCTION("""COMPUTED_VALUE"""),"Le-Moite") -> Le-Moite | E5: =IFERROR(__xludf.DUMMYFUNCTION("""COMPUTED_VALUE"""),"Faubourgs de Blancherive") -> Faubourgs de Blancherive | G5: =IFERROR(__xludf.DUMMYFUNCTION("""COMPUTED_VALUE"""),"Radié du service actif") -> Radié du service actif
A6: =IFERROR(__xludf.DUMMYFUNCTION("""COMPUTED_VALUE"""),FALSE) -> FALSE | B6: =IFERROR(__xludf.DUMMYFUNCTION("""COMPUTED_VALUE"""),"Garde") -> Garde | C6: =IFERROR(__xludf.DUMMYFUNCTION("""COMPUTED_VALUE"""),"Smaug") -> Smaug | E6: =IFERROR(__xludf.DUMMYFUNCTION("""COMPUTED_VALUE"""),"Faubourgs de Blancherive") -> Faubourgs de Blancherive | G6: =IFERROR(__xludf.DUMMYFUNCTION("""COMPUTED_VALUE"""),"Radié du service actif") -> Radié du service actif
A7: =IFERROR(__xludf.DUMMYFUNCTION("""COMPUTED_VALUE"""),FALSE) -> FALSE | B7: =IFERROR(__xludf.DUMMYFUNCTION("""COMPUTED_VALUE"""),"Garde") -> Garde | C7: =IFERROR(__xludf.DUMMYFUNCTION("""COMPUTED_VALUE"""),"Njalda") -> Njalda | E7: =IFERROR(__xludf.DUMMYFUNCTION("""COMPUTED_VALUE"""),"Faubourgs de Blancherive") -> Faubourgs de Blancherive | G7: =IFERROR(__xludf.DUMMYFUNCTION("""COMPUTED_VALUE"""),"Radié du service actif") -> Radié du service actif
A8: =IFERROR(__xludf.DUMMYFUNCTION("""COMPUTED_VALUE"""),FALSE) -> FALSE | B8: =IFERROR(__xludf.DUMMYFUNCTION("""COMPUTED_VALUE"""),"Garde") -> Garde | C8: =IFERROR(__xludf.DUMMYFUNCTION("""COMPUTED_VALUE"""),"Darina") -> Darina | E8: =IFERROR(__xludf.DUMMYFUNCTION("""COMPUTED_VALUE"""),"Faubourgs de Blancherive") -> Faubourgs de Blancherive | G8: =IFERROR(__xludf.DUMMYFUNCTION("""COMPUTED_VALUE"""),"Radié du service actif") -> Radié du service actif
A9: =IFERROR(__xludf.DUMMYFUNCTION("""COMPUTED_VALUE"""),FALSE) -> FALSE | B9: =IFERROR(__xludf.DUMMYFUNCTION("""COMPUTED_VALUE"""),"Sergent") -> Sergent | C9: =IFERROR(__xludf.DUMMYFUNCTION("""COMPUTED_VALUE"""),"Jeebam-dee") -> Jeebam-dee | E9: =IFERROR(__xludf.DUMMYFUNCTION("""COMPUTED_VALUE"""),"Faubourgs de Blancherive") -> Faubourgs de Blancherive | G9: =IFERROR(__xludf.DUMMYFUNCTION("""COMPUTED_VALUE"""),"Radié du service actif") -> Radié du service actif
A10: =IFERROR(__xludf.DUMMYFUNCTION("""COMPUTED_VALUE"""),FALSE) -> FALSE | B10: =IFERROR(__xludf.DUMMYFUNCTION("""COMPUTED_VALUE"""),"Garde") -> Garde | C10: =IFERROR(__xludf.DUMMYFUNCTION("""COMPUTED_VALUE"""),"Torald") -> Torald | D10: =IFERROR(__xludf.DUMMYFUNCTION("""COMPUTED_VALUE"""),"Brise-Roche") -> Brise-Roche | E10: =IFERROR(__xludf.DUMMYFUNCTION("""COMPUTED_VALUE"""),"Faubourgs de Blancherive") -> Faubourgs de Blancherive | G10: =IFERROR(__xludf.DUMMYFUNCTION("""COMPUTED_VALUE"""),"Radié du service actif") -> Radié du service actif
A11: =IFERROR(__xludf.DUMMYFUNCTION("""COMPUTED_VALUE"""),FALSE) -> FALSE | B11: =IFERROR(__xludf.DUMMYFUNCTION("""COMPUTED_VALUE"""),"Garde") -> Garde | C11: =IFERROR(__xludf.DUMMYFUNCTION("""COMPUTED_VALUE"""),"Bernis") -> Bernis | E11: =IFERROR(__xludf.DUMMYFUNCTION("""COMPUTED_VALUE"""),"Faubourgs de Blancherive") -> Faubourgs de Blancherive | F11: =IFERROR(__xludf.DUMMYFUNCTION("""COMPUTED_VALUE"""),"Garde") -> Garde | G11: =IFERROR(__xludf.DUMMYFUNCTION("""COMPUTED_VALUE"""),"Radié du service actif") -> Radié du service actif
A12: =IFERROR(__xludf.DUMMYFUNCTION("""COMPUTED_VALUE"""),FALSE) -> FALSE | B12: =IFERROR(__xludf.DUMMYFUNCTION("""COMPUTED_VALUE"""),"Cadet") -> Cadet | C12: =IFERROR(__xludf.DUMMYFUNCTION("""COMPUTED_VALUE"""),"Ina'ra") -> Ina'ra | E12: =IFERROR(__xludf.DUMMYFUNCTION("""COMPUTED_VALUE"""),"Faubourgs de Blancherive") -> Faubourgs de Blancherive | G12: =IFERROR(__xludf.DUMMYFUNCTION("""COMPUTED_VALUE"""),"Radié du service actif") -> Radié du service actif
A13: =IFERROR(__xludf.DUMMYFUNCTION("""COMPUTED_VALUE"""),FALSE) -> FALSE | B13: =IFERROR(__xludf.DUMMYFUNCTION("""COMPUTED_VALUE"""),"Sergent") -> Sergent | C13: =IFERROR(__xludf.DUMMYFUNCTION("""COMPUTED_VALUE"""),"Ja'Shanir") -> Ja'Shanir | E13: =IFERROR(__xludf.DUMMYFUNCTION("""COMPUTED_VALUE"""),"Faubourgs de Blancherive") -> Faubourgs de Blancherive | F13: =IFERROR(__xludf.DUMMYFUNCTION("""COMPUTED_VALUE"""),"Garde") -> Garde | G13: =IFERROR(__xludf.DUMMYFUNCTION("""COMPUTED_VALUE"""),"Démissionnaire") -> Démissionnaire
A14: =IFERROR(__xludf.DUMMYFUNCTION("""COMPUTED_VALUE"""),FALSE) -> FALSE | B14: =IFERROR(__xludf.DUMMYFUNCTION("""COMPUTED_VALUE"""),"Garde") -> Garde | C14: =IFERROR(__xludf.DUMMYFUNCTION("""COMPUTED_VALUE"""),"Meta Peau de Braise") -> Meta Peau de Braise | E14: =IFERROR(__xludf.DUMMYFUNCTION("""COMPUTED_VALUE"""),"Faubourgs de Blancherive") -> Faubourgs de Blancherive | G14: =IFERROR(__xludf.DUMMYFUNCTION("""COMPUTED_VALUE"""),"Radié du service actif") -> Radié du service actif
A15: =IFERROR(__xludf.DUMMYFUNCTION("""COMPUTED_VALUE"""),TRUE) -> TRUE | B15: =IFERROR(__xludf.DUMMYFUNCTION("""COMPUTED_VALUE"""),"Lieutenant-Chef") -> Lieutenant-Chef | C15: =IFERROR(__xludf.DUMMYFUNCTION("""COMPUTED_VALUE"""),"Thov") -> Thov | D15: =IFERROR(__xludf.DUMMYFUNCTION("""COMPUTED_VALUE"""),"Lémartes") -> Lémartes | E15: =IFERROR(__xludf.DUMMYFUNCTION("""COMPUTED_VALUE"""),"Faubourgs de Blancherive") -> Faubourgs de Blancherive | F15: =IFERROR(__xludf.DUMMYFUNCTION("""COMPUTED_VALUE"""),"Garde") -> Garde | G15: =IFERROR(__xludf.DUMMYFUNCTION("""COMPUTED_VALUE"""),"En service actif") -> En service actif
A16: =IFERROR(__xludf.DUMMYFUNCTION("""COMPUTED_VALUE"""),FALSE) -> FALSE | B16: =IFERROR(__xludf.DUMMYFUNCTION("""COMPUTED_VALUE"""),"Garde") -> Garde | C16: =IFERROR(__xludf.DUMMYFUNCTION("""COMPUTED_VALUE"""),"Asvald'ur") -> Asvald'ur | E16: =IFERROR(__xludf.DUMMYFUNCTION("""COMPUTED_VALUE"""),"Faubourgs de Blancherive") -> Faubourgs de Blancherive | G16: =IFERROR(__xludf.DUMMYFUNCTION("""COMPUTED_VALUE"""),"Démissionnaire") -> Démissionnaire
A17: =IFERROR(__xludf.DUMMYFUNCTION("""COMPUTED_VALUE"""),TRUE) -> TRUE | B17: =IFERROR(__xludf.DUMMYFUNCTION("""COMPUTED_VALUE"""),"Lieutenant") -> Lieutenant | C17: =IFERROR(__xludf.DUMMYFUNCTION("""COMPUTED_VALUE"""),"Claudus") -> Claudus | E17: =IFERROR(__xludf.DUMMYFUNCTION("""COMPUTED_VALUE"""),"Faubourgs de Blancherive") -> Faubourgs de Blancherive | F17: =IFERROR(__xludf.DUMMYFUNCTION("""COMPUTED_VALUE"""),"Garde") -> Garde | G17: =IFERROR(__xludf.DUMMYFUNCTION("""COMPUTED_VALUE"""),"En service actif") -> En service actif
A18: =IFERROR(__xludf.DUMMYFUNCTION("""COMPUTED_VALUE"""),TRUE) -> TRUE | B18: =IFERROR(__xludf.DUMMYFUNCTION("""COMPUTED_VALUE"""),"Capitaine") -> Capitaine | C18: =IFERROR(__xludf.DUMMYFUNCTION("""COMPUTED_VALUE"""),"Harald le hardi") -> Harald le hardi | E18: =IFERROR(__xludf.DUMMYFUNCTION("""COMPUTED_VALUE"""),"Faubourgs de Blancherive") -> Faubourgs de Blancherive | F18: =IFERROR(__xludf.DUMMYFUNCTION("""COMPUTED_VALUE"""),"Garde") -> Garde | G18: =IFERROR(__xludf.DUMMYFUNCTION("""COMPUTED_VALUE"""),"En service actif") -> En service actif
A19: =IFERROR(__xludf.DUMMYFUNCTION("""COMPUTED_VALUE"""),TRUE) -> TRUE | B19: =IFERROR(__xludf.DUMMYFUNCTION("""COMPUTED_VALUE"""),"Lieutenant-Chef") -> Lieutenant-Chef | C19: =IFERROR(__xludf.DUMMYFUNCTION("""COMPUTED_VALUE"""),"Knut") -> Knut | D19: =IFERROR(__xludf.DUMMYFUNCTION("""COMPUTED_VALUE"""),"Crâne-fou") -> Crâne-fou | E19: =IFERROR(__xludf.DUMMYFUNCTION("""COMPUTED_VALUE"""),"Faubourgs de Blancherive") -> Faubourgs de Blancherive | F19: =IFERROR(__xludf.DUMMYFUNCTION("""COMPUTED_VALUE"""),"Garde") -> Garde | G19: =IFERROR(__xludf.DUMMYFUNCTION("""COMPUTED_VALUE"""),"Mis en réserve") -> Mis en réserve
A20: =IFERROR(__xludf.DUMMYFUNCTION("""COMPUTED_VALUE"""),TRUE) -> TRUE | B20: =IFERROR(__xludf.DUMMYFUNCTION("""COMPUTED_VALUE"""),"Lieutenant") -> Lieutenant | C20: =IFERROR(__xludf.DUMMYFUNCTION("""COMPUTED_VALUE"""),"Asvaldur") -> Asvaldur | E20: =IFERROR(__xludf.DUMMYFUNCTION("""COMPUTED_VALUE"""),"Faubourgs de Blancherive") -> Faubourgs de Blancherive | F20: =IFERROR(__xludf.DUMMYFUNCTION("""COMPUTED_VALUE"""),"Garde") -> Garde | G20: =IFERROR(__xludf.DUMMYFUNCTION("""COMPUTED_VALUE"""),"En service actif") -> En service actif
A21: =IFERROR(__xludf.DUMMYFUNCTION("""COMPUTED_VALUE"""),FALSE) -> FALSE | B21: =IFERROR(__xludf.DUMMYFUNCTION("""COMPUTED_VALUE"""),"Recrue") -> Recrue | C21: =IFERROR(__xludf.DUMMYFUNCTION("""COMPUTED_VALUE"""),"Vaegon") -> Vaegon | E21: =IFERROR(__xludf.DUMMYFUNCTION("""COMPUTED_VALUE"""),"Faubourgs de Blancherive") -> Faubourgs de Blancherive | F21: =IFERROR(__xludf.DUMMYFUNCTION("""COMPUTED_VALUE"""),"Garde") -> Garde | G21: =IFERROR(__xludf.DUMMYFUNCTION("""COMPUTED_VALUE"""),"En service actif") -> En service actif
A22: =IFERROR(__xludf.DUMMYFUNCTION("""COMPUTED_VALUE"""),FALSE) -> FALSE | B22: =IFERROR(__xludf.DUMMYFUNCTION("""COMPUTED_VALUE"""),"Recrue") -> Recrue | C22: =IFERROR(__xludf.DUMMYFUNCTION("""COMPUTED_VALUE"""),"Nymor") -> Nymor | E22: =IFERROR(__xludf.DUMMYFUNCTION("""COMPUTED_VALUE"""),"Faubourgs de Blancherive") -> Faubourgs de Blancherive | F22: =IFERROR(__xludf.DUMMYFUNCTION("""COMPUTED_VALUE"""),"Garde") -> Garde | G22: =IFERROR(__xludf.DUMMYFUNCTION("""COMPUTED_VALUE"""),"En service actif") -> En service actif
A23: =IFERROR(__xludf.DUMMYFUNCTION("""COMPUTED_VALUE"""),TRUE) -> TRUE | B23: =IFERROR(__xludf.DUMMYFUNCTION("""COMPUTED_VALUE"""),"Recrue") -> Recrue | C23: =IFERROR(__xludf.DUMMYFUNCTION("""COMPUTED_VALUE"""),"Vahne") -> Vahne | E23: =IFERROR(__xludf.DUMMYFUNCTION("""COMPUTED_VALUE"""),"Faubourgs de Blancherive") -> Faubourgs de Blancherive | F23: =IFERROR(__xludf.DUMMYFUNCTION("""COMPUTED_VALUE"""),"Garde") -> Garde | G23: =IFERROR(__xludf.DUMMYFUNCTION("""COMPUTED_VALUE"""),"En service actif") -> En service actif

Sheet Hird du Jarl
A1: =IFERROR(__xludf.DUMMYFUNCTION("QUERY(Effectifs!A:Z, ""SELECT * WHERE E CONTAINS 'Hird' ORDER BY Z ASC"", 1)"),"Assermenté") -> Assermenté | B1: =IFERROR(__xludf.DUMMYFUNCTION("""COMPUTED_VALUE"""),"Grade") -> Grade | C1: =IFERROR(__xludf.DUMMYFUNCTION("""COMPUTED_VALUE"""),"Prénom") -> Prénom | D1: =IFERROR(__xludf.DUMMYFUNCTION("""COMPUTED_VALUE"""),"Nom") -> Nom | E1: =IFERROR(__xludf.DUMMYFUNCTION("""COMPUTED_VALUE"""),"Corps") -> Corps | F1: =IFERROR(__xludf.DUMMYFUNCTION("""COMPUTED_VALUE"""),"Spécialité") -> Spécialité | G1: =IFERROR(__xludf.DUMMYFUNCTION("""COMPUTED_VALUE"""),"Status") -> Status | H1: =IFERROR(__xludf.DUMMYFUNCTION("""COMPUTED_VALUE"""),"Métier") -> Métier | I1: =IFERROR(__xludf.DUMMYFUNCTION("""COMPUTED_VALUE"""),"") | J1: =IFERROR(__xludf.DUMMYFUNCTION("""COMPUTED_VALUE"""),"") | K1: =IFERROR(__xludf.DUMMYFUNCTION("""COMPUTED_VALUE"""),"") | L1: =IFERROR(__xludf.DUMMYFUNCTION("""COMPUTED_VALUE"""),"") | M1: =IFERROR(__xludf.DUMMYFUNCTION("""COMPUTED_VALUE"""),"") | N1: =IFERROR(__xludf.DUMMYFUNCTION("""COMPUTED_VALUE"""),"") | O1: =IFERROR(__xludf.DUMMYFUNCTION("""COMPUTED_VALUE"""),"") | P1: =IFERROR(__xludf.DUMMYFUNCTION("""COMPUTED_VALUE"""),"") | ... Z1: =IFERROR(__xludf.DUMMYFUNCTION("""COMPUTED_VALUE"""),"")
A2: =IFERROR(__xludf.DUMMYFUNCTION("""COMPUTED_VALUE"""),FALSE) -> FALSE | B2: =IFERROR(__xludf.DUMMYFUNCTION("""COMPUTED_VALUE"""),"Garde") -> Garde | C2: =IFERROR(__xludf.DUMMYFUNCTION("""COMPUTED_VALUE"""),"Kronk") -> Kronk | D2: =IFERROR(__xludf.DUMMYFUNCTION("""COMPUTED_VALUE"""),"Grognon") -> Grognon | E2: =IFERROR(__xludf.DUMMYFUNCTION("""COMPUTED_VALUE"""),"Hird du Jarl") -> Hird du Jarl | F2: =IFERROR(__xludf.DUMMYFUNCTION("""COMPUTED_VALUE"""),"Hird") -> Hird | G2: =IFERROR(__xludf.DUMMYFUNCTION("""COMPUTED_VALUE"""),"En service actif") -> En service actif
A3: =IFERROR(__xludf.DUMMYFUNCTION("""COMPUTED_VALUE"""),FALSE) -> FALSE | B3: =IFERROR(__xludf.DUMMYFUNCTION("""COMPUTED_VALUE"""),"Garde") -> Garde | C3: =IFERROR(__xludf.DUMMYFUNCTION("""COMPUTED_VALUE"""),"Gronk") -> Gronk | D3: =IFERROR(__xludf.DUMMYFUNCTION("""COMPUTED_VALUE"""),"Grognon") -> Grognon | E3: =IFERROR(__xludf.DUMMYFUNCTION("""COMPUTED_VALUE"""),"Hird du Jarl") -> Hird du Jarl | F3: =IFERROR(__xludf.DUMMYFUNCTION("""COMPUTED_VALUE"""),"Hird") -> Hird | G3: =IFERROR(__xludf.DUMMYFUNCTION("""COMPUTED_VALUE"""),"En service actif") -> En service actif
A4: =IFERROR(__xludf.DUMMYFUNCTION("""COMPUTED_VALUE"""),FALSE) -> FALSE | B4: =IFERROR(__xludf.DUMMYFUNCTION("""COMPUTED_VALUE"""),"Garde") -> Garde | C4: =IFERROR(__xludf.DUMMYFUNCTION("""COMPUTED_VALUE"""),"S'Khar") -> S'Khar | E4: =IFERROR(__xludf.DUMMYFUNCTION("""COMPUTED_VALUE"""),"Hird du Jarl") -> Hird du Jarl | F4: =IFERROR(__xludf.DUMMYFUNCTION("""COMPUTED_VALUE"""),"Hird") -> Hird | G4: =IFERROR(__xludf.DUMMYFUNCTION("""COMPUTED_VALUE"""),"En service actif") -> En service actif
A5: =IFERROR(__xludf.DUMMYFUNCTION("""COMPUTED_VALUE"""),FALSE) -> FALSE | B5: =IFERROR(__xludf.DUMMYFUNCTION("""COMPUTED_VALUE"""),"Garde") -> Garde | C5: =IFERROR(__xludf.DUMMYFUNCTION("""COMPUTED_VALUE"""),"Gorbash") -> Gorbash | D5: =IFERROR(__xludf.DUMMYFUNCTION("""COMPUTED_VALUE"""),"Tête-de-Pierre") -> Tête-de-Pierre | E5: =IFERROR(__xludf.DUMMYFUNCTION("""COMPUTED_VALUE"""),"Hird du Jarl") -> Hird du Jarl | F5: =IFERROR(__xludf.DUMMYFUNCTION("""COMPUTED_VALUE"""),"Hird") -> Hird | G5: =IFERROR(__xludf.DUMMYFUNCTION("""COMPUTED_VALUE"""),"En service actif") -> En service actif
A6: =IFERROR(__xludf.DUMMYFUNCTION("""COMPUTED_VALUE"""),FALSE) -> FALSE | B6: =IFERROR(__xludf.DUMMYFUNCTION("""COMPUTED_VALUE"""),"Garde") -> Garde | C6: =IFERROR(__xludf.DUMMYFUNCTION("""COMPUTED_VALUE"""),"Armand") -> Armand | D6: =IFERROR(__xludf.DUMMYFUNCTION("""COMPUTED_VALUE"""),"De Valclair") -> De Valclair | E6: =IFERROR(__xludf.DUMMYFUNCTION("""COMPUTED_VALUE"""),"Hird du Jarl") -> Hird du Jarl | F6: =IFERROR(__xludf.DUMMYFUNCTION("""COMPUTED_VALUE"""),"Hird") -> Hird | G6: =IFERROR(__xludf.DUMMYFUNCTION("""COMPUTED_VALUE"""),"Démissionnaire") -> Démissionnaire
A7: =IFERROR(__xludf.DUMMYFUNCTION("""COMPUTED_VALUE"""),FALSE) -> FALSE | B7: =IFERROR(__xludf.DUMMYFUNCTION("""COMPUTED_VALUE"""),"Garde") -> Garde | C7: =IFERROR(__xludf.DUMMYFUNCTION("""COMPUTED_VALUE"""),"Si'Yara") -> Si'Yara | D7: =IFERROR(__xludf.DUMMYFUNCTION("""COMPUTED_VALUE"""),"dite Fou") -> dite Fou | E7: =IFERROR(__xludf.DUMMYFUNCTION("""COMPUTED_VALUE"""),"Hird du Jarl") -> Hird du Jarl | F7: =IFERROR(__xludf.DUMMYFUNCTION("""COMPUTED_VALUE"""),"Hird") -> Hird | G7: =IFERROR(__xludf.DUMMYFUNCTION("""COMPUTED_VALUE"""),"En service actif") -> En service actif
A8: =IFERROR(__xludf.DUMMYFUNCTION("""COMPUTED_VALUE"""),FALSE) -> FALSE | B8: =IFERROR(__xludf.DUMMYFUNCTION("""COMPUTED_VALUE"""),"Garde") -> Garde | C8: =IFERROR(__xludf.DUMMYFUNCTION("""COMPUTED_VALUE"""),"Lokh") -> Lokh | D8: =IFERROR(__xludf.DUMMYFUNCTION("""COMPUTED_VALUE"""),"Tar") -> Tar | E8: =IFERROR(__xludf.DUMMYFUNCTION("""COMPUTED_VALUE"""),"Hird du Jarl") -> Hird du Jarl | F8: =IFERROR(__xludf.DUMMYFUNCTION("""COMPUTED_VALUE"""),"Hird") -> Hird | G8: =IFERROR(__xludf.DUMMYFUNCTION("""COMPUTED_VALUE"""),"En service actif") -> En service actif
A9: =IFERROR(__xludf.DUMMYFUNCTION("""COMPUTED_VALUE"""),FALSE) -> FALSE | B9: =IFERROR(__xludf.DUMMYFUNCTION("""COMPUTED_VALUE"""),"Capitaine") -> Capitaine | C9: =IFERROR(__xludf.DUMMYFUNCTION("""COMPUTED_VALUE"""),"Theodrek") -> Theodrek | D9: =IFERROR(__xludf.DUMMYFUNCTION("""COMPUTED_VALUE"""),"Heid") -> Heid | E9: =IFERROR(__xludf.DUMMYFUNCTION("""COMPUTED_VALUE"""),"Hird du Jarl") -> Hird du Jarl | F9: =IFERROR(__xludf.DUMMYFUNCTION("""COMPUTED_VALUE"""),"Hird") -> Hird | G9: =IFERROR(__xludf.DUMMYFUNCTION("""COMPUTED_VALUE"""),"En service actif") -> En service actif
A10: =IFERROR(__xludf.DUMMYFUNCTION("""COMPUTED_VALUE"""),FALSE) -> FALSE | B10: =IFERROR(__xludf.DUMMYFUNCTION("""COMPUTED_VALUE"""),"Garde") -> Garde | C10: =IFERROR(__xludf.DUMMYFUNCTION("""COMPUTED_VALUE"""),"Selene") -> Selene | E10: =IFERROR(__xludf.DUMMYFUNCTION("""COMPUTED_VALUE"""),"Hird du Jarl") -> Hird du Jarl | F10: =IFERROR(__xludf.DUMMYFUNCTION("""COMPUTED_VALUE"""),"Hird") -> Hird | G10: =IFERROR(__xludf.DUMMYFUNCTION("""COMPUTED_VALUE"""),"En service actif") -> En service actif
A11: =IFERROR(__xludf.DUMMYFUNCTION("""COMPUTED_VALUE"""),FALSE) -> FALSE | B11: =IFERROR(__xludf.DUMMYFUNCTION("""COMPUTED_VALUE"""),"Garde") -> Garde | C11: =IFERROR(__xludf.DUMMYFUNCTION("""COMPUTED_VALUE"""),"Lucius") -> Lucius | D11: =IFERROR(__xludf.DUMMYFUNCTION("""COMPUTED_VALUE"""),"Ravenshield") -> Ravenshield | E11: =IFERROR(__xludf.DUMMYFUNCTION("""COMPUTED_VALUE"""),"Hird du Jarl") -> Hird du Jarl | F11: =IFERROR(__xludf.DUMMYFUNCTION("""COMPUTED_VALUE"""),"Hird") -> Hird | G11: =IFERROR(__xludf.DUMMYFUNCTION("""COMPUTED_VALUE"""),"En service actif") -> En service actif
A12: =IFERROR(__xludf.DUMMYFUNCTION("""COMPUTED_VALUE"""),FALSE) -> FALSE | B12: =IFERROR(__xludf.DUMMYFUNCTION("""COMPUTED_VALUE"""),"Garde") -> Garde | C12: =IFERROR(__xludf.DUMMYFUNCTION("""COMPUTED_VALUE"""),"Faynir") -> Faynir | E12: =IFERROR(__xludf.DUMMYFUNCTION("""COMPUTED_VALUE"""),"Hird du Jarl") -> Hird du Jarl | F12: =IFERROR(__xludf.DUMMYFUNCTION("""COMPUTED_VALUE"""),"Hird") -> Hird | G12: =IFERROR(__xludf.DUMMYFUNCTION("""COMPUTED_VALUE"""),"En service actif") -> En service actif
A13: =IFERROR(__xludf.DUMMYFUNCTION("""COMPUTED_VALUE"""),FALSE) -> FALSE | B13: =IFERROR(__xludf.DUMMYFUNCTION("""COMPUTED_VALUE"""),"Garde") -> Garde | C13: =IFERROR(__xludf.DUMMYFUNCTION("""COMPUTED_VALUE"""),"Varaa") -> Varaa | D13: =IFERROR(__xludf.DUMMYFUNCTION("""COMPUTED_VALUE"""),"Uzgar") -> Uzgar | E13: =IFERROR(__xludf.DUMMYFUNCTION("""COMPUTED_VALUE"""),"Hird du Jarl") -> Hird du Jarl | F13: =IFERROR(__xludf.DUMMYFUNCTION("""COMPUTED_VALUE"""),"Hird") -> Hird | G13: =IFERROR(__xludf.DUMMYFUNCTION("""COMPUTED_VALUE"""),"En service actif") -> En service actif

Sheet Garde de Bois-de-Chêne
A1: =IFERROR(__xludf.DUMMYFUNCTION("QUERY(Effectifs!A:Z, ""SELECT * WHERE E CONTAINS 'Chêne' ORDER BY Z ASC"", 1)"),"Assermenté") -> Assermenté | B1: =IFERROR(__xludf.DUMMYFUNCTION("""COMPUTED_VALUE"""),"Grade") -> Grade | C1: =IFERROR(__xludf.DUMMYFUNCTION("""COMPUTED_VALUE"""),"Prénom") -> Prénom | D1: =IFERROR(__xludf.DUMMYFUNCTION("""COMPUTED_VALUE"""),"Nom") -> Nom | E1: =IFERROR(__xludf.DUMMYFUNCTION("""COMPUTED_VALUE"""),"Corps") -> Corps | F1: =IFERROR(__xludf.DUMMYFUNCTION("""COMPUTED_VALUE"""),"Spécialité") -> Spécialité | G1: =IFERROR(__xludf.DUMMYFUNCTION("""COMPUTED_VALUE"""),"Status") -> Status | H1: =IFERROR(__xludf.DUMMYFUNCTION("""COMPUTED_VALUE"""),"Métier") -> Métier | I1: =IFERROR(__xludf.DUMMYFUNCTION("""COMPUTED_VALUE"""),"") | J1: =IFERROR(__xludf.DUMMYFUNCTION("""COMPUTED_VALUE"""),"") | K1: =IFERROR(__xludf.DUMMYFUNCTION("""COMPUTED_VALUE"""),"") | L1: =IFERROR(__xludf.DUMMYFUNCTION("""COMPUTED_VALUE"""),"") | M1: =IFERROR(__xludf.DUMMYFUNCTION("""COMPUTED_VALUE"""),"") | N1: =IFERROR(__xludf.DUMMYFUNCTION("""COMPUTED_VALUE"""),"") | O1: =IFERROR(__xludf.DUMMYFUNCTION("""COMPUTED_VALUE"""),"") | P1: =IFERROR(__xludf.DUMMYFUNCTION("""COMPUTED_VALUE"""),"") | ... Z1: =IFERROR(__xludf.DUMMYFUNCTION("""COMPUTED_VALUE"""),"")
A2: =IFERROR(__xludf.DUMMYFUNCTION("""COMPUTED_VALUE"""),TRUE) -> TRUE | B2: =IFERROR(__xludf.DUMMYFUNCTION("""COMPUTED_VALUE"""),"Major") -> Major | C2: =IFERROR(__xludf.DUMMYFUNCTION("""COMPUTED_VALUE"""),"Rusco") -> Rusco | E2: =IFERROR(__xludf.DUMMYFUNCTION("""COMPUTED_VALUE"""),"Bois-de-Chêne") -> Bois-de-Chêne | F2: =IFERROR(__xludf.DUMMYFUNCTION("""COMPUTED_VALUE"""),"Garde") -> Garde | G2: =IFERROR(__xludf.DUMMYFUNCTION("""COMPUTED_VALUE"""),"En service actif") -> En service actif
A3: =IFERROR(__xludf.DUMMYFUNCTION("""COMPUTED_VALUE"""),FALSE) -> FALSE | B3: =IFERROR(__xludf.DUMMYFUNCTION("""COMPUTED_VALUE"""),"Recrue") -> Recrue | C3: =IFERROR(__xludf.DUMMYFUNCTION("""COMPUTED_VALUE"""),"Darius") -> Darius | D3: =IFERROR(__xludf.DUMMYFUNCTION("""COMPUTED_VALUE"""),"Blacktorn") -> Blacktorn | E3: =IFERROR(__xludf.DUMMYFUNCTION("""COMPUTED_VALUE"""),"Bois-de-Chêne") -> Bois-de-Chêne | F3: =IFERROR(__xludf.DUMMYFUNCTION("""COMPUTED_VALUE"""),"Garde, Collecteur de la garde") -> Garde, Collecteur de la garde | G3: =IFERROR(__xludf.DUMMYFUNCTION("""COMPUTED_VALUE"""),"Radié du service actif") -> Radié du service actif
A4: =IFERROR(__xludf.DUMMYFUNCTION("""COMPUTED_VALUE"""),TRUE) -> TRUE | B4: =IFERROR(__xludf.DUMMYFUNCTION("""COMPUTED_VALUE"""),"Capitaine") -> Capitaine | C4: =IFERROR(__xludf.DUMMYFUNCTION("""COMPUTED_VALUE"""),"Ra'zir") -> Ra'zir | D4: =IFERROR(__xludf.DUMMYFUNCTION("""COMPUTED_VALUE"""),"Poing-de-fer") -> Poing-de-fer | E4: =IFERROR(__xludf.DUMMYFUNCTION("""COMPUTED_VALUE"""),"Bois-de-Chêne") -> Bois-de-Chêne | F4: =IFERROR(__xludf.DUMMYFUNCTION("""COMPUTED_VALUE"""),"Garde, Collecteur de la garde") -> Garde, Collecteur de la garde | G4: =IFERROR(__xludf.DUMMYFUNCTION("""COMPUTED_VALUE"""),"En service actif") -> En service actif
A5: =IFERROR(__xludf.DUMMYFUNCTION("""COMPUTED_VALUE"""),TRUE) -> TRUE | B5: =IFERROR(__xludf.DUMMYFUNCTION("""COMPUTED_VALUE"""),"Sergent-Chef") -> Sergent-Chef | C5: =IFERROR(__xludf.DUMMYFUNCTION("""COMPUTED_VALUE"""),"Björn") -> Björn | D5: =IFERROR(__xludf.DUMMYFUNCTION("""COMPUTED_VALUE"""),"Horudin") -> Horudin | E5: =IFERROR(__xludf.DUMMYFUNCTION("""COMPUTED_VALUE"""),"Bois-de-Chêne") -> Bois-de-Chêne | F5: =IFERROR(__xludf.DUMMYFUNCTION("""COMPUTED_VALUE"""),"Garde") -> Garde | G5: =IFERROR(__xludf.DUMMYFUNCTION("""COMPUTED_VALUE"""),"En service actif") -> En service actif
A6: =IFERROR(__xludf.DUMMYFUNCTION("""COMPUTED_VALUE"""),TRUE) -> TRUE | B6: =IFERROR(__xludf.DUMMYFUNCTION("""COMPUTED_VALUE"""),"Garde") -> Garde | C6: =IFERROR(__xludf.DUMMYFUNCTION("""COMPUTED_VALUE"""),"Simon") -> Simon | D6: =IFERROR(__xludf.DUMMYFUNCTION("""COMPUTED_VALUE"""),"Démont") -> Démont | E6: =IFERROR(__xludf.DUMMYFUNCTION("""COMPUTED_VALUE"""),"Bois-de-Chêne") -> Bois-de-Chêne | F6: =IFERROR(__xludf.DUMMYFUNCTION("""COMPUTED_VALUE"""),"Garde") -> Garde | G6: =IFERROR(__xludf.DUMMYFUNCTION("""COMPUTED_VALUE"""),"Déserteur") -> Déserteur
A7: =IFERROR(__xludf.DUMMYFUNCTION("""COMPUTED_VALUE"""),FALSE) -> FALSE | B7: =IFERROR(__xludf.DUMMYFUNCTION("""COMPUTED_VALUE"""),"Sergent-Chef") -> Sergent-Chef | C7: =IFERROR(__xludf.DUMMYFUNCTION("""COMPUTED_VALUE"""),"Thorulf") -> Thorulf | E7: =IFERROR(__xludf.DUMMYFUNCTION("""COMPUTED_VALUE"""),"Bois-de-Chêne") -> Bois-de-Chêne | F7: =IFERROR(__xludf.DUMMYFUNCTION("""COMPUTED_VALUE"""),"Garde") -> Garde | G7: =IFERROR(__xludf.DUMMYFUNCTION("""COMPUTED_VALUE"""),"En service actif") -> En service actif
A8: =IFERROR(__xludf.DUMMYFUNCTION("""COMPUTED_VALUE"""),FALSE) -> FALSE | B8: =IFERROR(__xludf.DUMMYFUNCTION("""COMPUTED_VALUE"""),"Garde") -> Garde | C8: =IFERROR(__xludf.DUMMYFUNCTION("""COMPUTED_VALUE"""),"Aranthir") -> Aranthir | E8: =IFERROR(__xludf.DUMMYFUNCTION("""COMPUTED_VALUE"""),"Bois-de-Chêne") -> Bois-de-Chêne | F8: =IFERROR(__xludf.DUMMYFUNCTION("""COMPUTED_VALUE"""),"Garde, Eclaireur") -> Garde, Eclaireur | G8: =IFERROR(__xludf.DUMMYFUNCTION("""COMPUTED_VALUE"""),"Démissionnaire") -> Démissionnaire
A9: =IFERROR(__xludf.DUMMYFUNCTION("""COMPUTED_VALUE"""),FALSE) -> FALSE | B9: =IFERROR(__xludf.DUMMYFUNCTION("""COMPUTED_VALUE"""),"Garde") -> Garde | C9: =IFERROR(__xludf.DUMMYFUNCTION("""COMPUTED_VALUE"""),"Hemar") -> Hemar | D9: =IFERROR(__xludf.DUMMYFUNCTION("""COMPUTED_VALUE"""),"War-seer") -> War-seer | E9: =IFERROR(__xludf.DUMMYFUNCTION("""COMPUTED_VALUE"""),"Bois-de-Chêne") -> Bois-de-Chêne | F9: =IFERROR(__xludf.DUMMYFUNCTION("""COMPUTED_VALUE"""),"Garde") -> Garde | G9: =IFERROR(__xludf.DUMMYFUNCTION("""COMPUTED_VALUE"""),"Déserteur") -> Déserteur
A10: =IFERROR(__xludf.DUMMYFUNCTION("""COMPUTED_VALUE"""),TRUE) -> TRUE | B10: =IFERROR(__xludf.DUMMYFUNCTION("""COMPUTED_VALUE"""),"Garde") -> Garde | C10: =IFERROR(__xludf.DUMMYFUNCTION("""COMPUTED_VALUE"""),"Azan") -> Azan | D10: =IFERROR(__xludf.DUMMYFUNCTION("""COMPUTED_VALUE"""),"Korf") -> Korf | E10: =IFERROR(__xludf.DUMMYFUNCTION("""COMPUTED_VALUE"""),"Bois-de-Chêne") -> Bois-de-Chêne | F10: =IFERROR(__xludf.DUMMYFUNCTION("""COMPUTED_VALUE"""),"Garde") -> Garde | G10: =IFERROR(__xludf.DUMMYFUNCTION("""COMPUTED_VALUE"""),"Démissionnaire") -> Démissionnaire
A11: =IFERROR(__xludf.DUMMYFUNCTION("""COMPUTED_VALUE"""),FALSE) -> FALSE | B11: =IFERROR(__xludf.DUMMYFUNCTION("""COMPUTED_VALUE"""),"Garde") -> Garde | C11: =IFERROR(__xludf.DUMMYFUNCTION("""COMPUTED_VALUE"""),"Balmyra") -> Balmyra | E11: =IFERROR(__xludf.DUMMYFUNCTION("""COMPUTED_VALUE"""),"Bois-de-Chêne") -> Bois-de-Chêne | F11: =IFERROR(__xludf.DUMMYFUNCTION("""COMPUTED_VALUE"""),"Garde") -> Garde | G11: =IFERROR(__xludf.DUMMYFUNCTION("""COMPUTED_VALUE"""),"En service actif") -> En service actif

Sheet Garde de Rivebois
A1: =IFERROR(__xludf.DUMMYFUNCTION("QUERY(Effectifs!A:Z, ""SELECT * WHERE E CONTAINS 'Rivebois' ORDER BY Z ASC"", 1)"),"Assermenté") -> Assermenté | B1: =IFERROR(__xludf.DUMMYFUNCTION("""COMPUTED_VALUE"""),"Grade") -> Grade | C1: =IFERROR(__xludf.DUMMYFUNCTION("""COMPUTED_VALUE"""),"Prénom") -> Prénom | D1: =IFERROR(__xludf.DUMMYFUNCTION("""COMPUTED_VALUE"""),"Nom") -> Nom | E1: =IFERROR(__xludf.DUMMYFUNCTION("""COMPUTED_VALUE"""),"Corps") -> Corps | F1: =IFERROR(__xludf.DUMMYFUNCTION("""COMPUTED_VALUE"""),"Spécialité") -> Spécialité | G1: =IFERROR(__xludf.DUMMYFUNCTION("""COMPUTED_VALUE"""),"Status") -> Status | H1: =IFERROR(__xludf.DUMMYFUNCTION("""COMPUTED_VALUE"""),"Métier") -> Métier | I1: =IFERROR(__xludf.DUMMYFUNCTION("""COMPUTED_VALUE"""),"") | J1: =IFERROR(__xludf.DUMMYFUNCTION("""COMPUTED_VALUE"""),"") | K1: =IFERROR(__xludf.DUMMYFUNCTION("""COMPUTED_VALUE"""),"") | L1: =IFERROR(__xludf.DUMMYFUNCTION("""COMPUTED_VALUE"""),"") | M1: =IFERROR(__xludf.DUMMYFUNCTION("""COMPUTED_VALUE"""),"") | N1: =IFERROR(__xludf.DUMMYFUNCTION("""COMPUTED_VALUE"""),"") | O1: =IFERROR(__xludf.DUMMYFUNCTION("""COMPUTED_VALUE"""),"") | P1: =IFERROR(__xludf.DUMMYFUNCTION("""COMPUTED_VALUE"""),"") | ... Z1: =IFERROR(__xludf.DUMMYFUNCTION("""COMPUTED_VALUE"""),"")
A2: =IFERROR(__xludf.DUMMYFUNCTION("""COMPUTED_VALUE"""),FALSE) -> FALSE | B2: =IFERROR(__xludf.DUMMYFUNCTION("""COMPUTED_VALUE"""),"Capitaine") -> Capitaine | C2: =IFERROR(__xludf.DUMMYFUNCTION("""COMPUTED_VALUE"""),"Sigurd") -> Sigurd | D2: =IFERROR(__xludf.DUMMYFUNCTION("""COMPUTED_VALUE"""),"Grisetoison") -> Grisetoison | E2: =IFERROR(__xludf.DUMMYFUNCTION("""COMPUTED_VALUE"""),"Rivebois") -> Rivebois | F2: =IFERROR(__xludf.DUMMYFUNCTION("""COMPUTED_VALUE"""),"Garde, Collecteur de la garde") -> Garde, Collecteur de la garde | G2: =IFERROR(__xludf.DUMMYFUNCTION("""COMPUTED_VALUE"""),"Déserteur") -> Déserteur
A3: =IFERROR(__xludf.DUMMYFUNCTION("""COMPUTED_VALUE"""),TRUE) -> TRUE | B3: =IFERROR(__xludf.DUMMYFUNCTION("""COMPUTED_VALUE"""),"Lieutenant") -> Lieutenant | C3: =IFERROR(__xludf.DUMMYFUNCTION("""COMPUTED_VALUE"""),"Daric") -> Daric | E3: =IFERROR(__xludf.DUMMYFUNCTION("""COMPUTED_VALUE"""),"Rivebois") -> Rivebois | F3: =IFERROR(__xludf.DUMMYFUNCTION("""COMPUTED_VALUE"""),"Garde") -> Garde | G3: =IFERROR(__xludf.DUMMYFUNCTION("""COMPUTED_VALUE"""),"En service actif") -> En service actif
A4: =IFERROR(__xludf.DUMMYFUNCTION("""COMPUTED_VALUE"""),TRUE) -> TRUE | B4: =IFERROR(__xludf.DUMMYFUNCTION("""COMPUTED_VALUE"""),"Caporal") -> Caporal | C4: =IFERROR(__xludf.DUMMYFUNCTION("""COMPUTED_VALUE"""),"Athlan") -> Athlan | E4: =IFERROR(__xludf.DUMMYFUNCTION("""COMPUTED_VALUE"""),"Rivebois") -> Rivebois | F4: =IFERROR(__xludf.DUMMYFUNCTION("""COMPUTED_VALUE"""),"Garde") -> Garde | G4: =IFERROR(__xludf.DUMMYFUNCTION("""COMPUTED_VALUE"""),"En service actif") -> En service actif
A5: =IFERROR(__xludf.DUMMYFUNCTION("""COMPUTED_VALUE"""),FALSE) -> FALSE | B5: =IFERROR(__xludf.DUMMYFUNCTION("""COMPUTED_VALUE"""),"Major") -> Major | C5: =IFERROR(__xludf.DUMMYFUNCTION("""COMPUTED_VALUE"""),"Krakan ") -> Krakan | D5: =IFERROR(__xludf.DUMMYFUNCTION("""COMPUTED_VALUE"""),"Valyn") -> Valyn | E5: =IFERROR(__xludf.DUMMYFUNCTION("""COMPUTED_VALUE"""),"Rivebois") -> Rivebois | F5: =IFERROR(__xludf.DUMMYFUNCTION("""COMPUTED_VALUE"""),"Garde") -> Garde | G5: =IFERROR(__xludf.DUMMYFUNCTION("""COMPUTED_VALUE"""),"En service actif") -> En service actif
A6: =IFERROR(__xludf.DUMMYFUNCTION("""COMPUTED_VALUE"""),FALSE) -> FALSE | B6: =IFERROR(__xludf.DUMMYFUNCTION("""COMPUTED_VALUE"""),"Capitaine") -> Capitaine | C6: =IFERROR(__xludf.DUMMYFUNCTION("""COMPUTED_VALUE"""),"Hakon") -> Hakon | D6: =IFERROR(__xludf.DUMMYFUNCTION("""COMPUTED_VALUE"""),"Grisetoison") -> Grisetoison | E6: =IFERROR(__xludf.DUMMYFUNCTION("""COMPUTED_VALUE"""),"Rivebois") -> Rivebois | F6: =IFERROR(__xludf.DUMMYFUNCTION("""COMPUTED_VALUE"""),"Garde, Collecteur de la garde") -> Garde, Collecteur de la garde | G6: =IFERROR(__xludf.DUMMYFUNCTION("""COMPUTED_VALUE"""),"Mort en service actif") -> Mort en service actif
A7: =IFERROR(__xludf.DUMMYFUNCTION("""COMPUTED_VALUE"""),FALSE) -> FALSE | B7: =IFERROR(__xludf.DUMMYFUNCTION("""COMPUTED_VALUE"""),"Caporal-Chef") -> Caporal-Chef | C7: =IFERROR(__xludf.DUMMYFUNCTION("""COMPUTED_VALUE"""),"Lous") -> Lous | D7: =IFERROR(__xludf.DUMMYFUNCTION("""COMPUTED_VALUE"""),"Bois") -> Bois | E7: =IFERROR(__xludf.DUMMYFUNCTION("""COMPUTED_VALUE"""),"Rivebois") -> Rivebois | F7: =IFERROR(__xludf.DUMMYFUNCTION("""COMPUTED_VALUE"""),"Garde") -> Garde | G7: =IFERROR(__xludf.DUMMYFUNCTION("""COMPUTED_VALUE"""),"En service actif") -> En service actif
A8: =IFERROR(__xludf.DUMMYFUNCTION("""COMPUTED_VALUE"""),FALSE) -> FALSE | B8: =IFERROR(__xludf.DUMMYFUNCTION("""COMPUTED_VALUE"""),"Capitaine") -> Capitaine | C8: =IFERROR(__xludf.DUMMYFUNCTION("""COMPUTED_VALUE"""),"Brand") -> Brand | D8: =IFERROR(__xludf.DUMMYFUNCTION("""COMPUTED_VALUE"""),"Grisetoison") -> Grisetoison | E8: =IFERROR(__xludf.DUMMYFUNCTION("""COMPUTED_VALUE"""),"Rivebois") -> Rivebois | F8: =IFERROR(__xludf.DUMMYFUNCTION("""COMPUTED_VALUE"""),"Garde, Collecteur de la garde") -> Garde, Collecteur de la garde | G8: =IFERROR(__xludf.DUMMYFUNCTION("""COMPUTED_VALUE"""),"Mort en service actif") -> Mort en service actif
A9: =IFERROR(__xludf.DUMMYFUNCTION("""COMPUTED_VALUE"""),FALSE) -> FALSE | B9: =IFERROR(__xludf.DUMMYFUNCTION("""COMPUTED_VALUE"""),"Garde") -> Garde | C9: =IFERROR(__xludf.DUMMYFUNCTION("""COMPUTED_VALUE"""),"Silvius") -> Silvius | D9: =IFERROR(__xludf.DUMMYFUNCTION("""COMPUTED_VALUE"""),"Varro") -> Varro | E9: =IFERROR(__xludf.DUMMYFUNCTION("""COMPUTED_VALUE"""),"Rivebois") -> Rivebois | F9: =IFERROR(__xludf.DUMMYFUNCTION("""COMPUTED_VALUE"""),"Garde") -> Garde | G9: =IFERROR(__xludf.DUMMYFUNCTION("""COMPUTED_VALUE"""),"En service actif") -> En service actif
A10: =IFERROR(__xludf.DUMMYFUNCTION("""COMPUTED_VALUE"""),FALSE) -> FALSE | B10: =IFERROR(__xludf.DUMMYFUNCTION("""COMPUTED_VALUE"""),"Garde") -> Garde | C10: =IFERROR(__xludf.DUMMYFUNCTION("""COMPUTED_VALUE"""),"Chasse-poulet") -> Chasse-poulet | E10: =IFERROR(__xludf.DUMMYFUNCTION("""COMPUTED_VALUE"""),"Rivebois") -> Rivebois | F10: =IFERROR(__xludf.DUMMYFUNCTION("""COMPUTED_VALUE"""),"Garde") -> Garde | G10: =IFERROR(__xludf.DUMMYFUNCTION("""COMPUTED_VALUE"""),"En service actif") -> En service actif
A11: =IFERROR(__xludf.DUMMYFUNCTION("""COMPUTED_VALUE"""),FALSE) -> FALSE | B11: =IFERROR(__xludf.DUMMYFUNCTION("""COMPUTED_VALUE"""),"Garde") -> Garde | C11: =IFERROR(__xludf.DUMMYFUNCTION("""COMPUTED_VALUE"""),"Hrolf") -> Hrolf | D11: =IFERROR(__xludf.DUMMYFUNCTION("""COMPUTED_VALUE"""),"Fine-Lame") -> Fine-Lame | E11: =IFERROR(__xludf.DUMMYFUNCTION("""COMPUTED_VALUE"""),"Rivebois") -> Rivebois | F11: =IFERROR(__xludf.DUMMYFUNCTION("""COMPUTED_VALUE"""),"Garde") -> Garde | G11: =IFERROR(__xludf.DUMMYFUNCTION("""COMPUTED_VALUE"""),"En service actif") -> En service actif
A12: =IFERROR(__xludf.DUMMYFUNCTION("""COMPUTED_VALUE"""),FALSE) -> FALSE | B12: =IFERROR(__xludf.DUMMYFUNCTION("""COMPUTED_VALUE"""),"Caporal") -> Caporal | C12: =IFERROR(__xludf.DUMMYFUNCTION("""COMPUTED_VALUE"""),"Laguerta") -> Laguerta | D12: =IFERROR(__xludf.DUMMYFUNCTION("""COMPUTED_VALUE"""),"Fende-Sillon") -> Fende-Sillon | E12: =IFERROR(__xludf.DUMMYFUNCTION("""COMPUTED_VALUE"""),"Rivebois") -> Rivebois | F12: =IFERROR(__xludf.DUMMYFUNCTION("""COMPUTED_VALUE"""),"Garde") -> Garde | G12: =IFERROR(__xludf.DUMMYFUNCTION("""COMPUTED_VALUE"""),"En service actif") -> En service actif
A13: =IFERROR(__xludf.DUMMYFUNCTION("""COMPUTED_VALUE"""),FALSE) -> FALSE | B13: =IFERROR(__xludf.DUMMYFUNCTION("""COMPUTED_VALUE"""),"Garde") -> Garde | C13: =IFERROR(__xludf.DUMMYFUNCTION("""COMPUTED_VALUE"""),"Naevor") -> Naevor | D13: =IFERROR(__xludf.DUMMYFUNCTION("""COMPUTED_VALUE"""),"Feuille-Sombre") -> Feuille-Sombre | E13: =IFERROR(__xludf.DUMMYFUNCTION("""COMPUTED_VALUE"""),"Rivebois") -> Rivebois | F13: =IFERROR(__xludf.DUMMYFUNCTION("""COMPUTED_VALUE"""),"Garde") -> Garde | G13: =IFERROR(__xludf.DUMMYFUNCTION("""COMPUTED_VALUE"""),"En service actif") -> En service actif
A14: =IFERROR(__xludf.DUMMYFUNCTION("""COMPUTED_VALUE"""),FALSE) -> FALSE | B14: =IFERROR(__xludf.DUMMYFUNCTION("""COMPUTED_VALUE"""),"Lieutenant-Chef") -> Lieutenant-Chef | C14: =IFERROR(__xludf.DUMMYFUNCTION("""COMPUTED_VALUE"""),"Ulfgar") -> Ulfgar | D14: =IFERROR(__xludf.DUMMYFUNCTION("""COMPUTED_VALUE"""),"L'oiseau de nuit") -> L'oiseau de nuit | E14: =IFERROR(__xludf.DUMMYFUNCTION("""COMPUTED_VALUE"""),"Rivebois") -> Rivebois | F14: =IFERROR(__xludf.DUMMYFUNCTION("""COMPUTED_VALUE"""),"Garde") -> Garde | G14: =IFERROR(__xludf.DUMMYFUNCTION("""COMPUTED_VALUE"""),"En service actif") -> En service actif

Sheet Garde de Cap Granite
A1: =IFERROR(__xludf.DUMMYFUNCTION("QUERY(Effectifs!A:Z, ""SELECT * WHERE E CONTAINS 'Granite' ORDER BY Z ASC"", 1)"),"Assermenté") -> Assermenté | B1: =IFERROR(__xludf.DUMMYFUNCTION("""COMPUTED_VALUE"""),"Grade") -> Grade | C1: =IFERROR(__xludf.DUMMYFUNCTION("""COMPUTED_VALUE"""),"Prénom") -> Prénom | D1: =IFERROR(__xludf.DUMMYFUNCTION("""COMPUTED_VALUE"""),"Nom") -> Nom | E1: =IFERROR(__xludf.DUMMYFUNCTION("""COMPUTED_VALUE"""),"Corps") -> Corps | F1: =IFERROR(__xludf.DUMMYFUNCTION("""COMPUTED_VALUE"""),"Spécialité") -> Spécialité | G1: =IFERROR(__xludf.DUMMYFUNCTION("""COMPUTED_VALUE"""),"Status") -> Status | H1: =IFERROR(__xludf.DUMMYFUNCTION("""COMPUTED_VALUE"""),"Métier") -> Métier | I1: =IFERROR(__xludf.DUMMYFUNCTION("""COMPUTED_VALUE"""),"") | J1: =IFERROR(__xludf.DUMMYFUNCTION("""COMPUTED_VALUE"""),"") | K1: =IFERROR(__xludf.DUMMYFUNCTION("""COMPUTED_VALUE"""),"") | L1: =IFERROR(__xludf.DUMMYFUNCTION("""COMPUTED_VALUE"""),"") | M1: =IFERROR(__xludf.DUMMYFUNCTION("""COMPUTED_VALUE"""),"") | N1: =IFERROR(__xludf.DUMMYFUNCTION("""COMPUTED_VALUE"""),"") | O1: =IFERROR(__xludf.DUMMYFUNCTION("""COMPUTED_VALUE"""),"") | P1: =IFERROR(__xludf.DUMMYFUNCTION("""COMPUTED_VALUE"""),"") | ... Z1: =IFERROR(__xludf.DUMMYFUNCTION("""COMPUTED_VALUE"""),"")
A2: =IFERROR(__xludf.DUMMYFUNCTION("""COMPUTED_VALUE"""),FALSE) -> FALSE | B2: =IFERROR(__xludf.DUMMYFUNCTION("""COMPUTED_VALUE"""),"Capitaine") -> Capitaine | C2: =IFERROR(__xludf.DUMMYFUNCTION("""COMPUTED_VALUE"""),"Hastelvin") -> Hastelvin | E2: =IFERROR(__xludf.DUMMYFUNCTION("""COMPUTED_VALUE"""),"Cap Granite") -> Cap Granite | F2: =IFERROR(__xludf.DUMMYFUNCTION("""COMPUTED_VALUE"""),"Garde, Collecteur de la garde") -> Garde, Collecteur de la garde | G2: =IFERROR(__xludf.DUMMYFUNCTION("""COMPUTED_VALUE"""),"Démissionnaire") -> Démissionnaire
A3: =IFERROR(__xludf.DUMMYFUNCTION("""COMPUTED_VALUE"""),FALSE) -> FALSE | B3: =IFERROR(__xludf.DUMMYFUNCTION("""COMPUTED_VALUE"""),"Garde") -> Garde | C3: =IFERROR(__xludf.DUMMYFUNCTION("""COMPUTED_VALUE"""),"Malivor") -> Malivor | D3: =IFERROR(__xludf.DUMMYFUNCTION("""COMPUTED_VALUE"""),"Xernes") -> Xernes | E3: =IFERROR(__xludf.DUMMYFUNCTION("""COMPUTED_VALUE"""),"Cap Granite") -> Cap Granite | F3: =IFERROR(__xludf.DUMMYFUNCTION("""COMPUTED_VALUE"""),"Garde") -> Garde | G3: =IFERROR(__xludf.DUMMYFUNCTION("""COMPUTED_VALUE"""),"Démissionnaire") -> Démissionnaire
A4: =IFERROR(__xludf.DUMMYFUNCTION("""COMPUTED_VALUE"""),TRUE) -> TRUE | B4: =IFERROR(__xludf.DUMMYFUNCTION("""COMPUTED_VALUE"""),"Garde") -> Garde | C4: =IFERROR(__xludf.DUMMYFUNCTION("""COMPUTED_VALUE"""),"Bakhir") -> Bakhir | E4: =IFERROR(__xludf.DUMMYFUNCTION("""COMPUTED_VALUE"""),"Cap Granite") -> Cap Granite | F4: =IFERROR(__xludf.DUMMYFUNCTION("""COMPUTED_VALUE"""),"Garde") -> Garde | G4: =IFERROR(__xludf.DUMMYFUNCTION("""COMPUTED_VALUE"""),"En service actif") -> En service actif
A5: =IFERROR(__xludf.DUMMYFUNCTION("""COMPUTED_VALUE"""),TRUE) -> TRUE | B5: =IFERROR(__xludf.DUMMYFUNCTION("""COMPUTED_VALUE"""),"Lieutenant-Chef") -> Lieutenant-Chef | C5: =IFERROR(__xludf.DUMMYFUNCTION("""COMPUTED_VALUE"""),"Starkos") -> Starkos | D5: =IFERROR(__xludf.DUMMYFUNCTION("""COMPUTED_VALUE"""),"Coeurebene") -> Coeurebene | E5: =IFERROR(__xludf.DUMMYFUNCTION("""COMPUTED_VALUE"""),"Cap Granite") -> Cap Granite | F5: =IFERROR(__xludf.DUMMYFUNCTION("""COMPUTED_VALUE"""),"Garde") -> Garde | G5: =IFERROR(__xludf.DUMMYFUNCTION("""COMPUTED_VALUE"""),"En service actif") -> En service actif
A6: =IFERROR(__xludf.DUMMYFUNCTION("""COMPUTED_VALUE"""),FALSE) -> FALSE | B6: =IFERROR(__xludf.DUMMYFUNCTION("""COMPUTED_VALUE"""),"Garde") -> Garde | C6: =IFERROR(__xludf.DUMMYFUNCTION("""COMPUTED_VALUE"""),"Drakgor") -> Drakgor | D6: =IFERROR(__xludf.DUMMYFUNCTION("""COMPUTED_VALUE"""),"gro-Drakar") -> gro-Drakar | E6: =IFERROR(__xludf.DUMMYFUNCTION("""COMPUTED_VALUE"""),"Cap Granite") -> Cap Granite | F6: =IFERROR(__xludf.DUMMYFUNCTION("""COMPUTED_VALUE"""),"Garde") -> Garde | G6: =IFERROR(__xludf.DUMMYFUNCTION("""COMPUTED_VALUE"""),"Démissionnaire") -> Démissionnaire
A7: =IFERROR(__xludf.DUMMYFUNCTION("""COMPUTED_VALUE"""),FALSE) -> FALSE | B7: =IFERROR(__xludf.DUMMYFUNCTION("""COMPUTED_VALUE"""),"Lieutenant") -> Lieutenant | C7: =IFERROR(__xludf.DUMMYFUNCTION("""COMPUTED_VALUE"""),"Barnabas") -> Barnabas | D7: =IFERROR(__xludf.DUMMYFUNCTION("""COMPUTED_VALUE"""),"Tharmr") -> Tharmr | E7: =IFERROR(__xludf.DUMMYFUNCTION("""COMPUTED_VALUE"""),"Cap Granite") -> Cap Granite | F7: =IFERROR(__xludf.DUMMYFUNCTION("""COMPUTED_VALUE"""),"Garde") -> Garde | G7: =IFERROR(__xludf.DUMMYFUNCTION("""COMPUTED_VALUE"""),"En service actif") -> En service actif
A8: =IFERROR(__xludf.DUMMYFUNCTION("""COMPUTED_VALUE"""),FALSE) -> FALSE | B8: =IFERROR(__xludf.DUMMYFUNCTION("""COMPUTED_VALUE"""),"Capitaine") -> Capitaine | C8: =IFERROR(__xludf.DUMMYFUNCTION("""COMPUTED_VALUE"""),"Pavis") -> Pavis | D8: =IFERROR(__xludf.DUMMYFUNCTION("""COMPUTED_VALUE"""),"Gurdalval") -> Gurdalval | E8: =IFERROR(__xludf.DUMMYFUNCTION("""COMPUTED_VALUE"""),"Cap Granite") -> Cap Granite | F8: =IFERROR(__xludf.DUMMYFUNCTION("""COMPUTED_VALUE"""),"Garde") -> Garde | G8: =IFERROR(__xludf.DUMMYFUNCTION("""COMPUTED_VALUE"""),"En service actif") -> En service actif
A9: =IFERROR(__xludf.DUMMYFUNCTION("""COMPUTED_VALUE"""),FALSE) -> FALSE | B9: =IFERROR(__xludf.DUMMYFUNCTION("""COMPUTED_VALUE"""),"Sergent-Chef") -> Sergent-Chef | C9: =IFERROR(__xludf.DUMMYFUNCTION("""COMPUTED_VALUE"""),"Vranx") -> Vranx | D9: =IFERROR(__xludf.DUMMYFUNCTION("""COMPUTED_VALUE"""),"Thorgar") -> Thorgar | E9: =IFERROR(__xludf.DUMMYFUNCTION("""COMPUTED_VALUE"""),"Cap Granite") -> Cap Granite | F9: =IFERROR(__xludf.DUMMYFUNCTION("""COMPUTED_VALUE"""),"Garde") -> Garde | G9: =IFERROR(__xludf.DUMMYFUNCTION("""COMPUTED_VALUE"""),"En service actif") -> En service actif
A10: =IFERROR(__xludf.DUMMYFUNCTION("""COMPUTED_VALUE"""),FALSE) -> FALSE | B10: =IFERROR(__xludf.DUMMYFUNCTION("""COMPUTED_VALUE"""),"Garde") -> Garde | C10: =IFERROR(__xludf.DUMMYFUNCTION("""COMPUTED_VALUE"""),"Sigvard") -> Sigvard | D10: =IFERROR(__xludf.DUMMYFUNCTION("""COMPUTED_VALUE"""),"Coeurebene") -> Coeurebene | E10: =IFERROR(__xludf.DUMMYFUNCTION("""COMPUTED_VALUE"""),"Cap Granite") -> Cap Granite | F10: =IFERROR(__xludf.DUMMYFUNCTION("""COMPUTED_VALUE"""),"Garde") -> Garde | G10: =IFERROR(__xludf.DUMMYFUNCTION("""COMPUTED_VALUE"""),"En service actif") -> En service actif
A11: =IFERROR(__xludf.DUMMYFUNCTION("""COMPUTED_VALUE"""),FALSE) -> FALSE | B11: =IFERROR(__xludf.DUMMYFUNCTION("""COMPUTED_VALUE"""),"Recrue") -> Recrue | C11: =IFERROR(__xludf.DUMMYFUNCTION("""COMPUTED_VALUE"""),"Joki") -> Joki | E11: =IFERROR(__xludf.DUMMYFUNCTION("""COMPUTED_VALUE"""),"Cap Granite") -> Cap Granite | G11: =IFERROR(__xludf.DUMMYFUNCTION("""COMPUTED_VALUE"""),"En service actif") -> En service actif

Sheet Corps des éclaireurs
A1: =IFERROR(__xludf.DUMMYFUNCTION("QUERY(Effectifs!A:Z, ""SELECT * WHERE E CONTAINS 'Eclaireur' ORDER BY Z ASC"", 1)"),"Assermenté") -> Assermenté | B1: =IFERROR(__xludf.DUMMYFUNCTION("""COMPUTED_VALUE"""),"Grade") -> Grade | C1: =IFERROR(__xludf.DUMMYFUNCTION("""COMPUTED_VALUE"""),"Prénom") -> Prénom | D1: =IFERROR(__xludf.DUMMYFUNCTION("""COMPUTED_VALUE"""),"Nom") -> Nom | E1: =IFERROR(__xludf.DUMMYFUNCTION("""COMPUTED_VALUE"""),"Corps") -> Corps | F1: =IFERROR(__xludf.DUMMYFUNCTION("""COMPUTED_VALUE"""),"Spécialité") -> Spécialité | G1: =IFERROR(__xludf.DUMMYFUNCTION("""COMPUTED_VALUE"""),"Status") -> Status | H1: =IFERROR(__xludf.DUMMYFUNCTION("""COMPUTED_VALUE"""),"Métier") -> Métier | I1: =IFERROR(__xludf.DUMMYFUNCTION("""COMPUTED_VALUE"""),"") | J1: =IFERROR(__xludf.DUMMYFUNCTION("""COMPUTED_VALUE"""),"") | K1: =IFERROR(__xludf.DUMMYFUNCTION("""COMPUTED_VALUE"""),"") | L1: =IFERROR(__xludf.DUMMYFUNCTION("""COMPUTED_VALUE"""),"") | M1: =IFERROR(__xludf.DUMMYFUNCTION("""COMPUTED_VALUE"""),"") | N1: =IFERROR(__xludf.DUMMYFUNCTION("""COMPUTED_VALUE"""),"") | O1: =IFERROR(__xludf.DUMMYFUNCTION("""COMPUTED_VALUE"""),"") | P1: =IFERROR(__xludf.DUMMYFUNCTION("""COMPUTED_VALUE"""),"") | ... Z1: =IFERROR(__xludf.DUMMYFUNCTION("""COMPUTED_VALUE"""),"")
A2: =IFERROR(__xludf.DUMMYFUNCTION("""COMPUTED_VALUE"""),TRUE) -> TRUE | B2: =IFERROR(__xludf.DUMMYFUNCTION("""COMPUTED_VALUE"""),"Capitaine") -> Capitaine | C2: =IFERROR(__xludf.DUMMYFUNCTION("""COMPUTED_VALUE"""),"Glaemorandir") -> Glaemorandir | D2: =IFERROR(__xludf.DUMMYFUNCTION("""COMPUTED_VALUE"""),"Oeil-Perçant") -> Oeil-Perçant | E2: =IFERROR(__xludf.DUMMYFUNCTION("""COMPUTED_VALUE"""),"Eclaireur") -> Eclaireur | F2: =IFERROR(__xludf.DUMMYFUNCTION("""COMPUTED_VALUE"""),"Eclaireur, Garde, Collecteur de la garde") -> Eclaireur, Garde, Collecteur de la garde | G2: =IFERROR(__xludf.DUMMYFUNCTION("""COMPUTED_VALUE"""),"En service actif") -> En service actif | H2: =IFERROR(__xludf.DUMMYFUNCTION("""COMPUTED_VALUE"""),"Chasseur") -> Chasseur
A3: =IFERROR(__xludf.DUMMYFUNCTION("""COMPUTED_VALUE"""),TRUE) -> TRUE | B3: =IFERROR(__xludf.DUMMYFUNCTION("""COMPUTED_VALUE"""),"Capitaine") -> Capitaine | C3: =IFERROR(__xludf.DUMMYFUNCTION("""COMPUTED_VALUE"""),"Clemnir") -> Clemnir | D3: =IFERROR(__xludf.DUMMYFUNCTION("""COMPUTED_VALUE"""),"Arc-Vif") -> Arc-Vif | E3: =IFERROR(__xludf.DUMMYFUNCTION("""COMPUTED_VALUE"""),"Eclaireur") -> Eclaireur | F3: =IFERROR(__xludf.DUMMYFUNCTION("""COMPUTED_VALUE"""),"Eclaireur") -> Eclaireur | G3: =IFERROR(__xludf.DUMMYFUNCTION("""COMPUTED_VALUE"""),"Mort en service actif") -> Mort en service actif | H3: =IFERROR(__xludf.DUMMYFUNCTION("""COMPUTED_VALUE"""),"Chasseur") -> Chasseur
A4: =IFERROR(__xludf.DUMMYFUNCTION("""COMPUTED_VALUE"""),TRUE) -> TRUE | B4: =IFERROR(__xludf.DUMMYFUNCTION("""COMPUTED_VALUE"""),"Sergent-Chef") -> Sergent-Chef | C4: =IFERROR(__xludf.DUMMYFUNCTION("""COMPUTED_VALUE"""),"Magnar") -> Magnar | D4: =IFERROR(__xludf.DUMMYFUNCTION("""COMPUTED_VALUE"""),"Traquebrume") -> Traquebrume | E4: =IFERROR(__xludf.DUMMYFUNCTION("""COMPUTED_VALUE"""),"Eclaireur") -> Eclaireur | F4: =IFERROR(__xludf.DUMMYFUNCTION("""COMPUTED_VALUE"""),"Eclaireur, Garde") -> Eclaireur, Garde | G4: =IFERROR(__xludf.DUMMYFUNCTION("""COMPUTED_VALUE"""),"En service actif") -> En service actif | H4: =IFERROR(__xludf.DUMMYFUNCTION("""COMPUTED_VALUE"""),"Chasseur") -> Chasseur
A5: =IFERROR(__xludf.DUMMYFUNCTION("""COMPUTED_VALUE"""),TRUE) -> TRUE | B5: =IFERROR(__xludf.DUMMYFUNCTION("""COMPUTED_VALUE"""),"Lieutenant-Chef") -> Lieutenant-Chef | C5: =IFERROR(__xludf.DUMMYFUNCTION("""COMPUTED_VALUE"""),"Pethiceor") -> Pethiceor | D5: =IFERROR(__xludf.DUMMYFUNCTION("""COMPUTED_VALUE"""),"Le Borgne") -> Le Borgne | E5: =IFERROR(__xludf.DUMMYFUNCTION("""COMPUTED_VALUE"""),"Eclaireur") -> Eclaireur | F5: =IFERROR(__xludf.DUMMYFUNCTION("""COMPUTED_VALUE"""),"Eclaireur, Garde") -> Eclaireur, Garde | G5: =IFERROR(__xludf.DUMMYFUNCTION("""COMPUTED_VALUE"""),"En service actif") -> En service actif | H5: =IFERROR(__xludf.DUMMYFUNCTION("""COMPUTED_VALUE"""),"Chasseur") -> Chasseur
A6: =IFERROR(__xludf.DUMMYFUNCTION("""COMPUTED_VALUE"""),TRUE) -> TRUE | B6: =IFERROR(__xludf.DUMMYFUNCTION("""COMPUTED_VALUE"""),"Garde") -> Garde | C6: =IFERROR(__xludf.DUMMYFUNCTION("""COMPUTED_VALUE"""),"Ma'arl") -> Ma'arl | E6: =IFERROR(__xludf.DUMMYFUNCTION("""COMPUTED_VALUE"""),"Eclaireur") -> Eclaireur | F6: =IFERROR(__xludf.DUMMYFUNCTION("""COMPUTED_VALUE"""),"Eclaireur, Garde") -> Eclaireur, Garde | G6: =IFERROR(__xludf.DUMMYFUNCTION("""COMPUTED_VALUE"""),"En service actif") -> En service actif | H6: =IFERROR(__xludf.DUMMYFUNCTION("""COMPUTED_VALUE"""),"Mineur") -> Mineur
A7: =IFERROR(__xludf.DUMMYFUNCTION("""COMPUTED_VALUE"""),TRUE) -> TRUE | B7: =IFERROR(__xludf.DUMMYFUNCTION("""COMPUTED_VALUE"""),"Garde") -> Garde | C7: =IFERROR(__xludf.DUMMYFUNCTION("""COMPUTED_VALUE"""),"Do'Rhazir") -> Do'Rhazir | E7: =IFERROR(__xludf.DUMMYFUNCTION("""COMPUTED_VALUE"""),"Eclaireur") -> Eclaireur | F7: =IFERROR(__xludf.DUMMYFUNCTION("""COMPUTED_VALUE"""),"Eclaireur, Garde") -> Eclaireur, Garde | G7: =IFERROR(__xludf.DUMMYFUNCTION("""COMPUTED_VALUE"""),"En service actif") -> En service actif | H7: =IFERROR(__xludf.DUMMYFUNCTION("""COMPUTED_VALUE"""),"Menuisier-Charbonnier") -> Menuisier-Charbonnier
A8: =IFERROR(__xludf.DUMMYFUNCTION("""COMPUTED_VALUE"""),TRUE) -> TRUE | B8: =IFERROR(__xludf.DUMMYFUNCTION("""COMPUTED_VALUE"""),"Garde") -> Garde | C8: =IFERROR(__xludf.DUMMYFUNCTION("""COMPUTED_VALUE"""),"Ri'Jhan") -> Ri'Jhan | D8: =IFERROR(__xludf.DUMMYFUNCTION("""COMPUTED_VALUE"""),"MoonShadow") -> MoonShadow | E8: =IFERROR(__xludf.DUMMYFUNCTION("""COMPUTED_VALUE"""),"Eclaireur") -> Eclaireur | F8: =IFERROR(__xludf.DUMMYFUNCTION("""COMPUTED_VALUE"""),"Garde, Eclaireur") -> Garde, Eclaireur | G8: =IFERROR(__xludf.DUMMYFUNCTION("""COMPUTED_VALUE"""),"En service actif") -> En service actif
A9: =IFERROR(__xludf.DUMMYFUNCTION("""COMPUTED_VALUE"""),TRUE) -> TRUE | B9: =IFERROR(__xludf.DUMMYFUNCTION("""COMPUTED_VALUE"""),"Garde") -> Garde | C9: =IFERROR(__xludf.DUMMYFUNCTION("""COMPUTED_VALUE"""),"Jo'Vakhet") -> Jo'Vakhet | E9: =IFERROR(__xludf.DUMMYFUNCTION("""COMPUTED_VALUE"""),"Eclaireur") -> Eclaireur | F9: =IFERROR(__xludf.DUMMYFUNCTION("""COMPUTED_VALUE"""),"Eclaireur, Garde") -> Eclaireur, Garde | G9: =IFERROR(__xludf.DUMMYFUNCTION("""COMPUTED_VALUE"""),"En service actif") -> En service actif
A10: =IFERROR(__xludf.DUMMYFUNCTION("""COMPUTED_VALUE"""),FALSE) -> FALSE | B10: =IFERROR(__xludf.DUMMYFUNCTION("""COMPUTED_VALUE"""),"Cadet") -> Cadet | C10: =IFERROR(__xludf.DUMMYFUNCTION("""COMPUTED_VALUE"""),"Crocozaure") -> Crocozaure | E10: =IFERROR(__xludf.DUMMYFUNCTION("""COMPUTED_VALUE"""),"Eclaireur") -> Eclaireur | F10: =IFERROR(__xludf.DUMMYFUNCTION("""COMPUTED_VALUE"""),"Garde, Eclaireur") -> Garde, Eclaireur | G10: =IFERROR(__xludf.DUMMYFUNCTION("""COMPUTED_VALUE"""),"En service actif") -> En service actif

Sheet Données
A1: Grades | E1: Spécialité | G1: Corps | I1: Status | K1: Métier | M1: Element de ravitaillement | O1: =IFERROR(__xludf.DUMMYFUNCTION("SORT(FILTER(Effectifs!C2:C1000&"" ""&Effectifs!D2:D1000,Effectifs!C2:C1000<>"""",Effectifs!G2:G1000=""En service actif""))"),"Aldric Cendre-coeur") -> Aldric Cendre-coeur
A2: Maréchal | C2: {=IF(A2:A1000="",,MATCH(A2:A1000,'Données'!A$2:A1000,0))} -> 1 | E2: Hird | G2: Etat-Major | I2: En service actif | K2: Guerrier | M2: Vegetal Soup | O2: =IFERROR(__xludf.DUMMYFUNCTION("""COMPUTED_VALUE"""),"Amartas Après-rouge") -> Amartas Après-rouge
A3: Commander | C3: 2 | E3: Garde | G3: Cité de Blancherive | I3: Mis en réserve | K3: Chasseur | M3: Beef Stew | O3: =IFERROR(__xludf.DUMMYFUNCTION("""COMPUTED_VALUE"""),"Astrid Lame-Fine") -> Astrid Lame-Fine
A4: Major | C4: 3 | E4: Eclaireur | G4: Faubourgs de Blancherive | I4: Mort en service actif | K4: Enchenteur | M4: Venison Stew | O4: =IFERROR(__xludf.DUMMYFUNCTION("""COMPUTED_VALUE"""),"Astrild ") -> Astrild
A5: Capitaine | C5: 4 | E5: Intendant de la garde | G5: Rivebois | I5: Radié du service actif | K5: Alchimiste | O5: =IFERROR(__xludf.DUMMYFUNCTION("""COMPUTED_VALUE"""),"Asvaldur ") -> Asvaldur
A6: Lieutenant-Chef | C6: 5 | E6: Instructeur | G6: Bois-de-Chêne | I6: Déserteur | K6: Mineur | O6: =IFERROR(__xludf.DUMMYFUNCTION("""COMPUTED_VALUE"""),"Athlan ") -> Athlan
A7: Lieutenant | C7: 6 | E7: Tortionnaire | G7: Cap Granite | I7: Démissionnaire | K7: Couturier | O7: =IFERROR(__xludf.DUMMYFUNCTION("""COMPUTED_VALUE"""),"Bakhir ") -> Bakhir
A8: Sergent-Chef | C8: 7 | E8: Collecteur de la garde | G8: Eclaireur | K8: Menuisier-Charbonnier | O8: =IFERROR(__xludf.DUMMYFUNCTION("""COMPUTED_VALUE"""),"Balmyra ") -> Balmyra
A9: Sergent | C9: 8 | G9: Hird du Jarl | O9: =IFERROR(__xludf.DUMMYFUNCTION("""COMPUTED_VALUE"""),"Barnabas Tharmr") -> Barnabas Tharmr
A10: Caporal-Chef | C10: 9 | O10: =IFERROR(__xludf.DUMMYFUNCTION("""COMPUTED_VALUE"""),"Björn Horudin") -> Björn Horudin
A11: Caporal | C11: 10 | O11: =IFERROR(__xludf.DUMMYFUNCTION("""COMPUTED_VALUE"""),"Bjorn Kornseen") -> Bjorn Kornseen
A12: Garde | C12: 11 | O12: =IFERROR(__xludf.DUMMYFUNCTION("""COMPUTED_VALUE"""),"Chasse-poulet ") -> Chasse-poulet
A13: Cadet | C13: 12 | O13: =IFERROR(__xludf.DUMMYFUNCTION("""COMPUTED_VALUE"""),"Claudus ") -> Claudus
A14: Recrue | C14: 13 | O14: =IFERROR(__xludf.DUMMYFUNCTION("""COMPUTED_VALUE"""),"Crocozaure ") -> Crocozaure
O15: =IFERROR(__xludf.DUMMYFUNCTION("""COMPUTED_VALUE"""),"Daric ") -> Daric
O16: =IFERROR(__xludf.DUMMYFUNCTION("""COMPUTED_VALUE"""),"Darius Valtor") -> Darius Valtor | R16: :C&" "
O17: =IFERROR(__xludf.DUMMYFUNCTION("""COMPUTED_VALUE"""),"Do'Rhazir ") -> Do'Rhazir
O18: =IFERROR(__xludf.DUMMYFUNCTION("""COMPUTED_VALUE"""),"Drakane ") -> Drakane
O19: =IFERROR(__xludf.DUMMYFUNCTION("""COMPUTED_VALUE"""),"Erwan ") -> Erwan
O20: =IFERROR(__xludf.DUMMYFUNCTION("""COMPUTED_VALUE"""),"Faynir ") -> Faynir
O21: =IFERROR(__xludf.DUMMYFUNCTION("""COMPUTED_VALUE"""),"Filoki ") -> Filoki
O22: =IFERROR(__xludf.DUMMYFUNCTION("""COMPUTED_VALUE"""),"Glaemorandir Oeil-Perçant") -> Glaemorandir Oeil-Perçant
O23: =IFERROR(__xludf.DUMMYFUNCTION("""COMPUTED_VALUE"""),"Gorbash Tête-de-Pierre") -> Gorbash Tête-de-Pierre
O24: =IFERROR(__xludf.DUMMYFUNCTION("""COMPUTED_VALUE"""),"Gronk Grognon") -> Gronk Grognon
O25: =IFERROR(__xludf.DUMMYFUNCTION("""COMPUTED_VALUE"""),"Harald le hardi ") -> Harald le hardi
O26: =IFERROR(__xludf.DUMMYFUNCTION("""COMPUTED_VALUE"""),"Henry Bonacier") -> Henry Bonacier
O27: =IFERROR(__xludf.DUMMYFUNCTION("""COMPUTED_VALUE"""),"Hrolf Fine-Lame") -> Hrolf Fine-Lame
O28: =IFERROR(__xludf.DUMMYFUNCTION("""COMPUTED_VALUE"""),"Ilflynn ") -> Ilflynn
O29: =IFERROR(__xludf.DUMMYFUNCTION("""COMPUTED_VALUE"""),"Jo'Vakhet ") -> Jo'Vakhet
O30: =IFERROR(__xludf.DUMMYFUNCTION("""COMPUTED_VALUE"""),"Joki ") -> Joki
O31: =IFERROR(__xludf.DUMMYFUNCTION("""COMPUTED_VALUE"""),"Ka Yak") -> Ka Yak
O32: =IFERROR(__xludf.DUMMYFUNCTION("""COMPUTED_VALUE"""),"Kendall Delamare") -> Kendall Delamare
O33: =IFERROR(__xludf.DUMMYFUNCTION("""COMPUTED_VALUE"""),"Krakan Valyn") -> Krakan Valyn
O34: =IFERROR(__xludf.DUMMYFUNCTION("""COMPUTED_VALUE"""),"Kronk Grognon") -> Kronk Grognon
O35: =IFERROR(__xludf.DUMMYFUNCTION("""COMPUTED_VALUE"""),"Laguerta Fende-Sillon") -> Laguerta Fende-Sillon
O36: =IFERROR(__xludf.DUMMYFUNCTION("""COMPUTED_VALUE"""),"Laureen Toison-de-Sang") -> Laureen Toison-de-Sang
O37: =IFERROR(__xludf.DUMMYFUNCTION("""COMPUTED_VALUE"""),"Lazabard Jemelred") -> Lazabard Jemelred
O38: =IFERROR(__xludf.DUMMYFUNCTION("""COMPUTED_VALUE"""),"Lokh Tar") -> Lokh Tar
O39: =IFERROR(__xludf.DUMMYFUNCTION("""COMPUTED_VALUE"""),"Lous Bois") -> Lous Bois
O40: =IFERROR(__xludf.DUMMYFUNCTION("""COMPUTED_VALUE"""),"Lucius Ravenshield") -> Lucius Ravenshield
O41: =IFERROR(__xludf.DUMMYFUNCTION("""COMPUTED_VALUE"""),"Lyrielle Audrin") -> Lyrielle Audrin
O42: =IFERROR(__xludf.DUMMYFUNCTION("""COMPUTED_VALUE"""),"Ma'arl ") -> Ma'arl
O43: =IFERROR(__xludf.DUMMYFUNCTION("""COMPUTED_VALUE"""),"Magnar Traquebrume") -> Magnar Traquebrume
O44: =IFERROR(__xludf.DUMMYFUNCTION("""COMPUTED_VALUE"""),"Maludrar ") -> Maludrar
O45: =IFERROR(__xludf.DUMMYFUNCTION("""COMPUTED_VALUE"""),"Marius Renatus") -> Marius Renatus
O46: =IFERROR(__xludf.DUMMYFUNCTION("""COMPUTED_VALUE"""),"Naevor Feuille-Sombre") -> Naevor Feuille-Sombre
O47: =IFERROR(__xludf.DUMMYFUNCTION("""COMPUTED_VALUE"""),"Numerus Clausus") -> Numerus Clausus
O48: =IFERROR(__xludf.DUMMYFUNCTION("""COMPUTED_VALUE"""),"Nymor ") -> Nymor
O49: =IFERROR(__xludf.DUMMYFUNCTION("""COMPUTED_VALUE"""),"Pavis Gurdalval") -> Pavis Gurdalval
O50: =IFERROR(__xludf.DUMMYFUNCTION("""COMPUTED_VALUE"""),"Pethiceor Le Borgne") -> Pethiceor Le Borgne
O51: =IFERROR(__xludf.DUMMYFUNCTION("""COMPUTED_VALUE"""),"Ra'zir Poing-de-fer") -> Ra'zir Poing-de-fer
O52: =IFERROR(__xludf.DUMMYFUNCTION("""COMPUTED_VALUE"""),"Ri'Jhan MoonShadow") -> Ri'Jhan MoonShadow
O53: =IFERROR(__xludf.DUMMYFUNCTION("""COMPUTED_VALUE"""),"Ronin ") -> Ronin
O54: =IFERROR(__xludf.DUMMYFUNCTION("""COMPUTED_VALUE"""),"Rorik Marche-Hiver") -> Rorik Marche-Hiver
O55: =IFERROR(__xludf.DUMMYFUNCTION("""COMPUTED_VALUE"""),"Rusco ") -> Rusco
O56: =IFERROR(__xludf.DUMMYFUNCTION("""COMPUTED_VALUE"""),"S'Khar ") -> S'Khar
O57: =IFERROR(__xludf.DUMMYFUNCTION("""COMPUTED_VALUE"""),"Selene ") -> Selene
O58: =IFERROR(__xludf.DUMMYFUNCTION("""COMPUTED_VALUE"""),"Si'Yara dite Fou") -> Si'Yara dite Fou
O59: =IFERROR(__xludf.DUMMYFUNCTION("""COMPUTED_VALUE"""),"Sigvard Coeurebene") -> Sigvard Coeurebene
O60: =IFERROR(__xludf.DUMMYFUNCTION("""COMPUTED_VALUE"""),"Silvius Varro") -> Silvius Varro
O61: =IFERROR(__xludf.DUMMYFUNCTION("""COMPUTED_VALUE"""),"Starkos Coeurebene") -> Starkos Coeurebene
O62: =IFERROR(__xludf.DUMMYFUNCTION("""COMPUTED_VALUE"""),"Theodrek Heid") -> Theodrek Heid
O63: =IFERROR(__xludf.DUMMYFUNCTION("""COMPUTED_VALUE"""),"Thorulf ") -> Thorulf
O64: =IFERROR(__xludf.DUMMYFUNCTION("""COMPUTED_VALUE"""),"Thov Lémartes") -> Thov Lémartes
O65: =IFERROR(__xludf.DUMMYFUNCTION("""COMPUTED_VALUE"""),"Ulfar ") -> Ulfar
O66: =IFERROR(__xludf.DUMMYFUNCTION("""COMPUTED_VALUE"""),"Ulfgar L'oiseau de nuit") -> Ulfgar L'oiseau de nuit
O67: =IFERROR(__xludf.DUMMYFUNCTION("""COMPUTED_VALUE"""),"Vaegon ") -> Vaegon
O68: =IFERROR(__xludf.DUMMYFUNCTION("""COMPUTED_VALUE"""),"Vahne ") -> Vahne
O69: =IFERROR(__xludf.DUMMYFUNCTION("""COMPUTED_VALUE"""),"Varaa Uzgar") -> Varaa Uzgar
O70: =IFERROR(__xludf.DUMMYFUNCTION("""COMPUTED_VALUE"""),"Varkiath ") -> Varkiath
O71: =IFERROR(__xludf.DUMMYFUNCTION("""COMPUTED_VALUE"""),"Vranx Thorgar") -> Vranx Thorgar
O72: =IFERROR(__xludf.DUMMYFUNCTION("""COMPUTED_VALUE"""),"Wulfgar Durrock") -> Wulfgar Durrock
O73: =IFERROR(__xludf.DUMMYFUNCTION("""COMPUTED_VALUE"""),"Zeid Le Brise-Lames") -> Zeid Le Brise-Lames

Sheet SyncCodex
A1: Source | B1: Article | C1: Titre | D1: Classification | E1: Amende | F1: Travaux forcés (heures) | G1: Cachot (heures) | H1: Sanction complète | I1: Texte | J1: Alerte parsing | L1: Dropdown Amende | M1: Montant | N1: Dropdown Prison | O1: Cachot (heures) | R1: Source | S1: Famille | T1: Autorité | U1: Applicabilité | V1: Local | W1: Lien
A2: Codex Judiciaire de Blancherive | B2: Préambule | C2: Préambule | I2: CHÂTELLERIE DE BLANCHERIVE CODEX JUDICIAIRE DE BLANCHERIVE Code pénal de la Châtellerie de Blancherive Par l’autorité du Jarl Lucius Haldor, Seigneur des terres de Blancherive, Sous l’autorité de l’Empereur de Tamriel et dans le respect des prérogatives de l’Empire, Conformément au Corpus Juriscivilis Imperialis, au Corpus Proceduralis Imperialis, au Codex Penitus Imperialis et au De Re Nobilitatis, Considérant que : le Jarl est Seigneur des terres de la Châtellerie, protecteur du peuple et gardien des serments prêtés sous son autorité ; la paix, la justice et la prospérité du domaine reposent sur des lois connues de tous, claires dans leur énoncé et prévisibles dans leur application ; le droit propre de la Châtellerie s’est constitué par sédimentation successive, au prix de redites, de renvois incertains et de dispositions divergentes qu’il convient d’unifier ; le Corpus Juriscivilis Imperialis autorise les châtelleries à promulguer des lois supplémentaires conformes à leurs coutumes, dans le respect de ses dispositions ; nulle coutume locale ne saurait prévaloir sur le droit impérial, ni sur les compétences réservées aux juridictions de l’Empire ; il convient de refondre en un texte unique l’ensemble des incriminations applicables sur le territoire de la Châtellerie ; Le Jarl de Blancherive décrète ce qui suit : | L2: Art. 14 — De l’usurpation d’identité | M2: {"version":1,"options":[],"libre":true,"texte":"Sanction — appréciation de la Cour ; niveau délictuel en cas d’usurpation d’une qualité noble ou d’une fonction officielle."} | N2: Art. 14 — De l’usurpation d’identité | O2: {"version":1,"options":[],"libre":true,"texte":"Sanction — appréciation de la Cour ; niveau délictuel en cas d’usurpation d’une qualité noble ou d’une fonction officielle."} | R2: Codex Judiciaire de Blancherive | S2: Droit de Blancherive | T2: Châtellerie de Blancherive | U2: Justice et sanctions de la Garde | V2: oui | W2: https://docs.google.com/document/d/1_awmZGCcQ0TgQycHQGRiBXLTr-f6Yjsn4fR7dAMdQvk/edit
A3: Codex Judiciaire de Blancherive | B3: 1 | C3: De l’autorité du Jarl | I3: Le Jarl est Seigneur des terres de la Châtellerie, protecteur du peuple et gardien des serments prêtés sous son autorité. Il veille à la paix, à la justice et à la prospérité de son domaine. Il est la plus haute autorité civile, militaire et judiciaire de la Châtellerie. Les serments prêtés en son nom possèdent valeur juridique et morale. Cette autorité s’exerce dans le respect du droit impérial et des compétences réservées à l’Empire. | L3: Art. 15 — Des menaces | M3: {"version":1,"options":[{"value":250,"label":"250 septims — Sanction — 250 septims et 1 heure de travaux forcés."}],"libre":false,"texte":"Sanction — 250 septims et 1 heure de travaux forcés."} | N3: Art. 23 — Des violences et agressions aggravées | O3: {"version":1,"options":[{"value":1,"label":"1 h de cachot — Sanction — réparation, 2 heures de travaux forcés et 1 heure de cachot"}],"libre":true,"texte":"Sanction — réparation, 2 heures de travaux forcés et 1 heure de cachot ; amende de niveau criminel à l’appréciation du magistrat."} | R3: Corpus Juriscivilis Imperialis | S3: Droit impérial | T3: Empire de Tamriel | U3: Droit pénal impérial général | W3: https://docs.google.com/document/d/1Q44ArnKr6qsJIRP9pSVCq_eloSzgMxA1JTqbPl7PP-M/edit
A4: Codex Judiciaire de Blancherive | B4: 2 | C4: Du champ d’application | I4: Le présent Codex s’applique à l’ensemble des habitants, résidents, passants et visiteurs se trouvant sur le territoire de la Châtellerie de Blancherive. L’ignorance des présentes dispositions ne saurait constituer un moyen de défense. | L4: Art. 16 — Des menaces aggravées | M4: {"version":1,"options":[{"value":500,"label":"500 septims — Sanction — 500 septims, 3 heures de travaux forcés et, si l’auteur exerce une fonction publique, radiation de celle-ci."}],"libre":false,"texte":"Sanction — 500 septims, 3 heures de travaux forcés et, si l’auteur exerce une fonction publique, radiation de celle-ci."} | N4: Art. 24 — De la séquestration, de l’enlèvement et de la prise d’otage | O4: {"version":1,"options":[{"value":1,"label":"1 h de cachot — Sanction — 650 septims, 3 heures de travaux forcés et 1 heure de cachot."}],"libre":false,"texte":"Sanction — 650 septims, 3 heures de travaux forcés et 1 heure de cachot."} | R4: De Re Nobilitatis | S4: Droit impérial | T4: Empire de Tamriel | U4: Droit et statut de la noblesse | W4: https://docs.google.com/document/d/1hMA2J9FeE-LfKwdKXy15U6nrpKpdzRZdFg77hqywrzI/edit
A5: Codex Judiciaire de Blancherive | B5: 3 | C5: De la constitution d’une infraction | D5: Infraction | I5: Une infraction n’est constituée que si trois éléments sont réunis : un élément légal : un texte prévoit et interdit le comportement en cause ; un élément matériel : un acte ou un fait concret a été commis ou tenté ; un élément moral : l’auteur a agi volontairement ou en connaissance de cause. À défaut de l’un de ces éléments, aucune infraction ne peut être retenue. | L5: Art. 17 — De la rébellion | M5: {"version":1,"options":[{"value":100,"label":"100 septims — Sanction — 100 septims et 1 heure de travaux forcés"}],"libre":false,"texte":"Sanction — 100 septims et 1 heure de travaux forcés ; qualification délictuelle et sanction aggravée en cas de refus violent ou actif."} | N5: Art. 25 — De la séquestration aggravée | O5: {"version":1,"options":[{"value":1,"label":"1 h de cachot — Sanction — 800 septims, 3 heures de travaux forcés et 1 heure de cachot."}],"libre":false,"texte":"Sanction — 800 septims, 3 heures de travaux forcés et 1 heure de cachot."} | R5: Corpus Proceduralis Imperialis | S5: Droit impérial | T5: Empire de Tamriel | U5: Procédure pénale impériale | W5: https://docs.google.com/document/d/15ij3H8wqKr-kEAlmHtSSAY1EKslKLudAJT-iM78UERE/edit
A6: Codex Judiciaire de Blancherive | B6: 4 | C6: De la classification des infractions | I6: Les infractions sont classées selon leur gravité, conformément au Corpus Juriscivilis Imperialis : contraventions : infractions mineures, jusqu’à cinq cents (500) septims ; délits : infractions de gravité moyenne, de cinq cents (500) à deux mille cinq cents (2500) septims ; crimes : infractions les plus graves, au-delà de deux mille cinq cents (2500) septims. Lorsque la valeur du préjudice détermine la qualification, celle-ci est appréciée selon les seuils ci-dessus. | L6: Art. 18 — Du chantage | M6: {"version":1,"options":[{"value":250,"label":"250 septims — Sanction — 250 septims et 1 heure de travaux forcés."}],"libre":false,"texte":"Sanction — 250 septims et 1 heure de travaux forcés."} | N6: Art. 26 — De l’homicide involontaire | O6: {"version":1,"options":[],"libre":true,"texte":"Sanction — à l’appréciation du magistrat. Barème indicatif : 800 septims, réparation à la famille et 5 heures de travaux forcés."} | R6: Justicia Militaris | S6: Droit spécial | T6: Empire de Tamriel | U6: Justice militaire et Légion impériale | W6: https://docs.google.com/document/d/1OfwyV6KQynjJS3QyVJyLLbgoTuQc2IP3CoRBSt45soM/edit
A7: Codex Judiciaire de Blancherive | B7: 5 | C7: De la présomption de culpabilité | D7: Infraction | I7: La culpabilité d’une personne est établie conformément aux règles prévues par le Corpus Proceduralis Imperialis et par le présent Codex. La Cour apprécie l’ensemble des éléments constitutifs de l’infraction, notamment ses éléments légal, matériel et moral, tels que définis à l’article 3. Aucun de ces éléments ne saurait, sauf disposition expresse du présent Codex, être considéré comme prépondérant sur les autres. La culpabilité ne peut être retenue qu’au terme de l’examen des faits et des preuves selon la procédure applicable. | L7: Art. 21 — De la mise en danger de la vie d’autrui | M7: {"version":1,"options":[{"value":500,"label":"500 septims — Sanction — 500 septims et 1 heure de travaux forcés."}],"libre":false,"texte":"Sanction — 500 septims et 1 heure de travaux forcés."} | N7: Art. 27 — De l’homicide volontaire | O7: {"version":1,"options":[{"value":2,"label":"2 h de cachot — Sanction — à l’appréciation du magistrat. Barème indicatif : 1000 septims, réparation à la famille, 3 heures de travaux forcés et 2 heures de cachot."}],"libre":true,"texte":"Sanction — à l’appréciation du magistrat. Barème indicatif : 1000 septims, réparation à la famille, 3 heures de travaux forcés et 2 heures de cachot."} | R7: Codex Penitus Imperialis | S7: Droit spécial | T7: Empire de Tamriel | U7: Protection de l'autorité impériale | W7: https://docs.google.com/document/d/1AwLYSziNrCP5oLCyIUAaAauoWmeQVRjvrBcSIBYP000/edit
A8: Codex Judiciaire de Blancherive | B8: 6 | C8: Des sanctions | I8: Peuvent être prononcées, selon les circonstances et la gravité des faits : l’amende, la réparation ou la restitution, les travaux forcés, les travaux d’intérêt général, le cachot, la saisie ou confiscation de biens, le bannissement du territoire de la Châtellerie et, dans les cas expressément prévus, la peine de mort. La peine de mort ne peut être prononcée qu’à l’issue d’un verdict public et motivé du magistrat, conformément à l’article 11 du Corpus Proceduralis Imperialis. En cas d’insolvabilité réelle, l’amende peut être convertie en travaux forcés, en travaux d’intérêt général ou en saisie de biens. | J8: La sanction comporte une mesure non numérique. Peine capitale mentionnée. | L8: Art. 22 — Des violences et agressions simples | M8: {"version":1,"options":[{"value":550,"label":"550 septims — Sanction — réparation, 550 septims et 3 heures de travaux forcés."}],"libre":false,"texte":"Sanction — réparation, 550 septims et 3 heures de travaux forcés."} | N8: Art. 28 — De l’assassinat | O8: {"version":1,"options":[{"value":3,"label":"3 h de cachot — Sanction — à l’appréciation du magistrat. Barème indicatif : 1200 septims, 5 heures de travaux forcés et 3 heures de cachot."}],"libre":true,"texte":"Sanction — à l’appréciation du magistrat. Barème indicatif : 1200 septims, 5 heures de travaux forcés et 3 heures de cachot."} | R8: Décret sur le régime fiscal de Bordeciel | S8: Décrets impériaux | T8: Empire de Tamriel | U8: Fiscalité de la province | W8: https://docs.google.com/document/d/1u3x3SrbR0IAP3S2hZg-8szrQajtPUBz8dPnLdydb_hE/edit
A9: Codex Judiciaire de Blancherive | B9: 7 | C9: De la récidive | I9: En cas de récidive, la peine encourue est multipliée par deux. La récidive se compte à partir du jour de la dernière condamnation, constatée au registre judiciaire de la Cour. | L9: Art. 23 — Des violences et agressions aggravées | M9: {"version":1,"options":[],"libre":true,"texte":"Sanction — réparation, 2 heures de travaux forcés et 1 heure de cachot ; amende de niveau criminel à l’appréciation du magistrat."} | N9: Art. 29 — De la torture, de la mutilation et de la barbarie | O9: {"version":1,"options":[{"value":1,"label":"1 h de cachot — Sanction — à l’appréciation du magistrat. Barème indicatif : réparation, 800 septims, 5 heures de travaux forcés et 1 heure de cachot."}],"libre":true,"texte":"Sanction — à l’appréciation du magistrat. Barème indicatif : réparation, 800 septims, 5 heures de travaux forcés et 1 heure de cachot."} | R9: Décret sur l'imposition en Bordeciel | S9: Décrets impériaux | T9: Empire de Tamriel | U9: Impôts et contributions | W9: https://docs.google.com/document/d/1a2Iq5wEduHZlnoFFMbaOuBNHRG7kfhTQGxHM7PnJR-A/edit
A10: Codex Judiciaire de Blancherive | B10: 8 | C10: De la tentative et de la complicité | D10: Infraction | I10: La tentative est constituée dès lors que, manifestée par un commencement d’exécution, elle n’a pas été suspendue volontairement ou a manqué son effet. Elle est sanctionnée comme l’infraction consommée. Est complice quiconque, sciemment, par aide, assistance, don, promesse, menace, ordre ou abus d’autorité, a facilité la préparation ou la consommation d’une infraction, ou a omis de dénoncer ce dont il a été témoin. La complicité est sanctionnée comme le fait de l’auteur. | J10: Peine capitale mentionnée. | L10: Art. 24 — De la séquestration, de l’enlèvement et de la prise d’otage | M10: {"version":1,"options":[{"value":650,"label":"650 septims — Sanction — 650 septims, 3 heures de travaux forcés et 1 heure de cachot."}],"libre":false,"texte":"Sanction — 650 septims, 3 heures de travaux forcés et 1 heure de cachot."} | N10: Art. 30 — De la torture aggravée | O10: {"version":1,"options":[{"value":3,"label":"3 h de cachot — Sanction — à l’appréciation du magistrat. Barème indicatif : réparation, 1000 septims, 5 heures de travaux forcés et 3 heures de cachot."}],"libre":true,"texte":"Sanction — à l’appréciation du magistrat. Barème indicatif : réparation, 1000 septims, 5 heures de travaux forcés et 3 heures de cachot."} | R10: De Argentaria | S10: Décrets impériaux | T10: Empire de Tamriel | U10: Établissements bancaires | W10: https://docs.google.com/document/d/1OEoAUcDVqnjH22Knnyl8ki4v2ED5UYqdg9P6dqww1Zo/edit
A11: Codex Judiciaire de Blancherive | B11: 9 | C11: Des circonstances aggravantes générales | I11: Constituent des circonstances aggravantes, lorsque l’article applicable le prévoit ou lorsque le magistrat les retient expressément : la commission à main armée ou avec usage de magie ; la commission en réunion, soit par deux auteurs ou plus ; la commission à l’encontre d’un représentant de l’Empire, d’un membre de la Garde ou d’un dépositaire de l’autorité dans l’exercice de ses fonctions ; la commission à l’encontre d’une personne vulnérable, d’un enfant ou d’un prêtre des Huit Divins ; la préméditation ; la mutilation ou l’atteinte durable à l’intégrité de la victime ; la commission dans l’enceinte du Temple de Kynareth ou de tout lieu consacré. | L11: Art. 25 — De la séquestration aggravée | M11: {"version":1,"options":[{"value":800,"label":"800 septims — Sanction — 800 septims, 3 heures de travaux forcés et 1 heure de cachot."}],"libre":false,"texte":"Sanction — 800 septims, 3 heures de travaux forcés et 1 heure de cachot."} | N11: Art. 34 — De l’intrusion en propriété privée extérieure | O11: {"version":1,"options":[{"value":0.5,"label":"0.5 h de cachot — Sanction — 50 septims et 30 minutes de cachot."}],"libre":false,"texte":"Sanction — 50 septims et 30 minutes de cachot."} | R11: Décret sur les Avocatus de Bordeciel | S11: Décrets impériaux | T11: Empire de Tamriel | U11: Représentation en justice | W11: https://docs.google.com/document/d/1epKkQLkEHy9RhLZycOUt-HNxFwVP8szyh_zhBRv0lGQ/edit
A12: Codex Judiciaire de Blancherive | B12: 10 | C12: Du droit à un procès équitable | D12: Infraction | I12: Toute personne accusée d’une infraction a le droit d’être entendue devant une autorité compétente et de présenter sa défense, en produisant témoins et preuves lorsque ceux-ci existent. Nul ne peut être condamné sans avoir eu la possibilité de répondre aux accusations portées contre lui. | L12: Art. 26 — De l’homicide involontaire | M12: {"version":1,"options":[{"value":800,"label":"800 septims — Sanction — à l’appréciation du magistrat. Barème indicatif : 800 septims, réparation à la famille et 5 heures de travaux forcés."}],"libre":true,"texte":"Sanction — à l’appréciation du magistrat. Barème indicatif : 800 septims, réparation à la famille et 5 heures de travaux forcés."} | N12: Art. 35 — De l’intrusion en propriété privée intérieure | O12: {"version":1,"options":[{"value":1,"label":"1 h de cachot — Sanction — 500 septims et 1 heure de cachot."}],"libre":false,"texte":"Sanction — 500 septims et 1 heure de cachot."} | R12: Décret sur le statut des administrateurs impériaux | S12: Décrets impériaux | T12: Empire de Tamriel | U12: Administration impériale | W12: https://docs.google.com/document/d/1PAtsn1rI81OLlwCmNvjM8EvPbd6oAHGrnUE-rzS2jOA/edit
A13: Codex Judiciaire de Blancherive | B13: 11 | C13: Du serment devant les Divins | I13: Toute personne prêtant serment devant les Divins est tenue de dire la vérité. Le serment possède une valeur sacrée : le trompeur offense les hommes et les Divins. Le faux témoignage ou le mensonge sous serment est réprimé au titre du parjure, prévu à l’article 80 du présent Codex. | L13: Art. 27 — De l’homicide volontaire | M13: {"version":1,"options":[{"value":1000,"label":"1000 septims — Sanction — à l’appréciation du magistrat. Barème indicatif : 1000 septims, réparation à la famille, 3 heures de travaux forcés et 2 heures de cachot."}],"libre":true,"texte":"Sanction — à l’appréciation du magistrat. Barème indicatif : 1000 septims, réparation à la famille, 3 heures de travaux forcés et 2 heures de cachot."} | N13: Art. 36 — De l’intrusion aggravée | O13: {"version":1,"options":[{"value":1,"label":"1 h de cachot — Sanction — 70 septims et 1 heure de cachot"}],"libre":false,"texte":"Sanction — 70 septims et 1 heure de cachot ; qualification délictuelle en propriété publique."} | R13: Décret sur les successions des châtelleries | S13: Décrets impériaux | T13: Gouverneur impérial de Bordeciel | U13: Succession des Jarls et des charges | W13: https://docs.google.com/document/d/1AZpHX8bqLZktW9Y36AI7QiAN_qBkZdxMxdkXYycg7sU/edit
A14: Codex Judiciaire de Blancherive | B14: 12 | C14: Du duel judiciaire | I14: Les crimes de sang peuvent, avec l’autorisation du Jarl ou du juge compétent, être soumis à un duel judiciaire lorsque les preuves sont insuffisantes ou que les deux parties en acceptent le principe. Cette ancienne coutume nordique ne constitue pas un droit et demeure une procédure exceptionnelle. | L14: Art. 28 — De l’assassinat | M14: {"version":1,"options":[{"value":1200,"label":"1200 septims — Sanction — à l’appréciation du magistrat. Barème indicatif : 1200 septims, 5 heures de travaux forcés et 3 heures de cachot."}],"libre":true,"texte":"Sanction — à l’appréciation du magistrat. Barème indicatif : 1200 septims, 5 heures de travaux forcés et 3 heures de cachot."} | N14: Art. 43 — Du pillage | O14: {"version":1,"options":[],"libre":true,"texte":"Sanction — restitution ; sanction déterminée selon la classification de l’article 4 d’après la gravité et la valeur du dommage."} | R14: Décret sur la qualité de Chevalier de Bordeciel | S14: Décrets impériaux | T14: Empire de Tamriel | U14: Chevalerie de la province | W14: https://docs.google.com/document/d/1HprPbGwA0B_0eOA4wlTnckxFDZZK-ikCfbklJ_p6RwA/edit
A15: Codex Judiciaire de Blancherive | B15: 13 | C15: Du droit d’asile religieux | D15: Délit | I15: Les prêtres des temples reconnus par la Châtellerie peuvent accorder un asile temporaire aux personnes poursuivies injustement, dans l’attente d’une décision des autorités compétentes. Cet asile ne constitue pas une immunité. Il ne fait obstacle ni à une arrestation en cas de flagrant délit, ni aux infractions relevant de la compétence exclusive des juridictions impériales. | L15: Art. 29 — De la torture, de la mutilation et de la barbarie | M15: {"version":1,"options":[{"value":800,"label":"800 septims — Sanction — à l’appréciation du magistrat. Barème indicatif : réparation, 800 septims, 5 heures de travaux forcés et 1 heure de cachot."}],"libre":true,"texte":"Sanction — à l’appréciation du magistrat. Barème indicatif : réparation, 800 septims, 5 heures de travaux forcés et 1 heure de cachot."} | N15: Art. 47 — De la corruption passive | O15: {"version":1,"options":[{"value":3,"label":"3 h de cachot — Sanction — 1000 septims, 3 heures de cachot et bannissement des offices publics à titre de mesure accessoire."}],"libre":false,"texte":"Sanction — 1000 septims, 3 heures de cachot et bannissement des offices publics à titre de mesure accessoire."} | R15: Décret sur les Ordres Militaires Religieux | S15: Décrets impériaux | T15: Empire de Tamriel | U15: Ordres militaires religieux | W15: https://docs.google.com/document/d/105KB6YllsBgQr7m_gcOVj74vHQFy30e2ja0omh5BNfE/edit
A16: Codex Judiciaire de Blancherive | B16: 14 | C16: De l’usurpation d’identité | D16: Délit | H16: Sanction — appréciation de la Cour ; niveau délictuel en cas d’usurpation d’une qualité noble ou d’une fonction officielle. | I16: Constitue une usurpation d’identité le fait de se faire passer pour autrui afin d’obtenir un avantage ou d’échapper à ses obligations. [Contravention] L’infraction devient un délit lorsqu’elle porte sur une qualité noble ou une fonction officielle. Sanction — appréciation de la Cour ; niveau délictuel en cas d’usurpation d’une qualité noble ou d’une fonction officielle. | L16: Art. 30 — De la torture aggravée | M16: {"version":1,"options":[{"value":1000,"label":"1000 septims — Sanction — à l’appréciation du magistrat. Barème indicatif : réparation, 1000 septims, 5 heures de travaux forcés et 3 heures de cachot."}],"libre":true,"texte":"Sanction — à l’appréciation du magistrat. Barème indicatif : réparation, 1000 septims, 5 heures de travaux forcés et 3 heures de cachot."} | N16: Art. 48 — De la corruption active | O16: {"version":1,"options":[{"value":2,"label":"2 h de cachot — Sanction — 2000 septims, 2 heures de travaux forcés, 2 heures de cachot et bannissement des offices publics à titre de mesure accessoire."}],"libre":false,"texte":"Sanction — 2000 septims, 2 heures de travaux forcés, 2 heures de cachot et bannissement des offices publics à titre de mesure accessoire."} | R16: Décret sur les équipements stratégiques Orsimer | S16: Décrets impériaux | T16: Gouverneur impérial de Bordeciel | U16: Armes et équipements prohibés | W16: https://docs.google.com/document/d/19asrJHgFRAu3KDaHkXZjAAggqOI-gyFp5ZJl2jrepU8/edit
A17: Codex Judiciaire de Blancherive | B17: 15 | C17: Des menaces | D17: Contravention | E17: 250 | F17: 1 | H17: Sanction — 250 septims et 1 heure de travaux forcés. | I17: Constitue une menace toute parole, écrit ou geste annonçant à autrui un mal à venir. [Contravention] Sanction — 250 septims et 1 heure de travaux forcés. | L17: Art. 32 — De la destruction ou dégradation de bien public | M17: {"version":1,"options":[{"value":100,"label":"100 septims — Sanction — 100 septims, réparation et 1 heure de travaux forcés lorsque le dommage n’excède pas 500 septims"}],"libre":false,"texte":"Sanction — 100 septims, réparation et 1 heure de travaux forcés lorsque le dommage n’excède pas 500 septims ; requalification en délit ou en crime au-delà."} | N17: Art. 49 — De l’abus de pouvoir public | O17: {"version":1,"options":[{"value":2,"label":"2 h de cachot — Sanction — 500 septims, 2 heures de travaux forcés, 2 heures de cachot et bannissement des offices publics à titre de mesure accessoire."}],"libre":false,"texte":"Sanction — 500 septims, 2 heures de travaux forcés, 2 heures de cachot et bannissement des offices publics à titre de mesure accessoire."} | R17: Décret sur les équipements dwemers | S17: Décrets impériaux | T17: Empire de Tamriel | U17: Armes et équipements prohibés | W17: https://docs.google.com/document/d/1g9mqqedq0iUnzTN7CedVPvyNXLS4L2SiC_fvhbZQstQ/edit
A18: Codex Judiciaire de Blancherive | B18: 16 | C18: Des menaces aggravées | D18: Délit | E18: 500 | F18: 3 | H18: Sanction — 500 septims, 3 heures de travaux forcés et, si l’auteur exerce une fonction publique, radiation de celle-ci. | I18: La menace est aggravée lorsqu’elle vise la famille de la victime, une personne vulnérable, une personne en raison de sa race ou de sa foi envers les Huit Divins, un dépositaire de l’autorité ou un prêtre, ou lorsqu’elle est proférée à main armée ou avec usage de magie. [Délit] Sanction — 500 septims, 3 heures de travaux forcés et, si l’auteur exerce une fonction publique, radiation de celle-ci. | L18: Art. 33 — De la destruction ou dégradation de bien privé | M18: {"version":1,"options":[{"value":100,"label":"100 septims — Sanction — 100 septims, réparation et 1 heure de travaux forcés lorsque le dommage n’excède pas 500 septims"}],"libre":false,"texte":"Sanction — 100 septims, réparation et 1 heure de travaux forcés lorsque le dommage n’excède pas 500 septims ; requalification en délit ou en crime au-delà."} | N18: Art. 55 — De l’exhibition | O18: {"version":1,"options":[{"value":1,"label":"1 h de cachot — Sanction — 50 septims et 1 heure de cachot."}],"libre":false,"texte":"Sanction — 50 septims et 1 heure de cachot."} | R18: Décret sur les armes éthérées | S18: Décrets impériaux | T18: Gouverneur impérial de Bordeciel | U18: Armes et équipements prohibés | W18: https://docs.google.com/document/d/1vvolhoVSss_EEI8cECbNrVdQAgBpjbUbfN_iiZJoYG8/edit
A19: Codex Judiciaire de Blancherive | B19: 17 | C19: De la rébellion | D19: Délit | E19: 100 | F19: 1 | H19: Sanction — 100 septims et 1 heure de travaux forcés ; qualification délictuelle et sanction aggravée en cas de refus violent ou actif. | I19: Constitue une rébellion le refus opposé à une injonction d’un garde ou d’un dépositaire de la loi. Le refus non violent constitue une contravention ; le refus violent ou actif constitue un délit. Sanction — 100 septims et 1 heure de travaux forcés ; qualification délictuelle et sanction aggravée en cas de refus violent ou actif. | L19: Art. 34 — De l’intrusion en propriété privée extérieure | M19: {"version":1,"options":[{"value":50,"label":"50 septims — Sanction — 50 septims et 30 minutes de cachot."}],"libre":false,"texte":"Sanction — 50 septims et 30 minutes de cachot."} | N19: Art. 56 — De l’ivresse manifeste sur la voie publique | O19: {"version":1,"options":[],"libre":true,"texte":"Sanction — à l’appréciation des forces de l’ordre."} | R19: Decretum de Restitutione Bonorum Imperii | S19: Décrets impériaux | T19: Empire de Tamriel | U19: Restitution des biens de l'Empire | W19: https://docs.google.com/document/d/1x9jV2Ijc_4niwHQe4yK3PKmp28fqfWCN4FFuwRTTOzs/edit
A20: Codex Judiciaire de Blancherive | B20: 18 | C20: Du chantage | D20: Contravention | E20: 250 | F20: 1 | H20: Sanction — 250 septims et 1 heure de travaux forcés. | I20: Constitue un chantage la pression exercée sur autrui en vue d’obtenir un avantage. [Contravention] Sanction — 250 septims et 1 heure de travaux forcés. | L20: Art. 35 — De l’intrusion en propriété privée intérieure | M20: {"version":1,"options":[{"value":500,"label":"500 septims — Sanction — 500 septims et 1 heure de cachot."}],"libre":false,"texte":"Sanction — 500 septims et 1 heure de cachot."} | N20: Art. 57 — Du trouble à l’ordre public | O20: {"version":1,"options":[],"libre":true,"texte":"Sanction — à l’appréciation des forces de l’ordre."} | R20: Décret sur les recherches archéologiques et les artefacts | S20: Décrets impériaux | T20: Conseil des Anciens | U20: Fouilles, artefacts et archives historiques | W20: https://docs.google.com/document/d/1Fh_wqNvwbcpyYGCWYwq6hBOw8jdc8mKLBtkYszPnUno/edit
A21: Codex Judiciaire de Blancherive | B21: 19 | C21: De la diffamation | D21: Contravention | F21: 1 | H21: Sanction — réparation du dommage et 1 heure de travaux forcés. | I21: Constitue une diffamation l’atteinte portée à la réputation d’autrui par des propos mensongers ou dommageables. [Contravention] Sanction — réparation du dommage et 1 heure de travaux forcés. | L21: Art. 36 — De l’intrusion aggravée | M21: {"version":1,"options":[{"value":70,"label":"70 septims — Sanction — 70 septims et 1 heure de cachot"}],"libre":false,"texte":"Sanction — 70 septims et 1 heure de cachot ; qualification délictuelle en propriété publique."} | N21: Art. 58 — Des rixes et bagarres | O21: {"version":1,"options":[{"value":0.3333333333333333,"label":"0.3333333333333333 h de cachot — Sanction — 35 septims et 20 minutes de cachot"}],"libre":false,"texte":"Sanction — 35 septims et 20 minutes de cachot ; qualification supérieure en cas de blessures."}
A22: Codex Judiciaire de Blancherive | B22: 20 | C22: Du harcèlement | D22: Contravention | F22: 1 | H22: Sanction — réparation du dommage et 1 heure de travaux forcés. | I22: Constitue un harcèlement tout comportement répété portant atteinte à une personne. [Contravention] Sanction — réparation du dommage et 1 heure de travaux forcés. | L22: Art. 37 — Du vol simple | M22: {"version":1,"options":[{"value":50,"label":"50 septims — Sanction — réparation, amende de 50 septims au minimum ajustée à la valeur du bien, et 1 heure de travaux forcés."}],"libre":false,"texte":"Sanction — réparation, amende de 50 septims au minimum ajustée à la valeur du bien, et 1 heure de travaux forcés."} | N22: Art. 61 — De l’exercice illégal d’une profession réglementée | O22: {"version":1,"options":[],"libre":true,"texte":"Sanction — selon les régimes spéciaux applicables et l’appréciation de la Cour."}
A23: Codex Judiciaire de Blancherive | B23: 21 | C23: De la mise en danger de la vie d’autrui | D23: Délit | E23: 500 | F23: 1 | H23: Sanction — 500 septims et 1 heure de travaux forcés. | I23: Constitue une mise en danger le fait d’exposer autrui à un risque sérieux pour sa vie ou son intégrité. [Délit] Sanction — 500 septims et 1 heure de travaux forcés. | L23: Art. 38 — Du vol aggravé | M23: {"version":1,"options":[{"value":70,"label":"70 septims — Sanction — réparation, 70 septims et 2 heures de travaux forcés."}],"libre":false,"texte":"Sanction — réparation, 70 septims et 2 heures de travaux forcés."} | N23: Art. 66 — Des horaires des tavernes | O23: {"version":1,"options":[],"libre":true,"texte":"Sanction — à l’appréciation des forces de l’ordre ; fermeture administrative possible en cas de récidive.\n\nLes infractions du présent titre s’appliquent sans préjudice de la compétence exclusive des juridictions impériales lorsque les faits portent également atteinte à l’autorité impériale directe, à la Légion ou aux services de renseignement impériaux, au sens du Codex Penitus Imperialis."}
A24: Codex Judiciaire de Blancherive | B24: 22 | C24: Des violences et agressions simples | D24: Délit | E24: 550 | F24: 3 | H24: Sanction — réparation, 550 septims et 3 heures de travaux forcés. | I24: Constituent des violences ou agressions tous actes portant atteinte à l’intégrité physique d’une personne et ayant entraîné blessures, contusions ou incapacité, sans circonstance aggravante. [Délit] Sanction — réparation, 550 septims et 3 heures de travaux forcés. | L24: Art. 41 — Du recel | M24: {"version":1,"options":[{"value":100,"label":"100 septims — Sanction — 100 septims par bien, en sus de la valeur estimée du bien, et 2 heures de travaux forcés."}],"libre":false,"texte":"Sanction — 100 septims par bien, en sus de la valeur estimée du bien, et 2 heures de travaux forcés."} | N24: Art. 76 — Du non-respect d’une décision de justice | O24: {"version":1,"options":[],"libre":true,"texte":"Sanction — à l’appréciation du juge."}
A25: Codex Judiciaire de Blancherive | B25: 23 | C25: Des violences et agressions aggravées | D25: Crime | G25: 1 | H25: Sanction — réparation, 2 heures de travaux forcés et 1 heure de cachot ; amende de niveau criminel à l’appréciation du magistrat. | I25: Les violences sont aggravées lorsqu’elles sont commises dans l’une des circonstances prévues à l’article 9. [Crime] Sanction — réparation, 2 heures de travaux forcés et 1 heure de cachot ; amende de niveau criminel à l’appréciation du magistrat. | J25: Plusieurs durées de travaux détectées. | L25: Art. 42 — Du recel en bande organisée | M25: {"version":1,"options":[{"value":150,"label":"150 septims — Sanction — 150 septims par bien, en sus de la valeur estimée du bien, et 2 heures de travaux forcés."}],"libre":false,"texte":"Sanction — 150 septims par bien, en sus de la valeur estimée du bien, et 2 heures de travaux forcés."} | N25: Art. 77 — De l’entrave à la justice | O25: {"version":1,"options":[{"value":1,"label":"1 h de cachot — Sanction — 50 septims et 1 heure de cachot."}],"libre":false,"texte":"Sanction — 50 septims et 1 heure de cachot."}
A26: Codex Judiciaire de Blancherive | B26: 24 | C26: De la séquestration, de l’enlèvement et de la prise d’otage | D26: Crime | E26: 650 | G26: 1 | H26: Sanction — 650 septims, 3 heures de travaux forcés et 1 heure de cachot. | I26: Constitue une séquestration, un enlèvement ou une prise d’otage le fait de priver autrui de sa liberté d’aller et venir sans droit. [Crime] Sanction — 650 septims, 3 heures de travaux forcés et 1 heure de cachot. | J26: Plusieurs durées de travaux détectées. | L26: Art. 43 — Du pillage | M26: {"version":1,"options":[],"libre":true,"texte":"Sanction — restitution ; sanction déterminée selon la classification de l’article 4 d’après la gravité et la valeur du dommage."} | N26: Art. 78 — Du faux | O26: {"version":1,"options":[{"value":2,"label":"2 h de cachot — Sanction — 500 septims et 2 heures de cachot."}],"libre":false,"texte":"Sanction — 500 septims et 2 heures de cachot."}
A27: Codex Judiciaire de Blancherive | B27: 25 | C27: De la séquestration aggravée | D27: Crime | E27: 800 | G27: 1 | H27: Sanction — 800 septims, 3 heures de travaux forcés et 1 heure de cachot. | I27: L’infraction est aggravée lorsqu’elle est commise en réunion, avec violence, ou lorsqu’elle se prolonge dans la durée. [Crime] L’aggravation s’apprécie selon le nombre d’auteurs, la violence employée et la durée de la privation de liberté, et non selon le nombre de victimes. Sanction — 800 septims, 3 heures de travaux forcés et 1 heure de cachot. | J27: Plusieurs durées de travaux détectées. | L27: Art. 44 — Des ouvrages publics | M27: {"version":1,"options":[{"value":50,"label":"50 septims — Sanction — réparation et 50 septims"},{"value":200,"label":"200 septims — 200 septims en cas de récidive"}],"libre":false,"texte":"Sanction — réparation et 50 septims ; 200 septims en cas de récidive ; requalification selon la valeur du dommage."} | N27: Art. 79 — De l’usage de faux | O27: {"version":1,"options":[{"value":2,"label":"2 h de cachot — Sanction — 250 septims et 2 heures de cachot."}],"libre":false,"texte":"Sanction — 250 septims et 2 heures de cachot."}
A28: Codex Judiciaire de Blancherive | B28: 26 | C28: De l’homicide involontaire | D28: Crime | E28: 800 | F28: 5 | H28: Sanction — à l’appréciation du magistrat. Barème indicatif : 800 septims, réparation à la famille et 5 heures de travaux forcés. | I28: Constitue un homicide involontaire le décès d’autrui causé par imprudence, négligence ou manquement caractérisé à une obligation de prudence. [Crime] Sanction — à l’appréciation du magistrat. Barème indicatif : 800 septims, réparation à la famille et 5 heures de travaux forcés. | L28: Art. 45 — Des recours abusifs | M28: {"version":1,"options":[{"value":200,"label":"200 septims — Sanction — 200 septims."}],"libre":false,"texte":"Sanction — 200 septims."} | N28: Art. 90 — De la protection des sépultures | O28: {"version":1,"options":[],"libre":true,"texte":"Sanction — sanction déterminée selon l’article 88 ; qualification criminelle lorsque le motif est daedrique."}
A29: Codex Judiciaire de Blancherive | B29: 27 | C29: De l’homicide volontaire | D29: Crime | E29: 1000 | G29: 2 | H29: Sanction — à l’appréciation du magistrat. Barème indicatif : 1000 septims, réparation à la famille, 3 heures de travaux forcés et 2 heures de cachot. | I29: Constitue un homicide volontaire tout acte ayant entraîné volontairement la mort d’autrui. [Crime] Ne peuvent être qualifiés d’homicide les décès résultant d’une guerre déclarée, d’un usage légitime et proportionné de la force par les autorités, d’une exécution judiciaire régulière ou d’un duel légal consenti. Sanction — à l’appréciation du magistrat. Barème indicatif : 1000 septims, réparation à la famille, 3 heures de travaux forcés et 2 heures de cachot. | J29: Plusieurs durées de travaux détectées. | L29: Art. 46 — De la violation de la propriété de la Châtellerie | M29: {"version":1,"options":[{"value":100,"label":"100 septims — Sanction — amende de niveau délictuel, 100 septims au minimum."}],"libre":false,"texte":"Sanction — amende de niveau délictuel, 100 septims au minimum."} | N29: Art. 93 — De la corruption magique | O29: {"version":1,"options":[],"libre":true,"texte":"Sanction — à l’appréciation du magistrat, selon la classification retenue."}
A30: Codex Judiciaire de Blancherive | B30: 28 | C30: De l’assassinat | D30: Crime | E30: 1200 | G30: 3 | H30: Sanction — à l’appréciation du magistrat. Barème indicatif : 1200 septims, 5 heures de travaux forcés et 3 heures de cachot. | I30: Constitue un assassinat l’homicide volontaire commis avec préméditation. La préméditation suppose une préparation et une réflexion préalables. [Crime] Sont également aggravants les faits commis contre la famille, une personne vulnérable, un représentant de l’autorité, ou en raison de la race ou de la foi de la victime, ainsi que ceux commis en bande organisée ou à des fins d’intimidation. Sanction — à l’appréciation du magistrat. Barème indicatif : 1200 septims, 5 heures de travaux forcés et 3 heures de cachot. | J30: Plusieurs durées de travaux détectées. | L30: Art. 47 — De la corruption passive | M30: {"version":1,"options":[{"value":1000,"label":"1000 septims — Sanction — 1000 septims, 3 heures de cachot et bannissement des offices publics à titre de mesure accessoire."}],"libre":false,"texte":"Sanction — 1000 septims, 3 heures de cachot et bannissement des offices publics à titre de mesure accessoire."} | N30: Art. 106 — De la contrebande | O30: {"version":1,"options":[{"value":0.3333333333333333,"label":"0.3333333333333333 h de cachot — Sanction — 100 septims, 20 minutes de cachot et confiscation, la valeur de la marchandise saisie s’ajoutant à la peine"}],"libre":false,"texte":"Sanction — 100 septims, 20 minutes de cachot et confiscation, la valeur de la marchandise saisie s’ajoutant à la peine ; sanction aggravée selon l’article 64 en cas de trafic."}
A31: Codex Judiciaire de Blancherive | B31: 29 | C31: De la torture, de la mutilation et de la barbarie | D31: Crime | E31: 800 | G31: 1 | H31: Sanction — à l’appréciation du magistrat. Barème indicatif : réparation, 800 septims, 5 heures de travaux forcés et 1 heure de cachot. | I31: Constitue un acte de torture tout acte de barbarie, mutilation, violence extrême ou souffrance délibérément infligée. [Crime] Sanction — à l’appréciation du magistrat. Barème indicatif : réparation, 800 septims, 5 heures de travaux forcés et 1 heure de cachot. | J31: Plusieurs durées de travaux détectées. | L31: Art. 48 — De la corruption active | M31: {"version":1,"options":[{"value":2000,"label":"2000 septims — Sanction — 2000 septims, 2 heures de travaux forcés, 2 heures de cachot et bannissement des offices publics à titre de mesure accessoire."}],"libre":false,"texte":"Sanction — 2000 septims, 2 heures de travaux forcés, 2 heures de cachot et bannissement des offices publics à titre de mesure accessoire."} | N31: Art. 111 — De la protection des géants | O31: {"version":1,"options":[],"libre":true,"texte":"Sanction — vol : 100 septims ; provocation ou harcèlement : 150 septims ; mise à mort hors légitime défense : délit, jugement obligatoire, peine déterminée par le juge selon l’article 4, amende de niveau délictuel et cachot possible."}
A32: Codex Judiciaire de Blancherive | B32: 30 | C32: De la torture aggravée | D32: Crime | E32: 1000 | G32: 3 | H32: Sanction — à l’appréciation du magistrat. Barème indicatif : réparation, 1000 septims, 5 heures de travaux forcés et 3 heures de cachot. | I32: L’infraction est aggravée dans les circonstances prévues à l’article 9. [Crime] Sanction — à l’appréciation du magistrat. Barème indicatif : réparation, 1000 septims, 5 heures de travaux forcés et 3 heures de cachot. | J32: Plusieurs durées de travaux détectées. | L32: Art. 49 — De l’abus de pouvoir public | M32: {"version":1,"options":[{"value":500,"label":"500 septims — Sanction — 500 septims, 2 heures de travaux forcés, 2 heures de cachot et bannissement des offices publics à titre de mesure accessoire."}],"libre":false,"texte":"Sanction — 500 septims, 2 heures de travaux forcés, 2 heures de cachot et bannissement des offices publics à titre de mesure accessoire."}
A33: Codex Judiciaire de Blancherive | B33: 31 | C33: Du viol et des atteintes sexuelles sur enfant | D33: Crime | H33: Sanction — peine maximale encourue : mort et saisie des biens, sur verdict public et motivé du magistrat. | I33: Le viol et les atteintes sexuelles commises sur un enfant constituent les crimes les plus graves contre la personne. [Crime] Sanction — peine maximale encourue : mort et saisie des biens, sur verdict public et motivé du magistrat. | L33: Art. 50 — De l’abus de pouvoir lié à un statut | M33: {"version":1,"options":[{"value":500,"label":"500 septims — Sanction — 500 septims et 3 heures de travaux forcés."}],"libre":false,"texte":"Sanction — 500 septims et 3 heures de travaux forcés."}
A34: Codex Judiciaire de Blancherive | B34: 32 | C34: De la destruction ou dégradation de bien public | D34: Crime | F34: 1 | H34: Sanction — 100 septims, réparation et 1 heure de travaux forcés lorsque le dommage n’excède pas 500 septims ; requalification en délit ou en crime au-delà. | I34: Constitue une infraction la destruction ou la dégradation volontaire d’un bien appartenant à la Châtellerie ou affecté à l’usage public. La qualification suit la valeur du dommage selon l’article 4. Sanction — 100 septims, réparation et 1 heure de travaux forcés lorsque le dommage n’excède pas 500 septims ; requalification en délit ou en crime au-delà. | J34: Plusieurs montants d'amende détectés. | L34: Art. 51 — De l’usurpation de fonction | M34: {"version":1,"options":[{"value":500,"label":"500 septims — Sanction — 500 septims et 3 heures de travaux forcés."}],"libre":false,"texte":"Sanction — 500 septims et 3 heures de travaux forcés."}
A35: Codex Judiciaire de Blancherive | B35: 33 | C35: De la destruction ou dégradation de bien privé | D35: Crime | F35: 1 | H35: Sanction — 100 septims, réparation et 1 heure de travaux forcés lorsque le dommage n’excède pas 500 septims ; requalification en délit ou en crime au-delà. | I35: Constitue une infraction la destruction ou la dégradation volontaire du bien d’autrui. La qualification suit la valeur du dommage selon l’article 4. Sanction — 100 septims, réparation et 1 heure de travaux forcés lorsque le dommage n’excède pas 500 septims ; requalification en délit ou en crime au-delà. | J35: Plusieurs montants d'amende détectés. | L35: Art. 52 — De l’usage non autorisé de matériel de la Châtellerie | M35: {"version":1,"options":[{"value":150,"label":"150 septims — Sanction — saisie des biens, 150 septims par équipement et 30 minutes de travaux forcés."}],"libre":false,"texte":"Sanction — saisie des biens, 150 septims par équipement et 30 minutes de travaux forcés."}
A36: Codex Judiciaire de Blancherive | B36: 34 | C36: De l’intrusion en propriété privée extérieure | D36: Contravention | E36: 50 | G36: 0.5 | H36: Sanction — 50 septims et 30 minutes de cachot. | I36: Constitue une intrusion le fait de pénétrer ou de se maintenir sans autorisation sur un terrain, un enclos ou une dépendance appartenant à autrui. [Contravention] Chacun peut défendre ses terres et ses propriétés, dans les conditions autorisées par la Châtellerie. Sanction — 50 septims et 30 minutes de cachot. | L36: Art. 53 — De la divulgation d’information secrète de la Châtellerie | M36: {"version":1,"options":[{"value":1000,"label":"1000 septims — Sanction — 1000 septims et 5 heures de travaux forcés."}],"libre":false,"texte":"Sanction — 1000 septims et 5 heures de travaux forcés."}
A37: Codex Judiciaire de Blancherive | B37: 35 | C37: De l’intrusion en propriété privée intérieure | D37: Délit | E37: 500 | G37: 1 | H37: Sanction — 500 septims et 1 heure de cachot. | I37: Constitue une intrusion aggravée par le lieu le fait de pénétrer ou de se maintenir sans autorisation à l’intérieur de la demeure d’autrui. [Délit] Le propriétaire est déclaré en état de légitime défense après trois sommations demeurées sans effet. Sanction — 500 septims et 1 heure de cachot. | L37: Art. 54 — De la dissimulation du visage | M37: {"version":1,"options":[{"value":20,"label":"20 septims — Sanction — 20 septims."}],"libre":false,"texte":"Sanction — 20 septims."}
A38: Codex Judiciaire de Blancherive | B38: 36 | C38: De l’intrusion aggravée | D38: Délit | E38: 70 | G38: 1 | H38: Sanction — 70 septims et 1 heure de cachot ; qualification délictuelle en propriété publique. | I38: L’intrusion est aggravée lorsqu’elle est commise par force, à main armée, ou contre une personne vulnérable ou un dépositaire de l’autorité. Elle constitue un délit lorsqu’elle porte sur une propriété publique. Sanction — 70 septims et 1 heure de cachot ; qualification délictuelle en propriété publique. | L38: Art. 55 — De l’exhibition | M38: {"version":1,"options":[{"value":50,"label":"50 septims — Sanction — 50 septims et 1 heure de cachot."}],"libre":false,"texte":"Sanction — 50 septims et 1 heure de cachot."}
A39: Codex Judiciaire de Blancherive | B39: 37 | C39: Du vol simple | D39: Crime | E39: 50 | F39: 1 | H39: Sanction — réparation, amende de 50 septims au minimum ajustée à la valeur du bien, et 1 heure de travaux forcés. | I39: Constitue un vol toute appropriation frauduleuse d’un bien appartenant à autrui. [Délit] Les faits d’une valeur infime peuvent être traités en contravention sur appréciation du magistrat. Le vol devient un crime lorsque le bien est d’une valeur particulièrement élevée ou qu’il s’agit d’un objet sous licence. Sanction — réparation, amende de 50 septims au minimum ajustée à la valeur du bien, et 1 heure de travaux forcés. | J39: La sanction comporte une borne minimale ou maximale. | L39: Art. 56 — De l’ivresse manifeste sur la voie publique | M39: {"version":1,"options":[],"libre":true,"texte":"Sanction — à l’appréciation des forces de l’ordre."}
A40: Codex Judiciaire de Blancherive | B40: 38 | C40: Du vol aggravé | D40: Délit | E40: 70 | F40: 2 | H40: Sanction — réparation, 70 septims et 2 heures de travaux forcés. | I40: Le vol est aggravé lorsqu’il est commis contre une personne vulnérable ou un dépositaire de l’autorité, en raison de la race ou de la foi de la victime, à main armée, avec préméditation ou en bande organisée. [Délit] Sanction — réparation, 70 septims et 2 heures de travaux forcés. | L40: Art. 57 — Du trouble à l’ordre public | M40: {"version":1,"options":[],"libre":true,"texte":"Sanction — à l’appréciation des forces de l’ordre."}
A41: Codex Judiciaire de Blancherive | B41: 39 | C41: Du vol de bétail | H41: Sanction — restitution ou remboursement au triple, cumulé avec la peine prévue aux articles 37 et 38. | I41: Le bétail constitue une richesse essentielle des fermes et villages de la Châtellerie. Quiconque en est reconnu coupable doit restituer ou rembourser au triple du préjudice subi. Cette réparation civile s’ajoute à la peine principale, déterminée selon la gravité des faits. Sanction — restitution ou remboursement au triple, cumulé avec la peine prévue aux articles 37 et 38. | L41: Art. 58 — Des rixes et bagarres | M41: {"version":1,"options":[{"value":35,"label":"35 septims — Sanction — 35 septims et 20 minutes de cachot"}],"libre":false,"texte":"Sanction — 35 septims et 20 minutes de cachot ; qualification supérieure en cas de blessures."}
