Workbook

Sheet Vue globale
H2: Effectif total de la garde en service | I2: =COUNTIFS(Effectifs!B2:B1000,"<>",Effectifs!G2:G1000,"En service actif") -> 64 | K2: Solde hebdomadaire individuelle | L2: 50 | N2: Garde ayant une absence supérieure à 5 jours
K3: Budget hebdomadaire maximal | L3: =L2*7*I2 -> 22400 | N3: Garde | O3: Dernière présence
H5: =IFERROR(__xludf.DUMMYFUNCTION("QUERY( Effectifs!E2:G1000, ""SELECT E, COUNT(E) WHERE E IS NOT NULL AND G = 'En service actif' GROUP BY E ORDER BY COUNT(E) DESC LABEL E 'Corps de garde', COUNT(E) 'Effectif actif'"", 0 )"),"Corps de garde") -> Corps de garde | I5: =IFERROR(__xludf.DUMMYFUNCTION("""COMPUTED_VALUE"""),"Effectif actif") -> Effectif actif | K5: =IFERROR(__xludf.DUMMYFUNCTION("QUERY( Effectifs!E2:G1000, ""SELECT E, COUNT(E) * ""&(L2*7)&"" WHERE E IS NOT NULL AND G = 'En service actif' GROUP BY E ORDER BY COUNT(E) * ""&(L2*7)&"" DESC LABEL E 'Corps de garde', COUNT(E) * ""&(L2*7)&"" 'Budget maximal hebd"&"omadaire'"", 0 )"),"Corps de garde") -> Corps de garde | L5: =IFERROR(__xludf.DUMMYFUNCTION("""COMPUTED_VALUE"""),"Budget maximal hebdomadaire") -> Budget maximal hebdomadaire | N5: =IFERROR(__xludf.DUMMYFUNCTION("LET( semaines,FILTER('Présences'!A2:A1000,'Présences'!A2:A1000<>""""), pPrenoms,FILTER('Présences'!D2:D1000,'Présences'!A2:A1000<>""""), pNoms,FILTER('Présences'!E2:E1000,'Présences'!A2:A1000<>""""), jours,FILTER('Présences'!F2:L1000,'Présences'!A"&"2:A1000<>""""), lundiS1, DATE(YEAR(TODAY()),1,4) -WEEKDAY(DATE(YEAR(TODAY()),1,4),2) +1, dates, MAKEARRAY( ROWS(semaines), 7, LAMBDA(r,c, lundiS1 +(INDEX(semaines,r)-1)*7 +(c-1) ) )"&", personnesPresence, MAKEARRAY( ROWS(pPrenoms), 7, LAMBDA(r,c, TRIM( INDEX(pPrenoms,r) &"" ""& INDEX(pNoms,r) ) ) ), gardes, UNIQUE( FILTER( TRIM(Effecti"&"fs!C2:C1000&"" ""&Effectifs!D2:D1000), Effectifs!G2:G1000=""En service actif"", ((Effectifs!C2:C1000<>"""")+(Effectifs!D2:D1000<>""""))>0 ) ), dernieres, MAP( gardes, LAMBDA(garde, IFERROR( MA"&"X( FILTER( TOCOL(dates), TOCOL(personnesPresence)=garde, TOCOL(jours)=TRUE ) ), """" ) ) ), absents, FILTER( HSTACK(gardes,dernieres), "&" dernieres<>"""", dernieres<TODAY()-5 ), jamaisPresents, FILTER( gardes, dernieres="""" ), VSTACK( HSTACK(""— Absents depuis plusieurs jours —"",""""), absents, HSTACK(""— Jamais reporté présents —"","""")"&", HSTACK( jamaisPresents, MAP(jamaisPresents,LAMBDA(garde,""Jamais présent"")) ) ) )"),"— Absents depuis plusieurs jours —") -> — Absents depuis plusieurs jours — | O5: =IFERROR(__xludf.DUMMYFUNCTION("""COMPUTED_VALUE"""),"")
H6: =IFERROR(__xludf.DUMMYFUNCTION("""COMPUTED_VALUE"""),"Cité de Blancherive") -> Cité de Blancherive | I6: =IFERROR(__xludf.DUMMYFUNCTION("""COMPUTED_VALUE"""),17.0) -> 17 | K6: =IFERROR(__xludf.DUMMYFUNCTION("""COMPUTED_VALUE"""),"Cité de Blancherive") -> Cité de Blancherive | L6: =IFERROR(__xludf.DUMMYFUNCTION("""COMPUTED_VALUE"""),5950.0) -> 5950 | N6: =IFERROR(__xludf.DUMMYFUNCTION("""COMPUTED_VALUE"""),"Andor Viraes") -> Andor Viraes | O6: =IFERROR(__xludf.DUMMYFUNCTION("""COMPUTED_VALUE"""),46259.0) -> 46259
H7: =IFERROR(__xludf.DUMMYFUNCTION("""COMPUTED_VALUE"""),"Faubourgs de Blancherive") -> Faubourgs de Blancherive | I7: =IFERROR(__xludf.DUMMYFUNCTION("""COMPUTED_VALUE"""),12.0) -> 12 | K7: =IFERROR(__xludf.DUMMYFUNCTION("""COMPUTED_VALUE"""),"Faubourgs de Blancherive") -> Faubourgs de Blancherive | L7: =IFERROR(__xludf.DUMMYFUNCTION("""COMPUTED_VALUE"""),4200.0) -> 4200 | N7: =IFERROR(__xludf.DUMMYFUNCTION("""COMPUTED_VALUE"""),"— Jamais reporté présents —") -> — Jamais reporté présents — | O7: =IFERROR(__xludf.DUMMYFUNCTION("""COMPUTED_VALUE"""),"")
H8: =IFERROR(__xludf.DUMMYFUNCTION("""COMPUTED_VALUE"""),"Hird du Jarl") -> Hird du Jarl | I8: =IFERROR(__xludf.DUMMYFUNCTION("""COMPUTED_VALUE"""),11.0) -> 11 | K8: =IFERROR(__xludf.DUMMYFUNCTION("""COMPUTED_VALUE"""),"Hird du Jarl") -> Hird du Jarl | L8: =IFERROR(__xludf.DUMMYFUNCTION("""COMPUTED_VALUE"""),3850.0) -> 3850 | N8: =IFERROR(__xludf.DUMMYFUNCTION("""COMPUTED_VALUE"""),"Hastelvin") -> Hastelvin | O8: =IFERROR(__xludf.DUMMYFUNCTION("""COMPUTED_VALUE"""),"Jamais présent") -> Jamais présent
H9: =IFERROR(__xludf.DUMMYFUNCTION("""COMPUTED_VALUE"""),"Cap Granite") -> Cap Granite | I9: =IFERROR(__xludf.DUMMYFUNCTION("""COMPUTED_VALUE"""),8.0) -> 8 | K9: =IFERROR(__xludf.DUMMYFUNCTION("""COMPUTED_VALUE"""),"Cap Granite") -> Cap Granite | L9: =IFERROR(__xludf.DUMMYFUNCTION("""COMPUTED_VALUE"""),2800.0) -> 2800 | N9: =IFERROR(__xludf.DUMMYFUNCTION("""COMPUTED_VALUE"""),"Thorin Rivegel") -> Thorin Rivegel | O9: =IFERROR(__xludf.DUMMYFUNCTION("""COMPUTED_VALUE"""),"Jamais présent") -> Jamais présent
H10: =IFERROR(__xludf.DUMMYFUNCTION("""COMPUTED_VALUE"""),"Eclaireur") -> Eclaireur | I10: =IFERROR(__xludf.DUMMYFUNCTION("""COMPUTED_VALUE"""),6.0) -> 6 | K10: =IFERROR(__xludf.DUMMYFUNCTION("""COMPUTED_VALUE"""),"Eclaireur") -> Eclaireur | L10: =IFERROR(__xludf.DUMMYFUNCTION("""COMPUTED_VALUE"""),2100.0) -> 2100 | N10: =IFERROR(__xludf.DUMMYFUNCTION("""COMPUTED_VALUE"""),"Kronk Grognon") -> Kronk Grognon | O10: =IFERROR(__xludf.DUMMYFUNCTION("""COMPUTED_VALUE"""),"Jamais présent") -> Jamais présent
H11: =IFERROR(__xludf.DUMMYFUNCTION("""COMPUTED_VALUE"""),"Rivebois") -> Rivebois | I11: =IFERROR(__xludf.DUMMYFUNCTION("""COMPUTED_VALUE"""),6.0) -> 6 | K11: =IFERROR(__xludf.DUMMYFUNCTION("""COMPUTED_VALUE"""),"Rivebois") -> Rivebois | L11: =IFERROR(__xludf.DUMMYFUNCTION("""COMPUTED_VALUE"""),2100.0) -> 2100 | N11: =IFERROR(__xludf.DUMMYFUNCTION("""COMPUTED_VALUE"""),"Gronk Grognon") -> Gronk Grognon | O11: =IFERROR(__xludf.DUMMYFUNCTION("""COMPUTED_VALUE"""),"Jamais présent") -> Jamais présent
H12: =IFERROR(__xludf.DUMMYFUNCTION("""COMPUTED_VALUE"""),"Bois-de-Chêne") -> Bois-de-Chêne | I12: =IFERROR(__xludf.DUMMYFUNCTION("""COMPUTED_VALUE"""),2.0) -> 2 | K12: =IFERROR(__xludf.DUMMYFUNCTION("""COMPUTED_VALUE"""),"Bois-de-Chêne") -> Bois-de-Chêne | L12: =IFERROR(__xludf.DUMMYFUNCTION("""COMPUTED_VALUE"""),700.0) -> 700 | N12: =IFERROR(__xludf.DUMMYFUNCTION("""COMPUTED_VALUE"""),"S'Khar") -> S'Khar | O12: =IFERROR(__xludf.DUMMYFUNCTION("""COMPUTED_VALUE"""),"Jamais présent") -> Jamais présent
H13: =IFERROR(__xludf.DUMMYFUNCTION("""COMPUTED_VALUE"""),"Etat-Major") -> Etat-Major | I13: =IFERROR(__xludf.DUMMYFUNCTION("""COMPUTED_VALUE"""),2.0) -> 2 | K13: =IFERROR(__xludf.DUMMYFUNCTION("""COMPUTED_VALUE"""),"Etat-Major") -> Etat-Major | L13: =IFERROR(__xludf.DUMMYFUNCTION("""COMPUTED_VALUE"""),700.0) -> 700 | N13: =IFERROR(__xludf.DUMMYFUNCTION("""COMPUTED_VALUE"""),"Eldrim Hache-Grise") -> Eldrim Hache-Grise | O13: =IFERROR(__xludf.DUMMYFUNCTION("""COMPUTED_VALUE"""),"Jamais présent") -> Jamais présent
N14: =IFERROR(__xludf.DUMMYFUNCTION("""COMPUTED_VALUE"""),"Njalda") -> Njalda | O14: =IFERROR(__xludf.DUMMYFUNCTION("""COMPUTED_VALUE"""),"Jamais présent") -> Jamais présent
N15: =IFERROR(__xludf.DUMMYFUNCTION("""COMPUTED_VALUE"""),"Darina") -> Darina | O15: =IFERROR(__xludf.DUMMYFUNCTION("""COMPUTED_VALUE"""),"Jamais présent") -> Jamais présent
N16: =IFERROR(__xludf.DUMMYFUNCTION("""COMPUTED_VALUE"""),"Bernis") -> Bernis | O16: =IFERROR(__xludf.DUMMYFUNCTION("""COMPUTED_VALUE"""),"Jamais présent") -> Jamais présent
N17: =IFERROR(__xludf.DUMMYFUNCTION("""COMPUTED_VALUE"""),"Drakgor gro-Drakar") -> Drakgor gro-Drakar | O17: =IFERROR(__xludf.DUMMYFUNCTION("""COMPUTED_VALUE"""),"Jamais présent") -> Jamais présent
N18: =IFERROR(__xludf.DUMMYFUNCTION("""COMPUTED_VALUE"""),"Gorbash Tête-de-Pierre") -> Gorbash Tête-de-Pierre | O18: =IFERROR(__xludf.DUMMYFUNCTION("""COMPUTED_VALUE"""),"Jamais présent") -> Jamais présent
N19: =IFERROR(__xludf.DUMMYFUNCTION("""COMPUTED_VALUE"""),"Armand De Valclair") -> Armand De Valclair | O19: =IFERROR(__xludf.DUMMYFUNCTION("""COMPUTED_VALUE"""),"Jamais présent") -> Jamais présent
N20: =IFERROR(__xludf.DUMMYFUNCTION("""COMPUTED_VALUE"""),"Si'Yara dite Fou") -> Si'Yara dite Fou | O20: =IFERROR(__xludf.DUMMYFUNCTION("""COMPUTED_VALUE"""),"Jamais présent") -> Jamais présent
N21: =IFERROR(__xludf.DUMMYFUNCTION("""COMPUTED_VALUE"""),"Lokh Tar") -> Lokh Tar | O21: =IFERROR(__xludf.DUMMYFUNCTION("""COMPUTED_VALUE"""),"Jamais présent") -> Jamais présent
N22: =IFERROR(__xludf.DUMMYFUNCTION("""COMPUTED_VALUE"""),"Theodrek Heid") -> Theodrek Heid | O22: =IFERROR(__xludf.DUMMYFUNCTION("""COMPUTED_VALUE"""),"Jamais présent") -> Jamais présent
N23: =IFERROR(__xludf.DUMMYFUNCTION("""COMPUTED_VALUE"""),"Lucius Ravenshield") -> Lucius Ravenshield | O23: =IFERROR(__xludf.DUMMYFUNCTION("""COMPUTED_VALUE"""),"Jamais présent") -> Jamais présent
N24: =IFERROR(__xludf.DUMMYFUNCTION("""COMPUTED_VALUE"""),"Krakan Valyn") -> Krakan Valyn | O24: =IFERROR(__xludf.DUMMYFUNCTION("""COMPUTED_VALUE"""),"Jamais présent") -> Jamais présent
N25: =IFERROR(__xludf.DUMMYFUNCTION("""COMPUTED_VALUE"""),"Rusco") -> Rusco | O25: =IFERROR(__xludf.DUMMYFUNCTION("""COMPUTED_VALUE"""),"Jamais présent") -> Jamais présent
N26: =IFERROR(__xludf.DUMMYFUNCTION("""COMPUTED_VALUE"""),"Faynir") -> Faynir | O26: =IFERROR(__xludf.DUMMYFUNCTION("""COMPUTED_VALUE"""),"Jamais présent") -> Jamais présent
N27: =IFERROR(__xludf.DUMMYFUNCTION("""COMPUTED_VALUE"""),"Varaa Uzgar") -> Varaa Uzgar | O27: =IFERROR(__xludf.DUMMYFUNCTION("""COMPUTED_VALUE"""),"Jamais présent") -> Jamais présent
N28: =IFERROR(__xludf.DUMMYFUNCTION("""COMPUTED_VALUE"""),"Darius Blacktorn") -> Darius Blacktorn | O28: =IFERROR(__xludf.DUMMYFUNCTION("""COMPUTED_VALUE"""),"Jamais présent") -> Jamais présent
N47: Njalda

Sheet Effectifs
A1: Assermenté | B1: Grade | C1: Prénom | D1: Nom | E1: Corps | F1: Spécialité | G1: Status | H1: Métier | I1: Recrutement | J1: Jours travaillés | Z1: Grade Order
A2: TRUE | B2: Maréchal | C2: Lazabard | D2: Jemelred | E2: Etat-Major | F2: Garde, Collecteur de la garde | G2: En service actif | J2: =SUMIFS( 'Présences'!M:M, 'Présences'!D:D,C2, 'Présences'!E:E,D2 ) -> 4 | Z2: {=IF(B2:B988="",,MATCH(B2:B988,'Données'!A$2:A988,0))} -> 1
A3: TRUE | B3: Commander | C3: Filoki | E3: Etat-Major | F3: Garde, Collecteur de la garde | G3: En service actif | J3: =SUMIFS( 'Présences'!M:M, 'Présences'!D:D,C3, 'Présences'!E:E,D3 ) -> 0 | Z3: 2
A4: TRUE | B4: Major | C4: Dagbara | D4: Gronez | E4: Etat-Major | F4: Garde | G4: Mis en réserve | J4: =SUMIFS( 'Présences'!M:M, 'Présences'!D:D,C4, 'Présences'!E:E,D4 ) -> 0 | Z4: 3
A5: TRUE | B5: Capitaine | C5: Astrid | D5: Lame-Fine | E5: Cité de Blancherive | F5: Garde | G5: En service actif | H5: Chasseur | J5: =SUMIFS( 'Présences'!M:M, 'Présences'!D:D,C5, 'Présences'!E:E,D5 ) -> 10 | Z5: 4
A6: TRUE | B6: Capitaine | C6: Glaemorandir | D6: Oeil-Perçant | E6: Eclaireur | F6: Eclaireur, Garde | G6: En service actif | H6: Chasseur | I6: 46197 | J6: =SUMIFS( 'Présences'!M:M, 'Présences'!D:D,C6, 'Présences'!E:E,D6 ) -> 12 | Z6: 4
A7: TRUE | B7: Capitaine | C7: Edward | D7: Winters | E7: Cité de Blancherive | F7: Hird | G7: Mis en réserve | J7: =SUMIFS( 'Présences'!M:M, 'Présences'!D:D,C7, 'Présences'!E:E,D7 ) -> 0 | Z7: 4
A8: TRUE | B8: Capitaine | C8: Kah-Shir | D8: Sombre Griffe | E8: Faubourgs de Blancherive | F8: Garde, Collecteur de la garde | G8: En service actif | J8: =SUMIFS( 'Présences'!M:M, 'Présences'!D:D,C8, 'Présences'!E:E,D8 ) -> 4 | Z8: 4
A9: TRUE | B9: Capitaine | C9: Clemnir | D9: Arc-Vif | E9: Eclaireur | F9: Eclaireur | G9: Mort en service actif | H9: Chasseur | J9: =SUMIFS( 'Présences'!M:M, 'Présences'!D:D,C9, 'Présences'!E:E,D9 ) -> 0 | Z9: 4
A10: FALSE | B10: Capitaine | C10: Sigurd | D10: Grisetoison | E10: Rivebois | F10: Garde, Collecteur de la garde | G10: En service actif | J10: =SUMIFS( 'Présences'!M:M, 'Présences'!D:D,C10, 'Présences'!E:E,D10 ) -> 4 | Z10: 4
A11: FALSE | B11: Capitaine | C11: Hastelvin | E11: Cap Granite | F11: Garde, Collecteur de la garde | G11: En service actif | J11: =SUMIFS( 'Présences'!M:M, 'Présences'!D:D,C11, 'Présences'!E:E,D11 ) -> 0 | Z11: 4
A12: TRUE | B12: Lieutenant-Chef | C12: Ulfar | E12: Cité de Blancherive | F12: Garde, Instructeur | G12: En service actif | J12: =SUMIFS( 'Présences'!M:M, 'Présences'!D:D,C12, 'Présences'!E:E,D12 ) -> 0 | Z12: 5
A13: TRUE | B13: Lieutenant | C13: Ronin | E13: Cité de Blancherive | F13: Garde, Intendant de la garde, Collecteur de la garde | G13: En service actif | H13: Guerrier | I13: 46184 | J13: =SUMIFS( 'Présences'!M:M, 'Présences'!D:D,C13, 'Présences'!E:E,D13 ) -> 0 | Z13: 6
A14: TRUE | B14: Lieutenant | C14: Thorin | D14: Rivegel | E14: Cité de Blancherive | F14: Eclaireur, Garde | G14: En service actif | H14: Guerrier | J14: =SUMIFS( 'Présences'!M:M, 'Présences'!D:D,C14, 'Présences'!E:E,D14 ) -> 0 | Z14: 6
A15: TRUE | B15: Lieutenant-Chef | C15: Gisbern | D15: Isenbjorn | E15: Cité de Blancherive | F15: Garde | G15: En service actif | J15: =SUMIFS( 'Présences'!M:M, 'Présences'!D:D,C15, 'Présences'!E:E,D15 ) -> 5 | Z15: 5
A16: TRUE | B16: Sergent-Chef | C16: Rorik | D16: Marche-Hiver | E16: Cité de Blancherive | F16: Garde | G16: En service actif | J16: =SUMIFS( 'Présences'!M:M, 'Présences'!D:D,C16, 'Présences'!E:E,D16 ) -> 12 | Z16: 7
A17: TRUE | B17: Sergent-Chef | C17: Erwan | E17: Cité de Blancherive | F17: Garde | G17: En service actif | J17: =SUMIFS( 'Présences'!M:M, 'Présences'!D:D,C17, 'Présences'!E:E,D17 ) -> 0 | Z17: 7
A18: TRUE | B18: Lieutenant | C18: Daric | E18: Rivebois | F18: Garde | G18: En service actif | J18: =SUMIFS( 'Présences'!M:M, 'Présences'!D:D,C18, 'Présences'!E:E,D18 ) -> 0 | Z18: 6
A19: TRUE | B19: Caporal-Chef | C19: Ilflynn | E19: Cité de Blancherive | F19: Garde | G19: En service actif | J19: =SUMIFS( 'Présences'!M:M, 'Présences'!D:D,C19, 'Présences'!E:E,D19 ) -> 0 | Z19: 9
A20: TRUE | B20: Sergent-Chef | C20: Magnar | D20: Traquebrume | E20: Eclaireur | F20: Eclaireur, Garde | G20: En service actif | H20: Chasseur | I20: 46190 | J20: =SUMIFS( 'Présences'!M:M, 'Présences'!D:D,C20, 'Présences'!E:E,D20 ) -> 10 | Z20: 7
A21: TRUE | B21: Garde | C21: Pethiceor | D21: Le Borgne | E21: Eclaireur | F21: Eclaireur, Garde | G21: Mis en réserve | H21: Chasseur | I21: 46197 | J21: =SUMIFS( 'Présences'!M:M, 'Présences'!D:D,C21, 'Présences'!E:E,D21 ) -> 0 | Z21: 11
A22: TRUE | B22: Garde | C22: Laureen | D22: Toison-de-Sang | E22: Eclaireur | F22: Eclaireur, Garde | G22: En service actif | H22: Chasseur | I22: 46249 | J22: =SUMIFS( 'Présences'!M:M, 'Présences'!D:D,C22, 'Présences'!E:E,D22 ) -> 11 | Z22: 11
A23: FALSE | B23: Recrue | C23: Ma'arl | E23: Eclaireur | F23: Eclaireur, Garde | G23: En service actif | H23: Mineur | I23: 46259 | J23: =SUMIFS( 'Présences'!M:M, 'Présences'!D:D,C23, 'Présences'!E:E,D23 ) -> 0 | Z23: 13
A24: TRUE | B24: Garde | C24: Andor | D24: Viraes | E24: Cité de Blancherive | F24: Garde | G24: En service actif | J24: =SUMIFS( 'Présences'!M:M, 'Présences'!D:D,C24, 'Présences'!E:E,D24 ) -> 1 | Z24: 11
A25: FALSE | B25: Sergent-Chef | C25: Astrild | E25: Faubourgs de Blancherive | F25: Garde | G25: En service actif | J25: =SUMIFS( 'Présences'!M:M, 'Présences'!D:D,C25, 'Présences'!E:E,D25 ) -> 0 | Z25: 7
A26: TRUE | B26: Garde | C26: Athlan | E26: Cité de Blancherive | F26: Garde | G26: Démissionnaire | J26: =SUMIFS( 'Présences'!M:M, 'Présences'!D:D,C26, 'Présences'!E:E,D26 ) -> 0 | Z26: 11
A27: FALSE | B27: Lieutenant | C27: Encore-Un-Espoir | E27: Cité de Blancherive | F27: Garde, Tortionnaire, Instructeur | G27: En service actif | J27: =SUMIFS( 'Présences'!M:M, 'Présences'!D:D,C27, 'Présences'!E:E,D27 ) -> 0 | Z27: 6
A28: TRUE | B28: Garde | C28: Al'Dran | E28: Cité de Blancherive | F28: Garde | G28: En service actif | J28: =SUMIFS( 'Présences'!M:M, 'Présences'!D:D,C28, 'Présences'!E:E,D28 ) -> 0 | Z28: 11
A29: TRUE | B29: Garde | C29: Kendall | D29: Delamare | E29: Cité de Blancherive | F29: Garde | G29: En service actif | J29: =SUMIFS( 'Présences'!M:M, 'Présences'!D:D,C29, 'Présences'!E:E,D29 ) -> 7 | Z29: 11
A30: FALSE | B30: Garde | C30: Léonce | D30: Réve-épine | E30: Faubourgs de Blancherive | F30: Garde | G30: En service actif | J30: =SUMIFS( 'Présences'!M:M, 'Présences'!D:D,C30, 'Présences'!E:E,D30 ) -> 1 | Z30: 11
A31: FALSE | B31: Garde | C31: Kronk | D31: Grognon | E31: Hird du Jarl | F31: Hird | G31: En service actif | J31: =SUMIFS( 'Présences'!M:M, 'Présences'!D:D,C31, 'Présences'!E:E,D31 ) -> 0 | Z31: 11
A32: FALSE | B32: Garde | C32: Gronk | D32: Grognon | E32: Hird du Jarl | F32: Hird | G32: En service actif | J32: =SUMIFS( 'Présences'!M:M, 'Présences'!D:D,C32, 'Présences'!E:E,D32 ) -> 0 | Z32: 11
A33: FALSE | B33: Garde | C33: S'Khar | E33: Hird du Jarl | F33: Hird | G33: En service actif | J33: =SUMIFS( 'Présences'!M:M, 'Présences'!D:D,C33, 'Présences'!E:E,D33 ) -> 0 | Z33: 11
A34: FALSE | B34: Recrue | C34: Do'Rhazir | E34: Eclaireur | F34: Eclaireur, Garde | G34: En service actif | H34: Menuisier-Charbonnier | I34: 46261 | J34: =SUMIFS( 'Présences'!M:M, 'Présences'!D:D,C34, 'Présences'!E:E,D34 ) -> 0 | Z34: 13
A35: FALSE | B35: Cadet | C35: Eldrim | D35: Hache-Grise | E35: Cité de Blancherive | F35: Garde | G35: En service actif | J35: =SUMIFS( 'Présences'!M:M, 'Présences'!D:D,C35, 'Présences'!E:E,D35 ) -> 0 | Z35: 12
A36: FALSE | B36: Recrue | C36: Ro'minet | E36: Cité de Blancherive | F36: Garde | G36: Radié du service actif | J36: =SUMIFS( 'Présences'!M:M, 'Présences'!D:D,C36, 'Présences'!E:E,D36 ) -> 0 | Z36: 13
A37: FALSE | B37: Garde | C37: Bjorn | D37: Kornseen | E37: Cité de Blancherive | F37: Garde | G37: En service actif | J37: =SUMIFS( 'Présences'!M:M, 'Présences'!D:D,C37, 'Présences'!E:E,D37 ) -> 9 | Z37: 11
A38: FALSE | B38: Garde | C38: Wulfgar | D38: Durrock | E38: Cité de Blancherive | F38: Garde | G38: En service actif | J38: =SUMIFS( 'Présences'!M:M, 'Présences'!D:D,C38, 'Présences'!E:E,D38 ) -> 5 | Z38: 11
A39: FALSE | B39: Garde | C39: Lyosha | D39: Sullapierre | E39: Cité de Blancherive | F39: Garde | G39: Mis en réserve | J39: =SUMIFS( 'Présences'!M:M, 'Présences'!D:D,C39, 'Présences'!E:E,D39 ) -> 0 | Z39: 11
A40: FALSE | B40: Garde | C40: Brandon | D40: Alprazz | E40: Cité de Blancherive | F40: Garde | G40: Mis en réserve | J40: =SUMIFS( 'Présences'!M:M, 'Présences'!D:D,C40, 'Présences'!E:E,D40 ) -> 0 | Z40: 11
A41: FALSE | B41: Recrue | C41: Aldric | D41: Cendre-coeur | E41: Cité de Blancherive | F41: Garde | G41: En service actif | J41: =SUMIFS( 'Présences'!M:M, 'Présences'!D:D,C41, 'Présences'!E:E,D41 ) -> 2 | Z41: 13
A42: FALSE | B42: Lieutenant-Chef | C42: Il-draz | D42: De Chasse-au-bois | E42: Faubourgs de Blancherive | F42: Garde | G42: En service actif | J42: =SUMIFS( 'Présences'!M:M, 'Présences'!D:D,C42, 'Présences'!E:E,D42 ) -> 0 | Z42: 5
A43: FALSE | B43: Lieutenant | C43: Gorvin | D43: Le-Moite | E43: Faubourgs de Blancherive | F43: Garde | G43: En service actif | J43: =SUMIFS( 'Présences'!M:M, 'Présences'!D:D,C43, 'Présences'!E:E,D43 ) -> 3 | Z43: 6
A44: FALSE | B44: Garde | C44: Smaug | E44: Faubourgs de Blancherive | F44: Garde | G44: En service actif | J44: =SUMIFS( 'Présences'!M:M, 'Présences'!D:D,C44, 'Présences'!E:E,D44 ) -> 0 | Z44: 11
A45: FALSE | B45: Garde | C45: Njalda | E45: Faubourgs de Blancherive | F45: Garde | G45: En service actif | J45: =SUMIFS( 'Présences'!M:M, 'Présences'!D:D,C45, 'Présences'!E:E,D45 ) -> 0 | Z45: 11
A46: FALSE | B46: Garde | C46: Darina | E46: Faubourgs de Blancherive | F46: Garde | G46: En service actif | J46: =SUMIFS( 'Présences'!M:M, 'Présences'!D:D,C46, 'Présences'!E:E,D46 ) -> 0 | Z46: 11
A47: FALSE | B47: Sergent | C47: Jeebam-dee | E47: Faubourgs de Blancherive | F47: Garde | G47: En service actif | J47: =SUMIFS( 'Présences'!M:M, 'Présences'!D:D,C47, 'Présences'!E:E,D47 ) -> 0 | Z47: 8
A48: FALSE | B48: Garde | C48: Torald | D48: Brise-Roche | E48: Faubourgs de Blancherive | F48: Garde | G48: En service actif | J48: =SUMIFS( 'Présences'!M:M, 'Présences'!D:D,C48, 'Présences'!E:E,D48 ) -> 1 | Z48: 11
A49: FALSE | B49: Garde | C49: Bernis | E49: Faubourgs de Blancherive | F49: Garde | G49: En service actif | J49: =SUMIFS( 'Présences'!M:M, 'Présences'!D:D,C49, 'Présences'!E:E,D49 ) -> 0 | Z49: 11
A50: FALSE | B50: Cadet | C50: Ina'ra | E50: Faubourgs de Blancherive | F50: Garde | G50: En service actif | J50: =SUMIFS( 'Présences'!M:M, 'Présences'!D:D,C50, 'Présences'!E:E,D50 ) -> 0 | Z50: 12
A51: FALSE | B51: Sergent | C51: Ja'Shanir | E51: Faubourgs de Blancherive | F51: Garde | G51: Démissionnaire | J51: =SUMIFS( 'Présences'!M:M, 'Présences'!D:D,C51, 'Présences'!E:E,D51 ) -> 0 | Z51: 8
A52: FALSE | B52: Garde | C52: Malivor | D52: Xernes | E52: Cap Granite | F52: Garde | G52: En service actif | J52: =SUMIFS( 'Présences'!M:M, 'Présences'!D:D,C52, 'Présences'!E:E,D52 ) -> 4 | Z52: 11
A53: FALSE | B53: Garde | C53: Bakhir | E53: Cap Granite | F53: Garde | G53: En service actif | J53: =SUMIFS( 'Présences'!M:M, 'Présences'!D:D,C53, 'Présences'!E:E,D53 ) -> 0 | Z53: 11
A54: FALSE | B54: Sergent-Chef | C54: Starkos | D54: Coeurebene | E54: Cap Granite | F54: Garde | G54: En service actif | J54: =SUMIFS( 'Présences'!M:M, 'Présences'!D:D,C54, 'Présences'!E:E,D54 ) -> 4 | Z54: 7
A55: FALSE | B55: Garde | C55: Drakgor | D55: gro-Drakar | E55: Cap Granite | F55: Garde | G55: En service actif | J55: =SUMIFS( 'Présences'!M:M, 'Présences'!D:D,C55, 'Présences'!E:E,D55 ) -> 0 | Z55: 11
A56: FALSE | B56: Sergent-Chef | C56: Barnabas | D56: Tharmr | E56: Cap Granite | F56: Garde | G56: En service actif | J56: =SUMIFS( 'Présences'!M:M, 'Présences'!D:D,C56, 'Présences'!E:E,D56 ) -> 3 | Z56: 7
A57: FALSE | B57: Lieutenant-Chef | C57: Pavis | D57: Gurdalval | E57: Cap Granite | F57: Garde | G57: En service actif | J57: =SUMIFS( 'Présences'!M:M, 'Présences'!D:D,C57, 'Présences'!E:E,D57 ) -> 1 | Z57: 5
A58: FALSE | B58: Garde | C58: Gorbash | D58: Tête-de-Pierre | E58: Hird du Jarl | F58: Hird | G58: En service actif | J58: =SUMIFS( 'Présences'!M:M, 'Présences'!D:D,C58, 'Présences'!E:E,D58 ) -> 0 | Z58: 11
A59: FALSE | B59: Garde | C59: Armand | D59: De Valclair | E59: Hird du Jarl | F59: Hird | G59: En service actif | J59: =SUMIFS( 'Présences'!M:M, 'Présences'!D:D,C59, 'Présences'!E:E,D59 ) -> 0 | Z59: 11
A60: FALSE | B60: Garde | C60: Si'Yara | D60: dite Fou | E60: Hird du Jarl | F60: Hird | G60: En service actif | J60: =SUMIFS( 'Présences'!M:M, 'Présences'!D:D,C60, 'Présences'!E:E,D60 ) -> 0 | Z60: 11
A61: FALSE | B61: Garde | C61: Lokh | D61: Tar | E61: Hird du Jarl | F61: Hird | G61: En service actif | J61: =SUMIFS( 'Présences'!M:M, 'Présences'!D:D,C61, 'Présences'!E:E,D61 ) -> 0 | Z61: 11
A62: FALSE | B62: Capitaine | C62: Theodrek | D62: Heid | E62: Hird du Jarl | F62: Hird | G62: En service actif | J62: =SUMIFS( 'Présences'!M:M, 'Présences'!D:D,C62, 'Présences'!E:E,D62 ) -> 0 | Z62: 4
A63: FALSE | B63: Garde | C63: Selene | E63: Cité de Blancherive | F63: Garde | G63: Mis en réserve | J63: =SUMIFS( 'Présences'!M:M, 'Présences'!D:D,C63, 'Présences'!E:E,D63 ) -> 0 | Z63: 11
A64: FALSE | B64: Garde | C64: Lucius | D64: Ravenshield | E64: Hird du Jarl | F64: Hird | G64: En service actif | J64: =SUMIFS( 'Présences'!M:M, 'Présences'!D:D,C64, 'Présences'!E:E,D64 ) -> 0 | Z64: 11
A65: FALSE | B65: Major | C65: Krakan | D65: Valyn | E65: Rivebois | F65: Garde | G65: En service actif | J65: =SUMIFS( 'Présences'!M:M, 'Présences'!D:D,C65, 'Présences'!E:E,D65 ) -> 0 | Z65: 3
A66: FALSE | B66: Major | C66: Rusco | E66: Bois-de-Chêne | F66: Garde | G66: En service actif | J66: =SUMIFS( 'Présences'!M:M, 'Présences'!D:D,C66, 'Présences'!E:E,D66 ) -> 0 | Z66: 3
A67: FALSE | B67: Garde | C67: Faynir | E67: Hird du Jarl | F67: Hird | G67: En service actif | J67: =SUMIFS( 'Présences'!M:M, 'Présences'!D:D,C67, 'Présences'!E:E,D67 ) -> 0 | Z67: 11
A68: FALSE | B68: Garde | C68: Varaa | D68: Uzgar | E68: Hird du Jarl | F68: Hird | G68: En service actif | J68: =SUMIFS( 'Présences'!M:M, 'Présences'!D:D,C68, 'Présences'!E:E,D68 ) -> 0 | Z68: 11
A69: FALSE | B69: Recrue | C69: Aldrok | E69: Cité de Blancherive | F69: Garde | G69: Radié du service actif | I69: 46265 | J69: =SUMIFS( 'Présences'!M:M, 'Présences'!D:D,C69, 'Présences'!E:E,D69 ) -> 0 | Z69: 13
A70: FALSE | B70: Recrue | C70: Ri'Jhan | D70: MoonShadow | E70: Eclaireur | F70: Garde, Eclaireur | G70: En service actif | I70: 46266 | J70: =SUMIFS( 'Présences'!M:M, 'Présences'!D:D,C70, 'Présences'!E:E,D70 ) -> 3 | Z70: 13
A71: FALSE | B71: Recrue | C71: Zeid | D71: Le Brise-Lames | E71: Cité de Blancherive | F71: Garde | G71: En service actif | I71: 46266 | J71: =SUMIFS( 'Présences'!M:M, 'Présences'!D:D,C71, 'Présences'!E:E,D71 ) -> 2 | Z71: 13
A72: FALSE | B72: Recrue | C72: Gruseldorf | D72: E. Jackeet | E72: Cité de Blancherive | F72: Garde | G72: Radié du service actif | I72: 46264 | J72: =SUMIFS( 'Présences'!M:M, 'Présences'!D:D,C72, 'Présences'!E:E,D72 ) -> 0 | Z72: 13
A73: FALSE | B73: Recrue | C73: Mordecai | D73: E. Jackeet | E73: Cité de Blancherive | F73: Garde | G73: Radié du service actif | I73: 46264 | J73: =SUMIFS( 'Présences'!M:M, 'Présences'!D:D,C73, 'Présences'!E:E,D73 ) -> 0 | Z73: 13
A74: FALSE | B74: Lieutenant-Chef | C74: Hakon | D74: Grisetoison | E74: Rivebois | F74: Garde, Collecteur de la garde | G74: En service actif | J74: =SUMIFS( 'Présences'!M:M, 'Présences'!D:D,C74, 'Présences'!E:E,D74 ) -> 5 | Z74: 5
A75: FALSE | B75: Garde | C75: Lous | D75: Bois | E75: Rivebois | F75: Garde | G75: En service actif | Z75: 11
A76: FALSE | B76: Lieutenant | C76: Brand | D76: Grisetoison | E76: Rivebois | F76: Garde | G76: En service actif | Z76: 6
A77: FALSE | B77: Capitaine | C77: Darius | D77: Blacktorn | E77: Bois-de-Chêne | F77: Garde, Collecteur de la garde | G77: En service actif | Z77: 4
A78: FALSE | B78: Recrue | C78: Vranx | D78: Thorgar | E78: Cap Granite | F78: Garde | G78: En service actif | Z78: 13
A79: FALSE
A80: FALSE
A81: FALSE
A82: FALSE
A83: FALSE
A84: FALSE
A85: FALSE
A86: FALSE
A87: FALSE
A88: FALSE
A89: FALSE
A90: FALSE
... A988: FALSE

Sheet Présences
A1: Semaine | B1: Corps de garde | C1: Grade | D1: Prénom | E1: Nom | F1: Lun | G1: Mar | H1: Mer | I1: Jeu | J1: Ven | K1: Sam | L1: Dim | M1: Jours présents | N1: Solde | O1: Payé
A2: 35 | B2: Cap Granite | C2: Garde | D2: Bakhir | F2: FALSE | G2: FALSE | H2: FALSE | I2: FALSE | J2: FALSE | K2: FALSE | L2: FALSE | M2: =COUNTIF(F2:L2,TRUE) -> 0 | N2: =IF(OR(B2="Hird du Jarl",C2="Recrue"),0,IF(C2="Aspirant-Garde",M2*'Vue globale'!$L$2/2,M2*'Vue globale'!$L$2)) -> 0 | O2: FALSE
A3: 35 | B3: Cap Granite | C3: Garde | D3: Barnabas | E3: Tharmr | F3: FALSE | G3: FALSE | H3: FALSE | I3: FALSE | J3: FALSE | K3: FALSE | L3: FALSE | M3: =COUNTIF(F3:L3,TRUE) -> 0 | N3: =IF(OR(B3="Hird du Jarl",C3="Recrue"),0,IF(C3="Aspirant-Garde",M3*'Vue globale'!$L$2/2,M3*'Vue globale'!$L$2)) -> 0 | O3: FALSE
A4: 35 | B4: Cap Granite | C4: Garde | D4: Drakgor | E4: gro-Drakar | F4: FALSE | G4: FALSE | H4: FALSE | I4: FALSE | J4: FALSE | K4: FALSE | L4: FALSE | M4: =COUNTIF(F4:L4,TRUE) -> 0 | N4: =IF(OR(B4="Hird du Jarl",C4="Recrue"),0,IF(C4="Aspirant-Garde",M4*'Vue globale'!$L$2/2,M4*'Vue globale'!$L$2)) -> 0 | O4: FALSE | Q4: N'ajoutez jamais de ligne sur cette feuille. Si l'effectif a été modifié dans la page Effectifs, lancez le script "regenererSemaineCourante" pour ajouter les entrées manquantes ou changés tout en conservant les données précédentes.
A5: 35 | B5: Cap Granite | C5: Capitaine | D5: Hastelvin | F5: FALSE | G5: FALSE | H5: FALSE | I5: FALSE | J5: FALSE | K5: FALSE | L5: FALSE | M5: =COUNTIF(F5:L5,TRUE) -> 0 | N5: =IF(OR(B5="Hird du Jarl",C5="Recrue"),0,IF(C5="Aspirant-Garde",M5*'Vue globale'!$L$2/2,M5*'Vue globale'!$L$2)) -> 0 | O5: FALSE
A6: 35 | B6: Cap Granite | C6: Garde | D6: Malivor | E6: Xernes | F6: FALSE | G6: FALSE | H6: FALSE | I6: FALSE | J6: FALSE | K6: FALSE | L6: FALSE | M6: =COUNTIF(F6:L6,TRUE) -> 0 | N6: =IF(OR(B6="Hird du Jarl",C6="Recrue"),0,IF(C6="Aspirant-Garde",M6*'Vue globale'!$L$2/2,M6*'Vue globale'!$L$2)) -> 0 | O6: FALSE
A7: 35 | B7: Cap Granite | C7: Lieutenant-Chef | D7: Pavis | E7: Gurdalval | F7: FALSE | G7: FALSE | H7: FALSE | I7: FALSE | J7: FALSE | K7: FALSE | L7: FALSE | M7: =COUNTIF(F7:L7,TRUE) -> 0 | N7: =IF(OR(B7="Hird du Jarl",C7="Recrue"),0,IF(C7="Aspirant-Garde",M7*'Vue globale'!$L$2/2,M7*'Vue globale'!$L$2)) -> 0 | O7: FALSE
A8: 35 | B8: Cap Granite | C8: Garde | D8: Ragniir | E8: Coeurebene | F8: FALSE | G8: FALSE | H8: FALSE | I8: FALSE | J8: FALSE | K8: FALSE | L8: FALSE | M8: =COUNTIF(F8:L8,TRUE) -> 0 | N8: =IF(OR(B8="Hird du Jarl",C8="Recrue"),0,IF(C8="Aspirant-Garde",M8*'Vue globale'!$L$2/2,M8*'Vue globale'!$L$2)) -> 0 | O8: FALSE
A9: 35 | B9: Cap Granite | C9: Garde | D9: Starkos | E9: Coeurebene | F9: FALSE | G9: FALSE | H9: FALSE | I9: FALSE | J9: FALSE | K9: FALSE | L9: FALSE | M9: =COUNTIF(F9:L9,TRUE) -> 0 | N9: =IF(OR(B9="Hird du Jarl",C9="Recrue"),0,IF(C9="Aspirant-Garde",M9*'Vue globale'!$L$2/2,M9*'Vue globale'!$L$2)) -> 0 | O9: FALSE
A10: 35 | B10: Cité de Blancherive | C10: Garde | D10: Al'Dran | F10: TRUE | G10: TRUE | H10: TRUE | I10: TRUE | J10: TRUE | K10: TRUE | L10: TRUE | M10: =COUNTIF(F10:L10,TRUE) -> 7 | N10: =IF(OR(B10="Hird du Jarl",C10="Recrue"),0,IF(C10="Aspirant-Garde",M10*'Vue globale'!$L$2/2,M10*'Vue globale'!$L$2)) -> 350 | O10: FALSE
A11: 35 | B11: Cité de Blancherive | C11: Recrue | D11: Aldric | E11: Cendre-coeur | F11: FALSE | G11: FALSE | H11: FALSE | I11: FALSE | J11: FALSE | K11: TRUE | L11: FALSE | M11: =COUNTIF(F11:L11,TRUE) -> 1 | N11: =IF(OR(B11="Hird du Jarl",C11="Recrue"),0,IF(C11="Aspirant-Garde",M11*'Vue globale'!$L$2/2,M11*'Vue globale'!$L$2)) -> 0 | O11: FALSE
A12: 35 | B12: Cité de Blancherive | C12: Garde | D12: Andor | E12: Viraes | F12: FALSE | G12: TRUE | H12: FALSE | I12: FALSE | J12: FALSE | K12: FALSE | L12: FALSE | M12: =COUNTIF(F12:L12,TRUE) -> 1 | N12: =IF(OR(B12="Hird du Jarl",C12="Recrue"),0,IF(C12="Aspirant-Garde",M12*'Vue globale'!$L$2/2,M12*'Vue globale'!$L$2)) -> 50 | O12: FALSE
A13: 35 | B13: Cité de Blancherive | C13: Capitaine | D13: Astrid | E13: Lame-Fine | F13: TRUE | G13: TRUE | H13: TRUE | I13: FALSE | J13: TRUE | K13: TRUE | L13: TRUE | M13: =COUNTIF(F13:L13,TRUE) -> 6 | N13: =IF(OR(B13="Hird du Jarl",C13="Recrue"),0,IF(C13="Aspirant-Garde",M13*'Vue globale'!$L$2/2,M13*'Vue globale'!$L$2)) -> 300 | O13: TRUE
A14: 35 | B14: Cité de Blancherive | C14: Garde | D14: Athlan | F14: FALSE | G14: TRUE | H14: TRUE | I14: FALSE | J14: FALSE | K14: FALSE | L14: FALSE | M14: =COUNTIF(F14:L14,TRUE) -> 2 | N14: =IF(OR(B14="Hird du Jarl",C14="Recrue"),0,IF(C14="Aspirant-Garde",M14*'Vue globale'!$L$2/2,M14*'Vue globale'!$L$2)) -> 100 | O14: TRUE
A15: 35 | B15: Cité de Blancherive | C15: Garde | D15: Bjorn | E15: Kornseen | F15: TRUE | G15: TRUE | H15: FALSE | I15: TRUE | J15: FALSE | K15: TRUE | L15: TRUE | M15: =COUNTIF(F15:L15,TRUE) -> 5 | N15: =IF(OR(B15="Hird du Jarl",C15="Recrue"),0,IF(C15="Aspirant-Garde",M15*'Vue globale'!$L$2/2,M15*'Vue globale'!$L$2)) -> 250 | O15: TRUE
A16: 35 | B16: Cité de Blancherive | C16: Sergent | D16: Daric | F16: FALSE | G16: FALSE | H16: FALSE | I16: FALSE | J16: FALSE | K16: FALSE | L16: FALSE | M16: =COUNTIF(F16:L16,TRUE) -> 0 | N16: =IF(OR(B16="Hird du Jarl",C16="Recrue"),0,IF(C16="Aspirant-Garde",M16*'Vue globale'!$L$2/2,M16*'Vue globale'!$L$2)) -> 0 | O16: FALSE
A17: 35 | B17: Cité de Blancherive | C17: Aspirant-Garde | D17: Eldrim | E17: Hache-Grise | F17: FALSE | G17: FALSE | H17: FALSE | I17: FALSE | J17: FALSE | K17: FALSE | L17: FALSE | M17: =COUNTIF(F17:L17,TRUE) -> 0 | N17: =IF(OR(B17="Hird du Jarl",C17="Recrue"),0,IF(C17="Aspirant-Garde",M17*'Vue globale'!$L$2/2,M17*'Vue globale'!$L$2)) -> 0 | O17: FALSE
A18: 35 | B18: Cité de Blancherive | C18: Garde | D18: Encore-Un-Espoir | F18: FALSE | G18: FALSE | H18: FALSE | I18: FALSE | J18: FALSE | K18: FALSE | L18: FALSE | M18: =COUNTIF(F18:L18,TRUE) -> 0 | N18: =IF(OR(B18="Hird du Jarl",C18="Recrue"),0,IF(C18="Aspirant-Garde",M18*'Vue globale'!$L$2/2,M18*'Vue globale'!$L$2)) -> 0 | O18: FALSE
A19: 35 | B19: Cité de Blancherive | C19: Sergent | D19: Erwan | F19: TRUE | G19: TRUE | H19: FALSE | I19: TRUE | J19: FALSE | K19: TRUE | L19: TRUE | M19: =COUNTIF(F19:L19,TRUE) -> 5 | N19: =IF(OR(B19="Hird du Jarl",C19="Recrue"),0,IF(C19="Aspirant-Garde",M19*'Vue globale'!$L$2/2,M19*'Vue globale'!$L$2)) -> 250 | O19: TRUE
A20: 35 | B20: Cité de Blancherive | C20: Lieutenant | D20: Gisbern | E20: Isenbjorn | F20: TRUE | G20: TRUE | H20: FALSE | I20: FALSE | J20: TRUE | K20: FALSE | L20: FALSE | M20: =COUNTIF(F20:L20,TRUE) -> 3 | N20: =IF(OR(B20="Hird du Jarl",C20="Recrue"),0,IF(C20="Aspirant-Garde",M20*'Vue globale'!$L$2/2,M20*'Vue globale'!$L$2)) -> 150 | O20: FALSE
A21: 35 | B21: Cité de Blancherive | C21: Recrue | D21: Grub | F21: TRUE | G21: TRUE | H21: TRUE | I21: FALSE | J21: FALSE | K21: FALSE | L21: FALSE | M21: =COUNTIF(F21:L21,TRUE) -> 3 | N21: =IF(OR(B21="Hird du Jarl",C21="Recrue"),0,IF(C21="Aspirant-Garde",M21*'Vue globale'!$L$2/2,M21*'Vue globale'!$L$2)) -> 0 | O21: FALSE | Q21: Solde anticipée totale de la semaine courante | R21: =SUMIF('Présences'!A2:A702,ISOWEEKNUM(TODAY()),'Présences'!N2:N702) -> 5900
A22: 35 | B22: Cité de Blancherive | C22: Caporal-Chef | D22: Ilflynn | F22: TRUE | G22: TRUE | H22: TRUE | I22: TRUE | J22: TRUE | K22: TRUE | L22: TRUE | M22: =COUNTIF(F22:L22,TRUE) -> 7 | N22: =IF(OR(B22="Hird du Jarl",C22="Recrue"),0,IF(C22="Aspirant-Garde",M22*'Vue globale'!$L$2/2,M22*'Vue globale'!$L$2)) -> 350 | O22: TRUE | Q22: Solde totale à payer des semaines passés | R22: =SUMIFS( 'Présences'!N2:N702, 'Présences'!N2:N702,">0", 'Présences'!O2:O702,FALSE ) -> 6750
A23: 35 | B23: Cité de Blancherive | C23: Garde | D23: Kendall | E23: Delamare | F23: TRUE | G23: TRUE | H23: FALSE | I23: TRUE | J23: FALSE | K23: TRUE | L23: TRUE | M23: =COUNTIF(F23:L23,TRUE) -> 5 | N23: =IF(OR(B23="Hird du Jarl",C23="Recrue"),0,IF(C23="Aspirant-Garde",M23*'Vue globale'!$L$2/2,M23*'Vue globale'!$L$2)) -> 250 | O23: TRUE | Q23: Soldes impayés des semaines passés | R23: =COUNTIFS( 'Présences'!N2:N702,">0", 'Présences'!O2:O702,FALSE ) -> 40
A24: 35 | B24: Cité de Blancherive | C24: Recrue | D24: Léonce | E24: Réve-épine | F24: FALSE | G24: FALSE | H24: FALSE | I24: FALSE | J24: FALSE | K24: FALSE | L24: FALSE | M24: =COUNTIF(F24:L24,TRUE) -> 0 | N24: =IF(OR(B24="Hird du Jarl",C24="Recrue"),0,IF(C24="Aspirant-Garde",M24*'Vue globale'!$L$2/2,M24*'Vue globale'!$L$2)) -> 0 | O24: FALSE
A25: 35 | B25: Cité de Blancherive | C25: Recrue | D25: Ro'minet | F25: TRUE | G25: FALSE | H25: FALSE | I25: FALSE | J25: FALSE | K25: FALSE | L25: FALSE | M25: =COUNTIF(F25:L25,TRUE) -> 1 | N25: =IF(OR(B25="Hird du Jarl",C25="Recrue"),0,IF(C25="Aspirant-Garde",M25*'Vue globale'!$L$2/2,M25*'Vue globale'!$L$2)) -> 0 | O25: FALSE
A26: 35 | B26: Cité de Blancherive | C26: Lieutenant | D26: Ronin | F26: TRUE | G26: TRUE | H26: TRUE | I26: TRUE | J26: TRUE | K26: TRUE | L26: TRUE | M26: =COUNTIF(F26:L26,TRUE) -> 7 | N26: =IF(OR(B26="Hird du Jarl",C26="Recrue"),0,IF(C26="Aspirant-Garde",M26*'Vue globale'!$L$2/2,M26*'Vue globale'!$L$2)) -> 350 | O26: TRUE
A27: 35 | B27: Cité de Blancherive | C27: Sergent-Chef | D27: Rorik | E27: Marche-Hiver | F27: TRUE | G27: TRUE | H27: TRUE | I27: TRUE | J27: TRUE | K27: TRUE | L27: TRUE | M27: =COUNTIF(F27:L27,TRUE) -> 7 | N27: =IF(OR(B27="Hird du Jarl",C27="Recrue"),0,IF(C27="Aspirant-Garde",M27*'Vue globale'!$L$2/2,M27*'Vue globale'!$L$2)) -> 350 | O27: TRUE
A28: 35 | B28: Cité de Blancherive | C28: Lieutenant-Chef | D28: Ulfar | F28: TRUE | G28: FALSE | H28: TRUE | I28: FALSE | J28: TRUE | K28: FALSE | L28: TRUE | M28: =COUNTIF(F28:L28,TRUE) -> 4 | N28: =IF(OR(B28="Hird du Jarl",C28="Recrue"),0,IF(C28="Aspirant-Garde",M28*'Vue globale'!$L$2/2,M28*'Vue globale'!$L$2)) -> 200 | O28: FALSE
A29: 35 | B29: Cité de Blancherive | C29: Garde | D29: Wulfgar | E29: Durrock | F29: FALSE | G29: FALSE | H29: FALSE | I29: FALSE | J29: FALSE | K29: FALSE | L29: TRUE | M29: =COUNTIF(F29:L29,TRUE) -> 1 | N29: =IF(OR(B29="Hird du Jarl",C29="Recrue"),0,IF(C29="Aspirant-Garde",M29*'Vue globale'!$L$2/2,M29*'Vue globale'!$L$2)) -> 50 | O29: TRUE
A30: 35 | B30: Eclaireur | C30: Recrue | D30: Do'Rhazir | F30: FALSE | G30: FALSE | H30: FALSE | I30: FALSE | J30: TRUE | K30: TRUE | L30: TRUE | M30: =COUNTIF(F30:L30,TRUE) -> 3 | N30: =IF(OR(B30="Hird du Jarl",C30="Recrue"),0,IF(C30="Aspirant-Garde",M30*'Vue globale'!$L$2/2,M30*'Vue globale'!$L$2)) -> 0 | O30: TRUE
A31: 35 | B31: Eclaireur | C31: Capitaine | D31: Glaemorandir | E31: Oeil-Perçant | F31: TRUE | G31: TRUE | H31: TRUE | I31: TRUE | J31: TRUE | K31: TRUE | L31: TRUE | M31: =COUNTIF(F31:L31,TRUE) -> 7 | N31: =IF(OR(B31="Hird du Jarl",C31="Recrue"),0,IF(C31="Aspirant-Garde",M31*'Vue globale'!$L$2/2,M31*'Vue globale'!$L$2)) -> 350 | O31: TRUE
A32: 35 | B32: Eclaireur | C32: Garde | D32: Laureen | E32: Toison-de-Sang | F32: TRUE | G32: TRUE | H32: TRUE | I32: TRUE | J32: TRUE | K32: TRUE | L32: TRUE | M32: =COUNTIF(F32:L32,TRUE) -> 7 | N32: =IF(OR(B32="Hird du Jarl",C32="Recrue"),0,IF(C32="Aspirant-Garde",M32*'Vue globale'!$L$2/2,M32*'Vue globale'!$L$2)) -> 350 | O32: TRUE
A33: 35 | B33: Eclaireur | C33: Recrue | D33: Ma'arl | F33: FALSE | G33: TRUE | H33: TRUE | I33: FALSE | J33: TRUE | K33: TRUE | L33: TRUE | M33: =COUNTIF(F33:L33,TRUE) -> 5 | N33: =IF(OR(B33="Hird du Jarl",C33="Recrue"),0,IF(C33="Aspirant-Garde",M33*'Vue globale'!$L$2/2,M33*'Vue globale'!$L$2)) -> 0 | O33: TRUE
A34: 35 | B34: Eclaireur | C34: Garde | D34: Magnar | E34: Traquebrume | F34: TRUE | G34: TRUE | H34: TRUE | I34: TRUE | J34: TRUE | K34: FALSE | L34: TRUE | M34: =COUNTIF(F34:L34,TRUE) -> 6 | N34: =IF(OR(B34="Hird du Jarl",C34="Recrue"),0,IF(C34="Aspirant-Garde",M34*'Vue globale'!$L$2/2,M34*'Vue globale'!$L$2)) -> 300 | O34: TRUE
A35: 35 | B35: Eclaireur | C35: Lieutenant | D35: Thorin | E35: Rivegel | F35: FALSE | G35: FALSE | H35: FALSE | I35: FALSE | J35: FALSE | K35: FALSE | L35: FALSE | M35: =COUNTIF(F35:L35,TRUE) -> 0 | N35: =IF(OR(B35="Hird du Jarl",C35="Recrue"),0,IF(C35="Aspirant-Garde",M35*'Vue globale'!$L$2/2,M35*'Vue globale'!$L$2)) -> 0 | O35: FALSE
A36: 35 | B36: Etat-Major | C36: Commandant | D36: Filoki | F36: TRUE | G36: TRUE | H36: TRUE | I36: TRUE | J36: TRUE | K36: TRUE | L36: TRUE | M36: =COUNTIF(F36:L36,TRUE) -> 7 | N36: =IF(OR(B36="Hird du Jarl",C36="Recrue"),0,IF(C36="Aspirant-Garde",M36*'Vue globale'!$L$2/2,M36*'Vue globale'!$L$2)) -> 350 | O36: TRUE
A37: 35 | B37: Etat-Major | C37: Maréchal | D37: Lazabard | E37: Jemelred | F37: FALSE | G37: TRUE | H37: FALSE | I37: FALSE | J37: TRUE | K37: FALSE | L37: FALSE | M37: =COUNTIF(F37:L37,TRUE) -> 2 | N37: =IF(OR(B37="Hird du Jarl",C37="Recrue"),0,IF(C37="Aspirant-Garde",M37*'Vue globale'!$L$2/2,M37*'Vue globale'!$L$2)) -> 100 | O37: FALSE
A38: 35 | B38: Faubourgs de Blancherive | C38: Sergent-Chef | D38: Astrild | F38: FALSE | G38: FALSE | H38: FALSE | I38: FALSE | J38: FALSE | K38: FALSE | L38: FALSE | M38: =COUNTIF(F38:L38,TRUE) -> 0 | N38: =IF(OR(B38="Hird du Jarl",C38="Recrue"),0,IF(C38="Aspirant-Garde",M38*'Vue globale'!$L$2/2,M38*'Vue globale'!$L$2)) -> 0 | O38: FALSE
A39: 35 | B39: Faubourgs de Blancherive | C39: Garde | D39: Bernis | F39: FALSE | G39: FALSE | H39: FALSE | I39: FALSE | J39: FALSE | K39: FALSE | L39: FALSE | M39: =COUNTIF(F39:L39,TRUE) -> 0 | N39: =IF(OR(B39="Hird du Jarl",C39="Recrue"),0,IF(C39="Aspirant-Garde",M39*'Vue globale'!$L$2/2,M39*'Vue globale'!$L$2)) -> 0 | O39: FALSE
A40: 35 | B40: Faubourgs de Blancherive | C40: Garde | D40: Darina | F40: FALSE | G40: FALSE | H40: FALSE | I40: FALSE | J40: FALSE | K40: FALSE | L40: FALSE | M40: =COUNTIF(F40:L40,TRUE) -> 0 | N40: =IF(OR(B40="Hird du Jarl",C40="Recrue"),0,IF(C40="Aspirant-Garde",M40*'Vue globale'!$L$2/2,M40*'Vue globale'!$L$2)) -> 0 | O40: FALSE
A41: 35 | B41: Faubourgs de Blancherive | C41: Lieutenant | D41: Gorvin | E41: Le-Moite | F41: FALSE | G41: FALSE | H41: FALSE | I41: FALSE | J41: FALSE | K41: FALSE | L41: FALSE | M41: =COUNTIF(F41:L41,TRUE) -> 0 | N41: =IF(OR(B41="Hird du Jarl",C41="Recrue"),0,IF(C41="Aspirant-Garde",M41*'Vue globale'!$L$2/2,M41*'Vue globale'!$L$2)) -> 0 | O41: FALSE
A42: 35 | B42: Faubourgs de Blancherive | C42: Lieutenant-Chef | D42: Il-draz | E42: De Chasse-au-bois | F42: FALSE | G42: FALSE | H42: FALSE | I42: FALSE | J42: FALSE | K42: FALSE | L42: FALSE | M42: =COUNTIF(F42:L42,TRUE) -> 0 | N42: =IF(OR(B42="Hird du Jarl",C42="Recrue"),0,IF(C42="Aspirant-Garde",M42*'Vue globale'!$L$2/2,M42*'Vue globale'!$L$2)) -> 0 | O42: FALSE
A43: 35 | B43: Faubourgs de Blancherive | C43: Recrue | D43: Ina'ra | F43: FALSE | G43: FALSE | H43: FALSE | I43: FALSE | J43: FALSE | K43: FALSE | L43: FALSE | M43: =COUNTIF(F43:L43,TRUE) -> 0 | N43: =IF(OR(B43="Hird du Jarl",C43="Recrue"),0,IF(C43="Aspirant-Garde",M43*'Vue globale'!$L$2/2,M43*'Vue globale'!$L$2)) -> 0 | O43: FALSE
A44: 35 | B44: Faubourgs de Blancherive | C44: Sergent | D44: Ja'Shanir | F44: FALSE | G44: FALSE | H44: FALSE | I44: FALSE | J44: FALSE | K44: FALSE | L44: FALSE | M44: =COUNTIF(F44:L44,TRUE) -> 0 | N44: =IF(OR(B44="Hird du Jarl",C44="Recrue"),0,IF(C44="Aspirant-Garde",M44*'Vue globale'!$L$2/2,M44*'Vue globale'!$L$2)) -> 0 | O44: FALSE
A45: 35 | B45: Faubourgs de Blancherive | C45: Sergent | D45: Jeebam-dee | F45: FALSE | G45: FALSE | H45: FALSE | I45: FALSE | J45: FALSE | K45: FALSE | L45: FALSE | M45: =COUNTIF(F45:L45,TRUE) -> 0 | N45: =IF(OR(B45="Hird du Jarl",C45="Recrue"),0,IF(C45="Aspirant-Garde",M45*'Vue globale'!$L$2/2,M45*'Vue globale'!$L$2)) -> 0 | O45: FALSE
A46: 35 | B46: Faubourgs de Blancherive | C46: Capitaine | D46: Kah-Shir | E46: Sombre Griffe | F46: FALSE | G46: FALSE | H46: FALSE | I46: FALSE | J46: FALSE | K46: FALSE | L46: FALSE | M46: =COUNTIF(F46:L46,TRUE) -> 0 | N46: =IF(OR(B46="Hird du Jarl",C46="Recrue"),0,IF(C46="Aspirant-Garde",M46*'Vue globale'!$L$2/2,M46*'Vue globale'!$L$2)) -> 0 | O46: FALSE
A47: 35 | B47: Faubourgs de Blancherive | C47: Garde | D47: Léonce | F47: FALSE | G47: FALSE | H47: FALSE | I47: FALSE | J47: FALSE | K47: FALSE | L47: FALSE | M47: =COUNTIF(F47:L47,TRUE) -> 0 | N47: =IF(OR(B47="Hird du Jarl",C47="Recrue"),0,IF(C47="Aspirant-Garde",M47*'Vue globale'!$L$2/2,M47*'Vue globale'!$L$2)) -> 0 | O47: FALSE
A48: 35 | B48: Faubourgs de Blancherive | C48: Garde | D48: Njalda | F48: FALSE | G48: FALSE | H48: FALSE | I48: FALSE | J48: FALSE | K48: FALSE | L48: FALSE | M48: =COUNTIF(F48:L48,TRUE) -> 0 | N48: =IF(OR(B48="Hird du Jarl",C48="Recrue"),0,IF(C48="Aspirant-Garde",M48*'Vue globale'!$L$2/2,M48*'Vue globale'!$L$2)) -> 0 | O48: FALSE
A49: 35 | B49: Faubourgs de Blancherive | C49: Garde | D49: Smaug | F49: FALSE | G49: FALSE | H49: FALSE | I49: FALSE | J49: FALSE | K49: FALSE | L49: FALSE | M49: =COUNTIF(F49:L49,TRUE) -> 0 | N49: =IF(OR(B49="Hird du Jarl",C49="Recrue"),0,IF(C49="Aspirant-Garde",M49*'Vue globale'!$L$2/2,M49*'Vue globale'!$L$2)) -> 0 | O49: FALSE
A50: 35 | B50: Faubourgs de Blancherive | C50: Garde | D50: Torald | F50: FALSE | G50: FALSE | H50: FALSE | I50: FALSE | J50: FALSE | K50: FALSE | L50: FALSE | M50: =COUNTIF(F50:L50,TRUE) -> 0 | N50: =IF(OR(B50="Hird du Jarl",C50="Recrue"),0,IF(C50="Aspirant-Garde",M50*'Vue globale'!$L$2/2,M50*'Vue globale'!$L$2)) -> 0 | O50: FALSE
A51: 35 | B51: Hird du Jarl | C51: Garde | D51: Gronk | E51: Grognon | F51: FALSE | G51: FALSE | H51: FALSE | I51: FALSE | J51: FALSE | K51: FALSE | L51: FALSE | M51: =COUNTIF(F51:L51,TRUE) -> 0 | N51: =IF(OR(B51="Hird du Jarl",C51="Recrue"),0,IF(C51="Aspirant-Garde",M51*'Vue globale'!$L$2/2,M51*'Vue globale'!$L$2)) -> 0 | O51: FALSE
A52: 35 | B52: Hird du Jarl | C52: Garde | D52: Kronk | E52: Grognon | F52: FALSE | G52: FALSE | H52: FALSE | I52: FALSE | J52: FALSE | K52: FALSE | L52: FALSE | M52: =COUNTIF(F52:L52,TRUE) -> 0 | N52: =IF(OR(B52="Hird du Jarl",C52="Recrue"),0,IF(C52="Aspirant-Garde",M52*'Vue globale'!$L$2/2,M52*'Vue globale'!$L$2)) -> 0 | O52: FALSE
A53: 35 | B53: Hird du Jarl | C53: Garde | D53: S'Khar | F53: FALSE | G53: FALSE | H53: FALSE | I53: FALSE | J53: FALSE | K53: FALSE | L53: FALSE | M53: =COUNTIF(F53:L53,TRUE) -> 0 | N53: =IF(OR(B53="Hird du Jarl",C53="Recrue"),0,IF(C53="Aspirant-Garde",M53*'Vue globale'!$L$2/2,M53*'Vue globale'!$L$2)) -> 0 | O53: FALSE
A54: 35 | B54: Rivebois | C54: Capitaine | D54: Sigurd | E54: Grise-Toison | F54: FALSE | G54: FALSE | H54: FALSE | I54: FALSE | J54: FALSE | K54: FALSE | L54: FALSE | M54: =COUNTIF(F54:L54,TRUE) -> 0 | N54: =IF(OR(B54="Hird du Jarl",C54="Recrue"),0,IF(C54="Aspirant-Garde",M54*'Vue globale'!$L$2/2,M54*'Vue globale'!$L$2)) -> 0 | O54: FALSE
A55: 36 | B55: Bois-de-Chêne | C55: Capitaine | D55: Darius | E55: Blacktorn | F55: FALSE | G55: FALSE | H55: FALSE | I55: FALSE | J55: FALSE | K55: FALSE | L55: FALSE | M55: =COUNTIF(F55:L55,TRUE) -> 0 | N55: =IF(OR(B55="Hird du Jarl",C55="Recrue"),0,IF(C55="Aspirant-Garde",M55*'Vue globale'!$L$2/2,M55*'Vue globale'!$L$2)) -> 0 | O55: FALSE
A56: 36 | B56: Bois-de-Chêne | C56: Major | D56: Rusco | F56: FALSE | G56: FALSE | H56: FALSE | I56: FALSE | J56: FALSE | K56: FALSE | L56: FALSE | M56: =COUNTIF(F56:L56,TRUE) -> 0 | N56: =IF(OR(B56="Hird du Jarl",C56="Recrue"),0,IF(C56="Aspirant-Garde",M56*'Vue globale'!$L$2/2,M56*'Vue globale'!$L$2)) -> 0 | O56: FALSE
A57: 36 | B57: Cap Granite | C57: Garde | D57: Bakhir | F57: TRUE | G57: TRUE | H57: TRUE | I57: FALSE | J57: TRUE | K57: FALSE | L57: FALSE | M57: =COUNTIF(F57:L57,TRUE) -> 4 | N57: =IF(OR(B57="Hird du Jarl",C57="Recrue"),0,IF(C57="Aspirant-Garde",M57*'Vue globale'!$L$2/2,M57*'Vue globale'!$L$2)) -> 200 | O57: FALSE
A58: 36 | B58: Cap Granite | C58: Sergent-Chef | D58: Barnabas | E58: Tharmr | F58: TRUE | G58: TRUE | H58: FALSE | I58: TRUE | J58: FALSE | K58: FALSE | L58: FALSE | M58: =COUNTIF(F58:L58,TRUE) -> 3 | N58: =IF(OR(B58="Hird du Jarl",C58="Recrue"),0,IF(C58="Aspirant-Garde",M58*'Vue globale'!$L$2/2,M58*'Vue globale'!$L$2)) -> 150 | O58: FALSE
A59: 36 | B59: Cap Granite | C59: Garde | D59: Drakgor | E59: gro-Drakar | F59: FALSE | G59: FALSE | H59: FALSE | I59: FALSE | J59: FALSE | K59: FALSE | L59: FALSE | M59: =COUNTIF(F59:L59,TRUE) -> 0 | N59: =IF(OR(B59="Hird du Jarl",C59="Recrue"),0,IF(C59="Aspirant-Garde",M59*'Vue globale'!$L$2/2,M59*'Vue globale'!$L$2)) -> 0 | O59: FALSE
A60: 36 | B60: Cap Granite | C60: Capitaine | D60: Hastelvin | F60: FALSE | G60: FALSE | H60: FALSE | I60: FALSE | J60: FALSE | K60: FALSE | L60: FALSE | M60: =COUNTIF(F60:L60,TRUE) -> 0 | N60: =IF(OR(B60="Hird du Jarl",C60="Recrue"),0,IF(C60="Aspirant-Garde",M60*'Vue globale'!$L$2/2,M60*'Vue globale'!$L$2)) -> 0 | O60: FALSE
A61: 36 | B61: Cap Granite | C61: Garde | D61: Malivor | E61: Xernes | F61: TRUE | G61: TRUE | H61: TRUE | I61: TRUE | J61: FALSE | K61: FALSE | L61: FALSE | M61: =COUNTIF(F61:L61,TRUE) -> 4 | N61: =IF(OR(B61="Hird du Jarl",C61="Recrue"),0,IF(C61="Aspirant-Garde",M61*'Vue globale'!$L$2/2,M61*'Vue globale'!$L$2)) -> 200 | O61: FALSE
A62: 36 | B62: Cap Granite | C62: Lieutenant-Chef | D62: Pavis | E62: Gurdalval | F62: FALSE | G62: FALSE | H62: FALSE | I62: TRUE | J62: FALSE | K62: FALSE | L62: FALSE | M62: =COUNTIF(F62:L62,TRUE) -> 1 | N62: =IF(OR(B62="Hird du Jarl",C62="Recrue"),0,IF(C62="Aspirant-Garde",M62*'Vue globale'!$L$2/2,M62*'Vue globale'!$L$2)) -> 50 | O62: FALSE
A63: 36 | B63: Cap Granite | C63: Sergent-Chef | D63: Starkos | E63: Coeurebene | F63: TRUE | G63: TRUE | H63: TRUE | I63: TRUE | J63: FALSE | K63: FALSE | L63: FALSE | M63: =COUNTIF(F63:L63,TRUE) -> 4 | N63: =IF(OR(B63="Hird du Jarl",C63="Recrue"),0,IF(C63="Aspirant-Garde",M63*'Vue globale'!$L$2/2,M63*'Vue globale'!$L$2)) -> 200 | O63: FALSE
A64: 36 | B64: Cap Granite | C64: Recrue | D64: Vranx | E64: Thorgar | F64: FALSE | G64: FALSE | H64: FALSE | I64: TRUE | J64: FALSE | K64: FALSE | L64: FALSE | M64: =COUNTIF(F64:L64,TRUE) -> 1 | N64: =IF(OR(B64="Hird du Jarl",C64="Recrue"),0,IF(C64="Aspirant-Garde",M64*'Vue globale'!$L$2/2,M64*'Vue globale'!$L$2)) -> 0 | O64: FALSE
A65: 36 | B65: Cité de Blancherive | C65: Garde | D65: Al'Dran | F65: FALSE | G65: FALSE | H65: FALSE | I65: FALSE | J65: FALSE | K65: FALSE | L65: FALSE | M65: =COUNTIF(F65:L65,TRUE) -> 0 | N65: =IF(OR(B65="Hird du Jarl",C65="Recrue"),0,IF(C65="Aspirant-Garde",M65*'Vue globale'!$L$2/2,M65*'Vue globale'!$L$2)) -> 0 | O65: FALSE
A66: 36 | B66: Cité de Blancherive | C66: Recrue | D66: Aldric | E66: Cendre-coeur | F66: FALSE | G66: TRUE | H66: FALSE | I66: FALSE | J66: FALSE | K66: FALSE | L66: FALSE | M66: =COUNTIF(F66:L66,TRUE) -> 1 | N66: =IF(OR(B66="Hird du Jarl",C66="Recrue"),0,IF(C66="Aspirant-Garde",M66*'Vue globale'!$L$2/2,M66*'Vue globale'!$L$2)) -> 0 | O66: FALSE
A67: 36 | B67: Cité de Blancherive | C67: Garde | D67: Andor | E67: Viraes | F67: FALSE | G67: FALSE | H67: FALSE | I67: FALSE | J67: FALSE | K67: FALSE | L67: FALSE | M67: =COUNTIF(F67:L67,TRUE) -> 0 | N67: =IF(OR(B67="Hird du Jarl",C67="Recrue"),0,IF(C67="Aspirant-Garde",M67*'Vue globale'!$L$2/2,M67*'Vue globale'!$L$2)) -> 0 | O67: FALSE
A68: 36 | B68: Cité de Blancherive | C68: Capitaine | D68: Astrid | E68: Lame-Fine | F68: TRUE | G68: TRUE | H68: TRUE | I68: TRUE | J68: FALSE | K68: FALSE | L68: FALSE | M68: =COUNTIF(F68:L68,TRUE) -> 4 | N68: =IF(OR(B68="Hird du Jarl",C68="Recrue"),0,IF(C68="Aspirant-Garde",M68*'Vue globale'!$L$2/2,M68*'Vue globale'!$L$2)) -> 200 | O68: FALSE
A69: 36 | B69: Cité de Blancherive | C69: Garde | D69: Bjorn | E69: Kornseen | F69: TRUE | G69: TRUE | H69: TRUE | I69: TRUE | J69: FALSE | K69: FALSE | L69: FALSE | M69: =COUNTIF(F69:L69,TRUE) -> 4 | N69: =IF(OR(B69="Hird du Jarl",C69="Recrue"),0,IF(C69="Aspirant-Garde",M69*'Vue globale'!$L$2/2,M69*'Vue globale'!$L$2)) -> 200 | O69: FALSE
A70: 36 | B70: Cité de Blancherive | C70: Cadet | D70: Eldrim | E70: Hache-Grise | F70: FALSE | G70: FALSE | H70: FALSE | I70: FALSE | J70: FALSE | K70: FALSE | L70: FALSE | M70: =COUNTIF(F70:L70,TRUE) -> 0 | N70: =IF(OR(B70="Hird du Jarl",C70="Recrue"),0,IF(C70="Aspirant-Garde",M70*'Vue globale'!$L$2/2,M70*'Vue globale'!$L$2)) -> 0 | O70: FALSE
A71: 36 | B71: Cité de Blancherive | C71: Lieutenant | D71: Encore-Un-Espoir | F71: TRUE | G71: TRUE | H71: TRUE | I71: FALSE | J71: FALSE | K71: FALSE | L71: FALSE | M71: =COUNTIF(F71:L71,TRUE) -> 3 | N71: =IF(OR(B71="Hird du Jarl",C71="Recrue"),0,IF(C71="Aspirant-Garde",M71*'Vue globale'!$L$2/2,M71*'Vue globale'!$L$2)) -> 150 | O71: FALSE
A72: 36 | B72: Cité de Blancherive | C72: Sergent-Chef | D72: Erwan | F72: TRUE | G72: FALSE | H72: TRUE | I72: FALSE | J72: FALSE | K72: FALSE | L72: FALSE | M72: =COUNTIF(F72:L72,TRUE) -> 2 | N72: =IF(OR(B72="Hird du Jarl",C72="Recrue"),0,IF(C72="Aspirant-Garde",M72*'Vue globale'!$L$2/2,M72*'Vue globale'!$L$2)) -> 100 | O72: FALSE
A73: 36 | B73: Cité de Blancherive | C73: Lieutenant-Chef | D73: Gisbern | E73: Isenbjorn | F73: FALSE | G73: TRUE | H73: FALSE | I73: TRUE | J73: FALSE | K73: FALSE | L73: FALSE | M73: =COUNTIF(F73:L73,TRUE) -> 2 | N73: =IF(OR(B73="Hird du Jarl",C73="Recrue"),0,IF(C73="Aspirant-Garde",M73*'Vue globale'!$L$2/2,M73*'Vue globale'!$L$2)) -> 100 | O73: FALSE
A74: 36 | B74: Cité de Blancherive | C74: Caporal-Chef | D74: Ilflynn | F74: TRUE | G74: TRUE | H74: TRUE | I74: TRUE | J74: FALSE | K74: FALSE | L74: FALSE | M74: =COUNTIF(F74:L74,TRUE) -> 4 | N74: =IF(OR(B74="Hird du Jarl",C74="Recrue"),0,IF(C74="Aspirant-Garde",M74*'Vue globale'!$L$2/2,M74*'Vue globale'!$L$2)) -> 200 | O74: FALSE
A75: 36 | B75: Cité de Blancherive | C75: Garde | D75: Kendall | E75: Delamare | F75: FALSE | G75: TRUE | H75: TRUE | I75: FALSE | J75: FALSE | K75: FALSE | L75: FALSE | M75: =COUNTIF(F75:L75,TRUE) -> 2 | N75: =IF(OR(B75="Hird du Jarl",C75="Recrue"),0,IF(C75="Aspirant-Garde",M75*'Vue globale'!$L$2/2,M75*'Vue globale'!$L$2)) -> 100 | O75: FALSE
A76: 36 | B76: Cité de Blancherive | C76: Lieutenant | D76: Ronin | F76: TRUE | G76: TRUE | H76: TRUE | I76: TRUE | J76: TRUE | K76: FALSE | L76: FALSE | M76: =COUNTIF(F76:L76,TRUE) -> 5 | N76: =IF(OR(B76="Hird du Jarl",C76="Recrue"),0,IF(C76="Aspirant-Garde",M76*'Vue globale'!$L$2/2,M76*'Vue globale'!$L$2)) -> 250 | O76: FALSE
A77: 36 | B77: Cité de Blancherive | C77: Sergent-Chef | D77: Rorik | E77: Marche-Hiver | F77: TRUE | G77: TRUE | H77: TRUE | I77: TRUE | J77: TRUE | K77: FALSE | L77: FALSE | M77: =COUNTIF(F77:L77,TRUE) -> 5 | N77: =IF(OR(B77="Hird du Jarl",C77="Recrue"),0,IF(C77="Aspirant-Garde",M77*'Vue globale'!$L$2/2,M77*'Vue globale'!$L$2)) -> 250 | O77: FALSE
A78: 36 | B78: Cité de Blancherive | C78: Lieutenant | D78: Thorin | E78: Rivegel | F78: FALSE | G78: FALSE | H78: FALSE | I78: FALSE | J78: FALSE | K78: FALSE | L78: FALSE | M78: =COUNTIF(F78:L78,TRUE) -> 0 | N78: =IF(OR(B78="Hird du Jarl",C78="Recrue"),0,IF(C78="Aspirant-Garde",M78*'Vue globale'!$L$2/2,M78*'Vue globale'!$L$2)) -> 0 | O78: FALSE
A79: 36 | B79: Cité de Blancherive | C79: Lieutenant-Chef | D79: Ulfar | F79: FALSE | G79: FALSE | H79: FALSE | I79: TRUE | J79: FALSE | K79: FALSE | L79: FALSE | M79: =COUNTIF(F79:L79,TRUE) -> 1 | N79: =IF(OR(B79="Hird du Jarl",C79="Recrue"),0,IF(C79="Aspirant-Garde",M79*'Vue globale'!$L$2/2,M79*'Vue globale'!$L$2)) -> 50 | O79: FALSE
A80: 36 | B80: Cité de Blancherive | C80: Garde | D80: Wulfgar | E80: Durrock | F80: TRUE | G80: TRUE | H80: TRUE | I80: TRUE | J80: FALSE | K80: FALSE | L80: FALSE | M80: =COUNTIF(F80:L80,TRUE) -> 4 | N80: =IF(OR(B80="Hird du Jarl",C80="Recrue"),0,IF(C80="Aspirant-Garde",M80*'Vue globale'!$L$2/2,M80*'Vue globale'!$L$2)) -> 200 | O80: FALSE
A81: 36 | B81: Cité de Blancherive | C81: Recrue | D81: Zeid | E81: Le Brise-Lames | F81: FALSE | G81: TRUE | H81: TRUE | I81: FALSE | J81: FALSE | K81: FALSE | L81: FALSE | M81: =COUNTIF(F81:L81,TRUE) -> 2 | N81: =IF(OR(B81="Hird du Jarl",C81="Recrue"),0,IF(C81="Aspirant-Garde",M81*'Vue globale'!$L$2/2,M81*'Vue globale'!$L$2)) -> 0 | O81: FALSE
A82: 36 | B82: Eclaireur | C82: Recrue | D82: Do'Rhazir | F82: TRUE | G82: TRUE | H82: TRUE | I82: TRUE | J82: FALSE | K82: FALSE | L82: FALSE | M82: =COUNTIF(F82:L82,TRUE) -> 4 | N82: =IF(OR(B82="Hird du Jarl",C82="Recrue"),0,IF(C82="Aspirant-Garde",M82*'Vue globale'!$L$2/2,M82*'Vue globale'!$L$2)) -> 0 | O82: FALSE
A83: 36 | B83: Eclaireur | C83: Capitaine | D83: Glaemorandir | E83: Oeil-Perçant | F83: TRUE | G83: TRUE | H83: TRUE | I83: TRUE | J83: TRUE | K83: FALSE | L83: FALSE | M83: =COUNTIF(F83:L83,TRUE) -> 5 | N83: =IF(OR(B83="Hird du Jarl",C83="Recrue"),0,IF(C83="Aspirant-Garde",M83*'Vue globale'!$L$2/2,M83*'Vue globale'!$L$2)) -> 250 | O83: FALSE
A84: 36 | B84: Eclaireur | C84: Garde | D84: Laureen | E84: Toison-de-Sang | F84: TRUE | G84: TRUE | H84: TRUE | I84: TRUE | J84: FALSE | K84: FALSE | L84: FALSE | M84: =COUNTIF(F84:L84,TRUE) -> 4 | N84: =IF(OR(B84="Hird du Jarl",C84="Recrue"),0,IF(C84="Aspirant-Garde",M84*'Vue globale'!$L$2/2,M84*'Vue globale'!$L$2)) -> 200 | O84: FALSE
A85: 36 | B85: Eclaireur | C85: Recrue | D85: Ma'arl | F85: TRUE | G85: TRUE | H85: TRUE | I85: TRUE | J85: TRUE | K85: FALSE | L85: FALSE | M85: =COUNTIF(F85:L85,TRUE) -> 5 | N85: =IF(OR(B85="Hird du Jarl",C85="Recrue"),0,IF(C85="Aspirant-Garde",M85*'Vue globale'!$L$2/2,M85*'Vue globale'!$L$2)) -> 0 | O85: FALSE
A86: 36 | B86: Eclaireur | C86: Sergent-Chef | D86: Magnar | E86: Traquebrume | F86: TRUE | G86: TRUE | H86: TRUE | I86: TRUE | J86: FALSE | K86: FALSE | L86: FALSE | M86: =COUNTIF(F86:L86,TRUE) -> 4 | N86: =IF(OR(B86="Hird du Jarl",C86="Recrue"),0,IF(C86="Aspirant-Garde",M86*'Vue globale'!$L$2/2,M86*'Vue globale'!$L$2)) -> 200 | O86: FALSE
A87: 36 | B87: Eclaireur | C87: Recrue | D87: Ri'Jhan | E87: MoonShadow | F87: FALSE | G87: TRUE | H87: TRUE | I87: TRUE | J87: FALSE | K87: FALSE | L87: FALSE | M87: =COUNTIF(F87:L87,TRUE) -> 3 | N87: =IF(OR(B87="Hird du Jarl",C87="Recrue"),0,IF(C87="Aspirant-Garde",M87*'Vue globale'!$L$2/2,M87*'Vue globale'!$L$2)) -> 0 | O87: FALSE
A88: 36 | B88: Etat-Major | C88: Commander | D88: Filoki | F88: TRUE | G88: TRUE | H88: TRUE | I88: TRUE | J88: TRUE | K88: FALSE | L88: FALSE | M88: =COUNTIF(F88:L88,TRUE) -> 5 | N88: =IF(OR(B88="Hird du Jarl",C88="Recrue"),0,IF(C88="Aspirant-Garde",M88*'Vue globale'!$L$2/2,M88*'Vue globale'!$L$2)) -> 250 | O88: FALSE
A89: 36 | B89: Etat-Major | C89: Maréchal | D89: Lazabard | E89: Jemelred | F89: TRUE | G89: FALSE | H89: TRUE | I89: FALSE | J89: FALSE | K89: FALSE | L89: FALSE | M89: =COUNTIF(F89:L89,TRUE) -> 2 | N89: =IF(OR(B89="Hird du Jarl",C89="Recrue"),0,IF(C89="Aspirant-Garde",M89*'Vue globale'!$L$2/2,M89*'Vue globale'!$L$2)) -> 100 | O89: FALSE
A90: 36 | B90: Faubourgs de Blancherive | C90: Sergent-Chef | D90: Astrild | F90: TRUE | G90: TRUE | H90: TRUE | I90: FALSE | J90: FALSE | K90: FALSE | L90: FALSE | M90: =COUNTIF(F90:L90,TRUE) -> 3 | N90: =IF(OR(B90="Hird du Jarl",C90="Recrue"),0,IF(C90="Aspirant-Garde",M90*'Vue globale'!$L$2/2,M90*'Vue globale'!$L$2)) -> 150 | O90: FALSE
A91: 36 | B91: Faubourgs de Blancherive | C91: Garde | D91: Bernis | F91: FALSE | G91: FALSE | H91: FALSE | I91: FALSE | J91: FALSE | K91: FALSE | L91: FALSE | M91: =COUNTIF(F91:L91,TRUE) -> 0 | N91: =IF(OR(B91="Hird du Jarl",C91="Recrue"),0,IF(C91="Aspirant-Garde",M91*'Vue globale'!$L$2/2,M91*'Vue globale'!$L$2)) -> 0 | O91: FALSE
A92: 36 | B92: Faubourgs de Blancherive | C92: Garde | D92: Darina | F92: FALSE | G92: FALSE | H92: FALSE | I92: FALSE | J92: FALSE | K92: FALSE | L92: FALSE | M92: =COUNTIF(F92:L92,TRUE) -> 0 | N92: =IF(OR(B92="Hird du Jarl",C92="Recrue"),0,IF(C92="Aspirant-Garde",M92*'Vue globale'!$L$2/2,M92*'Vue globale'!$L$2)) -> 0 | O92: FALSE
A93: 36 | B93: Faubourgs de Blancherive | C93: Lieutenant | D93: Gorvin | E93: Le-Moite | F93: TRUE | G93: TRUE | H93: TRUE | I93: FALSE | J93: FALSE | K93: FALSE | L93: FALSE | M93: =COUNTIF(F93:L93,TRUE) -> 3 | N93: =IF(OR(B93="Hird du Jarl",C93="Recrue"),0,IF(C93="Aspirant-Garde",M93*'Vue globale'!$L$2/2,M93*'Vue globale'!$L$2)) -> 150 | O93: FALSE
A94: 36 | B94: Faubourgs de Blancherive | C94: Lieutenant-Chef | D94: Il-draz | E94: De Chasse-au-bois | F94: TRUE | G94: TRUE | H94: TRUE | I94: TRUE | J94: FALSE | K94: FALSE | L94: FALSE | M94: =COUNTIF(F94:L94,TRUE) -> 4 | N94: =IF(OR(B94="Hird du Jarl",C94="Recrue"),0,IF(C94="Aspirant-Garde",M94*'Vue globale'!$L$2/2,M94*'Vue globale'!$L$2)) -> 200 | O94: FALSE
A95: 36 | B95: Faubourgs de Blancherive | C95: Cadet | D95: Ina'ra | F95: TRUE | G95: TRUE | H95: TRUE | I95: FALSE | J95: FALSE | K95: FALSE | L95: FALSE | M95: =COUNTIF(F95:L95,TRUE) -> 3 | N95: =IF(OR(B95="Hird du Jarl",C95="Recrue"),0,IF(C95="Aspirant-Garde",M95*'Vue globale'!$L$2/2,M95*'Vue globale'!$L$2)) -> 150 | O95: FALSE
A96: 36 | B96: Faubourgs de Blancherive | C96: Sergent | D96: Jeebam-dee | F96: FALSE | G96: TRUE | H96: TRUE | I96: TRUE | J96: FALSE | K96: FALSE | L96: FALSE | M96: =COUNTIF(F96:L96,TRUE) -> 3 | N96: =IF(OR(B96="Hird du Jarl",C96="Recrue"),0,IF(C96="Aspirant-Garde",M96*'Vue globale'!$L$2/2,M96*'Vue globale'!$L$2)) -> 150 | O96: FALSE
A97: 36 | B97: Faubourgs de Blancherive | C97: Capitaine | D97: Kah-Shir | E97: Sombre Griffe | F97: TRUE | G97: TRUE | H97: TRUE | I97: TRUE | J97: FALSE | K97: FALSE | L97: FALSE | M97: =COUNTIF(F97:L97,TRUE) -> 4 | N97: =IF(OR(B97="Hird du Jarl",C97="Recrue"),0,IF(C97="Aspirant-Garde",M97*'Vue globale'!$L$2/2,M97*'Vue globale'!$L$2)) -> 200 | O97: FALSE
A98: 36 | B98: Faubourgs de Blancherive | C98: Garde | D98: Léonce | E98: Réve-épine | F98: FALSE | G98: TRUE | H98: FALSE | I98: FALSE | J98: FALSE | K98: FALSE | L98: FALSE | M98: =COUNTIF(F98:L98,TRUE) -> 1 | N98: =IF(OR(B98="Hird du Jarl",C98="Recrue"),0,IF(C98="Aspirant-Garde",M98*'Vue globale'!$L$2/2,M98*'Vue globale'!$L$2)) -> 50 | O98: FALSE
A99: 36 | B99: Faubourgs de Blancherive | C99: Garde | D99: Njalda | F99: FALSE | G99: FALSE | H99: FALSE | I99: FALSE | J99: FALSE | K99: FALSE | L99: FALSE | M99: =COUNTIF(F99:L99,TRUE) -> 0 | N99: =IF(OR(B99="Hird du Jarl",C99="Recrue"),0,IF(C99="Aspirant-Garde",M99*'Vue globale'!$L$2/2,M99*'Vue globale'!$L$2)) -> 0 | O99: FALSE
A100: 36 | B100: Faubourgs de Blancherive | C100: Garde | D100: Smaug | F100: TRUE | G100: TRUE | H100: FALSE | I100: TRUE | J100: FALSE | K100: FALSE | L100: FALSE | M100: =COUNTIF(F100:L100,TRUE) -> 3 | N100: =IF(OR(B100="Hird du Jarl",C100="Recrue"),0,IF(C100="Aspirant-Garde",M100*'Vue globale'!$L$2/2,M100*'Vue globale'!$L$2)) -> 150 | O100: FALSE
...

Sheet Ravitaillement
A1: Element | B1: Quantité
A2: Vegetal Soup | B2: 161
A3: Beef Stew | B3: 81
A4: Venison Stew | B4: 137

Sheet Amendes
A1: Date | B1: Garde | C1: Contrevenant | D1: Infraction | E1: Montant | F1: Payé | G1: Reversé
A2: 46267.5 | B2: Sigurd Grisetoison | C2: Jean Eude | D2: Art. 117 — Du vol dans les fermes | E2: 40 | F2: TRUE | G2: TRUE
A3: 46267.5 | B3: Erwan | C3: 'Lechatblanc'' | D3: Art. 114 — De la marche obligatoire | E3: 15 | F3: TRUE | G3: FALSE
A4: 46268.5 | B4: Wulfgar Durrock | C4: Daran la collectionneur | D4: Art. 114 — De la marche obligatoire | E4: 15 | F4: TRUE | G4: TRUE
A5: 46268.5 | B5: Ulfar | C5: Emric de la tour | D5: Art. 115 — Du visage découvert | E5: 15 | F5: TRUE | G5: TRUE
A6: 46268.5 | B6: Ulfar | C6: Moren Mont Sombre | D6: Art. 115 — Du visage découvert | E6: 15 | F6: TRUE | G6: TRUE
A7: 46269.5 | B7: Glaemorandir Oeil-Perçant | C7: Lucor | D7: Art. 115 — Du visage découvert | E7: 15 | F7: TRUE | G7: FALSE
E12: {=IF(D12="","",IFERROR(_xlfn.XLOOKUP(D12,SyncCodex!L:L,SyncCodex!M:M),""))} | F12: FALSE | G12: FALSE
E13: {=IF(D13="","",IFERROR(_xlfn.XLOOKUP(D13,SyncCodex!L:L,SyncCodex!M:M),""))} | F13: FALSE | G13: FALSE
E14: {=IF(D14="","",IFERROR(_xlfn.XLOOKUP(D14,SyncCodex!L:L,SyncCodex!M:M),""))} | F14: FALSE | G14: FALSE
E15: {=IF(D15="","",IFERROR(_xlfn.XLOOKUP(D15,SyncCodex!L:L,SyncCodex!M:M),""))} | F15: FALSE | G15: FALSE
E16: {=IF(D16="","",IFERROR(_xlfn.XLOOKUP(D16,SyncCodex!L:L,SyncCodex!M:M),""))} | F16: FALSE | G16: FALSE
E17: {=IF(D17="","",IFERROR(_xlfn.XLOOKUP(D17,SyncCodex!L:L,SyncCodex!M:M),""))} | F17: FALSE | G17: FALSE
E18: {=IF(D18="","",IFERROR(_xlfn.XLOOKUP(D18,SyncCodex!L:L,SyncCodex!M:M),""))} | F18: FALSE | G18: FALSE
E19: {=IF(D19="","",IFERROR(_xlfn.XLOOKUP(D19,SyncCodex!L:L,SyncCodex!M:M),""))} | F19: FALSE | G19: FALSE
E20: {=IF(D20="","",IFERROR(_xlfn.XLOOKUP(D20,SyncCodex!L:L,SyncCodex!M:M),""))} | F20: FALSE | G20: FALSE
E21: {=IF(D21="","",IFERROR(_xlfn.XLOOKUP(D21,SyncCodex!L:L,SyncCodex!M:M),""))} | F21: FALSE | G21: FALSE
E22: {=IF(D22="","",IFERROR(_xlfn.XLOOKUP(D22,SyncCodex!L:L,SyncCodex!M:M),""))} | F22: FALSE | G22: FALSE
E23: {=IF(D23="","",IFERROR(_xlfn.XLOOKUP(D23,SyncCodex!L:L,SyncCodex!M:M),""))} | F23: FALSE | G23: FALSE
... E996: {=IF(D996="","",IFERROR(_xlfn.XLOOKUP(D996,SyncCodex!L:L,SyncCodex!M:M),""))} | F996: FALSE | G996: FALSE

Sheet Prison
A1: Date | B1: Garde | C1: Détenu | D1: Cellule | E1: Infraction | F1: Durée prévue | G1: Heure d'entrée | H1: Heure de sortie prévue | I1: Libéré | J1: Saisies sur la personne | K1: Motif / Notes
F3: {=IF(E3="","",IFERROR(_xlfn.XLOOKUP(E3,SyncCodex!N:N,SyncCodex!O:O),""))} | H3: =IF(OR(G3="",F3=""),"",G3+(F3/24)) | I3: FALSE
F4: {=IF(E4="","",IFERROR(_xlfn.XLOOKUP(E4,SyncCodex!N:N,SyncCodex!O:O),""))} | H4: =IF(OR(G4="",F4=""),"",G4+(F4/24)) | I4: FALSE
F5: {=IF(E5="","",IFERROR(_xlfn.XLOOKUP(E5,SyncCodex!N:N,SyncCodex!O:O),""))} | H5: =IF(OR(G5="",F5=""),"",G5+(F5/24)) | I5: FALSE
F6: {=IF(E6="","",IFERROR(_xlfn.XLOOKUP(E6,SyncCodex!N:N,SyncCodex!O:O),""))} | H6: =IF(OR(G6="",F6=""),"",G6+(F6/24)) | I6: FALSE
F7: {=IF(E7="","",IFERROR(_xlfn.XLOOKUP(E7,SyncCodex!N:N,SyncCodex!O:O),""))} | H7: =IF(OR(G7="",F7=""),"",G7+(F7/24)) | I7: FALSE
F8: {=IF(E8="","",IFERROR(_xlfn.XLOOKUP(E8,SyncCodex!N:N,SyncCodex!O:O),""))} | H8: =IF(OR(G8="",F8=""),"",G8+(F8/24)) | I8: FALSE
F9: {=IF(E9="","",IFERROR(_xlfn.XLOOKUP(E9,SyncCodex!N:N,SyncCodex!O:O),""))} | H9: =IF(OR(G9="",F9=""),"",G9+(F9/24)) | I9: FALSE
F10: {=IF(E10="","",IFERROR(_xlfn.XLOOKUP(E10,SyncCodex!N:N,SyncCodex!O:O),""))} | H10: =IF(OR(G10="",F10=""),"",G10+(F10/24)) | I10: FALSE
F11: {=IF(E11="","",IFERROR(_xlfn.XLOOKUP(E11,SyncCodex!N:N,SyncCodex!O:O),""))} | H11: =IF(OR(G11="",F11=""),"",G11+(F11/24)) | I11: FALSE
F12: {=IF(E12="","",IFERROR(_xlfn.XLOOKUP(E12,SyncCodex!N:N,SyncCodex!O:O),""))} | H12: =IF(OR(G12="",F12=""),"",G12+(F12/24)) | I12: FALSE
F13: {=IF(E13="","",IFERROR(_xlfn.XLOOKUP(E13,SyncCodex!N:N,SyncCodex!O:O),""))} | H13: =IF(OR(G13="",F13=""),"",G13+(F13/24)) | I13: FALSE
F14: {=IF(E14="","",IFERROR(_xlfn.XLOOKUP(E14,SyncCodex!N:N,SyncCodex!O:O),""))} | H14: =IF(OR(G14="",F14=""),"",G14+(F14/24)) | I14: FALSE
... F997: {=IF(E997="","",IFERROR(_xlfn.XLOOKUP(E997,SyncCodex!N:N,SyncCodex!O:O),""))} | H997: =IF(OR(G997="",F997=""),"",G997+(F997/24)) | I997: FALSE

Sheet Garde de Blancherive
A1: =IFERROR(__xludf.DUMMYFUNCTION("QUERY(Effectifs!A:Z, ""SELECT * WHERE E CONTAINS 'Cité' OR E CONTAINS 'Major' ORDER BY Z ASC"", 1)"),"Assermenté") -> Assermenté | B1: =IFERROR(__xludf.DUMMYFUNCTION("""COMPUTED_VALUE"""),"Grade") -> Grade | C1: =IFERROR(__xludf.DUMMYFUNCTION("""COMPUTED_VALUE"""),"Prénom") -> Prénom | D1: =IFERROR(__xludf.DUMMYFUNCTION("""COMPUTED_VALUE"""),"Nom") -> Nom | E1: =IFERROR(__xludf.DUMMYFUNCTION("""COMPUTED_VALUE"""),"Corps") -> Corps | F1: =IFERROR(__xludf.DUMMYFUNCTION("""COMPUTED_VALUE"""),"Spécialité") -> Spécialité | G1: =IFERROR(__xludf.DUMMYFUNCTION("""COMPUTED_VALUE"""),"Status") -> Status | H1: =IFERROR(__xludf.DUMMYFUNCTION("""COMPUTED_VALUE"""),"Métier") -> Métier | I1: =IFERROR(__xludf.DUMMYFUNCTION("""COMPUTED_VALUE"""),"Recrutement") -> Recrutement | J1: =IFERROR(__xludf.DUMMYFUNCTION("""COMPUTED_VALUE"""),"Jours travaillés") -> Jours travaillés | K1: =IFERROR(__xludf.DUMMYFUNCTION("""COMPUTED_VALUE"""),"") | L1: =IFERROR(__xludf.DUMMYFUNCTION("""COMPUTED_VALUE"""),"") | M1: =IFERROR(__xludf.DUMMYFUNCTION("""COMPUTED_VALUE"""),"") | N1: =IFERROR(__xludf.DUMMYFUNCTION("""COMPUTED_VALUE"""),"") | O1: =IFERROR(__xludf.DUMMYFUNCTION("""COMPUTED_VALUE"""),"") | P1: =IFERROR(__xludf.DUMMYFUNCTION("""COMPUTED_VALUE"""),"") | Q1: =IFERROR(__xludf.DUMMYFUNCTION("""COMPUTED_VALUE"""),"") | R1: =IFERROR(__xludf.DUMMYFUNCTION("""COMPUTED_VALUE"""),"") | ... Y1: =IFERROR(__xludf.DUMMYFUNCTION("""COMPUTED_VALUE"""),"") | Z1: =IFERROR(__xludf.DUMMYFUNCTION("""COMPUTED_VALUE"""),"Grade Order") -> Grade Order
A2: =IFERROR(__xludf.DUMMYFUNCTION("""COMPUTED_VALUE"""),TRUE) -> TRUE | B2: =IFERROR(__xludf.DUMMYFUNCTION("""COMPUTED_VALUE"""),"Maréchal") -> Maréchal | C2: =IFERROR(__xludf.DUMMYFUNCTION("""COMPUTED_VALUE"""),"Lazabard") -> Lazabard | D2: =IFERROR(__xludf.DUMMYFUNCTION("""COMPUTED_VALUE"""),"Jemelred") -> Jemelred | E2: =IFERROR(__xludf.DUMMYFUNCTION("""COMPUTED_VALUE"""),"Etat-Major") -> Etat-Major | F2: =IFERROR(__xludf.DUMMYFUNCTION("""COMPUTED_VALUE"""),"Garde, Collecteur de la garde") -> Garde, Collecteur de la garde | G2: =IFERROR(__xludf.DUMMYFUNCTION("""COMPUTED_VALUE"""),"En service actif") -> En service actif | J2: =IFERROR(__xludf.DUMMYFUNCTION("""COMPUTED_VALUE"""),4.0) -> 4 | Z2: =IFERROR(__xludf.DUMMYFUNCTION("""COMPUTED_VALUE"""),1.0) -> 1
A3: =IFERROR(__xludf.DUMMYFUNCTION("""COMPUTED_VALUE"""),TRUE) -> TRUE | B3: =IFERROR(__xludf.DUMMYFUNCTION("""COMPUTED_VALUE"""),"Commander") -> Commander | C3: =IFERROR(__xludf.DUMMYFUNCTION("""COMPUTED_VALUE"""),"Filoki") -> Filoki | E3: =IFERROR(__xludf.DUMMYFUNCTION("""COMPUTED_VALUE"""),"Etat-Major") -> Etat-Major | F3: =IFERROR(__xludf.DUMMYFUNCTION("""COMPUTED_VALUE"""),"Garde, Collecteur de la garde") -> Garde, Collecteur de la garde | G3: =IFERROR(__xludf.DUMMYFUNCTION("""COMPUTED_VALUE"""),"En service actif") -> En service actif | J3: =IFERROR(__xludf.DUMMYFUNCTION("""COMPUTED_VALUE"""),0.0) -> 0 | Z3: =IFERROR(__xludf.DUMMYFUNCTION("""COMPUTED_VALUE"""),2.0) -> 2
A4: =IFERROR(__xludf.DUMMYFUNCTION("""COMPUTED_VALUE"""),TRUE) -> TRUE | B4: =IFERROR(__xludf.DUMMYFUNCTION("""COMPUTED_VALUE"""),"Major") -> Major | C4: =IFERROR(__xludf.DUMMYFUNCTION("""COMPUTED_VALUE"""),"Dagbara") -> Dagbara | D4: =IFERROR(__xludf.DUMMYFUNCTION("""COMPUTED_VALUE"""),"Gronez") -> Gronez | E4: =IFERROR(__xludf.DUMMYFUNCTION("""COMPUTED_VALUE"""),"Etat-Major") -> Etat-Major | F4: =IFERROR(__xludf.DUMMYFUNCTION("""COMPUTED_VALUE"""),"Garde") -> Garde | G4: =IFERROR(__xludf.DUMMYFUNCTION("""COMPUTED_VALUE"""),"Mis en réserve") -> Mis en réserve | J4: =IFERROR(__xludf.DUMMYFUNCTION("""COMPUTED_VALUE"""),0.0) -> 0 | Z4: =IFERROR(__xludf.DUMMYFUNCTION("""COMPUTED_VALUE"""),3.0) -> 3
A5: =IFERROR(__xludf.DUMMYFUNCTION("""COMPUTED_VALUE"""),TRUE) -> TRUE | B5: =IFERROR(__xludf.DUMMYFUNCTION("""COMPUTED_VALUE"""),"Capitaine") -> Capitaine | C5: =IFERROR(__xludf.DUMMYFUNCTION("""COMPUTED_VALUE"""),"Astrid") -> Astrid | D5: =IFERROR(__xludf.DUMMYFUNCTION("""COMPUTED_VALUE"""),"Lame-Fine") -> Lame-Fine | E5: =IFERROR(__xludf.DUMMYFUNCTION("""COMPUTED_VALUE"""),"Cité de Blancherive") -> Cité de Blancherive | F5: =IFERROR(__xludf.DUMMYFUNCTION("""COMPUTED_VALUE"""),"Garde") -> Garde | G5: =IFERROR(__xludf.DUMMYFUNCTION("""COMPUTED_VALUE"""),"En service actif") -> En service actif | H5: =IFERROR(__xludf.DUMMYFUNCTION("""COMPUTED_VALUE"""),"Chasseur") -> Chasseur | J5: =IFERROR(__xludf.DUMMYFUNCTION("""COMPUTED_VALUE"""),10.0) -> 10 | Z5: =IFERROR(__xludf.DUMMYFUNCTION("""COMPUTED_VALUE"""),4.0) -> 4
A6: =IFERROR(__xludf.DUMMYFUNCTION("""COMPUTED_VALUE"""),TRUE) -> TRUE | B6: =IFERROR(__xludf.DUMMYFUNCTION("""COMPUTED_VALUE"""),"Capitaine") -> Capitaine | C6: =IFERROR(__xludf.DUMMYFUNCTION("""COMPUTED_VALUE"""),"Edward") -> Edward | D6: =IFERROR(__xludf.DUMMYFUNCTION("""COMPUTED_VALUE"""),"Winters") -> Winters | E6: =IFERROR(__xludf.DUMMYFUNCTION("""COMPUTED_VALUE"""),"Cité de Blancherive") -> Cité de Blancherive | F6: =IFERROR(__xludf.DUMMYFUNCTION("""COMPUTED_VALUE"""),"Hird") -> Hird | G6: =IFERROR(__xludf.DUMMYFUNCTION("""COMPUTED_VALUE"""),"Mis en réserve") -> Mis en réserve | J6: =IFERROR(__xludf.DUMMYFUNCTION("""COMPUTED_VALUE"""),0.0) -> 0 | Z6: =IFERROR(__xludf.DUMMYFUNCTION("""COMPUTED_VALUE"""),4.0) -> 4
A7: =IFERROR(__xludf.DUMMYFUNCTION("""COMPUTED_VALUE"""),TRUE) -> TRUE | B7: =IFERROR(__xludf.DUMMYFUNCTION("""COMPUTED_VALUE"""),"Lieutenant-Chef") -> Lieutenant-Chef | C7: =IFERROR(__xludf.DUMMYFUNCTION("""COMPUTED_VALUE"""),"Ulfar") -> Ulfar | E7: =IFERROR(__xludf.DUMMYFUNCTION("""COMPUTED_VALUE"""),"Cité de Blancherive") -> Cité de Blancherive | F7: =IFERROR(__xludf.DUMMYFUNCTION("""COMPUTED_VALUE"""),"Garde, Instructeur") -> Garde, Instructeur | G7: =IFERROR(__xludf.DUMMYFUNCTION("""COMPUTED_VALUE"""),"En service actif") -> En service actif | J7: =IFERROR(__xludf.DUMMYFUNCTION("""COMPUTED_VALUE"""),0.0) -> 0 | Z7: =IFERROR(__xludf.DUMMYFUNCTION("""COMPUTED_VALUE"""),5.0) -> 5
A8: =IFERROR(__xludf.DUMMYFUNCTION("""COMPUTED_VALUE"""),TRUE) -> TRUE | B8: =IFERROR(__xludf.DUMMYFUNCTION("""COMPUTED_VALUE"""),"Lieutenant-Chef") -> Lieutenant-Chef | C8: =IFERROR(__xludf.DUMMYFUNCTION("""COMPUTED_VALUE"""),"Gisbern") -> Gisbern | D8: =IFERROR(__xludf.DUMMYFUNCTION("""COMPUTED_VALUE"""),"Isenbjorn") -> Isenbjorn | E8: =IFERROR(__xludf.DUMMYFUNCTION("""COMPUTED_VALUE"""),"Cité de Blancherive") -> Cité de Blancherive | F8: =IFERROR(__xludf.DUMMYFUNCTION("""COMPUTED_VALUE"""),"Garde") -> Garde | G8: =IFERROR(__xludf.DUMMYFUNCTION("""COMPUTED_VALUE"""),"En service actif") -> En service actif | J8: =IFERROR(__xludf.DUMMYFUNCTION("""COMPUTED_VALUE"""),5.0) -> 5 | Z8: =IFERROR(__xludf.DUMMYFUNCTION("""COMPUTED_VALUE"""),5.0) -> 5
A9: =IFERROR(__xludf.DUMMYFUNCTION("""COMPUTED_VALUE"""),TRUE) -> TRUE | B9: =IFERROR(__xludf.DUMMYFUNCTION("""COMPUTED_VALUE"""),"Lieutenant") -> Lieutenant | C9: =IFERROR(__xludf.DUMMYFUNCTION("""COMPUTED_VALUE"""),"Ronin") -> Ronin | E9: =IFERROR(__xludf.DUMMYFUNCTION("""COMPUTED_VALUE"""),"Cité de Blancherive") -> Cité de Blancherive | F9: =IFERROR(__xludf.DUMMYFUNCTION("""COMPUTED_VALUE"""),"Garde, Intendant de la garde, Collecteur de la garde") -> Garde, Intendant de la garde, Collecteur de la garde | G9: =IFERROR(__xludf.DUMMYFUNCTION("""COMPUTED_VALUE"""),"En service actif") -> En service actif | H9: =IFERROR(__xludf.DUMMYFUNCTION("""COMPUTED_VALUE"""),"Guerrier") -> Guerrier | I9: =IFERROR(__xludf.DUMMYFUNCTION("""COMPUTED_VALUE"""),46184.0) -> 46184 | J9: =IFERROR(__xludf.DUMMYFUNCTION("""COMPUTED_VALUE"""),0.0) -> 0 | Z9: =IFERROR(__xludf.DUMMYFUNCTION("""COMPUTED_VALUE"""),6.0) -> 6
A10: =IFERROR(__xludf.DUMMYFUNCTION("""COMPUTED_VALUE"""),TRUE) -> TRUE | B10: =IFERROR(__xludf.DUMMYFUNCTION("""COMPUTED_VALUE"""),"Lieutenant") -> Lieutenant | C10: =IFERROR(__xludf.DUMMYFUNCTION("""COMPUTED_VALUE"""),"Thorin") -> Thorin | D10: =IFERROR(__xludf.DUMMYFUNCTION("""COMPUTED_VALUE"""),"Rivegel") -> Rivegel | E10: =IFERROR(__xludf.DUMMYFUNCTION("""COMPUTED_VALUE"""),"Cité de Blancherive") -> Cité de Blancherive | F10: =IFERROR(__xludf.DUMMYFUNCTION("""COMPUTED_VALUE"""),"Eclaireur, Garde") -> Eclaireur, Garde | G10: =IFERROR(__xludf.DUMMYFUNCTION("""COMPUTED_VALUE"""),"En service actif") -> En service actif | H10: =IFERROR(__xludf.DUMMYFUNCTION("""COMPUTED_VALUE"""),"Guerrier") -> Guerrier | J10: =IFERROR(__xludf.DUMMYFUNCTION("""COMPUTED_VALUE"""),0.0) -> 0 | Z10: =IFERROR(__xludf.DUMMYFUNCTION("""COMPUTED_VALUE"""),6.0) -> 6
A11: =IFERROR(__xludf.DUMMYFUNCTION("""COMPUTED_VALUE"""),FALSE) -> FALSE | B11: =IFERROR(__xludf.DUMMYFUNCTION("""COMPUTED_VALUE"""),"Lieutenant") -> Lieutenant | C11: =IFERROR(__xludf.DUMMYFUNCTION("""COMPUTED_VALUE"""),"Encore-Un-Espoir") -> Encore-Un-Espoir | E11: =IFERROR(__xludf.DUMMYFUNCTION("""COMPUTED_VALUE"""),"Cité de Blancherive") -> Cité de Blancherive | F11: =IFERROR(__xludf.DUMMYFUNCTION("""COMPUTED_VALUE"""),"Garde, Tortionnaire, Instructeur") -> Garde, Tortionnaire, Instructeur | G11: =IFERROR(__xludf.DUMMYFUNCTION("""COMPUTED_VALUE"""),"En service actif") -> En service actif | J11: =IFERROR(__xludf.DUMMYFUNCTION("""COMPUTED_VALUE"""),0.0) -> 0 | Z11: =IFERROR(__xludf.DUMMYFUNCTION("""COMPUTED_VALUE"""),6.0) -> 6
A12: =IFERROR(__xludf.DUMMYFUNCTION("""COMPUTED_VALUE"""),TRUE) -> TRUE | B12: =IFERROR(__xludf.DUMMYFUNCTION("""COMPUTED_VALUE"""),"Sergent-Chef") -> Sergent-Chef | C12: =IFERROR(__xludf.DUMMYFUNCTION("""COMPUTED_VALUE"""),"Rorik") -> Rorik | D12: =IFERROR(__xludf.DUMMYFUNCTION("""COMPUTED_VALUE"""),"Marche-Hiver") -> Marche-Hiver | E12: =IFERROR(__xludf.DUMMYFUNCTION("""COMPUTED_VALUE"""),"Cité de Blancherive") -> Cité de Blancherive | F12: =IFERROR(__xludf.DUMMYFUNCTION("""COMPUTED_VALUE"""),"Garde") -> Garde | G12: =IFERROR(__xludf.DUMMYFUNCTION("""COMPUTED_VALUE"""),"En service actif") -> En service actif | J12: =IFERROR(__xludf.DUMMYFUNCTION("""COMPUTED_VALUE"""),12.0) -> 12 | Z12: =IFERROR(__xludf.DUMMYFUNCTION("""COMPUTED_VALUE"""),7.0) -> 7
A13: =IFERROR(__xludf.DUMMYFUNCTION("""COMPUTED_VALUE"""),TRUE) -> TRUE | B13: =IFERROR(__xludf.DUMMYFUNCTION("""COMPUTED_VALUE"""),"Sergent-Chef") -> Sergent-Chef | C13: =IFERROR(__xludf.DUMMYFUNCTION("""COMPUTED_VALUE"""),"Erwan") -> Erwan | E13: =IFERROR(__xludf.DUMMYFUNCTION("""COMPUTED_VALUE"""),"Cité de Blancherive") -> Cité de Blancherive | F13: =IFERROR(__xludf.DUMMYFUNCTION("""COMPUTED_VALUE"""),"Garde") -> Garde | G13: =IFERROR(__xludf.DUMMYFUNCTION("""COMPUTED_VALUE"""),"En service actif") -> En service actif | J13: =IFERROR(__xludf.DUMMYFUNCTION("""COMPUTED_VALUE"""),0.0) -> 0 | Z13: =IFERROR(__xludf.DUMMYFUNCTION("""COMPUTED_VALUE"""),7.0) -> 7
A14: =IFERROR(__xludf.DUMMYFUNCTION("""COMPUTED_VALUE"""),TRUE) -> TRUE | B14: =IFERROR(__xludf.DUMMYFUNCTION("""COMPUTED_VALUE"""),"Caporal-Chef") -> Caporal-Chef | C14: =IFERROR(__xludf.DUMMYFUNCTION("""COMPUTED_VALUE"""),"Ilflynn") -> Ilflynn | E14: =IFERROR(__xludf.DUMMYFUNCTION("""COMPUTED_VALUE"""),"Cité de Blancherive") -> Cité de Blancherive | F14: =IFERROR(__xludf.DUMMYFUNCTION("""COMPUTED_VALUE"""),"Garde") -> Garde | G14: =IFERROR(__xludf.DUMMYFUNCTION("""COMPUTED_VALUE"""),"En service actif") -> En service actif | J14: =IFERROR(__xludf.DUMMYFUNCTION("""COMPUTED_VALUE"""),0.0) -> 0 | Z14: =IFERROR(__xludf.DUMMYFUNCTION("""COMPUTED_VALUE"""),9.0) -> 9
A15: =IFERROR(__xludf.DUMMYFUNCTION("""COMPUTED_VALUE"""),TRUE) -> TRUE | B15: =IFERROR(__xludf.DUMMYFUNCTION("""COMPUTED_VALUE"""),"Garde") -> Garde | C15: =IFERROR(__xludf.DUMMYFUNCTION("""COMPUTED_VALUE"""),"Andor") -> Andor | D15: =IFERROR(__xludf.DUMMYFUNCTION("""COMPUTED_VALUE"""),"Viraes") -> Viraes | E15: =IFERROR(__xludf.DUMMYFUNCTION("""COMPUTED_VALUE"""),"Cité de Blancherive") -> Cité de Blancherive | F15: =IFERROR(__xludf.DUMMYFUNCTION("""COMPUTED_VALUE"""),"Garde") -> Garde | G15: =IFERROR(__xludf.DUMMYFUNCTION("""COMPUTED_VALUE"""),"En service actif") -> En service actif | J15: =IFERROR(__xludf.DUMMYFUNCTION("""COMPUTED_VALUE"""),1.0) -> 1 | Z15: =IFERROR(__xludf.DUMMYFUNCTION("""COMPUTED_VALUE"""),11.0) -> 11
A16: =IFERROR(__xludf.DUMMYFUNCTION("""COMPUTED_VALUE"""),TRUE) -> TRUE | B16: =IFERROR(__xludf.DUMMYFUNCTION("""COMPUTED_VALUE"""),"Garde") -> Garde | C16: =IFERROR(__xludf.DUMMYFUNCTION("""COMPUTED_VALUE"""),"Athlan") -> Athlan | E16: =IFERROR(__xludf.DUMMYFUNCTION("""COMPUTED_VALUE"""),"Cité de Blancherive") -> Cité de Blancherive | F16: =IFERROR(__xludf.DUMMYFUNCTION("""COMPUTED_VALUE"""),"Garde") -> Garde | G16: =IFERROR(__xludf.DUMMYFUNCTION("""COMPUTED_VALUE"""),"Démissionnaire") -> Démissionnaire | J16: =IFERROR(__xludf.DUMMYFUNCTION("""COMPUTED_VALUE"""),0.0) -> 0 | Z16: =IFERROR(__xludf.DUMMYFUNCTION("""COMPUTED_VALUE"""),11.0) -> 11
A17: =IFERROR(__xludf.DUMMYFUNCTION("""COMPUTED_VALUE"""),TRUE) -> TRUE | B17: =IFERROR(__xludf.DUMMYFUNCTION("""COMPUTED_VALUE"""),"Garde") -> Garde | C17: =IFERROR(__xludf.DUMMYFUNCTION("""COMPUTED_VALUE"""),"Al'Dran") -> Al'Dran | E17: =IFERROR(__xludf.DUMMYFUNCTION("""COMPUTED_VALUE"""),"Cité de Blancherive") -> Cité de Blancherive | F17: =IFERROR(__xludf.DUMMYFUNCTION("""COMPUTED_VALUE"""),"Garde") -> Garde | G17: =IFERROR(__xludf.DUMMYFUNCTION("""COMPUTED_VALUE"""),"En service actif") -> En service actif | J17: =IFERROR(__xludf.DUMMYFUNCTION("""COMPUTED_VALUE"""),0.0) -> 0 | Z17: =IFERROR(__xludf.DUMMYFUNCTION("""COMPUTED_VALUE"""),11.0) -> 11
A18: =IFERROR(__xludf.DUMMYFUNCTION("""COMPUTED_VALUE"""),TRUE) -> TRUE | B18: =IFERROR(__xludf.DUMMYFUNCTION("""COMPUTED_VALUE"""),"Garde") -> Garde | C18: =IFERROR(__xludf.DUMMYFUNCTION("""COMPUTED_VALUE"""),"Kendall") -> Kendall | D18: =IFERROR(__xludf.DUMMYFUNCTION("""COMPUTED_VALUE"""),"Delamare") -> Delamare | E18: =IFERROR(__xludf.DUMMYFUNCTION("""COMPUTED_VALUE"""),"Cité de Blancherive") -> Cité de Blancherive | F18: =IFERROR(__xludf.DUMMYFUNCTION("""COMPUTED_VALUE"""),"Garde") -> Garde | G18: =IFERROR(__xludf.DUMMYFUNCTION("""COMPUTED_VALUE"""),"En service actif") -> En service actif | J18: =IFERROR(__xludf.DUMMYFUNCTION("""COMPUTED_VALUE"""),7.0) -> 7 | Z18: =IFERROR(__xludf.DUMMYFUNCTION("""COMPUTED_VALUE"""),11.0) -> 11
A19: =IFERROR(__xludf.DUMMYFUNCTION("""COMPUTED_VALUE"""),FALSE) -> FALSE | B19: =IFERROR(__xludf.DUMMYFUNCTION("""COMPUTED_VALUE"""),"Garde") -> Garde | C19: =IFERROR(__xludf.DUMMYFUNCTION("""COMPUTED_VALUE"""),"Bjorn") -> Bjorn | D19: =IFERROR(__xludf.DUMMYFUNCTION("""COMPUTED_VALUE"""),"Kornseen") -> Kornseen | E19: =IFERROR(__xludf.DUMMYFUNCTION("""COMPUTED_VALUE"""),"Cité de Blancherive") -> Cité de Blancherive | F19: =IFERROR(__xludf.DUMMYFUNCTION("""COMPUTED_VALUE"""),"Garde") -> Garde | G19: =IFERROR(__xludf.DUMMYFUNCTION("""COMPUTED_VALUE"""),"En service actif") -> En service actif | J19: =IFERROR(__xludf.DUMMYFUNCTION("""COMPUTED_VALUE"""),9.0) -> 9 | Z19: =IFERROR(__xludf.DUMMYFUNCTION("""COMPUTED_VALUE"""),11.0) -> 11
A20: =IFERROR(__xludf.DUMMYFUNCTION("""COMPUTED_VALUE"""),FALSE) -> FALSE | B20: =IFERROR(__xludf.DUMMYFUNCTION("""COMPUTED_VALUE"""),"Garde") -> Garde | C20: =IFERROR(__xludf.DUMMYFUNCTION("""COMPUTED_VALUE"""),"Wulfgar") -> Wulfgar | D20: =IFERROR(__xludf.DUMMYFUNCTION("""COMPUTED_VALUE"""),"Durrock") -> Durrock | E20: =IFERROR(__xludf.DUMMYFUNCTION("""COMPUTED_VALUE"""),"Cité de Blancherive") -> Cité de Blancherive | F20: =IFERROR(__xludf.DUMMYFUNCTION("""COMPUTED_VALUE"""),"Garde") -> Garde | G20: =IFERROR(__xludf.DUMMYFUNCTION("""COMPUTED_VALUE"""),"En service actif") -> En service actif | J20: =IFERROR(__xludf.DUMMYFUNCTION("""COMPUTED_VALUE"""),5.0) -> 5 | Z20: =IFERROR(__xludf.DUMMYFUNCTION("""COMPUTED_VALUE"""),11.0) -> 11
A21: =IFERROR(__xludf.DUMMYFUNCTION("""COMPUTED_VALUE"""),FALSE) -> FALSE | B21: =IFERROR(__xludf.DUMMYFUNCTION("""COMPUTED_VALUE"""),"Garde") -> Garde | C21: =IFERROR(__xludf.DUMMYFUNCTION("""COMPUTED_VALUE"""),"Lyosha ") -> Lyosha | D21: =IFERROR(__xludf.DUMMYFUNCTION("""COMPUTED_VALUE"""),"Sullapierre") -> Sullapierre | E21: =IFERROR(__xludf.DUMMYFUNCTION("""COMPUTED_VALUE"""),"Cité de Blancherive") -> Cité de Blancherive | F21: =IFERROR(__xludf.DUMMYFUNCTION("""COMPUTED_VALUE"""),"Garde") -> Garde | G21: =IFERROR(__xludf.DUMMYFUNCTION("""COMPUTED_VALUE"""),"Mis en réserve") -> Mis en réserve | J21: =IFERROR(__xludf.DUMMYFUNCTION("""COMPUTED_VALUE"""),0.0) -> 0 | Z21: =IFERROR(__xludf.DUMMYFUNCTION("""COMPUTED_VALUE"""),11.0) -> 11
A22: =IFERROR(__xludf.DUMMYFUNCTION("""COMPUTED_VALUE"""),FALSE) -> FALSE | B22: =IFERROR(__xludf.DUMMYFUNCTION("""COMPUTED_VALUE"""),"Garde") -> Garde | C22: =IFERROR(__xludf.DUMMYFUNCTION("""COMPUTED_VALUE"""),"Brandon ") -> Brandon | D22: =IFERROR(__xludf.DUMMYFUNCTION("""COMPUTED_VALUE"""),"Alprazz") -> Alprazz | E22: =IFERROR(__xludf.DUMMYFUNCTION("""COMPUTED_VALUE"""),"Cité de Blancherive") -> Cité de Blancherive | F22: =IFERROR(__xludf.DUMMYFUNCTION("""COMPUTED_VALUE"""),"Garde") -> Garde | G22: =IFERROR(__xludf.DUMMYFUNCTION("""COMPUTED_VALUE"""),"Mis en réserve") -> Mis en réserve | J22: =IFERROR(__xludf.DUMMYFUNCTION("""COMPUTED_VALUE"""),0.0) -> 0 | Z22: =IFERROR(__xludf.DUMMYFUNCTION("""COMPUTED_VALUE"""),11.0) -> 11
A23: =IFERROR(__xludf.DUMMYFUNCTION("""COMPUTED_VALUE"""),FALSE) -> FALSE | B23: =IFERROR(__xludf.DUMMYFUNCTION("""COMPUTED_VALUE"""),"Garde") -> Garde | C23: =IFERROR(__xludf.DUMMYFUNCTION("""COMPUTED_VALUE"""),"Selene") -> Selene | E23: =IFERROR(__xludf.DUMMYFUNCTION("""COMPUTED_VALUE"""),"Cité de Blancherive") -> Cité de Blancherive | F23: =IFERROR(__xludf.DUMMYFUNCTION("""COMPUTED_VALUE"""),"Garde") -> Garde | G23: =IFERROR(__xludf.DUMMYFUNCTION("""COMPUTED_VALUE"""),"Mis en réserve") -> Mis en réserve | J23: =IFERROR(__xludf.DUMMYFUNCTION("""COMPUTED_VALUE"""),0.0) -> 0 | Z23: =IFERROR(__xludf.DUMMYFUNCTION("""COMPUTED_VALUE"""),11.0) -> 11
A24: =IFERROR(__xludf.DUMMYFUNCTION("""COMPUTED_VALUE"""),FALSE) -> FALSE | B24: =IFERROR(__xludf.DUMMYFUNCTION("""COMPUTED_VALUE"""),"Cadet") -> Cadet | C24: =IFERROR(__xludf.DUMMYFUNCTION("""COMPUTED_VALUE"""),"Eldrim") -> Eldrim | D24: =IFERROR(__xludf.DUMMYFUNCTION("""COMPUTED_VALUE"""),"Hache-Grise") -> Hache-Grise | E24: =IFERROR(__xludf.DUMMYFUNCTION("""COMPUTED_VALUE"""),"Cité de Blancherive") -> Cité de Blancherive | F24: =IFERROR(__xludf.DUMMYFUNCTION("""COMPUTED_VALUE"""),"Garde") -> Garde | G24: =IFERROR(__xludf.DUMMYFUNCTION("""COMPUTED_VALUE"""),"En service actif") -> En service actif | J24: =IFERROR(__xludf.DUMMYFUNCTION("""COMPUTED_VALUE"""),0.0) -> 0 | Z24: =IFERROR(__xludf.DUMMYFUNCTION("""COMPUTED_VALUE"""),12.0) -> 12
A25: =IFERROR(__xludf.DUMMYFUNCTION("""COMPUTED_VALUE"""),FALSE) -> FALSE | B25: =IFERROR(__xludf.DUMMYFUNCTION("""COMPUTED_VALUE"""),"Recrue") -> Recrue | C25: =IFERROR(__xludf.DUMMYFUNCTION("""COMPUTED_VALUE"""),"Ro'minet") -> Ro'minet | E25: =IFERROR(__xludf.DUMMYFUNCTION("""COMPUTED_VALUE"""),"Cité de Blancherive") -> Cité de Blancherive | F25: =IFERROR(__xludf.DUMMYFUNCTION("""COMPUTED_VALUE"""),"Garde") -> Garde | G25: =IFERROR(__xludf.DUMMYFUNCTION("""COMPUTED_VALUE"""),"Radié du service actif") -> Radié du service actif | J25: =IFERROR(__xludf.DUMMYFUNCTION("""COMPUTED_VALUE"""),0.0) -> 0 | Z25: =IFERROR(__xludf.DUMMYFUNCTION("""COMPUTED_VALUE"""),13.0) -> 13
A26: =IFERROR(__xludf.DUMMYFUNCTION("""COMPUTED_VALUE"""),FALSE) -> FALSE | B26: =IFERROR(__xludf.DUMMYFUNCTION("""COMPUTED_VALUE"""),"Recrue") -> Recrue | C26: =IFERROR(__xludf.DUMMYFUNCTION("""COMPUTED_VALUE"""),"Aldric") -> Aldric | D26: =IFERROR(__xludf.DUMMYFUNCTION("""COMPUTED_VALUE"""),"Cendre-coeur") -> Cendre-coeur | E26: =IFERROR(__xludf.DUMMYFUNCTION("""COMPUTED_VALUE"""),"Cité de Blancherive") -> Cité de Blancherive | F26: =IFERROR(__xludf.DUMMYFUNCTION("""COMPUTED_VALUE"""),"Garde") -> Garde | G26: =IFERROR(__xludf.DUMMYFUNCTION("""COMPUTED_VALUE"""),"En service actif") -> En service actif | J26: =IFERROR(__xludf.DUMMYFUNCTION("""COMPUTED_VALUE"""),2.0) -> 2 | Z26: =IFERROR(__xludf.DUMMYFUNCTION("""COMPUTED_VALUE"""),13.0) -> 13
A27: =IFERROR(__xludf.DUMMYFUNCTION("""COMPUTED_VALUE"""),FALSE) -> FALSE | B27: =IFERROR(__xludf.DUMMYFUNCTION("""COMPUTED_VALUE"""),"Recrue") -> Recrue | C27: =IFERROR(__xludf.DUMMYFUNCTION("""COMPUTED_VALUE"""),"Aldrok") -> Aldrok | E27: =IFERROR(__xludf.DUMMYFUNCTION("""COMPUTED_VALUE"""),"Cité de Blancherive") -> Cité de Blancherive | F27: =IFERROR(__xludf.DUMMYFUNCTION("""COMPUTED_VALUE"""),"Garde") -> Garde | G27: =IFERROR(__xludf.DUMMYFUNCTION("""COMPUTED_VALUE"""),"Radié du service actif") -> Radié du service actif | I27: =IFERROR(__xludf.DUMMYFUNCTION("""COMPUTED_VALUE"""),46265.0) -> 46265 | J27: =IFERROR(__xludf.DUMMYFUNCTION("""COMPUTED_VALUE"""),0.0) -> 0 | Z27: =IFERROR(__xludf.DUMMYFUNCTION("""COMPUTED_VALUE"""),13.0) -> 13
A28: =IFERROR(__xludf.DUMMYFUNCTION("""COMPUTED_VALUE"""),FALSE) -> FALSE | B28: =IFERROR(__xludf.DUMMYFUNCTION("""COMPUTED_VALUE"""),"Recrue") -> Recrue | C28: =IFERROR(__xludf.DUMMYFUNCTION("""COMPUTED_VALUE"""),"Zeid") -> Zeid | D28: =IFERROR(__xludf.DUMMYFUNCTION("""COMPUTED_VALUE"""),"Le Brise-Lames") -> Le Brise-Lames | E28: =IFERROR(__xludf.DUMMYFUNCTION("""COMPUTED_VALUE"""),"Cité de Blancherive") -> Cité de Blancherive | F28: =IFERROR(__xludf.DUMMYFUNCTION("""COMPUTED_VALUE"""),"Garde") -> Garde | G28: =IFERROR(__xludf.DUMMYFUNCTION("""COMPUTED_VALUE"""),"En service actif") -> En service actif | I28: =IFERROR(__xludf.DUMMYFUNCTION("""COMPUTED_VALUE"""),46266.0) -> 46266 | J28: =IFERROR(__xludf.DUMMYFUNCTION("""COMPUTED_VALUE"""),2.0) -> 2 | Z28: =IFERROR(__xludf.DUMMYFUNCTION("""COMPUTED_VALUE"""),13.0) -> 13
A29: =IFERROR(__xludf.DUMMYFUNCTION("""COMPUTED_VALUE"""),FALSE) -> FALSE | B29: =IFERROR(__xludf.DUMMYFUNCTION("""COMPUTED_VALUE"""),"Recrue") -> Recrue | C29: =IFERROR(__xludf.DUMMYFUNCTION("""COMPUTED_VALUE"""),"Gruseldorf") -> Gruseldorf | D29: =IFERROR(__xludf.DUMMYFUNCTION("""COMPUTED_VALUE"""),"E. Jackeet") -> E. Jackeet | E29: =IFERROR(__xludf.DUMMYFUNCTION("""COMPUTED_VALUE"""),"Cité de Blancherive") -> Cité de Blancherive | F29: =IFERROR(__xludf.DUMMYFUNCTION("""COMPUTED_VALUE"""),"Garde") -> Garde | G29: =IFERROR(__xludf.DUMMYFUNCTION("""COMPUTED_VALUE"""),"Radié du service actif") -> Radié du service actif | I29: =IFERROR(__xludf.DUMMYFUNCTION("""COMPUTED_VALUE"""),46264.0) -> 46264 | J29: =IFERROR(__xludf.DUMMYFUNCTION("""COMPUTED_VALUE"""),0.0) -> 0 | Z29: =IFERROR(__xludf.DUMMYFUNCTION("""COMPUTED_VALUE"""),13.0) -> 13
A30: =IFERROR(__xludf.DUMMYFUNCTION("""COMPUTED_VALUE"""),FALSE) -> FALSE | B30: =IFERROR(__xludf.DUMMYFUNCTION("""COMPUTED_VALUE"""),"Recrue") -> Recrue | C30: =IFERROR(__xludf.DUMMYFUNCTION("""COMPUTED_VALUE"""),"Mordecai") -> Mordecai | D30: =IFERROR(__xludf.DUMMYFUNCTION("""COMPUTED_VALUE"""),"E. Jackeet") -> E. Jackeet | E30: =IFERROR(__xludf.DUMMYFUNCTION("""COMPUTED_VALUE"""),"Cité de Blancherive") -> Cité de Blancherive | F30: =IFERROR(__xludf.DUMMYFUNCTION("""COMPUTED_VALUE"""),"Garde") -> Garde | G30: =IFERROR(__xludf.DUMMYFUNCTION("""COMPUTED_VALUE"""),"Radié du service actif") -> Radié du service actif | I30: =IFERROR(__xludf.DUMMYFUNCTION("""COMPUTED_VALUE"""),46264.0) -> 46264 | J30: =IFERROR(__xludf.DUMMYFUNCTION("""COMPUTED_VALUE"""),0.0) -> 0 | Z30: =IFERROR(__xludf.DUMMYFUNCTION("""COMPUTED_VALUE"""),13.0) -> 13

Sheet Garde des Faubourgs
A1: =IFERROR(__xludf.DUMMYFUNCTION("QUERY(Effectifs!A:Z, ""SELECT * WHERE E CONTAINS 'Faubourgs' ORDER BY Z ASC"", 1)"),"Assermenté") -> Assermenté | B1: =IFERROR(__xludf.DUMMYFUNCTION("""COMPUTED_VALUE"""),"Grade") -> Grade | C1: =IFERROR(__xludf.DUMMYFUNCTION("""COMPUTED_VALUE"""),"Prénom") -> Prénom | D1: =IFERROR(__xludf.DUMMYFUNCTION("""COMPUTED_VALUE"""),"Nom") -> Nom | E1: =IFERROR(__xludf.DUMMYFUNCTION("""COMPUTED_VALUE"""),"Corps") -> Corps | F1: =IFERROR(__xludf.DUMMYFUNCTION("""COMPUTED_VALUE"""),"Spécialité") -> Spécialité | G1: =IFERROR(__xludf.DUMMYFUNCTION("""COMPUTED_VALUE"""),"Status") -> Status | H1: =IFERROR(__xludf.DUMMYFUNCTION("""COMPUTED_VALUE"""),"Métier") -> Métier | I1: =IFERROR(__xludf.DUMMYFUNCTION("""COMPUTED_VALUE"""),"Recrutement") -> Recrutement | J1: =IFERROR(__xludf.DUMMYFUNCTION("""COMPUTED_VALUE"""),"Jours travaillés") -> Jours travaillés | K1: =IFERROR(__xludf.DUMMYFUNCTION("""COMPUTED_VALUE"""),"") | L1: =IFERROR(__xludf.DUMMYFUNCTION("""COMPUTED_VALUE"""),"") | M1: =IFERROR(__xludf.DUMMYFUNCTION("""COMPUTED_VALUE"""),"") | N1: =IFERROR(__xludf.DUMMYFUNCTION("""COMPUTED_VALUE"""),"") | O1: =IFERROR(__xludf.DUMMYFUNCTION("""COMPUTED_VALUE"""),"") | P1: =IFERROR(__xludf.DUMMYFUNCTION("""COMPUTED_VALUE"""),"") | Q1: =IFERROR(__xludf.DUMMYFUNCTION("""COMPUTED_VALUE"""),"") | R1: =IFERROR(__xludf.DUMMYFUNCTION("""COMPUTED_VALUE"""),"") | ... Y1: =IFERROR(__xludf.DUMMYFUNCTION("""COMPUTED_VALUE"""),"") | Z1: =IFERROR(__xludf.DUMMYFUNCTION("""COMPUTED_VALUE"""),"Grade Order") -> Grade Order
A2: =IFERROR(__xludf.DUMMYFUNCTION("""COMPUTED_VALUE"""),TRUE) -> TRUE | B2: =IFERROR(__xludf.DUMMYFUNCTION("""COMPUTED_VALUE"""),"Capitaine") -> Capitaine | C2: =IFERROR(__xludf.DUMMYFUNCTION("""COMPUTED_VALUE"""),"Kah-Shir") -> Kah-Shir | D2: =IFERROR(__xludf.DUMMYFUNCTION("""COMPUTED_VALUE"""),"Sombre Griffe") -> Sombre Griffe | E2: =IFERROR(__xludf.DUMMYFUNCTION("""COMPUTED_VALUE"""),"Faubourgs de Blancherive") -> Faubourgs de Blancherive | F2: =IFERROR(__xludf.DUMMYFUNCTION("""COMPUTED_VALUE"""),"Garde, Collecteur de la garde") -> Garde, Collecteur de la garde | G2: =IFERROR(__xludf.DUMMYFUNCTION("""COMPUTED_VALUE"""),"En service actif") -> En service actif | J2: =IFERROR(__xludf.DUMMYFUNCTION("""COMPUTED_VALUE"""),4.0) -> 4 | Z2: =IFERROR(__xludf.DUMMYFUNCTION("""COMPUTED_VALUE"""),4.0) -> 4
A3: =IFERROR(__xludf.DUMMYFUNCTION("""COMPUTED_VALUE"""),FALSE) -> FALSE | B3: =IFERROR(__xludf.DUMMYFUNCTION("""COMPUTED_VALUE"""),"Lieutenant-Chef") -> Lieutenant-Chef | C3: =IFERROR(__xludf.DUMMYFUNCTION("""COMPUTED_VALUE"""),"Il-draz ") -> Il-draz | D3: =IFERROR(__xludf.DUMMYFUNCTION("""COMPUTED_VALUE"""),"De Chasse-au-bois") -> De Chasse-au-bois | E3: =IFERROR(__xludf.DUMMYFUNCTION("""COMPUTED_VALUE"""),"Faubourgs de Blancherive") -> Faubourgs de Blancherive | F3: =IFERROR(__xludf.DUMMYFUNCTION("""COMPUTED_VALUE"""),"Garde") -> Garde | G3: =IFERROR(__xludf.DUMMYFUNCTION("""COMPUTED_VALUE"""),"En service actif") -> En service actif | J3: =IFERROR(__xludf.DUMMYFUNCTION("""COMPUTED_VALUE"""),0.0) -> 0 | Z3: =IFERROR(__xludf.DUMMYFUNCTION("""COMPUTED_VALUE"""),5.0) -> 5
A4: =IFERROR(__xludf.DUMMYFUNCTION("""COMPUTED_VALUE"""),FALSE) -> FALSE | B4: =IFERROR(__xludf.DUMMYFUNCTION("""COMPUTED_VALUE"""),"Lieutenant") -> Lieutenant | C4: =IFERROR(__xludf.DUMMYFUNCTION("""COMPUTED_VALUE"""),"Gorvin") -> Gorvin | D4: =IFERROR(__xludf.DUMMYFUNCTION("""COMPUTED_VALUE"""),"Le-Moite") -> Le-Moite | E4: =IFERROR(__xludf.DUMMYFUNCTION("""COMPUTED_VALUE"""),"Faubourgs de Blancherive") -> Faubourgs de Blancherive | F4: =IFERROR(__xludf.DUMMYFUNCTION("""COMPUTED_VALUE"""),"Garde") -> Garde | G4: =IFERROR(__xludf.DUMMYFUNCTION("""COMPUTED_VALUE"""),"En service actif") -> En service actif | J4: =IFERROR(__xludf.DUMMYFUNCTION("""COMPUTED_VALUE"""),3.0) -> 3 | Z4: =IFERROR(__xludf.DUMMYFUNCTION("""COMPUTED_VALUE"""),6.0) -> 6
A5: =IFERROR(__xludf.DUMMYFUNCTION("""COMPUTED_VALUE"""),FALSE) -> FALSE | B5: =IFERROR(__xludf.DUMMYFUNCTION("""COMPUTED_VALUE"""),"Sergent-Chef") -> Sergent-Chef | C5: =IFERROR(__xludf.DUMMYFUNCTION("""COMPUTED_VALUE"""),"Astrild") -> Astrild | E5: =IFERROR(__xludf.DUMMYFUNCTION("""COMPUTED_VALUE"""),"Faubourgs de Blancherive") -> Faubourgs de Blancherive | F5: =IFERROR(__xludf.DUMMYFUNCTION("""COMPUTED_VALUE"""),"Garde") -> Garde | G5: =IFERROR(__xludf.DUMMYFUNCTION("""COMPUTED_VALUE"""),"En service actif") -> En service actif | J5: =IFERROR(__xludf.DUMMYFUNCTION("""COMPUTED_VALUE"""),0.0) -> 0 | Z5: =IFERROR(__xludf.DUMMYFUNCTION("""COMPUTED_VALUE"""),7.0) -> 7
A6: =IFERROR(__xludf.DUMMYFUNCTION("""COMPUTED_VALUE"""),FALSE) -> FALSE | B6: =IFERROR(__xludf.DUMMYFUNCTION("""COMPUTED_VALUE"""),"Sergent") -> Sergent | C6: =IFERROR(__xludf.DUMMYFUNCTION("""COMPUTED_VALUE"""),"Jeebam-dee") -> Jeebam-dee | E6: =IFERROR(__xludf.DUMMYFUNCTION("""COMPUTED_VALUE"""),"Faubourgs de Blancherive") -> Faubourgs de Blancherive | F6: =IFERROR(__xludf.DUMMYFUNCTION("""COMPUTED_VALUE"""),"Garde") -> Garde | G6: =IFERROR(__xludf.DUMMYFUNCTION("""COMPUTED_VALUE"""),"En service actif") -> En service actif | J6: =IFERROR(__xludf.DUMMYFUNCTION("""COMPUTED_VALUE"""),0.0) -> 0 | Z6: =IFERROR(__xludf.DUMMYFUNCTION("""COMPUTED_VALUE"""),8.0) -> 8
A7: =IFERROR(__xludf.DUMMYFUNCTION("""COMPUTED_VALUE"""),FALSE) -> FALSE | B7: =IFERROR(__xludf.DUMMYFUNCTION("""COMPUTED_VALUE"""),"Sergent") -> Sergent | C7: =IFERROR(__xludf.DUMMYFUNCTION("""COMPUTED_VALUE"""),"Ja'Shanir") -> Ja'Shanir | E7: =IFERROR(__xludf.DUMMYFUNCTION("""COMPUTED_VALUE"""),"Faubourgs de Blancherive") -> Faubourgs de Blancherive | F7: =IFERROR(__xludf.DUMMYFUNCTION("""COMPUTED_VALUE"""),"Garde") -> Garde | G7: =IFERROR(__xludf.DUMMYFUNCTION("""COMPUTED_VALUE"""),"Démissionnaire") -> Démissionnaire | J7: =IFERROR(__xludf.DUMMYFUNCTION("""COMPUTED_VALUE"""),0.0) -> 0 | Z7: =IFERROR(__xludf.DUMMYFUNCTION("""COMPUTED_VALUE"""),8.0) -> 8
A8: =IFERROR(__xludf.DUMMYFUNCTION("""COMPUTED_VALUE"""),FALSE) -> FALSE | B8: =IFERROR(__xludf.DUMMYFUNCTION("""COMPUTED_VALUE"""),"Garde") -> Garde | C8: =IFERROR(__xludf.DUMMYFUNCTION("""COMPUTED_VALUE"""),"Léonce") -> Léonce | D8: =IFERROR(__xludf.DUMMYFUNCTION("""COMPUTED_VALUE"""),"Réve-épine") -> Réve-épine | E8: =IFERROR(__xludf.DUMMYFUNCTION("""COMPUTED_VALUE"""),"Faubourgs de Blancherive") -> Faubourgs de Blancherive | F8: =IFERROR(__xludf.DUMMYFUNCTION("""COMPUTED_VALUE"""),"Garde") -> Garde | G8: =IFERROR(__xludf.DUMMYFUNCTION("""COMPUTED_VALUE"""),"En service actif") -> En service actif | J8: =IFERROR(__xludf.DUMMYFUNCTION("""COMPUTED_VALUE"""),1.0) -> 1 | Z8: =IFERROR(__xludf.DUMMYFUNCTION("""COMPUTED_VALUE"""),11.0) -> 11
A9: =IFERROR(__xludf.DUMMYFUNCTION("""COMPUTED_VALUE"""),FALSE) -> FALSE | B9: =IFERROR(__xludf.DUMMYFUNCTION("""COMPUTED_VALUE"""),"Garde") -> Garde | C9: =IFERROR(__xludf.DUMMYFUNCTION("""COMPUTED_VALUE"""),"Smaug") -> Smaug | E9: =IFERROR(__xludf.DUMMYFUNCTION("""COMPUTED_VALUE"""),"Faubourgs de Blancherive") -> Faubourgs de Blancherive | F9: =IFERROR(__xludf.DUMMYFUNCTION("""COMPUTED_VALUE"""),"Garde") -> Garde | G9: =IFERROR(__xludf.DUMMYFUNCTION("""COMPUTED_VALUE"""),"En service actif") -> En service actif | J9: =IFERROR(__xludf.DUMMYFUNCTION("""COMPUTED_VALUE"""),0.0) -> 0 | Z9: =IFERROR(__xludf.DUMMYFUNCTION("""COMPUTED_VALUE"""),11.0) -> 11
A10: =IFERROR(__xludf.DUMMYFUNCTION("""COMPUTED_VALUE"""),FALSE) -> FALSE | B10: =IFERROR(__xludf.DUMMYFUNCTION("""COMPUTED_VALUE"""),"Garde") -> Garde | C10: =IFERROR(__xludf.DUMMYFUNCTION("""COMPUTED_VALUE"""),"Njalda") -> Njalda | E10: =IFERROR(__xludf.DUMMYFUNCTION("""COMPUTED_VALUE"""),"Faubourgs de Blancherive") -> Faubourgs de Blancherive | F10: =IFERROR(__xludf.DUMMYFUNCTION("""COMPUTED_VALUE"""),"Garde") -> Garde | G10: =IFERROR(__xludf.DUMMYFUNCTION("""COMPUTED_VALUE"""),"En service actif") -> En service actif | J10: =IFERROR(__xludf.DUMMYFUNCTION("""COMPUTED_VALUE"""),0.0) -> 0 | Z10: =IFERROR(__xludf.DUMMYFUNCTION("""COMPUTED_VALUE"""),11.0) -> 11
A11: =IFERROR(__xludf.DUMMYFUNCTION("""COMPUTED_VALUE"""),FALSE) -> FALSE | B11: =IFERROR(__xludf.DUMMYFUNCTION("""COMPUTED_VALUE"""),"Garde") -> Garde | C11: =IFERROR(__xludf.DUMMYFUNCTION("""COMPUTED_VALUE"""),"Darina") -> Darina | E11: =IFERROR(__xludf.DUMMYFUNCTION("""COMPUTED_VALUE"""),"Faubourgs de Blancherive") -> Faubourgs de Blancherive | F11: =IFERROR(__xludf.DUMMYFUNCTION("""COMPUTED_VALUE"""),"Garde") -> Garde | G11: =IFERROR(__xludf.DUMMYFUNCTION("""COMPUTED_VALUE"""),"En service actif") -> En service actif | J11: =IFERROR(__xludf.DUMMYFUNCTION("""COMPUTED_VALUE"""),0.0) -> 0 | Z11: =IFERROR(__xludf.DUMMYFUNCTION("""COMPUTED_VALUE"""),11.0) -> 11
A12: =IFERROR(__xludf.DUMMYFUNCTION("""COMPUTED_VALUE"""),FALSE) -> FALSE | B12: =IFERROR(__xludf.DUMMYFUNCTION("""COMPUTED_VALUE"""),"Garde") -> Garde | C12: =IFERROR(__xludf.DUMMYFUNCTION("""COMPUTED_VALUE"""),"Torald") -> Torald | D12: =IFERROR(__xludf.DUMMYFUNCTION("""COMPUTED_VALUE"""),"Brise-Roche") -> Brise-Roche | E12: =IFERROR(__xludf.DUMMYFUNCTION("""COMPUTED_VALUE"""),"Faubourgs de Blancherive") -> Faubourgs de Blancherive | F12: =IFERROR(__xludf.DUMMYFUNCTION("""COMPUTED_VALUE"""),"Garde") -> Garde | G12: =IFERROR(__xludf.DUMMYFUNCTION("""COMPUTED_VALUE"""),"En service actif") -> En service actif | J12: =IFERROR(__xludf.DUMMYFUNCTION("""COMPUTED_VALUE"""),1.0) -> 1 | Z12: =IFERROR(__xludf.DUMMYFUNCTION("""COMPUTED_VALUE"""),11.0) -> 11
A13: =IFERROR(__xludf.DUMMYFUNCTION("""COMPUTED_VALUE"""),FALSE) -> FALSE | B13: =IFERROR(__xludf.DUMMYFUNCTION("""COMPUTED_VALUE"""),"Garde") -> Garde | C13: =IFERROR(__xludf.DUMMYFUNCTION("""COMPUTED_VALUE"""),"Bernis") -> Bernis | E13: =IFERROR(__xludf.DUMMYFUNCTION("""COMPUTED_VALUE"""),"Faubourgs de Blancherive") -> Faubourgs de Blancherive | F13: =IFERROR(__xludf.DUMMYFUNCTION("""COMPUTED_VALUE"""),"Garde") -> Garde | G13: =IFERROR(__xludf.DUMMYFUNCTION("""COMPUTED_VALUE"""),"En service actif") -> En service actif | J13: =IFERROR(__xludf.DUMMYFUNCTION("""COMPUTED_VALUE"""),0.0) -> 0 | Z13: =IFERROR(__xludf.DUMMYFUNCTION("""COMPUTED_VALUE"""),11.0) -> 11
A14: =IFERROR(__xludf.DUMMYFUNCTION("""COMPUTED_VALUE"""),FALSE) -> FALSE | B14: =IFERROR(__xludf.DUMMYFUNCTION("""COMPUTED_VALUE"""),"Cadet") -> Cadet | C14: =IFERROR(__xludf.DUMMYFUNCTION("""COMPUTED_VALUE"""),"Ina'ra") -> Ina'ra | E14: =IFERROR(__xludf.DUMMYFUNCTION("""COMPUTED_VALUE"""),"Faubourgs de Blancherive") -> Faubourgs de Blancherive | F14: =IFERROR(__xludf.DUMMYFUNCTION("""COMPUTED_VALUE"""),"Garde") -> Garde | G14: =IFERROR(__xludf.DUMMYFUNCTION("""COMPUTED_VALUE"""),"En service actif") -> En service actif | J14: =IFERROR(__xludf.DUMMYFUNCTION("""COMPUTED_VALUE"""),0.0) -> 0 | Z14: =IFERROR(__xludf.DUMMYFUNCTION("""COMPUTED_VALUE"""),12.0) -> 12

Sheet Hird du Jarl
A1: =IFERROR(__xludf.DUMMYFUNCTION("QUERY(Effectifs!A:Z, ""SELECT * WHERE E CONTAINS 'Hird' ORDER BY Z ASC"", 1)"),"Assermenté") -> Assermenté | B1: =IFERROR(__xludf.DUMMYFUNCTION("""COMPUTED_VALUE"""),"Grade") -> Grade | C1: =IFERROR(__xludf.DUMMYFUNCTION("""COMPUTED_VALUE"""),"Prénom") -> Prénom | D1: =IFERROR(__xludf.DUMMYFUNCTION("""COMPUTED_VALUE"""),"Nom") -> Nom | E1: =IFERROR(__xludf.DUMMYFUNCTION("""COMPUTED_VALUE"""),"Corps") -> Corps | F1: =IFERROR(__xludf.DUMMYFUNCTION("""COMPUTED_VALUE"""),"Spécialité") -> Spécialité | G1: =IFERROR(__xludf.DUMMYFUNCTION("""COMPUTED_VALUE"""),"Status") -> Status | H1: =IFERROR(__xludf.DUMMYFUNCTION("""COMPUTED_VALUE"""),"Métier") -> Métier | I1: =IFERROR(__xludf.DUMMYFUNCTION("""COMPUTED_VALUE"""),"Recrutement") -> Recrutement | J1: =IFERROR(__xludf.DUMMYFUNCTION("""COMPUTED_VALUE"""),"Jours travaillés") -> Jours travaillés | K1: =IFERROR(__xludf.DUMMYFUNCTION("""COMPUTED_VALUE"""),"") | L1: =IFERROR(__xludf.DUMMYFUNCTION("""COMPUTED_VALUE"""),"") | M1: =IFERROR(__xludf.DUMMYFUNCTION("""COMPUTED_VALUE"""),"") | N1: =IFERROR(__xludf.DUMMYFUNCTION("""COMPUTED_VALUE"""),"") | O1: =IFERROR(__xludf.DUMMYFUNCTION("""COMPUTED_VALUE"""),"") | P1: =IFERROR(__xludf.DUMMYFUNCTION("""COMPUTED_VALUE"""),"") | Q1: =IFERROR(__xludf.DUMMYFUNCTION("""COMPUTED_VALUE"""),"") | R1: =IFERROR(__xludf.DUMMYFUNCTION("""COMPUTED_VALUE"""),"") | ... Y1: =IFERROR(__xludf.DUMMYFUNCTION("""COMPUTED_VALUE"""),"") | Z1: =IFERROR(__xludf.DUMMYFUNCTION("""COMPUTED_VALUE"""),"Grade Order") -> Grade Order
A2: =IFERROR(__xludf.DUMMYFUNCTION("""COMPUTED_VALUE"""),FALSE) -> FALSE | B2: =IFERROR(__xludf.DUMMYFUNCTION("""COMPUTED_VALUE"""),"Capitaine") -> Capitaine | C2: =IFERROR(__xludf.DUMMYFUNCTION("""COMPUTED_VALUE"""),"Theodrek") -> Theodrek | D2: =IFERROR(__xludf.DUMMYFUNCTION("""COMPUTED_VALUE"""),"Heid") -> Heid | E2: =IFERROR(__xludf.DUMMYFUNCTION("""COMPUTED_VALUE"""),"Hird du Jarl") -> Hird du Jarl | F2: =IFERROR(__xludf.DUMMYFUNCTION("""COMPUTED_VALUE"""),"Hird") -> Hird | G2: =IFERROR(__xludf.DUMMYFUNCTION("""COMPUTED_VALUE"""),"En service actif") -> En service actif | J2: =IFERROR(__xludf.DUMMYFUNCTION("""COMPUTED_VALUE"""),0.0) -> 0 | Z2: =IFERROR(__xludf.DUMMYFUNCTION("""COMPUTED_VALUE"""),4.0) -> 4
A3: =IFERROR(__xludf.DUMMYFUNCTION("""COMPUTED_VALUE"""),FALSE) -> FALSE | B3: =IFERROR(__xludf.DUMMYFUNCTION("""COMPUTED_VALUE"""),"Garde") -> Garde | C3: =IFERROR(__xludf.DUMMYFUNCTION("""COMPUTED_VALUE"""),"Kronk") -> Kronk | D3: =IFERROR(__xludf.DUMMYFUNCTION("""COMPUTED_VALUE"""),"Grognon") -> Grognon | E3: =IFERROR(__xludf.DUMMYFUNCTION("""COMPUTED_VALUE"""),"Hird du Jarl") -> Hird du Jarl | F3: =IFERROR(__xludf.DUMMYFUNCTION("""COMPUTED_VALUE"""),"Hird") -> Hird | G3: =IFERROR(__xludf.DUMMYFUNCTION("""COMPUTED_VALUE"""),"En service actif") -> En service actif | J3: =IFERROR(__xludf.DUMMYFUNCTION("""COMPUTED_VALUE"""),0.0) -> 0 | Z3: =IFERROR(__xludf.DUMMYFUNCTION("""COMPUTED_VALUE"""),11.0) -> 11
A4: =IFERROR(__xludf.DUMMYFUNCTION("""COMPUTED_VALUE"""),FALSE) -> FALSE | B4: =IFERROR(__xludf.DUMMYFUNCTION("""COMPUTED_VALUE"""),"Garde") -> Garde | C4: =IFERROR(__xludf.DUMMYFUNCTION("""COMPUTED_VALUE"""),"Gronk") -> Gronk | D4: =IFERROR(__xludf.DUMMYFUNCTION("""COMPUTED_VALUE"""),"Grognon") -> Grognon | E4: =IFERROR(__xludf.DUMMYFUNCTION("""COMPUTED_VALUE"""),"Hird du Jarl") -> Hird du Jarl | F4: =IFERROR(__xludf.DUMMYFUNCTION("""COMPUTED_VALUE"""),"Hird") -> Hird | G4: =IFERROR(__xludf.DUMMYFUNCTION("""COMPUTED_VALUE"""),"En service actif") -> En service actif | J4: =IFERROR(__xludf.DUMMYFUNCTION("""COMPUTED_VALUE"""),0.0) -> 0 | Z4: =IFERROR(__xludf.DUMMYFUNCTION("""COMPUTED_VALUE"""),11.0) -> 11
A5: =IFERROR(__xludf.DUMMYFUNCTION("""COMPUTED_VALUE"""),FALSE) -> FALSE | B5: =IFERROR(__xludf.DUMMYFUNCTION("""COMPUTED_VALUE"""),"Garde") -> Garde | C5: =IFERROR(__xludf.DUMMYFUNCTION("""COMPUTED_VALUE"""),"S'Khar") -> S'Khar | E5: =IFERROR(__xludf.DUMMYFUNCTION("""COMPUTED_VALUE"""),"Hird du Jarl") -> Hird du Jarl | F5: =IFERROR(__xludf.DUMMYFUNCTION("""COMPUTED_VALUE"""),"Hird") -> Hird | G5: =IFERROR(__xludf.DUMMYFUNCTION("""COMPUTED_VALUE"""),"En service actif") -> En service actif | J5: =IFERROR(__xludf.DUMMYFUNCTION("""COMPUTED_VALUE"""),0.0) -> 0 | Z5: =IFERROR(__xludf.DUMMYFUNCTION("""COMPUTED_VALUE"""),11.0) -> 11
A6: =IFERROR(__xludf.DUMMYFUNCTION("""COMPUTED_VALUE"""),FALSE) -> FALSE | B6: =IFERROR(__xludf.DUMMYFUNCTION("""COMPUTED_VALUE"""),"Garde") -> Garde | C6: =IFERROR(__xludf.DUMMYFUNCTION("""COMPUTED_VALUE"""),"Gorbash") -> Gorbash | D6: =IFERROR(__xludf.DUMMYFUNCTION("""COMPUTED_VALUE"""),"Tête-de-Pierre") -> Tête-de-Pierre | E6: =IFERROR(__xludf.DUMMYFUNCTION("""COMPUTED_VALUE"""),"Hird du Jarl") -> Hird du Jarl | F6: =IFERROR(__xludf.DUMMYFUNCTION("""COMPUTED_VALUE"""),"Hird") -> Hird | G6: =IFERROR(__xludf.DUMMYFUNCTION("""COMPUTED_VALUE"""),"En service actif") -> En service actif | J6: =IFERROR(__xludf.DUMMYFUNCTION("""COMPUTED_VALUE"""),0.0) -> 0 | Z6: =IFERROR(__xludf.DUMMYFUNCTION("""COMPUTED_VALUE"""),11.0) -> 11
A7: =IFERROR(__xludf.DUMMYFUNCTION("""COMPUTED_VALUE"""),FALSE) -> FALSE | B7: =IFERROR(__xludf.DUMMYFUNCTION("""COMPUTED_VALUE"""),"Garde") -> Garde | C7: =IFERROR(__xludf.DUMMYFUNCTION("""COMPUTED_VALUE"""),"Armand") -> Armand | D7: =IFERROR(__xludf.DUMMYFUNCTION("""COMPUTED_VALUE"""),"De Valclair") -> De Valclair | E7: =IFERROR(__xludf.DUMMYFUNCTION("""COMPUTED_VALUE"""),"Hird du Jarl") -> Hird du Jarl | F7: =IFERROR(__xludf.DUMMYFUNCTION("""COMPUTED_VALUE"""),"Hird") -> Hird | G7: =IFERROR(__xludf.DUMMYFUNCTION("""COMPUTED_VALUE"""),"En service actif") -> En service actif | J7: =IFERROR(__xludf.DUMMYFUNCTION("""COMPUTED_VALUE"""),0.0) -> 0 | Z7: =IFERROR(__xludf.DUMMYFUNCTION("""COMPUTED_VALUE"""),11.0) -> 11
A8: =IFERROR(__xludf.DUMMYFUNCTION("""COMPUTED_VALUE"""),FALSE) -> FALSE | B8: =IFERROR(__xludf.DUMMYFUNCTION("""COMPUTED_VALUE"""),"Garde") -> Garde | C8: =IFERROR(__xludf.DUMMYFUNCTION("""COMPUTED_VALUE"""),"Si'Yara") -> Si'Yara | D8: =IFERROR(__xludf.DUMMYFUNCTION("""COMPUTED_VALUE"""),"dite Fou") -> dite Fou | E8: =IFERROR(__xludf.DUMMYFUNCTION("""COMPUTED_VALUE"""),"Hird du Jarl") -> Hird du Jarl | F8: =IFERROR(__xludf.DUMMYFUNCTION("""COMPUTED_VALUE"""),"Hird") -> Hird | G8: =IFERROR(__xludf.DUMMYFUNCTION("""COMPUTED_VALUE"""),"En service actif") -> En service actif | J8: =IFERROR(__xludf.DUMMYFUNCTION("""COMPUTED_VALUE"""),0.0) -> 0 | Z8: =IFERROR(__xludf.DUMMYFUNCTION("""COMPUTED_VALUE"""),11.0) -> 11
A9: =IFERROR(__xludf.DUMMYFUNCTION("""COMPUTED_VALUE"""),FALSE) -> FALSE | B9: =IFERROR(__xludf.DUMMYFUNCTION("""COMPUTED_VALUE"""),"Garde") -> Garde | C9: =IFERROR(__xludf.DUMMYFUNCTION("""COMPUTED_VALUE"""),"Lokh") -> Lokh | D9: =IFERROR(__xludf.DUMMYFUNCTION("""COMPUTED_VALUE"""),"Tar") -> Tar | E9: =IFERROR(__xludf.DUMMYFUNCTION("""COMPUTED_VALUE"""),"Hird du Jarl") -> Hird du Jarl | F9: =IFERROR(__xludf.DUMMYFUNCTION("""COMPUTED_VALUE"""),"Hird") -> Hird | G9: =IFERROR(__xludf.DUMMYFUNCTION("""COMPUTED_VALUE"""),"En service actif") -> En service actif | J9: =IFERROR(__xludf.DUMMYFUNCTION("""COMPUTED_VALUE"""),0.0) -> 0 | Z9: =IFERROR(__xludf.DUMMYFUNCTION("""COMPUTED_VALUE"""),11.0) -> 11
A10: =IFERROR(__xludf.DUMMYFUNCTION("""COMPUTED_VALUE"""),FALSE) -> FALSE | B10: =IFERROR(__xludf.DUMMYFUNCTION("""COMPUTED_VALUE"""),"Garde") -> Garde | C10: =IFERROR(__xludf.DUMMYFUNCTION("""COMPUTED_VALUE"""),"Lucius") -> Lucius | D10: =IFERROR(__xludf.DUMMYFUNCTION("""COMPUTED_VALUE"""),"Ravenshield") -> Ravenshield | E10: =IFERROR(__xludf.DUMMYFUNCTION("""COMPUTED_VALUE"""),"Hird du Jarl") -> Hird du Jarl | F10: =IFERROR(__xludf.DUMMYFUNCTION("""COMPUTED_VALUE"""),"Hird") -> Hird | G10: =IFERROR(__xludf.DUMMYFUNCTION("""COMPUTED_VALUE"""),"En service actif") -> En service actif | J10: =IFERROR(__xludf.DUMMYFUNCTION("""COMPUTED_VALUE"""),0.0) -> 0 | Z10: =IFERROR(__xludf.DUMMYFUNCTION("""COMPUTED_VALUE"""),11.0) -> 11
A11: =IFERROR(__xludf.DUMMYFUNCTION("""COMPUTED_VALUE"""),FALSE) -> FALSE | B11: =IFERROR(__xludf.DUMMYFUNCTION("""COMPUTED_VALUE"""),"Garde") -> Garde | C11: =IFERROR(__xludf.DUMMYFUNCTION("""COMPUTED_VALUE"""),"Faynir") -> Faynir | E11: =IFERROR(__xludf.DUMMYFUNCTION("""COMPUTED_VALUE"""),"Hird du Jarl") -> Hird du Jarl | F11: =IFERROR(__xludf.DUMMYFUNCTION("""COMPUTED_VALUE"""),"Hird") -> Hird | G11: =IFERROR(__xludf.DUMMYFUNCTION("""COMPUTED_VALUE"""),"En service actif") -> En service actif | J11: =IFERROR(__xludf.DUMMYFUNCTION("""COMPUTED_VALUE"""),0.0) -> 0 | Z11: =IFERROR(__xludf.DUMMYFUNCTION("""COMPUTED_VALUE"""),11.0) -> 11
A12: =IFERROR(__xludf.DUMMYFUNCTION("""COMPUTED_VALUE"""),FALSE) -> FALSE | B12: =IFERROR(__xludf.DUMMYFUNCTION("""COMPUTED_VALUE"""),"Garde") -> Garde | C12: =IFERROR(__xludf.DUMMYFUNCTION("""COMPUTED_VALUE"""),"Varaa") -> Varaa | D12: =IFERROR(__xludf.DUMMYFUNCTION("""COMPUTED_VALUE"""),"Uzgar") -> Uzgar | E12: =IFERROR(__xludf.DUMMYFUNCTION("""COMPUTED_VALUE"""),"Hird du Jarl") -> Hird du Jarl | F12: =IFERROR(__xludf.DUMMYFUNCTION("""COMPUTED_VALUE"""),"Hird") -> Hird | G12: =IFERROR(__xludf.DUMMYFUNCTION("""COMPUTED_VALUE"""),"En service actif") -> En service actif | J12: =IFERROR(__xludf.DUMMYFUNCTION("""COMPUTED_VALUE"""),0.0) -> 0 | Z12: =IFERROR(__xludf.DUMMYFUNCTION("""COMPUTED_VALUE"""),11.0) -> 11

Sheet Garde de Bois-de-Chêne
A1: =IFERROR(__xludf.DUMMYFUNCTION("QUERY(Effectifs!A:Z, ""SELECT * WHERE E CONTAINS 'Chêne' ORDER BY Z ASC"", 1)"),"Assermenté") -> Assermenté | B1: =IFERROR(__xludf.DUMMYFUNCTION("""COMPUTED_VALUE"""),"Grade") -> Grade | C1: =IFERROR(__xludf.DUMMYFUNCTION("""COMPUTED_VALUE"""),"Prénom") -> Prénom | D1: =IFERROR(__xludf.DUMMYFUNCTION("""COMPUTED_VALUE"""),"Nom") -> Nom | E1: =IFERROR(__xludf.DUMMYFUNCTION("""COMPUTED_VALUE"""),"Corps") -> Corps | F1: =IFERROR(__xludf.DUMMYFUNCTION("""COMPUTED_VALUE"""),"Spécialité") -> Spécialité | G1: =IFERROR(__xludf.DUMMYFUNCTION("""COMPUTED_VALUE"""),"Status") -> Status | H1: =IFERROR(__xludf.DUMMYFUNCTION("""COMPUTED_VALUE"""),"Métier") -> Métier | I1: =IFERROR(__xludf.DUMMYFUNCTION("""COMPUTED_VALUE"""),"Recrutement") -> Recrutement | J1: =IFERROR(__xludf.DUMMYFUNCTION("""COMPUTED_VALUE"""),"Jours travaillés") -> Jours travaillés | K1: =IFERROR(__xludf.DUMMYFUNCTION("""COMPUTED_VALUE"""),"") | L1: =IFERROR(__xludf.DUMMYFUNCTION("""COMPUTED_VALUE"""),"") | M1: =IFERROR(__xludf.DUMMYFUNCTION("""COMPUTED_VALUE"""),"") | N1: =IFERROR(__xludf.DUMMYFUNCTION("""COMPUTED_VALUE"""),"") | O1: =IFERROR(__xludf.DUMMYFUNCTION("""COMPUTED_VALUE"""),"") | P1: =IFERROR(__xludf.DUMMYFUNCTION("""COMPUTED_VALUE"""),"") | Q1: =IFERROR(__xludf.DUMMYFUNCTION("""COMPUTED_VALUE"""),"") | R1: =IFERROR(__xludf.DUMMYFUNCTION("""COMPUTED_VALUE"""),"") | ... Y1: =IFERROR(__xludf.DUMMYFUNCTION("""COMPUTED_VALUE"""),"") | Z1: =IFERROR(__xludf.DUMMYFUNCTION("""COMPUTED_VALUE"""),"Grade Order") -> Grade Order
A2: =IFERROR(__xludf.DUMMYFUNCTION("""COMPUTED_VALUE"""),FALSE) -> FALSE | B2: =IFERROR(__xludf.DUMMYFUNCTION("""COMPUTED_VALUE"""),"Major") -> Major | C2: =IFERROR(__xludf.DUMMYFUNCTION("""COMPUTED_VALUE"""),"Rusco") -> Rusco | E2: =IFERROR(__xludf.DUMMYFUNCTION("""COMPUTED_VALUE"""),"Bois-de-Chêne") -> Bois-de-Chêne | F2: =IFERROR(__xludf.DUMMYFUNCTION("""COMPUTED_VALUE"""),"Garde") -> Garde | G2: =IFERROR(__xludf.DUMMYFUNCTION("""COMPUTED_VALUE"""),"En service actif") -> En service actif | J2: =IFERROR(__xludf.DUMMYFUNCTION("""COMPUTED_VALUE"""),0.0) -> 0 | Z2: =IFERROR(__xludf.DUMMYFUNCTION("""COMPUTED_VALUE"""),3.0) -> 3
A3: =IFERROR(__xludf.DUMMYFUNCTION("""COMPUTED_VALUE"""),FALSE) -> FALSE | B3: =IFERROR(__xludf.DUMMYFUNCTION("""COMPUTED_VALUE"""),"Capitaine") -> Capitaine | C3: =IFERROR(__xludf.DUMMYFUNCTION("""COMPUTED_VALUE"""),"Darius") -> Darius | D3: =IFERROR(__xludf.DUMMYFUNCTION("""COMPUTED_VALUE"""),"Blacktorn") -> Blacktorn | E3: =IFERROR(__xludf.DUMMYFUNCTION("""COMPUTED_VALUE"""),"Bois-de-Chêne") -> Bois-de-Chêne | F3: =IFERROR(__xludf.DUMMYFUNCTION("""COMPUTED_VALUE"""),"Garde, Collecteur de la garde") -> Garde, Collecteur de la garde | G3: =IFERROR(__xludf.DUMMYFUNCTION("""COMPUTED_VALUE"""),"En service actif") -> En service actif | Z3: =IFERROR(__xludf.DUMMYFUNCTION("""COMPUTED_VALUE"""),4.0) -> 4

Sheet Garde de Rivebois
A1: =IFERROR(__xludf.DUMMYFUNCTION("QUERY(Effectifs!A:Z, ""SELECT * WHERE E CONTAINS 'Rivebois' ORDER BY Z ASC"", 1)"),"Assermenté") -> Assermenté | B1: =IFERROR(__xludf.DUMMYFUNCTION("""COMPUTED_VALUE"""),"Grade") -> Grade | C1: =IFERROR(__xludf.DUMMYFUNCTION("""COMPUTED_VALUE"""),"Prénom") -> Prénom | D1: =IFERROR(__xludf.DUMMYFUNCTION("""COMPUTED_VALUE"""),"Nom") -> Nom | E1: =IFERROR(__xludf.DUMMYFUNCTION("""COMPUTED_VALUE"""),"Corps") -> Corps | F1: =IFERROR(__xludf.DUMMYFUNCTION("""COMPUTED_VALUE"""),"Spécialité") -> Spécialité | G1: =IFERROR(__xludf.DUMMYFUNCTION("""COMPUTED_VALUE"""),"Status") -> Status | H1: =IFERROR(__xludf.DUMMYFUNCTION("""COMPUTED_VALUE"""),"Métier") -> Métier | I1: =IFERROR(__xludf.DUMMYFUNCTION("""COMPUTED_VALUE"""),"Recrutement") -> Recrutement | J1: =IFERROR(__xludf.DUMMYFUNCTION("""COMPUTED_VALUE"""),"Jours travaillés") -> Jours travaillés | K1: =IFERROR(__xludf.DUMMYFUNCTION("""COMPUTED_VALUE"""),"") | L1: =IFERROR(__xludf.DUMMYFUNCTION("""COMPUTED_VALUE"""),"") | M1: =IFERROR(__xludf.DUMMYFUNCTION("""COMPUTED_VALUE"""),"") | N1: =IFERROR(__xludf.DUMMYFUNCTION("""COMPUTED_VALUE"""),"") | O1: =IFERROR(__xludf.DUMMYFUNCTION("""COMPUTED_VALUE"""),"") | P1: =IFERROR(__xludf.DUMMYFUNCTION("""COMPUTED_VALUE"""),"") | Q1: =IFERROR(__xludf.DUMMYFUNCTION("""COMPUTED_VALUE"""),"") | R1: =IFERROR(__xludf.DUMMYFUNCTION("""COMPUTED_VALUE"""),"") | ... Y1: =IFERROR(__xludf.DUMMYFUNCTION("""COMPUTED_VALUE"""),"") | Z1: =IFERROR(__xludf.DUMMYFUNCTION("""COMPUTED_VALUE"""),"Grade Order") -> Grade Order
A2: =IFERROR(__xludf.DUMMYFUNCTION("""COMPUTED_VALUE"""),FALSE) -> FALSE | B2: =IFERROR(__xludf.DUMMYFUNCTION("""COMPUTED_VALUE"""),"Major") -> Major | C2: =IFERROR(__xludf.DUMMYFUNCTION("""COMPUTED_VALUE"""),"Krakan ") -> Krakan | D2: =IFERROR(__xludf.DUMMYFUNCTION("""COMPUTED_VALUE"""),"Valyn") -> Valyn | E2: =IFERROR(__xludf.DUMMYFUNCTION("""COMPUTED_VALUE"""),"Rivebois") -> Rivebois | F2: =IFERROR(__xludf.DUMMYFUNCTION("""COMPUTED_VALUE"""),"Garde") -> Garde | G2: =IFERROR(__xludf.DUMMYFUNCTION("""COMPUTED_VALUE"""),"En service actif") -> En service actif | J2: =IFERROR(__xludf.DUMMYFUNCTION("""COMPUTED_VALUE"""),0.0) -> 0 | Z2: =IFERROR(__xludf.DUMMYFUNCTION("""COMPUTED_VALUE"""),3.0) -> 3
A3: =IFERROR(__xludf.DUMMYFUNCTION("""COMPUTED_VALUE"""),FALSE) -> FALSE | B3: =IFERROR(__xludf.DUMMYFUNCTION("""COMPUTED_VALUE"""),"Capitaine") -> Capitaine | C3: =IFERROR(__xludf.DUMMYFUNCTION("""COMPUTED_VALUE"""),"Sigurd") -> Sigurd | D3: =IFERROR(__xludf.DUMMYFUNCTION("""COMPUTED_VALUE"""),"Grisetoison") -> Grisetoison | E3: =IFERROR(__xludf.DUMMYFUNCTION("""COMPUTED_VALUE"""),"Rivebois") -> Rivebois | F3: =IFERROR(__xludf.DUMMYFUNCTION("""COMPUTED_VALUE"""),"Garde, Collecteur de la garde") -> Garde, Collecteur de la garde | G3: =IFERROR(__xludf.DUMMYFUNCTION("""COMPUTED_VALUE"""),"En service actif") -> En service actif | J3: =IFERROR(__xludf.DUMMYFUNCTION("""COMPUTED_VALUE"""),4.0) -> 4 | Z3: =IFERROR(__xludf.DUMMYFUNCTION("""COMPUTED_VALUE"""),4.0) -> 4
A4: =IFERROR(__xludf.DUMMYFUNCTION("""COMPUTED_VALUE"""),FALSE) -> FALSE | B4: =IFERROR(__xludf.DUMMYFUNCTION("""COMPUTED_VALUE"""),"Lieutenant-Chef") -> Lieutenant-Chef | C4: =IFERROR(__xludf.DUMMYFUNCTION("""COMPUTED_VALUE"""),"Hakon") -> Hakon | D4: =IFERROR(__xludf.DUMMYFUNCTION("""COMPUTED_VALUE"""),"Grisetoison") -> Grisetoison | E4: =IFERROR(__xludf.DUMMYFUNCTION("""COMPUTED_VALUE"""),"Rivebois") -> Rivebois | F4: =IFERROR(__xludf.DUMMYFUNCTION("""COMPUTED_VALUE"""),"Garde, Collecteur de la garde") -> Garde, Collecteur de la garde | G4: =IFERROR(__xludf.DUMMYFUNCTION("""COMPUTED_VALUE"""),"En service actif") -> En service actif | J4: =IFERROR(__xludf.DUMMYFUNCTION("""COMPUTED_VALUE"""),5.0) -> 5 | Z4: =IFERROR(__xludf.DUMMYFUNCTION("""COMPUTED_VALUE"""),5.0) -> 5
A5: =IFERROR(__xludf.DUMMYFUNCTION("""COMPUTED_VALUE"""),TRUE) -> TRUE | B5: =IFERROR(__xludf.DUMMYFUNCTION("""COMPUTED_VALUE"""),"Lieutenant") -> Lieutenant | C5: =IFERROR(__xludf.DUMMYFUNCTION("""COMPUTED_VALUE"""),"Daric") -> Daric | E5: =IFERROR(__xludf.DUMMYFUNCTION("""COMPUTED_VALUE"""),"Rivebois") -> Rivebois | F5: =IFERROR(__xludf.DUMMYFUNCTION("""COMPUTED_VALUE"""),"Garde") -> Garde | G5: =IFERROR(__xludf.DUMMYFUNCTION("""COMPUTED_VALUE"""),"En service actif") -> En service actif | J5: =IFERROR(__xludf.DUMMYFUNCTION("""COMPUTED_VALUE"""),0.0) -> 0 | Z5: =IFERROR(__xludf.DUMMYFUNCTION("""COMPUTED_VALUE"""),6.0) -> 6
A6: =IFERROR(__xludf.DUMMYFUNCTION("""COMPUTED_VALUE"""),FALSE) -> FALSE | B6: =IFERROR(__xludf.DUMMYFUNCTION("""COMPUTED_VALUE"""),"Lieutenant") -> Lieutenant | C6: =IFERROR(__xludf.DUMMYFUNCTION("""COMPUTED_VALUE"""),"Brand") -> Brand | D6: =IFERROR(__xludf.DUMMYFUNCTION("""COMPUTED_VALUE"""),"Grisetoison") -> Grisetoison | E6: =IFERROR(__xludf.DUMMYFUNCTION("""COMPUTED_VALUE"""),"Rivebois") -> Rivebois | F6: =IFERROR(__xludf.DUMMYFUNCTION("""COMPUTED_VALUE"""),"Garde") -> Garde | G6: =IFERROR(__xludf.DUMMYFUNCTION("""COMPUTED_VALUE"""),"En service actif") -> En service actif | Z6: =IFERROR(__xludf.DUMMYFUNCTION("""COMPUTED_VALUE"""),6.0) -> 6
A7: =IFERROR(__xludf.DUMMYFUNCTION("""COMPUTED_VALUE"""),FALSE) -> FALSE | B7: =IFERROR(__xludf.DUMMYFUNCTION("""COMPUTED_VALUE"""),"Garde") -> Garde | C7: =IFERROR(__xludf.DUMMYFUNCTION("""COMPUTED_VALUE"""),"Lous") -> Lous | D7: =IFERROR(__xludf.DUMMYFUNCTION("""COMPUTED_VALUE"""),"Bois") -> Bois | E7: =IFERROR(__xludf.DUMMYFUNCTION("""COMPUTED_VALUE"""),"Rivebois") -> Rivebois | F7: =IFERROR(__xludf.DUMMYFUNCTION("""COMPUTED_VALUE"""),"Garde") -> Garde | G7: =IFERROR(__xludf.DUMMYFUNCTION("""COMPUTED_VALUE"""),"En service actif") -> En service actif | Z7: =IFERROR(__xludf.DUMMYFUNCTION("""COMPUTED_VALUE"""),11.0) -> 11

Sheet Garde de Cap Granite
A1: =IFERROR(__xludf.DUMMYFUNCTION("QUERY(Effectifs!A:Z, ""SELECT * WHERE E CONTAINS 'Granite' ORDER BY Z ASC"", 1)"),"Assermenté") -> Assermenté | B1: =IFERROR(__xludf.DUMMYFUNCTION("""COMPUTED_VALUE"""),"Grade") -> Grade | C1: =IFERROR(__xludf.DUMMYFUNCTION("""COMPUTED_VALUE"""),"Prénom") -> Prénom | D1: =IFERROR(__xludf.DUMMYFUNCTION("""COMPUTED_VALUE"""),"Nom") -> Nom | E1: =IFERROR(__xludf.DUMMYFUNCTION("""COMPUTED_VALUE"""),"Corps") -> Corps | F1: =IFERROR(__xludf.DUMMYFUNCTION("""COMPUTED_VALUE"""),"Spécialité") -> Spécialité | G1: =IFERROR(__xludf.DUMMYFUNCTION("""COMPUTED_VALUE"""),"Status") -> Status | H1: =IFERROR(__xludf.DUMMYFUNCTION("""COMPUTED_VALUE"""),"Métier") -> Métier | I1: =IFERROR(__xludf.DUMMYFUNCTION("""COMPUTED_VALUE"""),"Recrutement") -> Recrutement | J1: =IFERROR(__xludf.DUMMYFUNCTION("""COMPUTED_VALUE"""),"Jours travaillés") -> Jours travaillés | K1: =IFERROR(__xludf.DUMMYFUNCTION("""COMPUTED_VALUE"""),"") | L1: =IFERROR(__xludf.DUMMYFUNCTION("""COMPUTED_VALUE"""),"") | M1: =IFERROR(__xludf.DUMMYFUNCTION("""COMPUTED_VALUE"""),"") | N1: =IFERROR(__xludf.DUMMYFUNCTION("""COMPUTED_VALUE"""),"") | O1: =IFERROR(__xludf.DUMMYFUNCTION("""COMPUTED_VALUE"""),"") | P1: =IFERROR(__xludf.DUMMYFUNCTION("""COMPUTED_VALUE"""),"") | Q1: =IFERROR(__xludf.DUMMYFUNCTION("""COMPUTED_VALUE"""),"") | R1: =IFERROR(__xludf.DUMMYFUNCTION("""COMPUTED_VALUE"""),"") | ... Y1: =IFERROR(__xludf.DUMMYFUNCTION("""COMPUTED_VALUE"""),"") | Z1: =IFERROR(__xludf.DUMMYFUNCTION("""COMPUTED_VALUE"""),"Grade Order") -> Grade Order
A2: =IFERROR(__xludf.DUMMYFUNCTION("""COMPUTED_VALUE"""),FALSE) -> FALSE | B2: =IFERROR(__xludf.DUMMYFUNCTION("""COMPUTED_VALUE"""),"Capitaine") -> Capitaine | C2: =IFERROR(__xludf.DUMMYFUNCTION("""COMPUTED_VALUE"""),"Hastelvin") -> Hastelvin | E2: =IFERROR(__xludf.DUMMYFUNCTION("""COMPUTED_VALUE"""),"Cap Granite") -> Cap Granite | F2: =IFERROR(__xludf.DUMMYFUNCTION("""COMPUTED_VALUE"""),"Garde, Collecteur de la garde") -> Garde, Collecteur de la garde | G2: =IFERROR(__xludf.DUMMYFUNCTION("""COMPUTED_VALUE"""),"En service actif") -> En service actif | J2: =IFERROR(__xludf.DUMMYFUNCTION("""COMPUTED_VALUE"""),0.0) -> 0 | Z2: =IFERROR(__xludf.DUMMYFUNCTION("""COMPUTED_VALUE"""),4.0) -> 4
A3: =IFERROR(__xludf.DUMMYFUNCTION("""COMPUTED_VALUE"""),FALSE) -> FALSE | B3: =IFERROR(__xludf.DUMMYFUNCTION("""COMPUTED_VALUE"""),"Lieutenant-Chef") -> Lieutenant-Chef | C3: =IFERROR(__xludf.DUMMYFUNCTION("""COMPUTED_VALUE"""),"Pavis") -> Pavis | D3: =IFERROR(__xludf.DUMMYFUNCTION("""COMPUTED_VALUE"""),"Gurdalval") -> Gurdalval | E3: =IFERROR(__xludf.DUMMYFUNCTION("""COMPUTED_VALUE"""),"Cap Granite") -> Cap Granite | F3: =IFERROR(__xludf.DUMMYFUNCTION("""COMPUTED_VALUE"""),"Garde") -> Garde | G3: =IFERROR(__xludf.DUMMYFUNCTION("""COMPUTED_VALUE"""),"En service actif") -> En service actif | J3: =IFERROR(__xludf.DUMMYFUNCTION("""COMPUTED_VALUE"""),1.0) -> 1 | Z3: =IFERROR(__xludf.DUMMYFUNCTION("""COMPUTED_VALUE"""),5.0) -> 5
A4: =IFERROR(__xludf.DUMMYFUNCTION("""COMPUTED_VALUE"""),FALSE) -> FALSE | B4: =IFERROR(__xludf.DUMMYFUNCTION("""COMPUTED_VALUE"""),"Sergent-Chef") -> Sergent-Chef | C4: =IFERROR(__xludf.DUMMYFUNCTION("""COMPUTED_VALUE"""),"Starkos") -> Starkos | D4: =IFERROR(__xludf.DUMMYFUNCTION("""COMPUTED_VALUE"""),"Coeurebene") -> Coeurebene | E4: =IFERROR(__xludf.DUMMYFUNCTION("""COMPUTED_VALUE"""),"Cap Granite") -> Cap Granite | F4: =IFERROR(__xludf.DUMMYFUNCTION("""COMPUTED_VALUE"""),"Garde") -> Garde | G4: =IFERROR(__xludf.DUMMYFUNCTION("""COMPUTED_VALUE"""),"En service actif") -> En service actif | J4: =IFERROR(__xludf.DUMMYFUNCTION("""COMPUTED_VALUE"""),4.0) -> 4 | Z4: =IFERROR(__xludf.DUMMYFUNCTION("""COMPUTED_VALUE"""),7.0) -> 7
A5: =IFERROR(__xludf.DUMMYFUNCTION("""COMPUTED_VALUE"""),FALSE) -> FALSE | B5: =IFERROR(__xludf.DUMMYFUNCTION("""COMPUTED_VALUE"""),"Sergent-Chef") -> Sergent-Chef | C5: =IFERROR(__xludf.DUMMYFUNCTION("""COMPUTED_VALUE"""),"Barnabas") -> Barnabas | D5: =IFERROR(__xludf.DUMMYFUNCTION("""COMPUTED_VALUE"""),"Tharmr") -> Tharmr | E5: =IFERROR(__xludf.DUMMYFUNCTION("""COMPUTED_VALUE"""),"Cap Granite") -> Cap Granite | F5: =IFERROR(__xludf.DUMMYFUNCTION("""COMPUTED_VALUE"""),"Garde") -> Garde | G5: =IFERROR(__xludf.DUMMYFUNCTION("""COMPUTED_VALUE"""),"En service actif") -> En service actif | J5: =IFERROR(__xludf.DUMMYFUNCTION("""COMPUTED_VALUE"""),3.0) -> 3 | Z5: =IFERROR(__xludf.DUMMYFUNCTION("""COMPUTED_VALUE"""),7.0) -> 7
A6: =IFERROR(__xludf.DUMMYFUNCTION("""COMPUTED_VALUE"""),FALSE) -> FALSE | B6: =IFERROR(__xludf.DUMMYFUNCTION("""COMPUTED_VALUE"""),"Garde") -> Garde | C6: =IFERROR(__xludf.DUMMYFUNCTION("""COMPUTED_VALUE"""),"Malivor") -> Malivor | D6: =IFERROR(__xludf.DUMMYFUNCTION("""COMPUTED_VALUE"""),"Xernes") -> Xernes | E6: =IFERROR(__xludf.DUMMYFUNCTION("""COMPUTED_VALUE"""),"Cap Granite") -> Cap Granite | F6: =IFERROR(__xludf.DUMMYFUNCTION("""COMPUTED_VALUE"""),"Garde") -> Garde | G6: =IFERROR(__xludf.DUMMYFUNCTION("""COMPUTED_VALUE"""),"En service actif") -> En service actif | J6: =IFERROR(__xludf.DUMMYFUNCTION("""COMPUTED_VALUE"""),4.0) -> 4 | Z6: =IFERROR(__xludf.DUMMYFUNCTION("""COMPUTED_VALUE"""),11.0) -> 11
A7: =IFERROR(__xludf.DUMMYFUNCTION("""COMPUTED_VALUE"""),FALSE) -> FALSE | B7: =IFERROR(__xludf.DUMMYFUNCTION("""COMPUTED_VALUE"""),"Garde") -> Garde | C7: =IFERROR(__xludf.DUMMYFUNCTION("""COMPUTED_VALUE"""),"Bakhir") -> Bakhir | E7: =IFERROR(__xludf.DUMMYFUNCTION("""COMPUTED_VALUE"""),"Cap Granite") -> Cap Granite | F7: =IFERROR(__xludf.DUMMYFUNCTION("""COMPUTED_VALUE"""),"Garde") -> Garde | G7: =IFERROR(__xludf.DUMMYFUNCTION("""COMPUTED_VALUE"""),"En service actif") -> En service actif | J7: =IFERROR(__xludf.DUMMYFUNCTION("""COMPUTED_VALUE"""),0.0) -> 0 | Z7: =IFERROR(__xludf.DUMMYFUNCTION("""COMPUTED_VALUE"""),11.0) -> 11
A8: =IFERROR(__xludf.DUMMYFUNCTION("""COMPUTED_VALUE"""),FALSE) -> FALSE | B8: =IFERROR(__xludf.DUMMYFUNCTION("""COMPUTED_VALUE"""),"Garde") -> Garde | C8: =IFERROR(__xludf.DUMMYFUNCTION("""COMPUTED_VALUE"""),"Drakgor") -> Drakgor | D8: =IFERROR(__xludf.DUMMYFUNCTION("""COMPUTED_VALUE"""),"gro-Drakar") -> gro-Drakar | E8: =IFERROR(__xludf.DUMMYFUNCTION("""COMPUTED_VALUE"""),"Cap Granite") -> Cap Granite | F8: =IFERROR(__xludf.DUMMYFUNCTION("""COMPUTED_VALUE"""),"Garde") -> Garde | G8: =IFERROR(__xludf.DUMMYFUNCTION("""COMPUTED_VALUE"""),"En service actif") -> En service actif | J8: =IFERROR(__xludf.DUMMYFUNCTION("""COMPUTED_VALUE"""),0.0) -> 0 | Z8: =IFERROR(__xludf.DUMMYFUNCTION("""COMPUTED_VALUE"""),11.0) -> 11
A9: =IFERROR(__xludf.DUMMYFUNCTION("""COMPUTED_VALUE"""),FALSE) -> FALSE | B9: =IFERROR(__xludf.DUMMYFUNCTION("""COMPUTED_VALUE"""),"Recrue") -> Recrue | C9: =IFERROR(__xludf.DUMMYFUNCTION("""COMPUTED_VALUE"""),"Vranx") -> Vranx | D9: =IFERROR(__xludf.DUMMYFUNCTION("""COMPUTED_VALUE"""),"Thorgar") -> Thorgar | E9: =IFERROR(__xludf.DUMMYFUNCTION("""COMPUTED_VALUE"""),"Cap Granite") -> Cap Granite | F9: =IFERROR(__xludf.DUMMYFUNCTION("""COMPUTED_VALUE"""),"Garde") -> Garde | G9: =IFERROR(__xludf.DUMMYFUNCTION("""COMPUTED_VALUE"""),"En service actif") -> En service actif | Z9: =IFERROR(__xludf.DUMMYFUNCTION("""COMPUTED_VALUE"""),13.0) -> 13

Sheet Corps des éclaireurs
A1: =IFERROR(__xludf.DUMMYFUNCTION("QUERY(Effectifs!A:Z, ""SELECT * WHERE E CONTAINS 'Eclaireur' ORDER BY Z ASC"", 1)"),"Assermenté") -> Assermenté | B1: =IFERROR(__xludf.DUMMYFUNCTION("""COMPUTED_VALUE"""),"Grade") -> Grade | C1: =IFERROR(__xludf.DUMMYFUNCTION("""COMPUTED_VALUE"""),"Prénom") -> Prénom | D1: =IFERROR(__xludf.DUMMYFUNCTION("""COMPUTED_VALUE"""),"Nom") -> Nom | E1: =IFERROR(__xludf.DUMMYFUNCTION("""COMPUTED_VALUE"""),"Corps") -> Corps | F1: =IFERROR(__xludf.DUMMYFUNCTION("""COMPUTED_VALUE"""),"Spécialité") -> Spécialité | G1: =IFERROR(__xludf.DUMMYFUNCTION("""COMPUTED_VALUE"""),"Status") -> Status | H1: =IFERROR(__xludf.DUMMYFUNCTION("""COMPUTED_VALUE"""),"Métier") -> Métier | I1: =IFERROR(__xludf.DUMMYFUNCTION("""COMPUTED_VALUE"""),"Recrutement") -> Recrutement | J1: =IFERROR(__xludf.DUMMYFUNCTION("""COMPUTED_VALUE"""),"Jours travaillés") -> Jours travaillés | K1: =IFERROR(__xludf.DUMMYFUNCTION("""COMPUTED_VALUE"""),"") | L1: =IFERROR(__xludf.DUMMYFUNCTION("""COMPUTED_VALUE"""),"") | M1: =IFERROR(__xludf.DUMMYFUNCTION("""COMPUTED_VALUE"""),"") | N1: =IFERROR(__xludf.DUMMYFUNCTION("""COMPUTED_VALUE"""),"") | O1: =IFERROR(__xludf.DUMMYFUNCTION("""COMPUTED_VALUE"""),"") | P1: =IFERROR(__xludf.DUMMYFUNCTION("""COMPUTED_VALUE"""),"") | Q1: =IFERROR(__xludf.DUMMYFUNCTION("""COMPUTED_VALUE"""),"") | R1: =IFERROR(__xludf.DUMMYFUNCTION("""COMPUTED_VALUE"""),"") | ... Y1: =IFERROR(__xludf.DUMMYFUNCTION("""COMPUTED_VALUE"""),"") | Z1: =IFERROR(__xludf.DUMMYFUNCTION("""COMPUTED_VALUE"""),"Grade Order") -> Grade Order
A2: =IFERROR(__xludf.DUMMYFUNCTION("""COMPUTED_VALUE"""),TRUE) -> TRUE | B2: =IFERROR(__xludf.DUMMYFUNCTION("""COMPUTED_VALUE"""),"Capitaine") -> Capitaine | C2: =IFERROR(__xludf.DUMMYFUNCTION("""COMPUTED_VALUE"""),"Glaemorandir") -> Glaemorandir | D2: =IFERROR(__xludf.DUMMYFUNCTION("""COMPUTED_VALUE"""),"Oeil-Perçant") -> Oeil-Perçant | E2: =IFERROR(__xludf.DUMMYFUNCTION("""COMPUTED_VALUE"""),"Eclaireur") -> Eclaireur | F2: =IFERROR(__xludf.DUMMYFUNCTION("""COMPUTED_VALUE"""),"Eclaireur, Garde") -> Eclaireur, Garde | G2: =IFERROR(__xludf.DUMMYFUNCTION("""COMPUTED_VALUE"""),"En service actif") -> En service actif | H2: =IFERROR(__xludf.DUMMYFUNCTION("""COMPUTED_VALUE"""),"Chasseur") -> Chasseur | I2: =IFERROR(__xludf.DUMMYFUNCTION("""COMPUTED_VALUE"""),46197.0) -> 46197 | J2: =IFERROR(__xludf.DUMMYFUNCTION("""COMPUTED_VALUE"""),12.0) -> 12 | Z2: =IFERROR(__xludf.DUMMYFUNCTION("""COMPUTED_VALUE"""),4.0) -> 4
A3: =IFERROR(__xludf.DUMMYFUNCTION("""COMPUTED_VALUE"""),TRUE) -> TRUE | B3: =IFERROR(__xludf.DUMMYFUNCTION("""COMPUTED_VALUE"""),"Capitaine") -> Capitaine | C3: =IFERROR(__xludf.DUMMYFUNCTION("""COMPUTED_VALUE"""),"Clemnir") -> Clemnir | D3: =IFERROR(__xludf.DUMMYFUNCTION("""COMPUTED_VALUE"""),"Arc-Vif") -> Arc-Vif | E3: =IFERROR(__xludf.DUMMYFUNCTION("""COMPUTED_VALUE"""),"Eclaireur") -> Eclaireur | F3: =IFERROR(__xludf.DUMMYFUNCTION("""COMPUTED_VALUE"""),"Eclaireur") -> Eclaireur | G3: =IFERROR(__xludf.DUMMYFUNCTION("""COMPUTED_VALUE"""),"Mort en service actif") -> Mort en service actif | H3: =IFERROR(__xludf.DUMMYFUNCTION("""COMPUTED_VALUE"""),"Chasseur") -> Chasseur | J3: =IFERROR(__xludf.DUMMYFUNCTION("""COMPUTED_VALUE"""),0.0) -> 0 | Z3: =IFERROR(__xludf.DUMMYFUNCTION("""COMPUTED_VALUE"""),4.0) -> 4
A4: =IFERROR(__xludf.DUMMYFUNCTION("""COMPUTED_VALUE"""),TRUE) -> TRUE | B4: =IFERROR(__xludf.DUMMYFUNCTION("""COMPUTED_VALUE"""),"Sergent-Chef") -> Sergent-Chef | C4: =IFERROR(__xludf.DUMMYFUNCTION("""COMPUTED_VALUE"""),"Magnar") -> Magnar | D4: =IFERROR(__xludf.DUMMYFUNCTION("""COMPUTED_VALUE"""),"Traquebrume") -> Traquebrume | E4: =IFERROR(__xludf.DUMMYFUNCTION("""COMPUTED_VALUE"""),"Eclaireur") -> Eclaireur | F4: =IFERROR(__xludf.DUMMYFUNCTION("""COMPUTED_VALUE"""),"Eclaireur, Garde") -> Eclaireur, Garde | G4: =IFERROR(__xludf.DUMMYFUNCTION("""COMPUTED_VALUE"""),"En service actif") -> En service actif | H4: =IFERROR(__xludf.DUMMYFUNCTION("""COMPUTED_VALUE"""),"Chasseur") -> Chasseur | I4: =IFERROR(__xludf.DUMMYFUNCTION("""COMPUTED_VALUE"""),46190.0) -> 46190 | J4: =IFERROR(__xludf.DUMMYFUNCTION("""COMPUTED_VALUE"""),10.0) -> 10 | Z4: =IFERROR(__xludf.DUMMYFUNCTION("""COMPUTED_VALUE"""),7.0) -> 7
A5: =IFERROR(__xludf.DUMMYFUNCTION("""COMPUTED_VALUE"""),TRUE) -> TRUE | B5: =IFERROR(__xludf.DUMMYFUNCTION("""COMPUTED_VALUE"""),"Garde") -> Garde | C5: =IFERROR(__xludf.DUMMYFUNCTION("""COMPUTED_VALUE"""),"Pethiceor") -> Pethiceor | D5: =IFERROR(__xludf.DUMMYFUNCTION("""COMPUTED_VALUE"""),"Le Borgne") -> Le Borgne | E5: =IFERROR(__xludf.DUMMYFUNCTION("""COMPUTED_VALUE"""),"Eclaireur") -> Eclaireur | F5: =IFERROR(__xludf.DUMMYFUNCTION("""COMPUTED_VALUE"""),"Eclaireur, Garde") -> Eclaireur, Garde | G5: =IFERROR(__xludf.DUMMYFUNCTION("""COMPUTED_VALUE"""),"Mis en réserve") -> Mis en réserve | H5: =IFERROR(__xludf.DUMMYFUNCTION("""COMPUTED_VALUE"""),"Chasseur") -> Chasseur | I5: =IFERROR(__xludf.DUMMYFUNCTION("""COMPUTED_VALUE"""),46197.0) -> 46197 | J5: =IFERROR(__xludf.DUMMYFUNCTION("""COMPUTED_VALUE"""),0.0) -> 0 | Z5: =IFERROR(__xludf.DUMMYFUNCTION("""COMPUTED_VALUE"""),11.0) -> 11
A6: =IFERROR(__xludf.DUMMYFUNCTION("""COMPUTED_VALUE"""),TRUE) -> TRUE | B6: =IFERROR(__xludf.DUMMYFUNCTION("""COMPUTED_VALUE"""),"Garde") -> Garde | C6: =IFERROR(__xludf.DUMMYFUNCTION("""COMPUTED_VALUE"""),"Laureen") -> Laureen | D6: =IFERROR(__xludf.DUMMYFUNCTION("""COMPUTED_VALUE"""),"Toison-de-Sang") -> Toison-de-Sang | E6: =IFERROR(__xludf.DUMMYFUNCTION("""COMPUTED_VALUE"""),"Eclaireur") -> Eclaireur | F6: =IFERROR(__xludf.DUMMYFUNCTION("""COMPUTED_VALUE"""),"Eclaireur, Garde") -> Eclaireur, Garde | G6: =IFERROR(__xludf.DUMMYFUNCTION("""COMPUTED_VALUE"""),"En service actif") -> En service actif | H6: =IFERROR(__xludf.DUMMYFUNCTION("""COMPUTED_VALUE"""),"Chasseur") -> Chasseur | I6: =IFERROR(__xludf.DUMMYFUNCTION("""COMPUTED_VALUE"""),46249.0) -> 46249 | J6: =IFERROR(__xludf.DUMMYFUNCTION("""COMPUTED_VALUE"""),11.0) -> 11 | Z6: =IFERROR(__xludf.DUMMYFUNCTION("""COMPUTED_VALUE"""),11.0) -> 11
A7: =IFERROR(__xludf.DUMMYFUNCTION("""COMPUTED_VALUE"""),FALSE) -> FALSE | B7: =IFERROR(__xludf.DUMMYFUNCTION("""COMPUTED_VALUE"""),"Recrue") -> Recrue | C7: =IFERROR(__xludf.DUMMYFUNCTION("""COMPUTED_VALUE"""),"Ma'arl") -> Ma'arl | E7: =IFERROR(__xludf.DUMMYFUNCTION("""COMPUTED_VALUE"""),"Eclaireur") -> Eclaireur | F7: =IFERROR(__xludf.DUMMYFUNCTION("""COMPUTED_VALUE"""),"Eclaireur, Garde") -> Eclaireur, Garde | G7: =IFERROR(__xludf.DUMMYFUNCTION("""COMPUTED_VALUE"""),"En service actif") -> En service actif | H7: =IFERROR(__xludf.DUMMYFUNCTION("""COMPUTED_VALUE"""),"Mineur") -> Mineur | I7: =IFERROR(__xludf.DUMMYFUNCTION("""COMPUTED_VALUE"""),46259.0) -> 46259 | J7: =IFERROR(__xludf.DUMMYFUNCTION("""COMPUTED_VALUE"""),0.0) -> 0 | Z7: =IFERROR(__xludf.DUMMYFUNCTION("""COMPUTED_VALUE"""),13.0) -> 13
A8: =IFERROR(__xludf.DUMMYFUNCTION("""COMPUTED_VALUE"""),FALSE) -> FALSE | B8: =IFERROR(__xludf.DUMMYFUNCTION("""COMPUTED_VALUE"""),"Recrue") -> Recrue | C8: =IFERROR(__xludf.DUMMYFUNCTION("""COMPUTED_VALUE"""),"Do'Rhazir") -> Do'Rhazir | E8: =IFERROR(__xludf.DUMMYFUNCTION("""COMPUTED_VALUE"""),"Eclaireur") -> Eclaireur | F8: =IFERROR(__xludf.DUMMYFUNCTION("""COMPUTED_VALUE"""),"Eclaireur, Garde") -> Eclaireur, Garde | G8: =IFERROR(__xludf.DUMMYFUNCTION("""COMPUTED_VALUE"""),"En service actif") -> En service actif | H8: =IFERROR(__xludf.DUMMYFUNCTION("""COMPUTED_VALUE"""),"Menuisier-Charbonnier") -> Menuisier-Charbonnier | I8: =IFERROR(__xludf.DUMMYFUNCTION("""COMPUTED_VALUE"""),46261.0) -> 46261 | J8: =IFERROR(__xludf.DUMMYFUNCTION("""COMPUTED_VALUE"""),0.0) -> 0 | Z8: =IFERROR(__xludf.DUMMYFUNCTION("""COMPUTED_VALUE"""),13.0) -> 13
A9: =IFERROR(__xludf.DUMMYFUNCTION("""COMPUTED_VALUE"""),FALSE) -> FALSE | B9: =IFERROR(__xludf.DUMMYFUNCTION("""COMPUTED_VALUE"""),"Recrue") -> Recrue | C9: =IFERROR(__xludf.DUMMYFUNCTION("""COMPUTED_VALUE"""),"Ri'Jhan") -> Ri'Jhan | D9: =IFERROR(__xludf.DUMMYFUNCTION("""COMPUTED_VALUE"""),"MoonShadow") -> MoonShadow | E9: =IFERROR(__xludf.DUMMYFUNCTION("""COMPUTED_VALUE"""),"Eclaireur") -> Eclaireur | F9: =IFERROR(__xludf.DUMMYFUNCTION("""COMPUTED_VALUE"""),"Garde, Eclaireur") -> Garde, Eclaireur | G9: =IFERROR(__xludf.DUMMYFUNCTION("""COMPUTED_VALUE"""),"En service actif") -> En service actif | I9: =IFERROR(__xludf.DUMMYFUNCTION("""COMPUTED_VALUE"""),46266.0) -> 46266 | J9: =IFERROR(__xludf.DUMMYFUNCTION("""COMPUTED_VALUE"""),3.0) -> 3 | Z9: =IFERROR(__xludf.DUMMYFUNCTION("""COMPUTED_VALUE"""),13.0) -> 13

Sheet Données
A1: Grades | E1: Spécialité | G1: Corps | I1: Status | K1: Métier | M1: Element de ravitaillement | O1: =IFERROR(__xludf.DUMMYFUNCTION("SORT(FILTER(Effectifs!C2:C1000&"" ""&Effectifs!D2:D1000,Effectifs!C2:C1000<>"""",Effectifs!G2:G1000=""En service actif""))"),"Al'Dran ") -> Al'Dran
A2: Maréchal | C2: {=IF(A2:A1000="",,MATCH(A2:A1000,'Données'!A$2:A1000,0))} -> 1 | E2: Hird | G2: Etat-Major | I2: En service actif | K2: Guerrier | M2: Vegetal Soup | O2: =IFERROR(__xludf.DUMMYFUNCTION("""COMPUTED_VALUE"""),"Aldric Cendre-coeur") -> Aldric Cendre-coeur
A3: Commander | C3: 2 | E3: Garde | G3: Cité de Blancherive | I3: Mis en réserve | K3: Chasseur | M3: Beef Stew | O3: =IFERROR(__xludf.DUMMYFUNCTION("""COMPUTED_VALUE"""),"Andor Viraes") -> Andor Viraes
A4: Major | C4: 3 | E4: Eclaireur | G4: Faubourgs de Blancherive | I4: Mort en service actif | K4: Enchenteur | M4: Venison Stew | O4: =IFERROR(__xludf.DUMMYFUNCTION("""COMPUTED_VALUE"""),"Armand De Valclair") -> Armand De Valclair
A5: Capitaine | C5: 4 | E5: Intendant de la garde | G5: Rivebois | I5: Radié du service actif | K5: Alchimiste | O5: =IFERROR(__xludf.DUMMYFUNCTION("""COMPUTED_VALUE"""),"Astrid Lame-Fine") -> Astrid Lame-Fine
A6: Lieutenant-Chef | C6: 5 | E6: Instructeur | G6: Bois-de-Chêne | I6: Déserteur | K6: Mineur | O6: =IFERROR(__xludf.DUMMYFUNCTION("""COMPUTED_VALUE"""),"Astrild ") -> Astrild
A7: Lieutenant | C7: 6 | E7: Tortionnaire | G7: Cap Granite | I7: Démissionnaire | K7: Couturier | O7: =IFERROR(__xludf.DUMMYFUNCTION("""COMPUTED_VALUE"""),"Bakhir ") -> Bakhir
A8: Sergent-Chef | C8: 7 | E8: Collecteur de la garde | G8: Eclaireur | K8: Menuisier-Charbonnier | O8: =IFERROR(__xludf.DUMMYFUNCTION("""COMPUTED_VALUE"""),"Barnabas Tharmr") -> Barnabas Tharmr
A9: Sergent | C9: 8 | G9: Hird du Jarl | O9: =IFERROR(__xludf.DUMMYFUNCTION("""COMPUTED_VALUE"""),"Bernis ") -> Bernis
A10: Caporal-Chef | C10: 9 | O10: =IFERROR(__xludf.DUMMYFUNCTION("""COMPUTED_VALUE"""),"Bjorn Kornseen") -> Bjorn Kornseen
A11: Caporal | C11: 10 | O11: =IFERROR(__xludf.DUMMYFUNCTION("""COMPUTED_VALUE"""),"Brand Grisetoison") -> Brand Grisetoison
A12: Garde | C12: 11 | O12: =IFERROR(__xludf.DUMMYFUNCTION("""COMPUTED_VALUE"""),"Daric ") -> Daric
A13: Cadet | C13: 12 | O13: =IFERROR(__xludf.DUMMYFUNCTION("""COMPUTED_VALUE"""),"Darina ") -> Darina
A14: Recrue | C14: 13 | O14: =IFERROR(__xludf.DUMMYFUNCTION("""COMPUTED_VALUE"""),"Darius Blacktorn") -> Darius Blacktorn
O15: =IFERROR(__xludf.DUMMYFUNCTION("""COMPUTED_VALUE"""),"Do'Rhazir ") -> Do'Rhazir
O16: =IFERROR(__xludf.DUMMYFUNCTION("""COMPUTED_VALUE"""),"Drakgor gro-Drakar") -> Drakgor gro-Drakar | R16: :C&" "
O17: =IFERROR(__xludf.DUMMYFUNCTION("""COMPUTED_VALUE"""),"Eldrim Hache-Grise") -> Eldrim Hache-Grise
O18: =IFERROR(__xludf.DUMMYFUNCTION("""COMPUTED_VALUE"""),"Encore-Un-Espoir ") -> Encore-Un-Espoir
O19: =IFERROR(__xludf.DUMMYFUNCTION("""COMPUTED_VALUE"""),"Erwan ") -> Erwan
O20: =IFERROR(__xludf.DUMMYFUNCTION("""COMPUTED_VALUE"""),"Faynir ") -> Faynir
O21: =IFERROR(__xludf.DUMMYFUNCTION("""COMPUTED_VALUE"""),"Filoki ") -> Filoki
O22: =IFERROR(__xludf.DUMMYFUNCTION("""COMPUTED_VALUE"""),"Gisbern Isenbjorn") -> Gisbern Isenbjorn
O23: =IFERROR(__xludf.DUMMYFUNCTION("""COMPUTED_VALUE"""),"Glaemorandir Oeil-Perçant") -> Glaemorandir Oeil-Perçant
O24: =IFERROR(__xludf.DUMMYFUNCTION("""COMPUTED_VALUE"""),"Gorbash Tête-de-Pierre") -> Gorbash Tête-de-Pierre
O25: =IFERROR(__xludf.DUMMYFUNCTION("""COMPUTED_VALUE"""),"Gorvin Le-Moite") -> Gorvin Le-Moite
O26: =IFERROR(__xludf.DUMMYFUNCTION("""COMPUTED_VALUE"""),"Gronk Grognon") -> Gronk Grognon
O27: =IFERROR(__xludf.DUMMYFUNCTION("""COMPUTED_VALUE"""),"Hakon Grisetoison") -> Hakon Grisetoison
O28: =IFERROR(__xludf.DUMMYFUNCTION("""COMPUTED_VALUE"""),"Hastelvin ") -> Hastelvin
O29: =IFERROR(__xludf.DUMMYFUNCTION("""COMPUTED_VALUE"""),"Il-draz De Chasse-au-bois") -> Il-draz De Chasse-au-bois
O30: =IFERROR(__xludf.DUMMYFUNCTION("""COMPUTED_VALUE"""),"Ilflynn ") -> Ilflynn
O31: =IFERROR(__xludf.DUMMYFUNCTION("""COMPUTED_VALUE"""),"Ina'ra ") -> Ina'ra
O32: =IFERROR(__xludf.DUMMYFUNCTION("""COMPUTED_VALUE"""),"Jeebam-dee ") -> Jeebam-dee
O33: =IFERROR(__xludf.DUMMYFUNCTION("""COMPUTED_VALUE"""),"Kah-Shir Sombre Griffe") -> Kah-Shir Sombre Griffe
O34: =IFERROR(__xludf.DUMMYFUNCTION("""COMPUTED_VALUE"""),"Kendall Delamare") -> Kendall Delamare
O35: =IFERROR(__xludf.DUMMYFUNCTION("""COMPUTED_VALUE"""),"Krakan Valyn") -> Krakan Valyn
O36: =IFERROR(__xludf.DUMMYFUNCTION("""COMPUTED_VALUE"""),"Kronk Grognon") -> Kronk Grognon
O37: =IFERROR(__xludf.DUMMYFUNCTION("""COMPUTED_VALUE"""),"Laureen Toison-de-Sang") -> Laureen Toison-de-Sang
O38: =IFERROR(__xludf.DUMMYFUNCTION("""COMPUTED_VALUE"""),"Lazabard Jemelred") -> Lazabard Jemelred
O39: =IFERROR(__xludf.DUMMYFUNCTION("""COMPUTED_VALUE"""),"Léonce Réve-épine") -> Léonce Réve-épine
O40: =IFERROR(__xludf.DUMMYFUNCTION("""COMPUTED_VALUE"""),"Lokh Tar") -> Lokh Tar
O41: =IFERROR(__xludf.DUMMYFUNCTION("""COMPUTED_VALUE"""),"Lous Bois") -> Lous Bois
O42: =IFERROR(__xludf.DUMMYFUNCTION("""COMPUTED_VALUE"""),"Lucius Ravenshield") -> Lucius Ravenshield
O43: =IFERROR(__xludf.DUMMYFUNCTION("""COMPUTED_VALUE"""),"Ma'arl ") -> Ma'arl
O44: =IFERROR(__xludf.DUMMYFUNCTION("""COMPUTED_VALUE"""),"Magnar Traquebrume") -> Magnar Traquebrume
O45: =IFERROR(__xludf.DUMMYFUNCTION("""COMPUTED_VALUE"""),"Malivor Xernes") -> Malivor Xernes
O46: =IFERROR(__xludf.DUMMYFUNCTION("""COMPUTED_VALUE"""),"Njalda ") -> Njalda
O47: =IFERROR(__xludf.DUMMYFUNCTION("""COMPUTED_VALUE"""),"Pavis Gurdalval") -> Pavis Gurdalval
O48: =IFERROR(__xludf.DUMMYFUNCTION("""COMPUTED_VALUE"""),"Ri'Jhan MoonShadow") -> Ri'Jhan MoonShadow
O49: =IFERROR(__xludf.DUMMYFUNCTION("""COMPUTED_VALUE"""),"Ronin ") -> Ronin
O50: =IFERROR(__xludf.DUMMYFUNCTION("""COMPUTED_VALUE"""),"Rorik Marche-Hiver") -> Rorik Marche-Hiver
O51: =IFERROR(__xludf.DUMMYFUNCTION("""COMPUTED_VALUE"""),"Rusco ") -> Rusco
O52: =IFERROR(__xludf.DUMMYFUNCTION("""COMPUTED_VALUE"""),"S'Khar ") -> S'Khar
O53: =IFERROR(__xludf.DUMMYFUNCTION("""COMPUTED_VALUE"""),"Si'Yara dite Fou") -> Si'Yara dite Fou
O54: =IFERROR(__xludf.DUMMYFUNCTION("""COMPUTED_VALUE"""),"Sigurd Grisetoison") -> Sigurd Grisetoison
O55: =IFERROR(__xludf.DUMMYFUNCTION("""COMPUTED_VALUE"""),"Smaug ") -> Smaug
O56: =IFERROR(__xludf.DUMMYFUNCTION("""COMPUTED_VALUE"""),"Starkos Coeurebene") -> Starkos Coeurebene
O57: =IFERROR(__xludf.DUMMYFUNCTION("""COMPUTED_VALUE"""),"Theodrek Heid") -> Theodrek Heid
O58: =IFERROR(__xludf.DUMMYFUNCTION("""COMPUTED_VALUE"""),"Thorin Rivegel") -> Thorin Rivegel
O59: =IFERROR(__xludf.DUMMYFUNCTION("""COMPUTED_VALUE"""),"Torald Brise-Roche") -> Torald Brise-Roche
O60: =IFERROR(__xludf.DUMMYFUNCTION("""COMPUTED_VALUE"""),"Ulfar ") -> Ulfar
O61: =IFERROR(__xludf.DUMMYFUNCTION("""COMPUTED_VALUE"""),"Varaa Uzgar") -> Varaa Uzgar
O62: =IFERROR(__xludf.DUMMYFUNCTION("""COMPUTED_VALUE"""),"Vranx Thorgar") -> Vranx Thorgar
O63: =IFERROR(__xludf.DUMMYFUNCTION("""COMPUTED_VALUE"""),"Wulfgar Durrock") -> Wulfgar Durrock
O64: =IFERROR(__xludf.DUMMYFUNCTION("""COMPUTED_VALUE"""),"Zeid Le Brise-Lames") -> Zeid Le Brise-Lames

Sheet SyncCodex
A1: Source | B1: Article | C1: Titre | D1: Classification | E1: Amende | F1: Travaux forcés (heures) | G1: Cachot (heures) | H1: Sanction complète | I1: Texte | J1: Alerte parsing | L1: Dropdown Amende | M1: Montant | N1: Dropdown Prison | O1: Cachot (heures) | P1: Dropdown Garde
A2: Codex Judiciaire de Blancherive | B2: Préambule | C2: Préambule | I2: CHÂTELLERIE DE BLANCHERIVE CODEX JUDICIAIRE DE BLANCHERIVE Code pénal de la Châtellerie de Blancherive Par l’autorité du Jarl Lucius Haldor, Seigneur des terres de Blancherive, Sous l’autorité de l’Empereur de Tamriel et dans le respect des prérogatives de l’Empire, Conformément au Corpus Juriscivilis Imperialis, au Corpus Proceduralis Imperialis, au Codex Penitus Imperialis et au De Re Nobilitatis, Considérant que : le Jarl est Seigneur des terres de la Châtellerie, protecteur du peuple et gardien des serments prêtés sous son autorité ; la paix, la justice et la prospérité du domaine reposent sur des lois connues de tous, claires dans leur énoncé et prévisibles dans leur application ; le droit propre de la Châtellerie s’est constitué par sédimentation successive, au prix de redites, de renvois incertains et de dispositions divergentes qu’il convient d’unifier ; le Corpus Juriscivilis Imperialis autorise les châtelleries à promulguer des lois supplémentaires conformes à leurs coutumes, dans le respect de ses dispositions ; nulle coutume locale ne saurait prévaloir sur le droit impérial, ni sur les compétences réservées aux juridictions de l’Empire ; il convient de refondre en un texte unique l’ensemble des incriminations applicables sur le territoire de la Châtellerie ; Le Jarl de Blancherive décrète ce qui suit : Titre préliminaire — Dispositions générales | L2: Art. 6 — Des sanctions | N2: Art. 6 — Des sanctions | P2: Al'Dran
A3: Codex Judiciaire de Blancherive | B3: 1 | C3: De l’autorité du Jarl | I3: Le Jarl est Seigneur des terres de la Châtellerie, protecteur du peuple et gardien des serments prêtés sous son autorité. Il veille à la paix, à la justice et à la prospérité de son domaine. Il est la plus haute autorité civile, militaire et judiciaire de la Châtellerie. Les serments prêtés en son nom possèdent valeur juridique et morale. Cette autorité s’exerce dans le respect du droit impérial et des compétences réservées à l’Empire. | L3: Art. 8 — De la tentative et de la complicité | N3: Art. 8 — De la tentative et de la complicité | P3: Aldric Cendre-coeur
A4: Codex Judiciaire de Blancherive | B4: 2 | C4: Du champ d’application | I4: Le présent Codex s’applique à l’ensemble des habitants, résidents, passants et visiteurs se trouvant sur le territoire de la Châtellerie de Blancherive. L’ignorance des présentes dispositions ne saurait constituer un moyen de défense. | L4: Art. 15 — Des menaces | M4: 250 | N4: Art. 23 — Des violences et agressions aggravées | O4: 2 | P4: Andor Viraes
A5: Codex Judiciaire de Blancherive | B5: 3 | C5: De la constitution d’une infraction | D5: Infraction | I5: Une infraction n’est constituée que si trois éléments sont réunis : un élément légal : un texte prévoit et interdit le comportement en cause ; un élément matériel : un acte ou un fait concret a été commis ou tenté ; un élément moral : l’auteur a agi volontairement ou en connaissance de cause. À défaut de l’un de ces éléments, aucune infraction ne peut être retenue. | L5: Art. 16 — Des menaces aggravées | M5: 500 | N5: Art. 24 — De la séquestration, de l’enlèvement et de la prise d’otage | O5: 3 | P5: Armand De Valclair
A6: Codex Judiciaire de Blancherive | B6: 4 | C6: De la classification des infractions | I6: Les infractions sont classées selon leur gravité, conformément au Corpus Juriscivilis Imperialis : contraventions : infractions mineures, jusqu’à cinq cents (500) septims ; délits : infractions de gravité moyenne, de cinq cents (500) à deux mille cinq cents (2500) septims ; crimes : infractions les plus graves, au-delà de deux mille cinq cents (2500) septims. Lorsque la valeur du préjudice détermine la qualification, celle-ci est appréciée selon les seuils ci-dessus. | L6: Art. 17 — De la rébellion | M6: 100 | N6: Art. 25 — De la séquestration aggravée | O6: 3 | P6: Astrid Lame-Fine
A7: Codex Judiciaire de Blancherive | B7: 5 | C7: De la présomption de culpabilité | D7: Infraction | I7: La culpabilité d’une personne est établie conformément aux règles prévues par le Corpus Proceduralis Imperialis et par le présent Codex. La Cour apprécie l’ensemble des éléments constitutifs de l’infraction, notamment ses éléments légal, matériel et moral, tels que définis à l’article 3. Aucun de ces éléments ne saurait, sauf disposition expresse du présent Codex, être considéré comme prépondérant sur les autres. La culpabilité ne peut être retenue qu’au terme de l’examen des faits et des preuves selon la procédure applicable. | L7: Art. 18 — Du chantage | M7: 250 | N7: Art. 27 — De l’homicide volontaire | O7: 3 | P7: Astrild
A8: Codex Judiciaire de Blancherive | B8: 6 | C8: Des sanctions | I8: Peuvent être prononcées, selon les circonstances et la gravité des faits : l’amende, la réparation ou la restitution, les travaux forcés, les travaux d’intérêt général, le cachot, la saisie ou confiscation de biens, le bannissement du territoire de la Châtellerie et, dans les cas expressément prévus, la peine de mort. La peine de mort ne peut être prononcée qu’à l’issue d’un verdict public et motivé du magistrat, conformément à l’article 11 du Corpus Proceduralis Imperialis. En cas d’insolvabilité réelle, l’amende peut être convertie en travaux forcés, en travaux d’intérêt général ou en saisie de biens. | J8: La sanction comporte une mesure non numérique. Peine capitale mentionnée. | L8: Art. 21 — De la mise en danger de la vie d’autrui | M8: 500 | N8: Art. 28 — De l’assassinat | O8: 5 | P8: Bakhir
A9: Codex Judiciaire de Blancherive | B9: 7 | C9: De la récidive | I9: En cas de récidive, la peine encourue est multipliée par deux. La récidive se compte à partir du jour de la dernière condamnation, constatée au registre judiciaire de la Cour. | L9: Art. 22 — Des violences et agressions simples | M9: 550 | N9: Art. 29 — De la torture, de la mutilation et de la barbarie | O9: 5 | P9: Barnabas Tharmr
A10: Codex Judiciaire de Blancherive | B10: 8 | C10: De la tentative et de la complicité | D10: Infraction | I10: La tentative est constituée dès lors que, manifestée par un commencement d’exécution, elle n’a pas été suspendue volontairement ou a manqué son effet. Elle est sanctionnée comme l’infraction consommée. Est complice quiconque, sciemment, par aide, assistance, don, promesse, menace, ordre ou abus d’autorité, a facilité la préparation ou la consommation d’une infraction, ou a omis de dénoncer ce dont il a été témoin. La complicité est sanctionnée comme le fait de l’auteur. | J10: Peine capitale mentionnée. | L10: Art. 23 — Des violences et agressions aggravées | N10: Art. 30 — De la torture aggravée | O10: 5 | P10: Bernis
A11: Codex Judiciaire de Blancherive | B11: 9 | C11: Des circonstances aggravantes générales | I11: Constituent des circonstances aggravantes, lorsque l’article applicable le prévoit ou lorsque le magistrat les retient expressément : la commission à main armée ou avec usage de magie ; la commission en réunion, soit par deux auteurs ou plus ; la commission à l’encontre d’un représentant de l’Empire, d’un membre de la Garde ou d’un dépositaire de l’autorité dans l’exercice de ses fonctions ; la commission à l’encontre d’une personne vulnérable, d’un enfant ou d’un prêtre des Huit Divins ; la préméditation ; la mutilation ou l’atteinte durable à l’intégrité de la victime ; la commission dans l’enceinte du Temple de Kynareth ou de tout lieu consacré. Titre I — Des garanties fondamentales | L11: Art. 24 — De la séquestration, de l’enlèvement et de la prise d’otage | M11: 650 | N11: Art. 32 — De la destruction ou dégradation de bien public | P11: Bjorn Kornseen
A12: Codex Judiciaire de Blancherive | B12: 10 | C12: Du droit à un procès équitable | D12: Infraction | I12: Toute personne accusée d’une infraction a le droit d’être entendue devant une autorité compétente et de présenter sa défense, en produisant témoins et preuves lorsque ceux-ci existent. Nul ne peut être condamné sans avoir eu la possibilité de répondre aux accusations portées contre lui. | L12: Art. 25 — De la séquestration aggravée | M12: 800 | N12: Art. 33 — De la destruction ou dégradation de bien privé | P12: Brand Grisetoison
A13: Codex Judiciaire de Blancherive | B13: 11 | C13: Du serment devant les Divins | I13: Toute personne prêtant serment devant les Divins est tenue de dire la vérité. Le serment possède une valeur sacrée : le trompeur offense les hommes et les Divins. Le faux témoignage ou le mensonge sous serment est réprimé au titre du parjure, prévu à l’article 80 du présent Codex. | L13: Art. 26 — De l’homicide involontaire | M13: 800 | N13: Art. 34 — De l’intrusion en propriété privée extérieure | O13: 0.5 | P13: Daric
A14: Codex Judiciaire de Blancherive | B14: 12 | C14: Du duel judiciaire | I14: Les crimes de sang peuvent, avec l’autorisation du Jarl ou du juge compétent, être soumis à un duel judiciaire lorsque les preuves sont insuffisantes ou que les deux parties en acceptent le principe. Cette ancienne coutume nordique ne constitue pas un droit et demeure une procédure exceptionnelle. | L14: Art. 27 — De l’homicide volontaire | M14: 1000 | N14: Art. 35 — De l’intrusion en propriété privée intérieure | O14: 1 | P14: Darina
A15: Codex Judiciaire de Blancherive | B15: 13 | C15: Du droit d’asile religieux | D15: Délit | I15: Les prêtres des temples reconnus par la Châtellerie peuvent accorder un asile temporaire aux personnes poursuivies injustement, dans l’attente d’une décision des autorités compétentes. Cet asile ne constitue pas une immunité. Il ne fait obstacle ni à une arrestation en cas de flagrant délit, ni aux infractions relevant de la compétence exclusive des juridictions impériales. Titre II — Des atteintes aux personnes | L15: Art. 28 — De l’assassinat | M15: 1200 | N15: Art. 36 — De l’intrusion aggravée | O15: 1 | P15: Darius Blacktorn
A16: Codex Judiciaire de Blancherive | B16: 14 | C16: De l’usurpation d’identité | D16: Délit | H16: Sanction — appréciation de la Cour ; niveau délictuel en cas d’usurpation d’une qualité noble ou d’une fonction officielle. | I16: Constitue une usurpation d’identité le fait de se faire passer pour autrui afin d’obtenir un avantage ou d’échapper à ses obligations. [Contravention] L’infraction devient un délit lorsqu’elle porte sur une qualité noble ou une fonction officielle. Sanction — appréciation de la Cour ; niveau délictuel en cas d’usurpation d’une qualité noble ou d’une fonction officielle. | L16: Art. 29 — De la torture, de la mutilation et de la barbarie | M16: 800 | N16: Art. 37 — Du vol simple | P16: Do'Rhazir
A17: Codex Judiciaire de Blancherive | B17: 15 | C17: Des menaces | D17: Contravention | E17: 250 | F17: 1 | H17: Sanction — 250 septims et 1 heure de travaux forcés. | I17: Constitue une menace toute parole, écrit ou geste annonçant à autrui un mal à venir. [Contravention] Sanction — 250 septims et 1 heure de travaux forcés. | L17: Art. 30 — De la torture aggravée | M17: 1000 | N17: Art. 44 — Des ouvrages publics | P17: Drakgor gro-Drakar
A18: Codex Judiciaire de Blancherive | B18: 16 | C18: Des menaces aggravées | D18: Délit | E18: 500 | F18: 3 | H18: Sanction — 500 septims, 3 heures de travaux forcés et, si l’auteur exerce une fonction publique, radiation de celle-ci. | I18: La menace est aggravée lorsqu’elle vise la famille de la victime, une personne vulnérable, une personne en raison de sa race ou de sa foi envers les Huit Divins, un dépositaire de l’autorité ou un prêtre, ou lorsqu’elle est proférée à main armée ou avec usage de magie. [Délit] Sanction — 500 septims, 3 heures de travaux forcés et, si l’auteur exerce une fonction publique, radiation de celle-ci. | L18: Art. 32 — De la destruction ou dégradation de bien public | N18: Art. 46 — De la violation de la propriété de la Châtellerie | P18: Eldrim Hache-Grise
A19: Codex Judiciaire de Blancherive | B19: 17 | C19: De la rébellion | D19: Délit | E19: 100 | F19: 1 | H19: Sanction — 100 septims et 1 heure de travaux forcés ; qualification délictuelle et sanction aggravée en cas de refus violent ou actif. | I19: Constitue une rébellion le refus opposé à une injonction d’un garde ou d’un dépositaire de la loi. Le refus non violent constitue une contravention ; le refus violent ou actif constitue un délit. Sanction — 100 septims et 1 heure de travaux forcés ; qualification délictuelle et sanction aggravée en cas de refus violent ou actif. | L19: Art. 33 — De la destruction ou dégradation de bien privé | N19: Art. 47 — De la corruption passive | O19: 3 | P19: Encore-Un-Espoir
A20: Codex Judiciaire de Blancherive | B20: 18 | C20: Du chantage | D20: Contravention | E20: 250 | F20: 1 | H20: Sanction — 250 septims et 1 heure de travaux forcés. | I20: Constitue un chantage la pression exercée sur autrui en vue d’obtenir un avantage. [Contravention] Sanction — 250 septims et 1 heure de travaux forcés. | L20: Art. 34 — De l’intrusion en propriété privée extérieure | M20: 50 | N20: Art. 48 — De la corruption active | O20: 2 | P20: Erwan
A21: Codex Judiciaire de Blancherive | B21: 19 | C21: De la diffamation | D21: Contravention | F21: 1 | H21: Sanction — réparation du dommage et 1 heure de travaux forcés. | I21: Constitue une diffamation l’atteinte portée à la réputation d’autrui par des propos mensongers ou dommageables. [Contravention] Sanction — réparation du dommage et 1 heure de travaux forcés. | L21: Art. 35 — De l’intrusion en propriété privée intérieure | M21: 500 | N21: Art. 49 — De l’abus de pouvoir public | O21: 2 | P21: Faynir
A22: Codex Judiciaire de Blancherive | B22: 20 | C22: Du harcèlement | D22: Contravention | F22: 1 | H22: Sanction — réparation du dommage et 1 heure de travaux forcés. | I22: Constitue un harcèlement tout comportement répété portant atteinte à une personne. [Contravention] Sanction — réparation du dommage et 1 heure de travaux forcés. | L22: Art. 36 — De l’intrusion aggravée | M22: 70 | N22: Art. 55 — De l’exhibition | O22: 1 | P22: Filoki
A23: Codex Judiciaire de Blancherive | B23: 21 | C23: De la mise en danger de la vie d’autrui | D23: Délit | E23: 500 | F23: 1 | H23: Sanction — 500 septims et 1 heure de travaux forcés. | I23: Constitue une mise en danger le fait d’exposer autrui à un risque sérieux pour sa vie ou son intégrité. [Délit] Sanction — 500 septims et 1 heure de travaux forcés. | L23: Art. 37 — Du vol simple | M23: 50 | N23: Art. 58 — Des rixes et bagarres | O23: 0.3333 | P23: Gisbern Isenbjorn
A24: Codex Judiciaire de Blancherive | B24: 22 | C24: Des violences et agressions simples | D24: Délit | E24: 550 | F24: 3 | H24: Sanction — réparation, 550 septims et 3 heures de travaux forcés. | I24: Constituent des violences ou agressions tous actes portant atteinte à l’intégrité physique d’une personne et ayant entraîné blessures, contusions ou incapacité, sans circonstance aggravante. [Délit] Sanction — réparation, 550 septims et 3 heures de travaux forcés. | L24: Art. 38 — Du vol aggravé | M24: 70 | N24: Art. 70 — De l’espionnage | O24: 5 | P24: Glaemorandir Oeil-Perçant
A25: Codex Judiciaire de Blancherive | B25: 23 | C25: Des violences et agressions aggravées | D25: Crime | G25: 2 | H25: Sanction — réparation, 2 heures de travaux forcés et 1 heure de cachot ; amende de niveau criminel à l’appréciation du magistrat. | I25: Les violences sont aggravées lorsqu’elles sont commises dans l’une des circonstances prévues à l’article 9. [Crime] Sanction — réparation, 2 heures de travaux forcés et 1 heure de cachot ; amende de niveau criminel à l’appréciation du magistrat. | J25: Plusieurs durées de travaux détectées. | L25: Art. 41 — Du recel | M25: 100 | N25: Art. 71 — De la désertion | P25: Gorbash Tête-de-Pierre
A26: Codex Judiciaire de Blancherive | B26: 24 | C26: De la séquestration, de l’enlèvement et de la prise d’otage | D26: Crime | E26: 650 | G26: 3 | H26: Sanction — 650 septims, 3 heures de travaux forcés et 1 heure de cachot. | I26: Constitue une séquestration, un enlèvement ou une prise d’otage le fait de priver autrui de sa liberté d’aller et venir sans droit. [Crime] Sanction — 650 septims, 3 heures de travaux forcés et 1 heure de cachot. | J26: Plusieurs durées de travaux détectées. | L26: Art. 42 — Du recel en bande organisée | M26: 150 | N26: Art. 74 — De l’outrage | P26: Gorvin Le-Moite
A27: Codex Judiciaire de Blancherive | B27: 25 | C27: De la séquestration aggravée | D27: Crime | E27: 800 | G27: 3 | H27: Sanction — 800 septims, 3 heures de travaux forcés et 1 heure de cachot. | I27: L’infraction est aggravée lorsqu’elle est commise en réunion, avec violence, ou lorsqu’elle se prolonge dans la durée. [Crime] L’aggravation s’apprécie selon le nombre d’auteurs, la violence employée et la durée de la privation de liberté, et non selon le nombre de victimes. Sanction — 800 septims, 3 heures de travaux forcés et 1 heure de cachot. | J27: Plusieurs durées de travaux détectées. | L27: Art. 44 — Des ouvrages publics | N27: Art. 77 — De l’entrave à la justice | O27: 1 | P27: Gronk Grognon
A28: Codex Judiciaire de Blancherive | B28: 26 | C28: De l’homicide involontaire | D28: Crime | E28: 800 | F28: 5 | H28: Sanction — à l’appréciation du magistrat. Barème indicatif : 800 septims, réparation à la famille et 5 heures de travaux forcés. | I28: Constitue un homicide involontaire le décès d’autrui causé par imprudence, négligence ou manquement caractérisé à une obligation de prudence. [Crime] Sanction — à l’appréciation du magistrat. Barème indicatif : 800 septims, réparation à la famille et 5 heures de travaux forcés. | L28: Art. 45 — Des recours abusifs | M28: 200 | N28: Art. 78 — Du faux | O28: 2 | P28: Hakon Grisetoison
A29: Codex Judiciaire de Blancherive | B29: 27 | C29: De l’homicide volontaire | D29: Crime | E29: 1000 | G29: 3 | H29: Sanction — à l’appréciation du magistrat. Barème indicatif : 1000 septims, réparation à la famille, 3 heures de travaux forcés et 2 heures de cachot. | I29: Constitue un homicide volontaire tout acte ayant entraîné volontairement la mort d’autrui. [Crime] Ne peuvent être qualifiés d’homicide les décès résultant d’une guerre déclarée, d’un usage légitime et proportionné de la force par les autorités, d’une exécution judiciaire régulière ou d’un duel légal consenti. Sanction — à l’appréciation du magistrat. Barème indicatif : 1000 septims, réparation à la famille, 3 heures de travaux forcés et 2 heures de cachot. | J29: Plusieurs durées de travaux détectées. | L29: Art. 46 — De la violation de la propriété de la Châtellerie | M29: 100 | N29: Art. 79 — De l’usage de faux | O29: 2 | P29: Hastelvin
A30: Codex Judiciaire de Blancherive | B30: 28 | C30: De l’assassinat | D30: Crime | E30: 1200 | G30: 5 | H30: Sanction — à l’appréciation du magistrat. Barème indicatif : 1200 septims, 5 heures de travaux forcés et 3 heures de cachot. | I30: Constitue un assassinat l’homicide volontaire commis avec préméditation. La préméditation suppose une préparation et une réflexion préalables. [Crime] Sont également aggravants les faits commis contre la famille, une personne vulnérable, un représentant de l’autorité, ou en raison de la race ou de la foi de la victime, ainsi que ceux commis en bande organisée ou à des fins d’intimidation. Sanction — à l’appréciation du magistrat. Barème indicatif : 1200 septims, 5 heures de travaux forcés et 3 heures de cachot. | J30: Plusieurs durées de travaux détectées. | L30: Art. 47 — De la corruption passive | M30: 1000 | N30: Art. 83 — Des armes interdites | P30: Il-draz De Chasse-au-bois
A31: Codex Judiciaire de Blancherive | B31: 29 | C31: De la torture, de la mutilation et de la barbarie | D31: Crime | E31: 800 | G31: 5 | H31: Sanction — à l’appréciation du magistrat. Barème indicatif : réparation, 800 septims, 5 heures de travaux forcés et 1 heure de cachot. | I31: Constitue un acte de torture tout acte de barbarie, mutilation, violence extrême ou souffrance délibérément infligée. [Crime] Sanction — à l’appréciation du magistrat. Barème indicatif : réparation, 800 septims, 5 heures de travaux forcés et 1 heure de cachot. | J31: Plusieurs durées de travaux détectées. | L31: Art. 48 — De la corruption active | M31: 2000 | N31: Art. 96 — De la magie de foudre | P31: Ilflynn
A32: Codex Judiciaire de Blancherive | B32: 30 | C32: De la torture aggravée | D32: Crime | E32: 1000 | G32: 5 | H32: Sanction — à l’appréciation du magistrat. Barème indicatif : réparation, 1000 septims, 5 heures de travaux forcés et 3 heures de cachot. | I32: L’infraction est aggravée dans les circonstances prévues à l’article 9. [Crime] Sanction — à l’appréciation du magistrat. Barème indicatif : réparation, 1000 septims, 5 heures de travaux forcés et 3 heures de cachot. | J32: Plusieurs durées de travaux détectées. | L32: Art. 49 — De l’abus de pouvoir public | M32: 500 | N32: Art. 103 — De la fraude commerciale | P32: Ina'ra
A33: Codex Judiciaire de Blancherive | B33: 31 | C33: Du viol et des atteintes sexuelles sur enfant | D33: Crime | H33: Sanction — peine maximale encourue : mort et saisie des biens, sur verdict public et motivé du magistrat. Titre III — Des atteintes aux biens | I33: Le viol et les atteintes sexuelles commises sur un enfant constituent les crimes les plus graves contre la personne. [Crime] Sanction — peine maximale encourue : mort et saisie des biens, sur verdict public et motivé du magistrat. Titre III — Des atteintes aux biens | L33: Art. 50 — De l’abus de pouvoir lié à un statut | M33: 500 | N33: Art. 105 — De la vente à la criée | P33: Jeebam-dee
A34: Codex Judiciaire de Blancherive | B34: 32 | C34: De la destruction ou dégradation de bien public | D34: Crime | F34: 1 | H34: Sanction — 100 septims, réparation et 1 heure de travaux forcés lorsque le dommage n’excède pas 500 septims ; requalification en délit ou en crime au-delà. | I34: Constitue une infraction la destruction ou la dégradation volontaire d’un bien appartenant à la Châtellerie ou affecté à l’usage public. La qualification suit la valeur du dommage selon l’article 4. Sanction — 100 septims, réparation et 1 heure de travaux forcés lorsque le dommage n’excède pas 500 septims ; requalification en délit ou en crime au-delà. | J34: Plusieurs montants d'amende détectés. | L34: Art. 51 — De l’usurpation de fonction | M34: 500 | N34: Art. 106 — De la contrebande | O34: 0.3333 | P34: Kah-Shir Sombre Griffe
A35: Codex Judiciaire de Blancherive | B35: 33 | C35: De la destruction ou dégradation de bien privé | D35: Crime | F35: 1 | H35: Sanction — 100 septims, réparation et 1 heure de travaux forcés lorsque le dommage n’excède pas 500 septims ; requalification en délit ou en crime au-delà. | I35: Constitue une infraction la destruction ou la dégradation volontaire du bien d’autrui. La qualification suit la valeur du dommage selon l’article 4. Sanction — 100 septims, réparation et 1 heure de travaux forcés lorsque le dommage n’excède pas 500 septims ; requalification en délit ou en crime au-delà. | J35: Plusieurs montants d'amende détectés. | L35: Art. 52 — De l’usage non autorisé de matériel de la Châtellerie | M35: 150 | N35: Art. 111 — De la protection des géants | P35: Kendall Delamare
A36: Codex Judiciaire de Blancherive | B36: 34 | C36: De l’intrusion en propriété privée extérieure | D36: Contravention | E36: 50 | G36: 0.5 | H36: Sanction — 50 septims et 30 minutes de cachot. | I36: Constitue une intrusion le fait de pénétrer ou de se maintenir sans autorisation sur un terrain, un enclos ou une dépendance appartenant à autrui. [Contravention] Chacun peut défendre ses terres et ses propriétés, dans les conditions autorisées par la Châtellerie. Sanction — 50 septims et 30 minutes de cachot. | L36: Art. 53 — De la divulgation d’information secrète de la Châtellerie | M36: 1000 | P36: Krakan Valyn
A37: Codex Judiciaire de Blancherive | B37: 35 | C37: De l’intrusion en propriété privée intérieure | D37: Délit | E37: 500 | G37: 1 | H37: Sanction — 500 septims et 1 heure de cachot. | I37: Constitue une intrusion aggravée par le lieu le fait de pénétrer ou de se maintenir sans autorisation à l’intérieur de la demeure d’autrui. [Délit] Le propriétaire est déclaré en état de légitime défense après trois sommations demeurées sans effet. Sanction — 500 septims et 1 heure de cachot. | L37: Art. 54 — De la dissimulation du visage | M37: 20 | P37: Kronk Grognon
A38: Codex Judiciaire de Blancherive | B38: 36 | C38: De l’intrusion aggravée | D38: Délit | E38: 70 | G38: 1 | H38: Sanction — 70 septims et 1 heure de cachot ; qualification délictuelle en propriété publique. | I38: L’intrusion est aggravée lorsqu’elle est commise par force, à main armée, ou contre une personne vulnérable ou un dépositaire de l’autorité. Elle constitue un délit lorsqu’elle porte sur une propriété publique. Sanction — 70 septims et 1 heure de cachot ; qualification délictuelle en propriété publique. | L38: Art. 55 — De l’exhibition | M38: 50 | P38: Laureen Toison-de-Sang
A39: Codex Judiciaire de Blancherive | B39: 37 | C39: Du vol simple | D39: Crime | E39: 50 | F39: 1 | H39: Sanction — réparation, amende de 50 septims au minimum ajustée à la valeur du bien, et 1 heure de travaux forcés. | I39: Constitue un vol toute appropriation frauduleuse d’un bien appartenant à autrui. [Délit] Les faits d’une valeur infime peuvent être traités en contravention sur appréciation du magistrat. Le vol devient un crime lorsque le bien est d’une valeur particulièrement élevée ou qu’il s’agit d’un objet sous licence. Sanction — réparation, amende de 50 septims au minimum ajustée à la valeur du bien, et 1 heure de travaux forcés. | J39: La sanction comporte une borne minimale ou maximale. | L39: Art. 58 — Des rixes et bagarres | M39: 35 | P39: Lazabard Jemelred
A40: Codex Judiciaire de Blancherive | B40: 38 | C40: Du vol aggravé | D40: Délit | E40: 70 | F40: 2 | H40: Sanction — réparation, 70 septims et 2 heures de travaux forcés. | I40: Le vol est aggravé lorsqu’il est commis contre une personne vulnérable ou un dépositaire de l’autorité, en raison de la race ou de la foi de la victime, à main armée, avec préméditation ou en bande organisée. [Délit] Sanction — réparation, 70 septims et 2 heures de travaux forcés. | L40: Art. 59 — Du rassemblement illégal | M40: 25 | P40: Léonce Réve-épine
A41: Codex Judiciaire de Blancherive | B41: 39 | C41: Du vol de bétail | H41: Sanction — restitution ou remboursement au triple, cumulé avec la peine prévue aux articles 37 et 38. | I41: Le bétail constitue une richesse essentielle des fermes et villages de la Châtellerie. Quiconque en est reconnu coupable doit restituer ou rembourser au triple du préjudice subi. Cette réparation civile s’ajoute à la peine principale, déterminée selon la gravité des faits. Sanction — restitution ou remboursement au triple, cumulé avec la peine prévue aux articles 37 et 38. | L41: Art. 60 — De l’association de malfaiteurs | M41: 100 | P41: Lokh Tar
A42: Codex Judiciaire de Blancherive | B42: 40 | C42: De la récidive en matière de vol | H42: Sanction — perte du droit de cité et bannissement, sur décision motivée. | I42: Toute récidive en matière de vol peut entraîner une aggravation de la peine conformément aux dispositions relatives à la récidive prévues par le présent Codex. Lorsque les faits sont répétés, graves ou démontrent une volonté manifeste de persister dans une activité criminelle, la Cour peut prononcer des sanctions complémentaires. La perte du droit de cité ou le bannissement ne peuvent être prononcés que par décision motivée de la Cour, lorsque les sanctions ordinaires apparaissent manifestement insuffisantes au regard du nombre de récidives, de leur gravité et du comportement du condamné. Ces mesures ne peuvent résulter automatiquement de la seule existence d’une récidive. Sanction — perte du droit de cité et bannissement, sur décision motivée. | L42: Art. 62 — De la divulgation d’un secret professionnel | M42: 500 | P42: Lous Bois
A43: Codex Judiciaire de Blancherive | B43: 41 | C43: Du recel | D43: Délit | E43: 100 | F43: 2 | H43: Sanction — 100 septims par bien, en sus de la valeur estimée du bien, et 2 heures de travaux forcés. | I43: Constitue un recel le fait de transporter, détenir, commercialiser, transformer ou dissimuler un bien provenant d’une infraction, en ne pouvant raisonnablement en ignorer l’origine illicite. [Délit] Sanction — 100 septims par bien, en sus de la valeur estimée du bien, et 2 heures de travaux forcés. | L43: Art. 63 — Du refus d’obtempérer | M43: 50 | P43: Lucius Ravenshield
A44: Codex Judiciaire de Blancherive | B44: 42 | C44: Du recel en bande organisée | D44: Délit | E44: 150 | F44: 2 | H44: Sanction — 150 septims par bien, en sus de la valeur estimée du bien, et 2 heures de travaux forcés. | I44: Le recel commis de manière organisée ou concertée est aggravé. [Délit] Sanction — 150 septims par bien, en sus de la valeur estimée du bien, et 2 heures de travaux forcés. | L44: Art. 64 — De la fabrication et de la vente de substances illégales | M44: 250 | P44: Ma'arl
A45: Codex Judiciaire de Blancherive | B45: 43 | C45: Du pillage | H45: Sanction — restitution ; sanction déterminée selon la classification de l’article 4 d’après la gravité et la valeur du dommage. | I45: Le pillage des terres alliées, des villages protégés par le Jarl ou des biens des sujets fidèles de la Châtellerie est interdit, y compris en temps de guerre. Sanction — restitution ; sanction déterminée selon la classification de l’article 4 d’après la gravité et la valeur du dommage. | L45: Art. 65 — De la fausse alerte | M45: 100 | P45: Magnar Traquebrume
A46: Codex Judiciaire de Blancherive | B46: 44 | C46: Des ouvrages publics | D46: Infraction | H46: Sanction — réparation et 50 septims ; 200 septims en cas de récidive ; requalification selon la valeur du dommage. Titre IV — Des atteintes aux services de la Châtellerie | I46: Les moulins, ponts, puits et tout ouvrage d’utilité publique sont placés sous la protection de la loi. Toute dégradation, sabotage ou destruction volontaire constitue une infraction grave. Sanction — réparation et 50 septims ; 200 septims en cas de récidive ; requalification selon la valeur du dommage. Titre IV — Des atteintes aux services de la Châtellerie | J46: Plusieurs montants d'amende détectés. | L46: Art. 70 — De l’espionnage | M46: 1000 | P46: Malivor Xernes
A47: Codex Judiciaire de Blancherive | B47: 45 | C47: Des recours abusifs | D47: Contravention | E47: 200 | H47: Sanction — 200 septims. | I47: Constitue un recours abusif l’usage manifestement injustifié des procédures ou demandes adressées aux services de la Châtellerie. [Contravention] Sanction — 200 septims. | L47: Art. 71 — De la désertion | P47: Njalda
A48: Codex Judiciaire de Blancherive | B48: 46 | C48: De la violation de la propriété de la Châtellerie | D48: Délit | E48: 100 | H48: Sanction — amende de niveau délictuel, 100 septims au minimum. | I48: Constitue un délit l’intrusion ou le maintien sans droit dans une propriété de la Châtellerie. Sanction — amende de niveau délictuel, 100 septims au minimum. | J48: La sanction comporte une borne minimale ou maximale. | L48: Art. 74 — De l’outrage | P48: Pavis Gurdalval
A49: Codex Judiciaire de Blancherive | B49: 47 | C49: De la corruption passive | D49: Crime | E49: 1000 | G49: 3 | H49: Sanction — 1000 septims, 3 heures de cachot et bannissement des offices publics à titre de mesure accessoire. | I49: Commet une corruption passive l’agent qui sollicite ou accepte un avantage indu en vue d’influencer une décision, une action ou une omission relevant de ses fonctions. [Crime] Sanction — 1000 septims, 3 heures de cachot et bannissement des offices publics à titre de mesure accessoire. | L49: Art. 77 — De l’entrave à la justice | M49: 50 | P49: Ri'Jhan MoonShadow
A50: Codex Judiciaire de Blancherive | B50: 48 | C50: De la corruption active | D50: Crime | E50: 2000 | F50: 2 | G50: 2 | H50: Sanction — 2000 septims, 2 heures de travaux forcés, 2 heures de cachot et bannissement des offices publics à titre de mesure accessoire. | I50: Commet une corruption active quiconque offre ou promet un avantage indu à une personne investie d’une autorité ou d’une fonction. [Crime] Sanction — 2000 septims, 2 heures de travaux forcés, 2 heures de cachot et bannissement des offices publics à titre de mesure accessoire. | L50: Art. 78 — Du faux | M50: 500 | P50: Ronin
A51: Codex Judiciaire de Blancherive | B51: 49 | C51: De l’abus de pouvoir public | D51: Crime | E51: 500 | F51: 2 | G51: 2 | H51: Sanction — 500 septims, 2 heures de travaux forcés, 2 heures de cachot et bannissement des offices publics à titre de mesure accessoire. | I51: Commet un abus de pouvoir toute personne investie d’une fonction publique locale qui en use de manière détournée, excessive ou illégitime. [Crime] Sanction — 500 septims, 2 heures de travaux forcés, 2 heures de cachot et bannissement des offices publics à titre de mesure accessoire. | L51: Art. 79 — De l’usage de faux | M51: 250 | P51: Rorik Marche-Hiver
A52: Codex Judiciaire de Blancherive | B52: 50 | C52: De l’abus de pouvoir lié à un statut | D52: Crime | E52: 500 | F52: 3 | H52: Sanction — 500 septims et 3 heures de travaux forcés. | I52: Le présent article vise les abus commis au titre d’un statut nobiliaire, corporatif ou de guilde, à l’exclusion des fonctions publiques locales régies par l’article 49. [Crime] Sanction — 500 septims et 3 heures de travaux forcés. | L52: Art. 80 — Du parjure | M52: 200 | P52: Rusco
A53: Codex Judiciaire de Blancherive | B53: 51 | C53: De l’usurpation de fonction | D53: Délit | E53: 500 | F53: 3 | H53: Sanction — 500 septims et 3 heures de travaux forcés. | I53: Commet une usurpation de fonction quiconque se prétend titulaire d’une charge ou d’une fonction sans en avoir le titre. [Délit] Sanction — 500 septims et 3 heures de travaux forcés. | L53: Art. 81 — De l’évasion | M53: 2000 | P53: S'Khar
A54: Codex Judiciaire de Blancherive | B54: 52 | C54: De l’usage non autorisé de matériel de la Châtellerie | D54: Contravention | E54: 150 | F54: 0.5 | H54: Sanction — saisie des biens, 150 septims par équipement et 30 minutes de travaux forcés. | I54: Constitue une infraction l’utilisation sans droit d’un équipement appartenant à la Châtellerie. [Contravention] Sanction — saisie des biens, 150 septims par équipement et 30 minutes de travaux forcés. | L54: Art. 83 — Des armes interdites | P54: Si'Yara dite Fou
A55: Codex Judiciaire de Blancherive | B55: 53 | C55: De la divulgation d’information secrète de la Châtellerie | D55: Infraction | E55: 1000 | F55: 5 | H55: Sanction — 1000 septims et 5 heures de travaux forcés. Titre V — Des atteintes à l’ordre public et à la société | I55: Constitue une infraction la divulgation volontaire, sans autorisation légitime, d’une information officiellement tenue secrète par la Châtellerie lorsque cette divulgation est susceptible de porter atteinte à ses intérêts, à son administration, à sa sécurité ou à celle de ses habitants. Le présent article ne s’applique qu’aux informations relevant de la compétence propre de la Châtellerie. Lorsque les informations concernées touchent également à la sécurité de l’Empire, à la Légion impériale, au renseignement impérial ou à toute matière relevant du Codex Penitus Imperialis, la compétence des autorités impériales prévaut. Dans ce cas, la Cour de Blancherive se dessaisit de l’affaire et transmet aux autorités impériales compétentes les informations et éléments recueillis. Sanction — 1000 septims et 5 heures de travaux forcés. Titre V — Des atteintes à l’ordre public et à la société | L55: Art. 87 — De la possession d’artefact daedrique | M55: 500 | P55: Sigurd Grisetoison
A56: Codex Judiciaire de Blancherive | B56: 54 | C56: De la dissimulation du visage | D56: Infraction | E56: 20 | H56: Sanction — 20 septims. | I56: Le fait de dissimuler son visage en violation des dispositions prévues à l’article 115 du présent Codex constitue une infraction. Les interdictions, exceptions éventuelles et limites territoriales applicables à la dissimulation du visage sont celles définies à l’article 115. Toute dissimulation volontaire destinée à empêcher l’identification d’une personne par la Garde ou par une autre autorité légitime peut être retenue comme circonstance aggravante. Le refus de découvrir son visage après une injonction légitime d’une autorité peut également donner lieu à l’application des dispositions relatives au refus d’obtempérer. Sanction — 20 septims. | L56: Art. 88 — De la profanation de lieu saint | M56: 500 | P56: Smaug
A57: Codex Judiciaire de Blancherive | B57: 55 | C57: De l’exhibition | D57: Contravention | E57: 50 | G57: 1 | H57: Sanction — 50 septims et 1 heure de cachot. | I57: Constitue une exhibition tout dénuement ou comportement indécent exposé au regard du public. [Contravention] Sanction — 50 septims et 1 heure de cachot. | L57: Art. 96 — De la magie de foudre | M57: 2500 | P57: Starkos Coeurebene
A58: Codex Judiciaire de Blancherive | B58: 56 | C58: De l’ivresse manifeste sur la voie publique | D58: Contravention | H58: Sanction — à l’appréciation des forces de l’ordre. | I58: L’état d’ivresse manifeste sur la voie publique constitue une contravention. Sanction — à l’appréciation des forces de l’ordre. | L58: Art. 101 — De la taxe citoyenne | M58: 50 | P58: Theodrek Heid
A59: Codex Judiciaire de Blancherive | B59: 57 | C59: Du trouble à l’ordre public | D59: Contravention | H59: Sanction — à l’appréciation des forces de l’ordre. | I59: Constitue un trouble à l’ordre public tout comportement perturbant la tranquillité ou la sécurité publique. [Contravention] Sanction — à l’appréciation des forces de l’ordre. | L59: Art. 103 — De la fraude commerciale | P59: Thorin Rivegel
A60: Codex Judiciaire de Blancherive | B60: 58 | C60: Des rixes et bagarres | D60: Délit | E60: 35 | G60: 0.3333 | H60: Sanction — 35 septims et 20 minutes de cachot ; qualification supérieure en cas de blessures. | I60: Toute bagarre, rixe ou altercation violente sur la voie publique est interdite sur l’ensemble du territoire de la Châtellerie, hormis dans les tavernes et avec l’accord du tenancier. Le trouble sans blessure constitue une contravention ; l’altercation ayant causé des blessures constitue un délit relevant de l’article 22, aggravé le cas échéant selon l’article 9. Sanction — 35 septims et 20 minutes de cachot ; qualification supérieure en cas de blessures. | L60: Art. 104 — De la vente de gros et des étals | M60: 65 | P60: Torald Brise-Roche
A61: Codex Judiciaire de Blancherive | B61: 59 | C61: Du rassemblement illégal | D61: Contravention | E61: 25 | F61: 1 | H61: Sanction — 25 septims et 1 heure de travaux forcés. | I61: Constitue un rassemblement illégal tout regroupement interdit ou tenu sans autorisation. [Contravention] Sanction — 25 septims et 1 heure de travaux forcés. | L61: Art. 105 — De la vente à la criée | P61: Ulfar
A62: Codex Judiciaire de Blancherive | B62: 60 | C62: De l’association de malfaiteurs | D62: Délit | E62: 100 | F62: 2 | H62: Sanction — 100 septims et 2 heures de travaux forcés. | I62: Constitue une association de malfaiteurs tout groupement formé en vue de commettre des infractions. [Délit] Cette qualification peut également être retenue à titre de circonstance aggravante. Sanction — 100 septims et 2 heures de travaux forcés. | L62: Art. 106 — De la contrebande | M62: 100 | P62: Varaa Uzgar
A63: Codex Judiciaire de Blancherive | B63: 61 | C63: De l’exercice illégal d’une profession réglementée | D63: Contravention | H63: Sanction — selon les régimes spéciaux applicables et l’appréciation de la Cour. | I63: Sont réglementés notamment le commerce, l’alchimie, la guérison et la chasse. Leur exercice sans droit constitue une contravention. [Contravention] Sanction — selon les régimes spéciaux applicables et l’appréciation de la Cour. | L63: Art. 108 — De la chasse sans permis | M63: 100 | P63: Vranx Thorgar
A64: Codex Judiciaire de Blancherive | B64: 62 | C64: De la divulgation d’un secret professionnel | D64: Contravention | E64: 500 | F64: 3 | H64: Sanction — 500 septims et 3 heures de travaux forcés. | I64: Constitue une infraction la divulgation d’informations couvertes par un secret professionnel, commercial, industriel, religieux ou médical. [Contravention] Sanction — 500 septims et 3 heures de travaux forcés. | L64: Art. 109 — De la cruauté envers les bêtes | M64: 150 | P64: Wulfgar Durrock
A65: Codex Judiciaire de Blancherive | B65: 63 | C65: Du refus d’obtempérer | D65: Délit | E65: 50 | F65: 1 | H65: Sanction — 50 septims et 1 heure de travaux forcés ; mise en état de travail ou retrait de charrette possible. | I65: Constitue un refus d’obtempérer le fait de se soustraire volontairement à un contrôle ou à une injonction d’une autorité légitime. [Contravention] L’infraction devient un délit en cas d’usage de violence, de magie ou de potions. Sanction — 50 septims et 1 heure de travaux forcés ; mise en état de travail ou retrait de charrette possible. | L65: Art. 110 — De la chasse au mammouth | M65: 200 | P65: Zeid Le Brise-Lames
A66: Codex Judiciaire de Blancherive | B66: 64 | C66: De la fabrication et de la vente de substances illégales | D66: Crime | E66: 250 | F66: 3 | H66: Sanction — 250 septims par unité et 3 heures de travaux forcés. | I66: Sont prohibés la fabrication et le commerce de poisons, de skooma et de sucre-lune. [Délit] En cas de trafic de grande ampleur, notamment lorsque le cumul excède 2500 septims, l’infraction est requalifiée en crime. Sanction — 250 septims par unité et 3 heures de travaux forcés. | L66: Art. 111 — De la protection des géants
A67: Codex Judiciaire de Blancherive | B67: 65 | C67: De la fausse alerte | D67: Contravention | E67: 100 | F67: 1 | H67: Sanction — 100 septims et 1 heure de travaux forcés. | I67: Constitue une fausse alerte toute alerte mensongère ou abusive donnée à la Garde ou aux autorités. [Contravention] Sanction — 100 septims et 1 heure de travaux forcés. | L67: Art. 114 — De la marche obligatoire | M67: 15
A68: Codex Judiciaire de Blancherive | B68: 66 | C68: Des horaires des tavernes | H68: Sanction — à l’appréciation des forces de l’ordre ; fermeture administrative possible en cas de récidive. Titre VI — Des atteintes à la Châtellerie Les infractions du présent titre s’appliquent sans préjudice de la compétence exclusive des juridictions impériales lorsque les faits portent également atteinte à l’autorité impériale directe, à la Légion ou aux services de renseignement impériaux, au sens du Codex Penitus Imperialis. | I68: Les tavernes, auberges et établissements servant des boissons ferment au troisième appel de cloche, sauf autorisation exceptionnelle du Jarl ou de son représentant. Sanction — à l’appréciation des forces de l’ordre ; fermeture administrative possible en cas de récidive. Titre VI — Des atteintes à la Châtellerie Les infractions du présent titre s’appliquent sans préjudice de la compétence exclusive des juridictions impériales lorsque les faits portent également atteinte à l’autorité impériale directe, à la Légion ou aux services de renseignement impériaux, au sens du Codex Penitus Imperialis. | L68: Art. 115 — Du visage découvert | M68: 15
A69: Codex Judiciaire de Blancherive | B69: 67 | C69: De la trahison envers la Châtellerie | D69: Crime | H69: Sanction — peine maximale encourue : mort et saisie des biens, sur verdict public et motivé. | I69: Commet un acte de haute trahison quiconque apporte volontairement aide, assistance, refuge, renseignements ou ravitaillement à un dragon hostile, à un culte draconique ennemi ou à toute organisation cherchant à nuire à la Châtellerie. [Crime] Le présent article vise exclusivement les atteintes portées à la Châtellerie elle-même. Sanction — peine maximale encourue : mort et saisie des biens, sur verdict public et motivé. | L69: Art. 116 — Du saut des murailles | M69: 55
A70: Codex Judiciaire de Blancherive | B70: 68 | C70: Du terrorisme | D70: Crime | H70: Sanction — peine maximale encourue : mort et saisie des biens, sur verdict public et motivé. | I70: Constitue un acte de terrorisme toute entreprise visant à répandre la terreur au sein de la population ou à contraindre les autorités par la violence. [Crime] Sanction — peine maximale encourue : mort et saisie des biens, sur verdict public et motivé. | L70: Art. 117 — Du vol dans les fermes | M70: 40
A71: Codex Judiciaire de Blancherive | B71: 69 | C71: De la conspiration | D71: Crime | H71: Sanction — peine maximale encourue : mort et saisie des biens, sur verdict public et motivé. | I71: Constitue une conspiration tout projet concerté dirigé contre la Châtellerie ou ses institutions. [Crime] Sanction — peine maximale encourue : mort et saisie des biens, sur verdict public et motivé.
A72: Codex Judiciaire de Blancherive | B72: 70 | C72: De l’espionnage | D72: Crime | E72: 1000 | G72: 5 | H72: Sanction — 1000 septims et 5 heures de cachot. | I72: Constitue un espionnage la collecte ou la transmission d’informations au profit d’une puissance ou d’une organisation hostile à la Châtellerie. [Crime] Sanction — 1000 septims et 5 heures de cachot.
A73: Codex Judiciaire de Blancherive | B73: 71 | C73: De la désertion | D73: Crime | H73: Sanction — exil ; peine de mort encourue sur verdict public et motivé lorsque les circonstances l’exigent. | I73: Est coupable de désertion quiconque abandonne volontairement son poste durant une bataille ou fuit devant l’ennemi sans ordre de son commandement. [Crime] La peine de mort ne peut être prononcée que par une autorité judiciaire compétente, à l’issue d’une procédure régulière, et non par simple décision de commandement — sans préjudice du droit de tout chef militaire de faire cesser sur-le-champ un péril immédiat par la force. Sanction — exil ; peine de mort encourue sur verdict public et motivé lorsque les circonstances l’exigent. | J73: Peine capitale mentionnée.
A74: Codex Judiciaire de Blancherive | B74: 72 | C74: De l’obligation militaire | H74: Sanction — fourniture d’un combattant ou compensation financière fixée par l’Intendance. | I74: Chaque foyer est tenu de fournir au moins un combattant lorsque le Cor de Guerre est sonné. Lorsqu’aucun membre du foyer n’est en mesure de servir pour un motif légitime, une compensation financière est versée au trésor de la Châtellerie. Sanction — fourniture d’un combattant ou compensation financière fixée par l’Intendance.
A75: Codex Judiciaire de Blancherive | B75: 73 | C75: Des Compagnons | I75: Les Compagnons de Jorrvaskr demeurent une confrérie libre et conservent leur indépendance dans leurs affaires quotidiennes. Lors d’une guerre officiellement déclarée par le Jarl, ils sont tenus d’apporter leur concours à la défense de la Châtellerie, conformément aux anciens serments qui les unissent à Blancherive. Titre VII — Des atteintes au gouvernement et à la justice
A76: Codex Judiciaire de Blancherive | B76: 74 | C76: De l’outrage | D76: Délit | I76: Constitue un outrage toute atteinte verbale ou symbolique portée à une autorité de la Châtellerie. L’outrage se gradue comme suit : outrage à la Garde — 100 septims ; le contrevenant peut être retenu jusqu’à comparution devant une autorité. [Contravention] outrage à la Châtellerie — 200 septims et 1 heure de travaux forcés. [Contravention] outrage au Jarl ou à la Cour — 500 septims et 3 heures de travaux forcés. [Délit] L’outrage commis à l’audience relève de la police de l’audience et du Codex Procédural de Blancherive. | J76: Plusieurs montants d'amende détectés. Plusieurs durées de travaux détectées.
A77: Codex Judiciaire de Blancherive | B77: 75 | C77: Du non-acquittement d’une peine pécuniaire | D77: Délit | F77: 1 | H77: Sanction — refus délibéré : doublement de l’amende et 1 heure de travaux forcés ; insolvabilité réelle : conversion en travaux forcés, travaux d’intérêt général ou saisie de biens. | I77: Le refus délibéré d’acquitter une amende constitue un délit. L’insolvabilité réelle donne lieu à conversion et non à aggravation. Sanction — refus délibéré : doublement de l’amende et 1 heure de travaux forcés ; insolvabilité réelle : conversion en travaux forcés, travaux d’intérêt général ou saisie de biens.
A78: Codex Judiciaire de Blancherive | B78: 76 | C78: Du non-respect d’une décision de justice | D78: Délit | H78: Sanction — à l’appréciation du juge. | I78: Constitue un délit la violation d’une décision rendue par la Cour de la Châtellerie. Sanction — à l’appréciation du juge.
A79: Codex Judiciaire de Blancherive | B79: 77 | C79: De l’entrave à la justice | D79: Contravention | E79: 50 | G79: 1 | H79: Sanction — 50 septims et 1 heure de cachot. | I79: Constitue une entrave tout obstacle volontaire au fonctionnement de la justice de la Châtellerie. [Contravention] Sanction — 50 septims et 1 heure de cachot.
A80: Codex Judiciaire de Blancherive | B80: 78 | C80: Du faux | D80: Crime | E80: 500 | G80: 2 | H80: Sanction — 500 septims et 2 heures de cachot. | I80: Constitue un faux la fabrication ou la falsification d’un document, d’un registre, d’un sceau ou de tout élément destiné à faire foi. [Contravention] L’infraction est requalifiée en délit ou en crime selon la gravité de ses conséquences, notamment l’usurpation d’une fonction officielle ou un préjudice financier important. Sanction — 500 septims et 2 heures de cachot.
A81: Codex Judiciaire de Blancherive | B81: 79 | C81: De l’usage de faux | D81: Contravention | E81: 250 | G81: 2 | H81: Sanction — 250 septims et 2 heures de cachot. | I81: Constitue un usage de faux l’utilisation d’un élément dont le caractère falsifié ne pouvait être ignoré. [Contravention] L’infraction est requalifiée selon la gravité de ses conséquences. Sanction — 250 septims et 2 heures de cachot.
A82: Codex Judiciaire de Blancherive | B82: 80 | C82: Du parjure | D82: Délit | E82: 200 | F82: 2 | H82: Sanction — 200 septims et 2 heures de travaux forcés. | I82: Constitue un parjure le mensonge ou le faux témoignage, oral ou écrit, produit devant la Cour ou sous serment. [Délit] Sanction — 200 septims et 2 heures de travaux forcés.
A83: Codex Judiciaire de Blancherive | B83: 81 | C83: De l’évasion | D83: Crime | E83: 2000 | F83: 4 | H83: Sanction — 2000 septims et 4 heures de travaux forcés. Titre VIII — De l’armement | I83: Constitue une évasion le fait, pour une personne placée sous garde ou sous contrainte judiciaire, de se soustraire à la surveillance ou à la mesure qui lui est imposée. [Crime] Sanction — 2000 septims et 4 heures de travaux forcés. Titre VIII — De l’armement
A84: Codex Judiciaire de Blancherive | B84: 82 | C84: Du port d’arme | D84: Contravention | I84: Le port d’arme est autorisé sur le territoire de la Châtellerie, sous réserve des interdictions prévues à l’article 83 et des restrictions particulières décidées par le Jarl ou la Cour. [Contravention en cas de méconnaissance]
A85: Codex Judiciaire de Blancherive | B85: 83 | C85: Des armes interdites | H85: Sanction — déclaration obligatoire ; surveillance conservatoire, confiscation ou destruction sur décision de la Cour. Titre IX — Du culte | I85: Toute arme daedrique, maudite, nécromantique ou présentant un danger particulier pour la population doit être déclarée aux autorités compétentes. La mise sous surveillance provisoire peut être ordonnée à titre conservatoire. La confiscation ou la destruction définitive n’intervient qu’après décision de la Cour. Sanction — déclaration obligatoire ; surveillance conservatoire, confiscation ou destruction sur décision de la Cour. Titre IX — Du culte | J85: La sanction comporte une mesure non numérique.
A86: Codex Judiciaire de Blancherive | B86: 84 | C86: De la religion officielle | D86: Délit | F86: 0.5 | H86: Sanction — 30 minutes de travaux forcés, ajustables au niveau délictuel par le magistrat. | I86: Le culte des Huit Divins est reconnu par la Châtellerie de Blancherive. La pratique d’un culte non reconnu par l’Empire constitue un délit, conformément à l’article 9 du Corpus Juriscivilis Imperialis, sous réserve du régime de tolérance conditionnelle prévu à l’article 85. Sanction — 30 minutes de travaux forcés, ajustables au niveau délictuel par le magistrat.
A87: Codex Judiciaire de Blancherive | B87: 85 | C87: De la tolérance conditionnelle | D87: Crime | I87: Les cultes autres que celui des Huit Divins peuvent faire l’objet d’une tolérance conditionnelle. Sont tolérées les pratiques qui : n’impliquent aucune violence, contrainte ou atteinte à l’intégrité physique ou mentale d’autrui ; n’encouragent ni meurtre, ni sacrifice, ni crime, ni rébellion contre l’autorité ; ne font usage d’aucune magie interdite, coercitive ou de rituel occulte dangereux ; ne troublent pas la paix publique. La pratique respectant ces conditions ne constitue pas une infraction. Sa méconnaissance constitue un délit.
A88: Codex Judiciaire de Blancherive | B88: 86 | C88: Du culte daedrique | D88: Crime | H88: Sanction — peine maximale encourue : mort et saisie des biens, sur verdict public et motivé. | I88: Le culte daedrique relève du régime de tolérance conditionnelle prévu à l’article 85. Seul le culte daedrique méconnaissant ces conditions constitue un crime. Sanction — peine maximale encourue : mort et saisie des biens, sur verdict public et motivé.
A89: Codex Judiciaire de Blancherive | B89: 87 | C89: De la possession d’artefact daedrique | D89: Crime | E89: 500 | F89: 2 | H89: Sanction — saisie de l’artefact, 500 septims et 2 heures de travaux forcés. | I89: La simple possession d’objets, symboles ou reliques liés à un culte toléré ne constitue pas une infraction. Constitue un crime la possession d’artefacts liés à une pratique non tolérée, ou d’objets dont la dangerosité intrinsèque est démontrée. Sanction — saisie de l’artefact, 500 septims et 2 heures de travaux forcés.
A90: Codex Judiciaire de Blancherive | B90: 88 | C90: De la profanation de lieu saint | D90: Délit | E90: 500 | F90: 3 | H90: Sanction — 500 septims et 3 heures de travaux forcés ; qualification criminelle lorsque le motif est daedrique. | I90: Constitue une profanation toute atteinte portée au caractère sacré d’un lieu, d’un objet, d’un office religieux ou d’une personne en raison de son appartenance religieuse. [Délit] Sanction — 500 septims et 3 heures de travaux forcés ; qualification criminelle lorsque le motif est daedrique.
A91: Codex Judiciaire de Blancherive | B91: 89 | C91: Du Temple de Kynareth | I91: Le Temple de Kynareth est reconnu terre sacrée et bénéficie de la protection permanente de la Châtellerie. Les fidèles doivent pouvoir y prier en paix sous la protection du Jarl. Toute violence, profanation, vol ou trouble commis dans son enceinte constitue une circonstance aggravante.
A92: Codex Judiciaire de Blancherive | B92: 90 | C92: De la protection des sépultures | D92: Délit | H92: Sanction — sanction déterminée selon l’article 88 ; qualification criminelle lorsque le motif est daedrique. | I92: Il est interdit de profaner tombes, tertres funéraires, cairns, pierres runiques et tout lieu consacré aux morts. [Délit] Sanction — sanction déterminée selon l’article 88 ; qualification criminelle lorsque le motif est daedrique.
A93: Codex Judiciaire de Blancherive | B93: 91 | C93: Des rites funéraires | I93: Tout défunt doit recevoir des funérailles dignes selon ses croyances, qu’il s’agisse d’un bûcher, d’une inhumation ou de tout autre rite reconnu. Les familles ou, à défaut, la Châtellerie veillent à ce qu’aucun défunt ne demeure sans sépulture.
A94: Codex Judiciaire de Blancherive | B94: 92 | C94: Des engagements diplomatiques de l’Empire | I94: La Châtellerie prend acte des traités et engagements diplomatiques conclus par l’Empire, dont l’application et l’interprétation relèvent exclusivement des autorités impériales et des parties signataires. La Châtellerie ne dispose d’aucune compétence pour connaître de leur méconnaissance. Lorsqu’un fait porté à sa connaissance paraît susceptible de méconnaître un tel engagement, la Cour en avise immédiatement l’autorité impériale compétente ainsi que l’ambassade concernée, et se dessaisit à leur profit. Titre X — De l’occulte et de la magie
A95: Codex Judiciaire de Blancherive | B95: 93 | C95: De la corruption magique | D95: Crime | H95: Sanction — à l’appréciation du magistrat, selon la classification retenue. | I95: Le fait d’utiliser volontairement la magie sur une personne, sans son consentement, afin d’altérer son jugement, ses perceptions, ses émotions ou son comportement constitue un délit. L’infraction est requalifiée en crime lorsque la magie employée entraîne une suppression totale ou durable du libre arbitre de la victime, son asservissement, sa soumission forcée ou l’oblige à accomplir des actes qu’elle n’aurait raisonnablement pas accomplis sans cette influence. La gravité de l’atteinte, sa durée, les conséquences subies par la victime et l’intention de l’auteur sont prises en considération lors de la détermination de la peine. En cas de preuve avéré de corruption magique, il est nécessaire de se référer à la loi impérial (Codex Juriscilivis Impérialis) pour l’application de la peine finale. Sanction — à l’appréciation du magistrat, selon la classification retenue.
A96: Codex Judiciaire de Blancherive | B96: 94 | C96: De la nécromancie | D96: Crime | H96: Sanction — peine maximale encourue : mort et saisie des biens, sur verdict public et motivé. | I96: La pratique de la nécromancie est interdite sur l’ensemble des terres de la Châtellerie : arts nécromantiques, animation des morts, expérimentation sur cadavres, invocation d’esprits, détention de biens liés, sorts, recherches et rituels. [Crime] La nécromancie trouble le repos des défunts, met en danger les vivants et menace la sécurité publique. Sanction — peine maximale encourue : mort et saisie des biens, sur verdict public et motivé.
A97: Codex Judiciaire de Blancherive | B97: 95 | C97: Collaboration Profane | D97: Crime | H97: Sanction — peine maximale encourue : mort et saisie des biens, sur verdict public et motivé. | I97: La collaboration profane est le fait de travailler, d’échanger, d’aider les creatures (vampire, loup-garou) et force daédrique (cultes) de manière consciente et que les faits soient avérés (Se référer à l’article 3 du Codex Judiciaire de Blancherive). Il est considéré comme un crime au sein de la châtellerie et juger par les autorités compétente de la cour et de l’empire en vertue de l’article 9 et 16 du Corpus Juriscivilis Imperialis. Sanction — peine maximale encourue : mort et saisie des biens, sur verdict public et motivé.
A98: Codex Judiciaire de Blancherive | B98: 96 | C98: De la magie de foudre | D98: Crime | E98: 2500 | F98: 5 | H98: Sanction — 2500 septims au minimum et 5 heures de travaux forcés ; peine de mort encourue en cas d’usage dangereux, offensif ou coercitif, sur verdict public et motivé. Titre XI — Des terres, du commerce et de la fiscalité | I98: L’utilisation et la maîtrise de la magie de la foudre sont prohibées sur le territoire de la Châtellerie. [Crime] Sanction — 2500 septims au minimum et 5 heures de travaux forcés ; peine de mort encourue en cas d’usage dangereux, offensif ou coercitif, sur verdict public et motivé. Titre XI — Des terres, du commerce et de la fiscalité | J98: La sanction comporte une borne minimale ou maximale. Peine capitale mentionnée.
A99: Codex Judiciaire de Blancherive | B99: 97 | C99: De la propriété des terres cultivées | I99: Les terres cultivées appartiennent de plein droit à ceux qui les exploitent loyalement, les entretiennent avec diligence et en assurent la mise en valeur au profit de la Châtellerie. Le droit de propriété repose non seulement sur la possession, mais aussi sur l’entretien.
A100: Codex Judiciaire de Blancherive | B100: 98 | C100: Des terres abandonnées | I100: Toute ferme, exploitation ou domaine abandonné durant une période prolongée, sans motif légitime ni représentant désigné, revient de plein droit au Jarl et peut être réattribué à un exploitant capable d’en assurer la production.
...
